Workbook
Name ActivePayoff: Disposition!$C$18
Name AssessedValueStab: Operating!$C$56
Name AvgUnitSF: UnitMatrix!$C$19
Name BaseLowRentMo: UnitMatrix!$C$21
Name BaseMarketRentMo: UnitMatrix!$C$20
Name BasisPerUnitCur: Returns!$C$29
Name BasisPerUnitExit: Returns!$C$30
Name BlendedExitCap: Disposition!$C$9
Name BrokerCost: Disposition!$C$14
Name BuildableSF: UnitMatrix!$C$18
Name Chk_ConBalEnd: ConLoan!$C$47
Name Chk_DebtDraws: ConLoan!$C$44
Name Chk_EquityDraws: ConLoan!$C$45
Name Chk_IntReserve: ConLoan!$C$48
Name Chk_LeaseUpReached: LeaseUp!$C$13
Name Chk_LoanRetired: Disposition!$C$24
Name Chk_Reassess: Disposition!$C$25
Name Chk_RefiBalance: PermLoan!$C$33
Name Chk_TaxMethod: Operating!$C$59
Name Chk_UnitsDelivered: LeaseUp!$C$14
Name Chk_Uses: ConLoan!$C$46
Name ConCostBasis: ConLoan!$C$4
Name ConCostCommit: ConLoan!$C$8
Name ConCostExInt: ConLoan!$C$11
Name ConDSCRtest: ConLoan!$C$17
Name ConDYtest: ConLoan!$C$16
Name ConLoanTotal: ConLoan!$C$37
Name ConMaturity: Timeline!$C$18
Name ConPayoffBal: ConLoan!$C$38
Name ConPayoffMonth: Timeline!$C$25
Name ConPoints: ConLoan!$C$9
Name ConRealizedLTC: ConLoan!$C$18
Name ConStart: Timeline!$C$17
Name DebtShare: ConLoan!$C$12
Name DebtYieldStab: Returns!$C$25
Name DeliverStart: Timeline!$C$19
Name DevSpreadBps: Returns!$C$22
Name DevSpreadPct: Returns!$C$21
Name DispoEffTaxRate: Operating!$C$55
Name DispoMonth: Timeline!$C$21
Name EffTaxRateOnValue: Operating!$C$54
Name EquityBudget: ConLoan!$C$13
Name EquityTotal: ConLoan!$C$40
Name ExitValue: Disposition!$C$10
Name FwdEGI: Disposition!$C$6
Name FwdNOIafter: Disposition!$C$5
Name FwdNOIbt: Disposition!$C$4
Name FwdRetail: Disposition!$C$7
Name GrossSale: Disposition!$C$13
Name GrowthStartMonth: Timeline!$C$22
Name InterestReserveAccrued: ConLoan!$C$35
Name InterestReserveFunded: ConLoan!$C$36
Name LevDistros: CashFlow!$C$11
Name LevEquityIn: CashFlow!$C$10
Name LevIRR: Returns!$C$4
Name LevIRRgross: Returns!$C$14
Name LevMOIC: Returns!$C$6
Name LevMOICgross: Returns!$C$16
Name LevNetProfit: CashFlow!$C$12
Name LowUnits: UnitMatrix!$C$16

Sheet Dashboard
B1: ="Multifamily Development Model — "&PropertyName
B2: =City&", "&State&" • "&TotalUnits&" units • "&TEXT(NRSF,"#,##0")&" NRSF"
B4: =IF(ErrorsFound=0,"✔ ALL CHECKS PASS — model is clean","⚠ "&ErrorsFound&" ERROR(S) FOUND — REVIEW DIAGNOSTICS") | F4: ="Warnings: "&WarningsFound
B6: Development Return (untrended) | E6: Cost & Basis
B7: Yield on Cost (untrended) | C7: =YieldOnCost | E7: Total Development Cost | F7: =TDC_Total
B8: Exit Cap Rate | C8: =ExitCapResidential | E8: TDC / Unit | F8: =TDCperUnit
B9: Development Spread | C9: =DevSpreadBps | E9: TDC / NRSF | F9: =TDCperSF
B10: Return on Cost (stabilized) | C10: =ROCstab | E10: Exit Value | F10: =ExitValue
B11: Debt Yield (stab, active loan) | C11: =DebtYieldStab | E11: Exit Basis / Unit | F11: =BasisPerUnitExit
E12: Static Value (untrended) | F12: =StaticValue
B13: Trended Performance (with growth) | E13: Sources & Uses
B14: Stabilized NOI (trended) | C14: =StabNOI | E14: Construction Loan | F14: =ConLoanTotal
E15: Equity | F15: =EquityTotal
B16: Returns | E16: Total Sources | F16: =ConLoanTotal+EquityTotal
B17: Levered IRR (net) | C17: =LevIRR | E17: Total Uses (TDC) | F17: =TDC_Total
B18: Levered IRR (gross) | C18: =LevIRRgross | E18: Sources − Uses (check) | F18: =ConLoanTotal+EquityTotal-TDC_Total
B19: Unlevered IRR (net) | C19: =UnlevIRR
B20: Levered MOIC (net) | C20: =LevMOIC | E20: Loan Sizing (binding constraint)
B21: Unlevered MOIC (net) | C21: =UnlevMOIC | E21: Refi or Sell | F21: =IF(RefiFlag=1,"Refinance then hold","Sell during construction")
B22: Static Unlevered IRR (no-growth) | C22: =StaticUnlevIRR | E22: Construction Loan — binding | F22: =ConBinding
E23: Con Debt Yield / DSCR | F23: =ConDYtest&" / "&ConDSCRtest
B24: Timeline (months) | E24: Permanent Loan — binding | F24: =PermBinding
B25: Construction Start → Maturity | C25: =ConStart&" → "&ConMaturity | E25: Perm LTV / DSCR | F25: =PermLTVtest&" / "&PermDSCRtest
B26: 1st Delivery → Stabilization | C26: =DeliverStart&" → "&StabMonth
B27: Refi / Disposition | C27: =IF(RefiFlag=1,RefiMonth,0)&" / "&DispoMonth | E27: Validation
E28: Errors / Warnings / Sanity flags | F28: =ErrorsFound&" / "&WarningsFound&" / "&SanityFlags

Sheet Annual
B1: Annual Summary
B2: ="Hold: "&HoldPeriodMonths&" months • Disposition month "&DispoMonth
B4: Sources & Uses
B5: Uses
B6: Land | C6: =BudgetLand
B7: Hard Costs | C7: =BudgetHard
B8: Soft Costs | C8: =BudgetSoft
B9: Development Fee | C9: =DevFee
B10: Loan Costs (points, recourse, other) | C10: =ConPoints+RecourseFee+ConOtherCosts
B11: Interest Reserve | C11: =InterestReserveFunded
B12: Operating Reserve | C12: =OpReserve
B13: Total Uses (TDC) | C13: =TDC_Total
B14: Sources
B15: Construction Loan | C15: =ConLoanTotal
B16: Equity | C16: =EquityTotal
B17: Refi Cash-Out (memo) | C17: =RefiCashOut
B18: Total Sources | C18: =ConLoanTotal+EquityTotal
B19: Sources − Uses (check = 0) | C19: =ConLoanTotal+EquityTotal-TDC_Total
B21: Annual Cash Flow (Year 1 … 31)
B22: Year → | C22: 1 | D22: 2 | E22: 3 | F22: 4 | G22: 5 | H22: 6 | I22: 7 | J22: 8 | K22: 9 | L22: 10 | M22: 11 | N22: 12 | O22: 13 | P22: 14 | Q22: 15 | R22: 16 | S22: 17 | T22: 18 | U22: 19 | V22: 20 | W22: 21 | X22: 22 | Y22: 23 | Z22: 24 | AA22: 25 | AB22: 26 | AC22: 27 | AD22: 28 | AE22: 29 | AF22: 30 | AG22: 31
B23: Development Cost (cash, ex-interest) | C23: =SUM(INDEX(ConLoan!$E$26:$NL$26,((C$22-1)*12+1)):INDEX(ConLoan!$E$26:$NL$26,((C$22-1)*12+1)+11)) | D23: =SUM(INDEX(ConLoan!$E$26:$NL$26,((D$22-1)*12+1)):INDEX(ConLoan!$E$26:$NL$26,((D$22-1)*12+1)+11)) | E23: =SUM(INDEX(ConLoan!$E$26:$NL$26,((E$22-1)*12+1)):INDEX(ConLoan!$E$26:$NL$26,((E$22-1)*12+1)+11)) | F23: =SUM(INDEX(ConLoan!$E$26:$NL$26,((F$22-1)*12+1)):INDEX(ConLoan!$E$26:$NL$26,((F$22-1)*12+1)+11)) | G23: =SUM(INDEX(ConLoan!$E$26:$NL$26,((G$22-1)*12+1)):INDEX(ConLoan!$E$26:$NL$26,((G$22-1)*12+1)+11)) | H23: =SUM(INDEX(ConLoan!$E$26:$NL$26,((H$22-1)*12+1)):INDEX(ConLoan!$E$26:$NL$26,((H$22-1)*12+1)+11)) | I23: =SUM(INDEX(ConLoan!$E$26:$NL$26,((I$22-1)*12+1)):INDEX(ConLoan!$E$26:$NL$26,((I$22-1)*12+1)+11)) | J23: =SUM(INDEX(ConLoan!$E$26:$NL$26,((J$22-1)*12+1)):INDEX(ConLoan!$E$26:$NL$26,((J$22-1)*12+1)+11)) | ... AG23: =SUM(INDEX(ConLoan!$E$26:$NL$26,((AG$22-1)*12+1)):INDEX(ConLoan!$E$26:$NL$26,((AG$22-1)*12+1)+11))
B24: Construction Debt Draw | C24: =SUM(INDEX(ConLoan!$E$29:$NL$29,((C$22-1)*12+1)):INDEX(ConLoan!$E$29:$NL$29,((C$22-1)*12+1)+11)) | D24: =SUM(INDEX(ConLoan!$E$29:$NL$29,((D$22-1)*12+1)):INDEX(ConLoan!$E$29:$NL$29,((D$22-1)*12+1)+11)) | E24: =SUM(INDEX(ConLoan!$E$29:$NL$29,((E$22-1)*12+1)):INDEX(ConLoan!$E$29:$NL$29,((E$22-1)*12+1)+11)) | F24: =SUM(INDEX(ConLoan!$E$29:$NL$29,((F$22-1)*12+1)):INDEX(ConLoan!$E$29:$NL$29,((F$22-1)*12+1)+11)) | G24: =SUM(INDEX(ConLoan!$E$29:$NL$29,((G$22-1)*12+1)):INDEX(ConLoan!$E$29:$NL$29,((G$22-1)*12+1)+11)) | H24: =SUM(INDEX(ConLoan!$E$29:$NL$29,((H$22-1)*12+1)):INDEX(ConLoan!$E$29:$NL$29,((H$22-1)*12+1)+11)) | I24: =SUM(INDEX(ConLoan!$E$29:$NL$29,((I$22-1)*12+1)):INDEX(ConLoan!$E$29:$NL$29,((I$22-1)*12+1)+11)) | J24: =SUM(INDEX(ConLoan!$E$29:$NL$29,((J$22-1)*12+1)):INDEX(ConLoan!$E$29:$NL$29,((J$22-1)*12+1)+11)) | ... AG24: =SUM(INDEX(ConLoan!$E$29:$NL$29,((AG$22-1)*12+1)):INDEX(ConLoan!$E$29:$NL$29,((AG$22-1)*12+1)+11))
B25: Equity Draw | C25: =SUM(INDEX(ConLoan!$E$27:$NL$27,((C$22-1)*12+1)):INDEX(ConLoan!$E$27:$NL$27,((C$22-1)*12+1)+11)) | D25: =SUM(INDEX(ConLoan!$E$27:$NL$27,((D$22-1)*12+1)):INDEX(ConLoan!$E$27:$NL$27,((D$22-1)*12+1)+11)) | E25: =SUM(INDEX(ConLoan!$E$27:$NL$27,((E$22-1)*12+1)):INDEX(ConLoan!$E$27:$NL$27,((E$22-1)*12+1)+11)) | F25: =SUM(INDEX(ConLoan!$E$27:$NL$27,((F$22-1)*12+1)):INDEX(ConLoan!$E$27:$NL$27,((F$22-1)*12+1)+11)) | G25: =SUM(INDEX(ConLoan!$E$27:$NL$27,((G$22-1)*12+1)):INDEX(ConLoan!$E$27:$NL$27,((G$22-1)*12+1)+11)) | H25: =SUM(INDEX(ConLoan!$E$27:$NL$27,((H$22-1)*12+1)):INDEX(ConLoan!$E$27:$NL$27,((H$22-1)*12+1)+11)) | I25: =SUM(INDEX(ConLoan!$E$27:$NL$27,((I$22-1)*12+1)):INDEX(ConLoan!$E$27:$NL$27,((I$22-1)*12+1)+11)) | J25: =SUM(INDEX(ConLoan!$E$27:$NL$27,((J$22-1)*12+1)):INDEX(ConLoan!$E$27:$NL$27,((J$22-1)*12+1)+11)) | ... AG25: =SUM(INDEX(ConLoan!$E$27:$NL$27,((AG$22-1)*12+1)):INDEX(ConLoan!$E$27:$NL$27,((AG$22-1)*12+1)+11))
B26: Effective Gross Income | C26: =SUM(INDEX(Operating!$E$23:$NL$23,((C$22-1)*12+1)):INDEX(Operating!$E$23:$NL$23,((C$22-1)*12+1)+11)) | D26: =SUM(INDEX(Operating!$E$23:$NL$23,((D$22-1)*12+1)):INDEX(Operating!$E$23:$NL$23,((D$22-1)*12+1)+11)) | E26: =SUM(INDEX(Operating!$E$23:$NL$23,((E$22-1)*12+1)):INDEX(Operating!$E$23:$NL$23,((E$22-1)*12+1)+11)) | F26: =SUM(INDEX(Operating!$E$23:$NL$23,((F$22-1)*12+1)):INDEX(Operating!$E$23:$NL$23,((F$22-1)*12+1)+11)) | G26: =SUM(INDEX(Operating!$E$23:$NL$23,((G$22-1)*12+1)):INDEX(Operating!$E$23:$NL$23,((G$22-1)*12+1)+11)) | H26: =SUM(INDEX(Operating!$E$23:$NL$23,((H$22-1)*12+1)):INDEX(Operating!$E$23:$NL$23,((H$22-1)*12+1)+11)) | I26: =SUM(INDEX(Operating!$E$23:$NL$23,((I$22-1)*12+1)):INDEX(Operating!$E$23:$NL$23,((I$22-1)*12+1)+11)) | J26: =SUM(INDEX(Operating!$E$23:$NL$23,((J$22-1)*12+1)):INDEX(Operating!$E$23:$NL$23,((J$22-1)*12+1)+11)) | ... AG26: =SUM(INDEX(Operating!$E$23:$NL$23,((AG$22-1)*12+1)):INDEX(Operating!$E$23:$NL$23,((AG$22-1)*12+1)+11))
B27: Net Operating Income | C27: =SUM(INDEX(Operating!$E$38:$NL$38,((C$22-1)*12+1)):INDEX(Operating!$E$38:$NL$38,((C$22-1)*12+1)+11)) | D27: =SUM(INDEX(Operating!$E$38:$NL$38,((D$22-1)*12+1)):INDEX(Operating!$E$38:$NL$38,((D$22-1)*12+1)+11)) | E27: =SUM(INDEX(Operating!$E$38:$NL$38,((E$22-1)*12+1)):INDEX(Operating!$E$38:$NL$38,((E$22-1)*12+1)+11)) | F27: =SUM(INDEX(Operating!$E$38:$NL$38,((F$22-1)*12+1)):INDEX(Operating!$E$38:$NL$38,((F$22-1)*12+1)+11)) | G27: =SUM(INDEX(Operating!$E$38:$NL$38,((G$22-1)*12+1)):INDEX(Operating!$E$38:$NL$38,((G$22-1)*12+1)+11)) | H27: =SUM(INDEX(Operating!$E$38:$NL$38,((H$22-1)*12+1)):INDEX(Operating!$E$38:$NL$38,((H$22-1)*12+1)+11)) | I27: =SUM(INDEX(Operating!$E$38:$NL$38,((I$22-1)*12+1)):INDEX(Operating!$E$38:$NL$38,((I$22-1)*12+1)+11)) | J27: =SUM(INDEX(Operating!$E$38:$NL$38,((J$22-1)*12+1)):INDEX(Operating!$E$38:$NL$38,((J$22-1)*12+1)+11)) | ... AG27: =SUM(INDEX(Operating!$E$38:$NL$38,((AG$22-1)*12+1)):INDEX(Operating!$E$38:$NL$38,((AG$22-1)*12+1)+11))
B28: Construction Interest (capitalized, financed) | C28: =SUM(INDEX(ConLoan!$E$31:$NL$31,((C$22-1)*12+1)):INDEX(ConLoan!$E$31:$NL$31,((C$22-1)*12+1)+11)) | D28: =SUM(INDEX(ConLoan!$E$31:$NL$31,((D$22-1)*12+1)):INDEX(ConLoan!$E$31:$NL$31,((D$22-1)*12+1)+11)) | E28: =SUM(INDEX(ConLoan!$E$31:$NL$31,((E$22-1)*12+1)):INDEX(ConLoan!$E$31:$NL$31,((E$22-1)*12+1)+11)) | F28: =SUM(INDEX(ConLoan!$E$31:$NL$31,((F$22-1)*12+1)):INDEX(ConLoan!$E$31:$NL$31,((F$22-1)*12+1)+11)) | G28: =SUM(INDEX(ConLoan!$E$31:$NL$31,((G$22-1)*12+1)):INDEX(ConLoan!$E$31:$NL$31,((G$22-1)*12+1)+11)) | H28: =SUM(INDEX(ConLoan!$E$31:$NL$31,((H$22-1)*12+1)):INDEX(ConLoan!$E$31:$NL$31,((H$22-1)*12+1)+11)) | I28: =SUM(INDEX(ConLoan!$E$31:$NL$31,((I$22-1)*12+1)):INDEX(ConLoan!$E$31:$NL$31,((I$22-1)*12+1)+11)) | J28: =SUM(INDEX(ConLoan!$E$31:$NL$31,((J$22-1)*12+1)):INDEX(ConLoan!$E$31:$NL$31,((J$22-1)*12+1)+11)) | ... AG28: =SUM(INDEX(ConLoan!$E$31:$NL$31,((AG$22-1)*12+1)):INDEX(ConLoan!$E$31:$NL$31,((AG$22-1)*12+1)+11))
B29: Permanent Debt Service | C29: =SUM(INDEX(PermLoan!$E$29:$NL$29,((C$22-1)*12+1)):INDEX(PermLoan!$E$29:$NL$29,((C$22-1)*12+1)+11)) | D29: =SUM(INDEX(PermLoan!$E$29:$NL$29,((D$22-1)*12+1)):INDEX(PermLoan!$E$29:$NL$29,((D$22-1)*12+1)+11)) | E29: =SUM(INDEX(PermLoan!$E$29:$NL$29,((E$22-1)*12+1)):INDEX(PermLoan!$E$29:$NL$29,((E$22-1)*12+1)+11)) | F29: =SUM(INDEX(PermLoan!$E$29:$NL$29,((F$22-1)*12+1)):INDEX(PermLoan!$E$29:$NL$29,((F$22-1)*12+1)+11)) | G29: =SUM(INDEX(PermLoan!$E$29:$NL$29,((G$22-1)*12+1)):INDEX(PermLoan!$E$29:$NL$29,((G$22-1)*12+1)+11)) | H29: =SUM(INDEX(PermLoan!$E$29:$NL$29,((H$22-1)*12+1)):INDEX(PermLoan!$E$29:$NL$29,((H$22-1)*12+1)+11)) | I29: =SUM(INDEX(PermLoan!$E$29:$NL$29,((I$22-1)*12+1)):INDEX(PermLoan!$E$29:$NL$29,((I$22-1)*12+1)+11)) | J29: =SUM(INDEX(PermLoan!$E$29:$NL$29,((J$22-1)*12+1)):INDEX(PermLoan!$E$29:$NL$29,((J$22-1)*12+1)+11)) | ... AG29: =SUM(INDEX(PermLoan!$E$29:$NL$29,((AG$22-1)*12+1)):INDEX(PermLoan!$E$29:$NL$29,((AG$22-1)*12+1)+11))
B30: Unlevered Cash Flow | C30: =SUM(INDEX(CashFlow!$E$7:$NL$7,((C$22-1)*12+1)):INDEX(CashFlow!$E$7:$NL$7,((C$22-1)*12+1)+11)) | D30: =SUM(INDEX(CashFlow!$E$7:$NL$7,((D$22-1)*12+1)):INDEX(CashFlow!$E$7:$NL$7,((D$22-1)*12+1)+11)) | E30: =SUM(INDEX(CashFlow!$E$7:$NL$7,((E$22-1)*12+1)):INDEX(CashFlow!$E$7:$NL$7,((E$22-1)*12+1)+11)) | F30: =SUM(INDEX(CashFlow!$E$7:$NL$7,((F$22-1)*12+1)):INDEX(CashFlow!$E$7:$NL$7,((F$22-1)*12+1)+11)) | G30: =SUM(INDEX(CashFlow!$E$7:$NL$7,((G$22-1)*12+1)):INDEX(CashFlow!$E$7:$NL$7,((G$22-1)*12+1)+11)) | H30: =SUM(INDEX(CashFlow!$E$7:$NL$7,((H$22-1)*12+1)):INDEX(CashFlow!$E$7:$NL$7,((H$22-1)*12+1)+11)) | I30: =SUM(INDEX(CashFlow!$E$7:$NL$7,((I$22-1)*12+1)):INDEX(CashFlow!$E$7:$NL$7,((I$22-1)*12+1)+11)) | J30: =SUM(INDEX(CashFlow!$E$7:$NL$7,((J$22-1)*12+1)):INDEX(CashFlow!$E$7:$NL$7,((J$22-1)*12+1)+11)) | ... AG30: =SUM(INDEX(CashFlow!$E$7:$NL$7,((AG$22-1)*12+1)):INDEX(CashFlow!$E$7:$NL$7,((AG$22-1)*12+1)+11))
B31: Levered Cash Flow | C31: =SUM(INDEX(CashFlow!$E$6:$NL$6,((C$22-1)*12+1)):INDEX(CashFlow!$E$6:$NL$6,((C$22-1)*12+1)+11)) | D31: =SUM(INDEX(CashFlow!$E$6:$NL$6,((D$22-1)*12+1)):INDEX(CashFlow!$E$6:$NL$6,((D$22-1)*12+1)+11)) | E31: =SUM(INDEX(CashFlow!$E$6:$NL$6,((E$22-1)*12+1)):INDEX(CashFlow!$E$6:$NL$6,((E$22-1)*12+1)+11)) | F31: =SUM(INDEX(CashFlow!$E$6:$NL$6,((F$22-1)*12+1)):INDEX(CashFlow!$E$6:$NL$6,((F$22-1)*12+1)+11)) | G31: =SUM(INDEX(CashFlow!$E$6:$NL$6,((G$22-1)*12+1)):INDEX(CashFlow!$E$6:$NL$6,((G$22-1)*12+1)+11)) | H31: =SUM(INDEX(CashFlow!$E$6:$NL$6,((H$22-1)*12+1)):INDEX(CashFlow!$E$6:$NL$6,((H$22-1)*12+1)+11)) | I31: =SUM(INDEX(CashFlow!$E$6:$NL$6,((I$22-1)*12+1)):INDEX(CashFlow!$E$6:$NL$6,((I$22-1)*12+1)+11)) | J31: =SUM(INDEX(CashFlow!$E$6:$NL$6,((J$22-1)*12+1)):INDEX(CashFlow!$E$6:$NL$6,((J$22-1)*12+1)+11)) | ... AG31: =SUM(INDEX(CashFlow!$E$6:$NL$6,((AG$22-1)*12+1)):INDEX(CashFlow!$E$6:$NL$6,((AG$22-1)*12+1)+11))
B32: Construction Loan Balance (EOY) | C32: =INDEX(ConLoan!$E$32:$NL$32,((C$22-1)*12+1)+11) | D32: =INDEX(ConLoan!$E$32:$NL$32,((D$22-1)*12+1)+11) | E32: =INDEX(ConLoan!$E$32:$NL$32,((E$22-1)*12+1)+11) | F32: =INDEX(ConLoan!$E$32:$NL$32,((F$22-1)*12+1)+11) | G32: =INDEX(ConLoan!$E$32:$NL$32,((G$22-1)*12+1)+11) | H32: =INDEX(ConLoan!$E$32:$NL$32,((H$22-1)*12+1)+11) | I32: =INDEX(ConLoan!$E$32:$NL$32,((I$22-1)*12+1)+11) | J32: =INDEX(ConLoan!$E$32:$NL$32,((J$22-1)*12+1)+11) | ... AG32: =INDEX(ConLoan!$E$32:$NL$32,((AG$22-1)*12+1)+11)
B33: Permanent Loan Balance (EOY) | C33: =INDEX(PermLoan!$E$30:$NL$30,((C$22-1)*12+1)+11) | D33: =INDEX(PermLoan!$E$30:$NL$30,((D$22-1)*12+1)+11) | E33: =INDEX(PermLoan!$E$30:$NL$30,((E$22-1)*12+1)+11) | F33: =INDEX(PermLoan!$E$30:$NL$30,((F$22-1)*12+1)+11) | G33: =INDEX(PermLoan!$E$30:$NL$30,((G$22-1)*12+1)+11) | H33: =INDEX(PermLoan!$E$30:$NL$30,((H$22-1)*12+1)+11) | I33: =INDEX(PermLoan!$E$30:$NL$30,((I$22-1)*12+1)+11) | J33: =INDEX(PermLoan!$E$30:$NL$30,((J$22-1)*12+1)+11) | ... AG33: =INDEX(PermLoan!$E$30:$NL$30,((AG$22-1)*12+1)+11)
B34: Physical Occupancy (EOY) | C34: =INDEX(LeaseUp!$E$10:$NL$10,((C$22-1)*12+1)+11) | D34: =INDEX(LeaseUp!$E$10:$NL$10,((D$22-1)*12+1)+11) | E34: =INDEX(LeaseUp!$E$10:$NL$10,((E$22-1)*12+1)+11) | F34: =INDEX(LeaseUp!$E$10:$NL$10,((F$22-1)*12+1)+11) | G34: =INDEX(LeaseUp!$E$10:$NL$10,((G$22-1)*12+1)+11) | H34: =INDEX(LeaseUp!$E$10:$NL$10,((H$22-1)*12+1)+11) | I34: =INDEX(LeaseUp!$E$10:$NL$10,((I$22-1)*12+1)+11) | J34: =INDEX(LeaseUp!$E$10:$NL$10,((J$22-1)*12+1)+11) | ... AG34: =INDEX(LeaseUp!$E$10:$NL$10,((AG$22-1)*12+1)+11)
B36: Check: ΣAnnual NOI − monthly total | C36: =SUM(C27:AG27)-Operating!$D$38
B37: Check: Σ Dev Cost + Σ Cap. Interest − TDC | C37: =SUM(C23:AG23)+SUM(C28:AG28)-TDC_Total | D37: =IF(ABS(C37)<1,"PASS","FAIL")

Sheet Proforma
B1: Stabilized Operating Proforma — Untrended
B2: =""&PropertyName&" • "&City&", "&State&" • point-in-time at stabilized occupancy (no growth trending)"
B4: Basis
B5: Total Units | C5: =TotalUnits | E5: Occupied Units (stab) | F5: =StabLeasedTarget
B6: Net Rentable SF | C6: =NRSF | E6: Stabilized Occupancy | F6: =StabilizedOccupancy
B7: Avg Unit SF | C7: =AvgUnitSF | E7: Effective Tax Rate on Value | F7: =EffTaxRateOnValue
B10: Untrended Stabilized Proforma | C10: % of / amt | D10: $ / SF /mo | E10: $ / Unit /mo | F10: $ / Month | G10: $ / Year | H10: Trended $/yr (ref)
B11: Revenue
B12: Gross Potential Rent | C12: =(BaseMarketRentMo+BaseLowRentMo)/TotalUnits | D12: =IF(NRSF=0,0,G12/12/NRSF) | E12: =IF(TotalUnits=0,0,G12/12/TotalUnits) | F12: =G12/12 | G12: =(BaseMarketRentMo+BaseLowRentMo)*12 | H12: =SUM(INDEX(Operating!$E$14:$NL$14,StabMonth):INDEX(Operating!$E$14:$NL$14,StabMonth+11))
B13: Vacancy Loss | C13: -0.06 | D13: =IF(NRSF=0,0,G13/12/NRSF) | E13: =IF(TotalUnits=0,0,G13/12/TotalUnits) | F13: =G13/12 | G13: =G12*VacancyPct | H13: =SUM(INDEX(Operating!$E$15:$NL$15,StabMonth):INDEX(Operating!$E$15:$NL$15,StabMonth+11))
B14: Gain / (Loss) to Lease | C14: 0 | D14: =IF(NRSF=0,0,G14/12/NRSF) | E14: =IF(TotalUnits=0,0,G14/12/TotalUnits) | F14: =G14/12 | G14: =G12*LossToLeasePct | H14: =SUM(INDEX(Operating!$E$16:$NL$16,StabMonth):INDEX(Operating!$E$16:$NL$16,StabMonth+11))
B15: Bad Debt | C15: -0.005 | D15: =IF(NRSF=0,0,G15/12/NRSF) | E15: =IF(TotalUnits=0,0,G15/12/TotalUnits) | F15: =G15/12 | G15: =G12*BadDebtPct | H15: =SUM(INDEX(Operating!$E$17:$NL$17,StabMonth):INDEX(Operating!$E$17:$NL$17,StabMonth+11))
B16: Concessions | C16: 0 | D16: =IF(NRSF=0,0,G16/12/NRSF) | E16: =IF(TotalUnits=0,0,G16/12/TotalUnits) | F16: =G16/12 | G16: =G12*ConcessionsPct | H16: =SUM(INDEX(Operating!$E$18:$NL$18,StabMonth):INDEX(Operating!$E$18:$NL$18,StabMonth+11))
B17: Model / Down Units | C17: 1 | D17: =IF(NRSF=0,0,G17/12/NRSF) | E17: =IF(TotalUnits=0,0,G17/12/TotalUnits) | F17: =G17/12 | G17: =-G12*ModelUnits/TotalUnits
B18: Parking & Storage | C18: 50 | D18: =IF(NRSF=0,0,G18/12/NRSF) | E18: =IF(TotalUnits=0,0,G18/12/TotalUnits) | F18: =G18/12 | G18: =ParkingPerUnitMo*StabLeasedTarget*12 | H18: =SUM(INDEX(Operating!$E$19:$NL$19,StabMonth):INDEX(Operating!$E$19:$NL$19,StabMonth+11))
B19: Utility Reimbursement | C19: 50 | D19: =IF(NRSF=0,0,G19/12/NRSF) | E19: =IF(TotalUnits=0,0,G19/12/TotalUnits) | F19: =G19/12 | G19: =UtilReimbPerUnitMo*StabLeasedTarget*12 | H19: =SUM(INDEX(Operating!$E$20:$NL$20,StabMonth):INDEX(Operating!$E$20:$NL$20,StabMonth+11))
B20: Other Income | C20: 50 | D20: =IF(NRSF=0,0,G20/12/NRSF) | E20: =IF(TotalUnits=0,0,G20/12/TotalUnits) | F20: =G20/12 | G20: =OtherIncPerUnitMo*StabLeasedTarget*12 | H20: =SUM(INDEX(Operating!$E$21:$NL$21,StabMonth):INDEX(Operating!$E$21:$NL$21,StabMonth+11))
B21: Retail Income | C21: =RetailRentMo | D21: =IF(NRSF=0,0,G21/12/NRSF) | E21: =IF(TotalUnits=0,0,G21/12/TotalUnits) | F21: =G21/12 | G21: =RetailRentMo*StabilizedOccupancy*12 | H21: =SUM(INDEX(Operating!$E$22:$NL$22,StabMonth):INDEX(Operating!$E$22:$NL$22,StabMonth+11))
B22: Effective Gross Income | D22: =IF(NRSF=0,0,G22/12/NRSF) | E22: =IF(TotalUnits=0,0,G22/12/TotalUnits) | F22: =G22/12 | G22: =SUM(G12:G21) | H22: =SUM(INDEX(Operating!$E$23:$NL$23,StabMonth):INDEX(Operating!$E$23:$NL$23,StabMonth+11))
B23: Operating Expenses
B24: Insurance | C24: 500 | D24: =IF(NRSF=0,0,G24/12/NRSF) | E24: =IF(TotalUnits=0,0,G24/12/TotalUnits) | F24: =G24/12 | G24: =ExpInsurancePerUnit*TotalUnits | H24: =SUM(INDEX(Operating!$E$25:$NL$25,StabMonth):INDEX(Operating!$E$25:$NL$25,StabMonth+11))
B25: Utilities | C25: 1000 | D25: =IF(NRSF=0,0,G25/12/NRSF) | E25: =IF(TotalUnits=0,0,G25/12/TotalUnits) | F25: =G25/12 | G25: =ExpUtilitiesPerUnit*TotalUnits | H25: =SUM(INDEX(Operating!$E$27:$NL$27,StabMonth):INDEX(Operating!$E$27:$NL$27,StabMonth+11))
B26: Payroll | C26: 1544 | D26: =IF(NRSF=0,0,G26/12/NRSF) | E26: =IF(TotalUnits=0,0,G26/12/TotalUnits) | F26: =G26/12 | G26: =ExpPayrollPerUnit*TotalUnits | H26: =SUM(INDEX(Operating!$E$31:$NL$31,StabMonth):INDEX(Operating!$E$31:$NL$31,StabMonth+11))
B27: Management Fee | C27: 0.034 | D27: =IF(NRSF=0,0,G27/12/NRSF) | E27: =IF(TotalUnits=0,0,G27/12/TotalUnits) | F27: =G27/12 | G27: =MgmtFeePct*G22 | H27: =SUM(INDEX(Operating!$E$33:$NL$33,StabMonth):INDEX(Operating!$E$33:$NL$33,StabMonth+11))
B28: Repairs & Maintenance | C28: 365 | D28: =IF(NRSF=0,0,G28/12/NRSF) | E28: =IF(TotalUnits=0,0,G28/12/TotalUnits) | F28: =G28/12 | G28: =ExpRMPerUnit*TotalUnits | H28: =SUM(INDEX(Operating!$E$28:$NL$28,StabMonth):INDEX(Operating!$E$28:$NL$28,StabMonth+11))
B29: Turnover | C29: 335 | D29: =IF(NRSF=0,0,G29/12/NRSF) | E29: =IF(TotalUnits=0,0,G29/12/TotalUnits) | F29: =G29/12 | G29: =ExpTurnoverPerUnit*TotalUnits | H29: =SUM(INDEX(Operating!$E$29:$NL$29,StabMonth):INDEX(Operating!$E$29:$NL$29,StabMonth+11))
B30: Contract Services | C30: =441+408 | D30: =IF(NRSF=0,0,G30/12/NRSF) | E30: =IF(TotalUnits=0,0,G30/12/TotalUnits) | F30: =G30/12 | G30: =ExpContractPerUnit*TotalUnits | H30: =SUM(INDEX(Operating!$E$30:$NL$30,StabMonth):INDEX(Operating!$E$30:$NL$30,StabMonth+11))
B31: Admin & Legal | C31: 478 | D31: =IF(NRSF=0,0,G31/12/NRSF) | E31: =IF(TotalUnits=0,0,G31/12/TotalUnits) | F31: =G31/12 | G31: =ExpAdminPerUnit*TotalUnits | H31: =SUM(INDEX(Operating!$E$26:$NL$26,StabMonth):INDEX(Operating!$E$26:$NL$26,StabMonth+11))
B32: Advertising | C32: 200 | D32: =IF(NRSF=0,0,G32/12/NRSF) | E32: =IF(TotalUnits=0,0,G32/12/TotalUnits) | F32: =G32/12 | G32: =ExpAdvertisingPerUnit*TotalUnits | H32: =SUM(INDEX(Operating!$E$32:$NL$32,StabMonth):INDEX(Operating!$E$32:$NL$32,StabMonth+11))
B33: Property Taxes | C33: =UntrendedTaxRate | D33: =IF(NRSF=0,0,G33/12/NRSF) | E33: =IF(TotalUnits=0,0,G33/12/TotalUnits) | F33: =G33/12 | G33: =IF(TaxYear1Override>0,TaxYear1Override,(G22-SUM(G24:G32))/(EntryCapRate+UntrendedTaxRate)*UntrendedTaxRate) | H33: =SUM(INDEX(Operating!$E$36:$NL$36,StabMonth):INDEX(Operating!$E$36:$NL$36,StabMonth+11))
B34: Total Operating Expenses | D34: =IF(NRSF=0,0,G34/12/NRSF) | E34: =IF(TotalUnits=0,0,G34/12/TotalUnits) | F34: =G34/12 | G34: =SUM(G24:G33) | H34: =SUM(INDEX(Operating!$E$37:$NL$37,StabMonth):INDEX(Operating!$E$37:$NL$37,StabMonth+11))
B35: Net Operating Income | D35: =IF(NRSF=0,0,G35/12/NRSF) | E35: =IF(TotalUnits=0,0,G35/12/TotalUnits) | F35: =G35/12 | G35: =G22-G34 | H35: =SUM(INDEX(Operating!$E$38:$NL$38,StabMonth):INDEX(Operating!$E$38:$NL$38,StabMonth+11))
B36: Below-the-Line Expenses
B37: Capital Reserves | C37: 300 | D37: =IF(NRSF=0,0,G37/12/NRSF) | E37: =IF(TotalUnits=0,0,G37/12/TotalUnits) | F37: =G37/12 | G37: =CapReservePerUnit*TotalUnits
B38: Tax Prep & Appraisal | C38: 0 | D38: =IF(NRSF=0,0,G38/12/NRSF) | E38: =IF(TotalUnits=0,0,G38/12/TotalUnits) | F38: =G38/12 | G38: =TaxPrepPerUnit*TotalUnits
B39: Asset Management Fees | C39: 0.01 | D39: =IF(NRSF=0,0,G39/12/NRSF) | E39: =IF(TotalUnits=0,0,G39/12/TotalUnits) | F39: =G39/12 | G39: =AssetMgmtFeePct*G22
B40: Total Below-the-Line | D40: =IF(NRSF=0,0,G40/12/NRSF) | E40: =IF(TotalUnits=0,0,G40/12/TotalUnits) | F40: =G40/12 | G40: =SUM(G37:G39)
B41: Proforma Operating Cash Flow | D41: =IF(NRSF=0,0,G41/12/NRSF) | E41: =IF(TotalUnits=0,0,G41/12/TotalUnits) | F41: =G41/12 | G41: =G35-G40 | H41: =SUM(INDEX(Operating!$E$42:$NL$42,StabMonth):INDEX(Operating!$E$42:$NL$42,StabMonth+11))
B43: Untrended Stabilized NOI before Property Tax | G43: =G22-SUM(G24:G32)
B45: Reconciliation
B46: Untrended NOI ≤ Trended NOI (growth ≥ 0) | C46: =StabNOI_Untrended-StabNOI | D46: =IF(OR(GrowthRent<0,GrowthExpense<0),"n/a",IF(StabNOI_Untrended<=StabNOI+1,"PASS","FAIL"))
B47: Untrended YOC (StabNOI_Untrended / TDC) | C47: =IF(TDC_Total=0,0,StabNOI_Untrended/TDC_Total) | D47: =IF(YieldOnCost-ExitCapResidential<0,"SPREAD<0","OK")
B49: Untrended Tax Rate (reassess-aware) | C49: =IF(ReassessOnSale>=1,DispoEffTaxRate,EffTaxRateOnValue)

Sheet Inputs
B1: ="Multifamily Development Model — Master Input | "&PropertyName
B3: Levered IRR (net) | E3: Levered MOIC | H3: Untrended YOC | K3: Dev Spread | N3: TDC | Q3: TDC / Unit
B4: =LevIRR | E4: =LevMOIC | H4: =YieldOnCost | K4: =DevSpreadBps | N4: =TDC_Total | R4: =TDCperUnit
B6: Unlevered IRR (net) | E6: Unlevered MOIC | H6: Static Value | K6: Realized LTC | N6: Debt Yield (stab) | Q6: Model Status
B7: =UnlevIRR | E7: =UnlevMOIC | H7: =StaticValue | K7: =LTC_Realized | N7: =DebtYieldStab | Q7: =IF(ErrorsFound=0,"PASS","REVIEW")
B8: Property Details | J8: Permanent Loan (Refinance) | N8: Site Details | R8: Derived & Static Value
B9: Investment Type | C9: Ground-Up Development | J9: Perm Max LTV | K9: 0.65 | N9: Land Cost | O9: 567000 | R9: Effective Tax Rate on Value | S9: =TaxLevyPct*TaxAssessmentPct*TaxValueAdjFactor
B10: Property Name | C10: The Verde | J10: Perm Rate | K10: 0.0625 | N10: Gross Acres | O10: 3.65 | R10: Stabilized Tax / Unit / Yr | S10: =IF(TotalUnits=0,0,StabTaxAnnual/TotalUnits)
B11: City | C11: Cottonwood | J11: Perm Term (mo) | K11: 360 | N11: Net Acres | O11: =+GrossAcres | R11: Static Value (Untrended NOI ÷ Entry Cap) | S11: =IF(EntryCapRate=0,0,StabNOI_Untrended/EntryCapRate)
B12: State | C12: AZ | J12: Perm I/O (mo) | K12: 24 | N12: FAR Ratio | O12: 1.75 | R12: Static Value / Unit | S12: =IF(TotalUnits=0,0,StaticValue/TotalUnits)
B13: Market | C13: Verde Valley | J13: Perm Amort (mo) | K13: 360 | N13: Efficiency Ratio | O13: 0.85 | R13: Density (units / net acre) | S13: =IF(NetAcres=0,0,TotalUnits/NetAcres)
B14: Product Type | C14: Garden | J14: Perm Interest Calc | K14: 30/360 | L14: =IF(K14="Actual/360",1,0) | N14: Existing Structure Cost | O14: 0 | R14: Max Buildable SF by FAR | S14: =FARRatio*NetAcres*43560
B15: Location | C15: Suburban | J15: Perm Points | K15: 0.0075
B16: Open Escrow Date | C16: 46210 | J16: Perm Min Debt Yield | K16: 0.08 | R16: Input Sanity (soft warnings)
J17: Perm Min DSCR | K17: 1.15 | R17: Construction term ≤ 48 mo | S17: =ConLoanTermMonths | T17: =IF(ConLoanTermMonths<=48,"OK","CHECK")
B18: Investment Details | J18: Cash-Out at Refi | K18: Cash-Out Permitted | L18: =IF(K18="No Cash-Out (solve LTV to zero)",1,0) | R18: Stab tax/unit $500–$4,000 | S18: =IF(TotalUnits=0,0,StabTaxAnnual/TotalUnits) | T18: =IF(AND(StabTaxAnnual/TotalUnits>=500,StabTaxAnnual/TotalUnits<=4000),"OK","CHECK")
B19: Hold Period (mo) | C19: 120 | J19: Refi Month Override | K19: 0 | R19: Absorption ≤ delivery pace | S19: =UnitsLeasedPerMo | T19: =IF(UnitsLeasedPerMo<=UnitsDeliveredPerMo,"OK","CHECK")
B20: Entry Cap Rate | C20: 0.0525 | R20: Untrended YOC ≥ exit cap | S20: =YieldOnCost-ExitCapResidential | T20: =IF(YieldOnCost>=ExitCapResidential,"OK","CHECK")
F21: Capitalization & Funding | J21: Sponsor Fees | R21: Occupancy 85%–98% | S21: =StabilizedOccupancy | T21: =IF(AND(StabilizedOccupancy>=0.85,StabilizedOccupancy<=0.98),"OK","CHECK")
B22: Cap Rate & Adjustments | F22: Funding Order | G22: Equity First | H22: =IF(G22="Pari-Passu",1,0) | J22: Dev Fee % of Direct | K22: 0 | R22: Rent growth ≤ 5% | S22: =GrowthRent | T22: =IF(GrowthRent<=0.05,"OK","CHECK")
B23: Cap Adj — Location | C23: 0 | F23: Target LTC | G23: 0.65 | J23: 3rd-Party Fee Split | K23: 0 | R23: Sanity checks flagged | S23: =COUNTIF(T17:T22,"CHECK")
B24: Cap Adj — Size | C24: 0 | F24: Op Reserve Coverage | G24: 1.1 | J24: Sponsor Dispo Fee | K24: 0
B25: Cap Adj — Aging | C25: 0 | F25: Op Reserve Min Months | G25: 3 | J25: Recourse Fee | K25: 0
B26: Exit Cap — Residential | C26: =EntryCapRate+CapAdjLocation+CapAdjSize+CapAdjAging
B27: Exit Cap — Retail | C27: 0.065 | F27: Construction Loan | J27: Disposition & Sale
F28: Con Loan Term (mo) | G28: 36 | J28: Broker / Sale Cost | K28: 0.01
B29: Default Growth Rates | F29: Con Rate | G29: 0.057 | J29: Transfer / Sales Tax | K29: 0
B30: Rent Growth | C30: 0.03 | F30: Con Interest Calc | G30: Actual/360 | H30: =IF(G30="Actual/360",1,0) | J30: Tax Proration (mo) | K30: 2
B31: Low-Income Rent Growth | C31: 0.03 | F31: Con Points | G31: 0.01
B32: Expense Growth | C32: 0.03 | F32: Con Other Costs | G32: 250000 | J32: Property Taxes
B33: Utility Growth | C33: 0.03 | F33: Con Min Debt Yield | G33: 0.07 | J33: Tax Levy % | K33: 0.0185
B34: Tax Growth | C34: 0.03 | F34: Con Min DSCR | G34: 1.15 | J34: Assessment Ratio % | K34: 0.1
B35: Other-Income Growth | C35: 0.03 | F35: Lender Reserve Override | G35: 0 | J35: Value-Adj Factor | K35: 0.5
B36: Growth Start Date (effective) | C36: =IF(ISNUMBER(GrowthStartOverride),GrowthStartOverride,EOMONTH(InceptionDate,1)) | J36: Post-Stab Tax Method | K36: Value Approach | L36: =IF(K36="Value Approach",1,0)
B37: → Override (blank = auto) | F37: Construction Interest & Refi | J37: Year-1 Tax Override | K37: 0
B38: Unit Delivery & Lease-Up | F38: Refi Lag (mo) | G38: 1 | J38: Dispo Tax Driver | K38: Imputed | L38: =IF(K38="Reassessed",1,0)
B39: Lease-Up Income | C39: Offset vs equity | D39: =IF(C39="Offset vs equity",1,0) | F39: Interest Method | G39: Current Pay | H39: =IF(G39="Current Pay",1,0) | J39: Buyer Tax Rate | K39: 0
B40: Units Delivered / Mo | C40: 24 | F40: Interest Conversion Mo | G40: 0 | J40: Lease-Up Tax | K40: Capitalize in budget | L40: =IF(K40="Capitalize in budget",1,0)
B41: Units Leased / Mo | C41: 18
B42: Lease-Up Opex Ramp | C42: 0.6
B43: Lease-Up Opex Uplift | C43: 0.25
B44: Stabilized Occupancy (= 1 + vacancy, derived) | C44: =1+VacancyPct
B45: Delivery Lag (mo) | C45: 19

Sheet UnitMatrix
B1: Unit Matrix — Residential & Retail
B3: Plan | C3: Class | D3: Units | E3: Avg SF | F3: Total SF | G3: Market Rent | H3: Net Eff. Rent | I3: Annual Rent | J3: Rent / SF | K3: % of Total
B4: Studio | C4: Market | D4: 30 | E4: 750 | F4: =D4*E4 | G4: 1625 | H4: =+G4 | I4: =D4*G4*12 | J4: =IF(E4=0,0,G4/E4) | K4: =IF(TotalUnits=0,0,D4/TotalUnits)
B5: 1BR-A | C5: Market | D5: 38 | E5: 1025 | F5: =D5*E5 | G5: 1850 | H5: =+G5 | I5: =D5*G5*12 | J5: =IF(E5=0,0,G5/E5) | K5: =IF(TotalUnits=0,0,D5/TotalUnits)
B6: 1BR-B | C6: Market | D6: 0 | E6: 0 | F6: =D6*E6 | G6: 0 | H6: =+G6 | I6: =D6*G6*12 | J6: =IF(E6=0,0,G6/E6) | K6: =IF(TotalUnits=0,0,D6/TotalUnits)
B7: 2BR-A | C7: Market | D7: 0 | E7: 0 | F7: =D7*E7 | G7: 0 | H7: =+G7 | I7: =D7*G7*12 | J7: =IF(E7=0,0,G7/E7) | K7: =IF(TotalUnits=0,0,D7/TotalUnits)
B8: 2BR-B | C8: Market | D8: 0 | E8: 0 | F8: =D8*E8 | G8: 0 | H8: =+G8 | I8: =D8*G8*12 | J8: =IF(E8=0,0,G8/E8) | K8: =IF(TotalUnits=0,0,D8/TotalUnits)
B9: 1BR-LI | C9: Low | D9: 0 | E9: 0 | F9: =D9*E9 | G9: 0 | H9: =+G9 | I9: =D9*G9*12 | J9: =IF(E9=0,0,G9/E9) | K9: =IF(TotalUnits=0,0,D9/TotalUnits)
B10: 2BR-LI | C10: Low | D10: 0 | E10: 0 | F10: =D10*E10 | G10: 0 | H10: =+G10 | I10: =D10*G10*12 | J10: =IF(E10=0,0,G10/E10) | K10: =IF(TotalUnits=0,0,D10/TotalUnits)
B11: Total / Weighted | D11: =SUM(D4:D10) | E11: =SUMPRODUCT(E4:E10,$D$4:$D$10)/$D$11 | F11: =SUM(F4:F10) | G11: =SUMPRODUCT(G4:G10,$D$4:$D$10)/$D$11 | H11: =SUMPRODUCT(H4:H10,$D$4:$D$10)/$D$11 | I11: =SUM(I4:I10) | J11: =SUMPRODUCT(J4:J10,$D$4:$D$10)/$D$11 | K11: =SUM(K4:K10)
B13: Derived Unit Metrics
B14: Total Units | C14: =SUM(D4:D10)
B15: Market-Rate Units | C15: =SUMIF(C4:C10,"Market",D4:D10)
B16: Low-Income Units | C16: =SUMIF(C4:C10,"Low",D4:D10)
B17: Net Rentable SF (NRSF) | C17: =SUM(F4:F10)
B18: Buildable SF | C18: =NRSF/EfficiencyRatio
B19: Avg Unit SF | C19: =IF(TotalUnits=0,0,NRSF/TotalUnits)
B20: Base Market Rent / mo | C20: =SUMPRODUCT((C4:C10="Market")*D4:D10*G4:G10)
B21: Base Low-Income Rent / mo | C21: =SUMPRODUCT((C4:C10="Low")*D4:D10*G4:G10)
B23: Retail Matrix
B24: Suite | C24: SF | D24: Rent / SF / yr | E24: Annual Rent | F24: Monthly Rent
B25: Retail-1 | C25: 0 | D25: 0 | E25: =C25*D25 | F25: =C25*D25/12
B26: Retail-2 | C26: 0 | D26: 0 | E26: =C26*D26 | F26: =C26*D26/12
B27: Retail Rent / mo | C27: =SUM(F25:F26)

Sheet Budget
B1: Development Budget & Cost Assumptions
B2: Basis: abs=$ unit=$/unit sf=$/NRSF. Modifier shifts the phase start/end by whole months (+later / −earlier). Modeled Total drives the cost-curve engine.
I3: ± months vs. phase
B4: Line Item | C4: Group | D4: Type | E4: Basis | F4: Amount | G4: Phase | H4: Cost Curve | I4: Modifier (months) | J4: Modeled Total | K4: Per Unit | L4: Per SF | M4: % of TDC
B5: Land Purchase Costs | C5: Land | D5: Land | E5: abs | F5: =LandCost | G5: Pre-Construction | H5: Single_Point | I5: 0 | J5: =IF(E5="abs",F5,IF(E5="unit",F5*TotalUnits,IF(E5="sf",F5*NRSF,F5))) | K5: =IF(TotalUnits=0,0,J5/TotalUnits) | L5: =IF(NRSF=0,0,J5/NRSF) | M5: =IF(TDC_Total=0,0,J5/TDC_Total)
B6: Broker Fee | C6: Land | D6: Land | E6: abs | F6: 0 | G6: Entitlement | H6: Single_Point | I6: 0 | J6: =IF(E6="abs",F6,IF(E6="unit",F6*TotalUnits,IF(E6="sf",F6*NRSF,F6))) | K6: =IF(TotalUnits=0,0,J6/TotalUnits) | L6: =IF(NRSF=0,0,J6/NRSF) | M6: =IF(TDC_Total=0,0,J6/TDC_Total)
B7: Other Land Cost | C7: Land | D7: Land | E7: abs | F7: 0 | G7: Entitlement | H7: Single_Point | I7: 0 | J7: =IF(E7="abs",F7,IF(E7="unit",F7*TotalUnits,IF(E7="sf",F7*NRSF,F7))) | K7: =IF(TotalUnits=0,0,J7/TotalUnits) | L7: =IF(NRSF=0,0,J7/NRSF) | M7: =IF(TDC_Total=0,0,J7/TDC_Total)
B8: Legal: Entity Formation | C8: Soft | D8: Due Diligence | E8: abs | F8: 0 | G8: Entitlement | H8: Straight_Line | I8: 0 | J8: =IF(E8="abs",F8,IF(E8="unit",F8*TotalUnits,IF(E8="sf",F8*NRSF,F8))) | K8: =IF(TotalUnits=0,0,J8/TotalUnits) | L8: =IF(NRSF=0,0,J8/NRSF) | M8: =IF(TDC_Total=0,0,J8/TDC_Total)
B9: Legal: Closing Costs/Title/Escrow | C9: Soft | D9: Due Diligence | E9: abs | F9: 0 | G9: Entitlement | H9: Straight_Line | I9: 0 | J9: =IF(E9="abs",F9,IF(E9="unit",F9*TotalUnits,IF(E9="sf",F9*NRSF,F9))) | K9: =IF(TotalUnits=0,0,J9/TotalUnits) | L9: =IF(NRSF=0,0,J9/NRSF) | M9: =IF(TDC_Total=0,0,J9/TDC_Total)
B10: Legal: Misc. | C10: Soft | D10: Due Diligence | E10: abs | F10: 0 | G10: Construction | H10: Straight_Line | I10: 0 | J10: =IF(E10="abs",F10,IF(E10="unit",F10*TotalUnits,IF(E10="sf",F10*NRSF,F10))) | K10: =IF(TotalUnits=0,0,J10/TotalUnits) | L10: =IF(NRSF=0,0,J10/NRSF) | M10: =IF(TDC_Total=0,0,J10/TDC_Total)
B11: HOA/CC&R's/Land Use | C11: Soft | D11: Due Diligence | E11: abs | F11: 0 | G11: Lease-Up | H11: Straight_Line | I11: 0 | J11: =IF(E11="abs",F11,IF(E11="unit",F11*TotalUnits,IF(E11="sf",F11*NRSF,F11))) | K11: =IF(TotalUnits=0,0,J11/TotalUnits) | L11: =IF(NRSF=0,0,J11/NRSF) | M11: =IF(TDC_Total=0,0,J11/TDC_Total)
B12: Market Study/Appraisal | C12: Soft | D12: Due Diligence | E12: abs | F12: 0 | G12: Entitlement | H12: Straight_Line | I12: 0 | J12: =IF(E12="abs",F12,IF(E12="unit",F12*TotalUnits,IF(E12="sf",F12*NRSF,F12))) | K12: =IF(TotalUnits=0,0,J12/TotalUnits) | L12: =IF(NRSF=0,0,J12/NRSF) | M12: =IF(TDC_Total=0,0,J12/TDC_Total)
B13: Other Due Diligence (DD Report, Tax, Misc.) | C13: Soft | D13: Due Diligence | E13: abs | F13: 60000 | G13: Due Diligence | H13: Straight_Line | I13: 0 | J13: =IF(E13="abs",F13,IF(E13="unit",F13*TotalUnits,IF(E13="sf",F13*NRSF,F13))) | K13: =IF(TotalUnits=0,0,J13/TotalUnits) | L13: =IF(NRSF=0,0,J13/NRSF) | M13: =IF(TDC_Total=0,0,J13/TDC_Total)
B14: Municipal Fees: Entitlement Phase | C14: Soft | D14: Entitlements | E14: abs | F14: 0 | G14: Entitlement | H14: Straight_Line | I14: 0 | J14: =IF(E14="abs",F14,IF(E14="unit",F14*TotalUnits,IF(E14="sf",F14*NRSF,F14))) | K14: =IF(TotalUnits=0,0,J14/TotalUnits) | L14: =IF(NRSF=0,0,J14/NRSF) | M14: =IF(TDC_Total=0,0,J14/TDC_Total)
B15: Municipal Fees: Plan Review Fees | C15: Soft | D15: Entitlements | E15: abs | F15: 0 | G15: Entitlement | H15: Straight_Line | I15: 0 | J15: =IF(E15="abs",F15,IF(E15="unit",F15*TotalUnits,IF(E15="sf",F15*NRSF,F15))) | K15: =IF(TotalUnits=0,0,J15/TotalUnits) | L15: =IF(NRSF=0,0,J15/NRSF) | M15: =IF(TDC_Total=0,0,J15/TDC_Total)
B16: Municipal Fees: Development Fees | C16: Soft | D16: Entitlements | E16: abs | F16: 460000 | G16: Entitlement | H16: Straight_Line | I16: 0 | J16: =IF(E16="abs",F16,IF(E16="unit",F16*TotalUnits,IF(E16="sf",F16*NRSF,F16))) | K16: =IF(TotalUnits=0,0,J16/TotalUnits) | L16: =IF(NRSF=0,0,J16/NRSF) | M16: =IF(TDC_Total=0,0,J16/TDC_Total)
B17: Municipal Fees: Permit Fees | C17: Soft | D17: Entitlements | E17: abs | F17: 0 | G17: Entitlement | H17: Straight_Line | I17: 0 | J17: =IF(E17="abs",F17,IF(E17="unit",F17*TotalUnits,IF(E17="sf",F17*NRSF,F17))) | K17: =IF(TotalUnits=0,0,J17/TotalUnits) | L17: =IF(NRSF=0,0,J17/NRSF) | M17: =IF(TDC_Total=0,0,J17/TDC_Total)
... B84: Off Site Improvements (Not Included Above) | C84: Hard | D84: Hard | E84: abs | F84: 0 | G84: Construction | H84: Straight_Line | I84: 0 | J84: =IF(E84="abs",F84,IF(E84="unit",F84*TotalUnits,IF(E84="sf",F84*NRSF,F84))) | K84: =IF(TotalUnits=0,0,J84/TotalUnits) | L84: =IF(NRSF=0,0,J84/NRSF) | M84: =IF(TDC_Total=0,0,J84/TDC_Total)
B85: Demolition (Not Included Above) | C85: Hard | D85: Hard | E85: abs | F85: =ExistingStructureCost | G85: Construction | H85: Straight_Line | I85: 0 | J85: =IF(E85="abs",F85,IF(E85="unit",F85*TotalUnits,IF(E85="sf",F85*NRSF,F85))) | K85: =IF(TotalUnits=0,0,J85/TotalUnits) | L85: =IF(NRSF=0,0,J85/NRSF) | M85: =IF(TDC_Total=0,0,J85/TDC_Total)
B86: Utility System Installation Costs | C86: Hard | D86: Hard | E86: abs | F86: 0 | G86: Construction | H86: Straight_Line | I86: 0 | J86: =IF(E86="abs",F86,IF(E86="unit",F86*TotalUnits,IF(E86="sf",F86*NRSF,F86))) | K86: =IF(TotalUnits=0,0,J86/TotalUnits) | L86: =IF(NRSF=0,0,J86/NRSF) | M86: =IF(TDC_Total=0,0,J86/TDC_Total)
B87: Other Hard Costs Outside GC Contract | C87: Hard | D87: Hard | E87: abs | F87: 0 | G87: Lease-Up | H87: Straight_Line | I87: 0 | J87: =IF(E87="abs",F87,IF(E87="unit",F87*TotalUnits,IF(E87="sf",F87*NRSF,F87))) | K87: =IF(TotalUnits=0,0,J87/TotalUnits) | L87: =IF(NRSF=0,0,J87/NRSF) | M87: =IF(TDC_Total=0,0,J87/TDC_Total)
B88: Hard Cost Contingency | C88: Hard | D88: Hard | E88: abs | F88: 0 | G88: Construction | H88: Straight_Line | I88: 0 | J88: =IF(E88="abs",F88,IF(E88="unit",F88*TotalUnits,IF(E88="sf",F88*NRSF,F88))) | K88: =IF(TotalUnits=0,0,J88/TotalUnits) | L88: =IF(NRSF=0,0,J88/NRSF) | M88: =IF(TDC_Total=0,0,J88/TDC_Total)
B89: Tenant Improvements | C89: Hard | D89: Hard | E89: abs | F89: 0 | G89: Lease-Up | H89: Straight_Line | I89: 0 | J89: =IF(E89="abs",F89,IF(E89="unit",F89*TotalUnits,IF(E89="sf",F89*NRSF,F89))) | K89: =IF(TotalUnits=0,0,J89/TotalUnits) | L89: =IF(NRSF=0,0,J89/NRSF) | M89: =IF(TDC_Total=0,0,J89/TDC_Total)
B90: Taxes - State Excise & Other | C90: Hard | D90: Hard | E90: abs | F90: 0 | G90: Construction | H90: Bell_Curve | I90: 0 | J90: =IF(E90="abs",F90,IF(E90="unit",F90*TotalUnits,IF(E90="sf",F90*NRSF,F90))) | K90: =IF(TotalUnits=0,0,J90/TotalUnits) | L90: =IF(NRSF=0,0,J90/NRSF) | M90: =IF(TDC_Total=0,0,J90/TDC_Total)
B91: Insurance - Builders Risk, OCIP, Pollution | C91: Hard | D91: Hard | E91: abs | F91: 0 | G91: Construction | H91: Straight_Line | I91: 0 | J91: =IF(E91="abs",F91,IF(E91="unit",F91*TotalUnits,IF(E91="sf",F91*NRSF,F91))) | K91: =IF(TotalUnits=0,0,J91/TotalUnits) | L91: =IF(NRSF=0,0,J91/NRSF) | M91: =IF(TDC_Total=0,0,J91/TDC_Total)
B92: Unit Finish Upgrades Outside GC Contract | C92: Hard | D92: Hard | E92: abs | F92: 0 | G92: Construction | H92: Straight_Line | I92: 0 | J92: =IF(E92="abs",F92,IF(E92="unit",F92*TotalUnits,IF(E92="sf",F92*NRSF,F92))) | K92: =IF(TotalUnits=0,0,J92/TotalUnits) | L92: =IF(NRSF=0,0,J92/NRSF) | M92: =IF(TDC_Total=0,0,J92/TDC_Total)
B93: GC Fee | C93: Hard | D93: Hard | E93: abs | F93: 0 | G93: Construction | H93: Bell_Curve | I93: 0 | J93: =IF(E93="abs",F93,IF(E93="unit",F93*TotalUnits,IF(E93="sf",F93*NRSF,F93))) | K93: =IF(TotalUnits=0,0,J93/TotalUnits) | L93: =IF(NRSF=0,0,J93/NRSF) | M93: =IF(TDC_Total=0,0,J93/TDC_Total)
B94: Other Hard Cost Item 1 | C94: Hard | D94: Hard | E94: abs | F94: 0 | G94: Construction | H94: Straight_Line | I94: 0 | J94: =IF(E94="abs",F94,IF(E94="unit",F94*TotalUnits,IF(E94="sf",F94*NRSF,F94))) | K94: =IF(TotalUnits=0,0,J94/TotalUnits) | L94: =IF(NRSF=0,0,J94/NRSF) | M94: =IF(TDC_Total=0,0,J94/TDC_Total)
B95: Other Hard Cost Item 2 | C95: Hard | D95: Hard | E95: abs | F95: 0 | G95: Construction | H95: Straight_Line | I95: 0 | J95: =IF(E95="abs",F95,IF(E95="unit",F95*TotalUnits,IF(E95="sf",F95*NRSF,F95))) | K95: =IF(TotalUnits=0,0,J95/TotalUnits) | L95: =IF(NRSF=0,0,J95/NRSF) | M95: =IF(TDC_Total=0,0,J95/TDC_Total)
B96: Other Hard Cost Item 3 | C96: Hard | D96: Hard | E96: abs | F96: 0 | G96: Construction | H96: Straight_Line | I96: 0 | J96: =IF(E96="abs",F96,IF(E96="unit",F96*TotalUnits,IF(E96="sf",F96*NRSF,F96))) | K96: =IF(TotalUnits=0,0,J96/TotalUnits) | L96: =IF(NRSF=0,0,J96/NRSF) | M96: =IF(TDC_Total=0,0,J96/TDC_Total)
B97: Other Hard Cost Item 4 | C97: Hard | D97: Hard | E97: abs | F97: 0 | G97: Construction | H97: Straight_Line | I97: 0 | J97: =IF(E97="abs",F97,IF(E97="unit",F97*TotalUnits,IF(E97="sf",F97*NRSF,F97))) | K97: =IF(TotalUnits=0,0,J97/TotalUnits) | L97: =IF(NRSF=0,0,J97/NRSF) | M97: =IF(TDC_Total=0,0,J97/TDC_Total)
B99: Financing & Reserves (captured in capitalization — not in Direct Costs)
B100: Points / Origination | C100: Memo | D100: Financing & Reserves | E100: abs | F100: =ConPoints | J100: =F100 | M100: =IF(TDC_Total=0,0,J100/TDC_Total)
B101: Other Loan / Closing Costs | C101: Memo | D101: Financing & Reserves | E101: abs | F101: =ConOtherCosts | J101: =F101 | M101: =IF(TDC_Total=0,0,J101/TDC_Total)
B102: Recourse / Indemnity Fee | C102: Memo | D102: Financing & Reserves | E102: abs | F102: =RecourseFee | J102: =F102 | M102: =IF(TDC_Total=0,0,J102/TDC_Total)
B103: Debt Service (Interest Reserve) | C103: Memo | D103: Financing & Reserves | E103: abs | F103: =InterestReserveFunded | J103: =F103 | M103: =IF(TDC_Total=0,0,J103/TDC_Total)
B104: Operating Reserve / Initial Operating Deficit | C104: Memo | D104: Financing & Reserves | E104: abs | F104: =OpReserve | J104: =F104 | M104: =IF(TDC_Total=0,0,J104/TDC_Total)
B105: Construction-Period Property Taxes | C105: Memo | D105: Financing & Reserves | E105: abs | F105: =ConTaxTotal | J105: =F105 | M105: =IF(TDC_Total=0,0,J105/TDC_Total)
B106: Sponsor Development Fee | C106: Memo | D106: Financing & Reserves | E106: abs | F106: =DevFee | J106: =F106 | M106: =IF(TDC_Total=0,0,J106/TDC_Total)
B108: Budget Summary
B109: Land | J109: =SUMIF($C$5:$C$97,"Land",$J$5:$J$97) | M109: =IF(TDC_Total=0,0,J109/TDC_Total)
B110: Soft Costs | J110: =SUMIF($C$5:$C$97,"Soft",$J$5:$J$97) | M110: =IF(TDC_Total=0,0,J110/TDC_Total)
B111: Hard Costs | J111: =SUMIF($C$5:$C$97,"Hard",$J$5:$J$97) | M111: =IF(TDC_Total=0,0,J111/TDC_Total)
B112: Direct Costs (subtotal) | J112: =SUM($J$5:$J$97) | M112: =IF(TDC_Total=0,0,J112/TDC_Total)
B113: Sponsor Development Fee | J113: =DevFeePctDirect*DirectCosts | M113: =IF(TDC_Total=0,0,J113/TDC_Total)
B114: Total Development Cost (TDC) | J114: =TDC_Total | M114: =IF(TDC_Total=0,0,J114/TDC_Total)
B116: Total Uses (Capitalization)
B117: Direct Costs | J117: =DirectCosts | M117: =IF(TDC_Total=0,0,J117/TDC_Total)
B118: Development Fee | J118: =DevFee | M118: =IF(TDC_Total=0,0,J118/TDC_Total)
B119: Origination Points | J119: =ConPoints | M119: =IF(TDC_Total=0,0,J119/TDC_Total)
B120: Recourse / Indemnity Fee | J120: =RecourseFee | M120: =IF(TDC_Total=0,0,J120/TDC_Total)
B121: Other Loan / Closing Costs | J121: =ConOtherCosts | M121: =IF(TDC_Total=0,0,J121/TDC_Total)
B122: Interest Reserve | J122: =InterestReserveFunded | M122: =IF(TDC_Total=0,0,J122/TDC_Total)
B123: Operating Reserve | J123: =OpReserve | M123: =IF(TDC_Total=0,0,J123/TDC_Total)
B124: TOTAL USES (TDC) | J124: =TDC_Total | M124: =IF(TDC_Total=0,0,J124/TDC_Total)
B126: Sources
B127: Construction Loan | J127: =ConLoanTotal
B128: Equity | J128: =EquityTotal
B129: TOTAL SOURCES | J129: =ConLoanTotal+EquityTotal
B130: Sources − Uses (check = 0) | J130: =ConLoanTotal+EquityTotal-TDC_Total

Sheet Timeline
B1: Timeline Engine — Milestones & Monthly Period Grid
B3: Milestone | C3: Start (mo) | D3: Duration (mo) | E3: End (mo)
B4: Due Diligence | C4: 1 | D4: 4 | E4: =SUM(C4:D4)-1
B5: Entitlement | C5: =+MS_Due_Diligence_End | D5: 5 | E5: =SUM(C5:D5)-1
B6: Pre-Construction | C6: =+MS_Entitlement_End | D6: 3 | E6: =SUM(C6:D6)-1
B7: Construction | C7: =+MS_Pre_Construction_End | D7: 22 | E7: =SUM(C7:D7)-1
B8: 1st Unit Delivery | C8: =+MS_Construction_Start+DeliveryLagMonths | D8: 1 | E8: =SUM(C8:D8)-1
B9: Lease-Up | C9: =+MS_1st_Unit_Delivery_Start | D9: =MAX(CEILING(StabLeasedTarget/UnitsLeasedPerMo,1),CEILING(StabLeasedTarget/UnitsDeliveredPerMo,1)) | E9: =SUM(C9:D9)-1
B10: Stabilization | C10: =+MS_Lease_Up_End | D10: 1 | E10: =SUM(C10:D10)-1
A11: Exit | B11: Recapitalization/Refinance | C11: =IF(RefiFlag=1,RefiMonth,MS_Stabilization_End) | D11: 1 | E11: =SUM(C11:D11)-1
B12: Disposition | C12: =HoldPeriodMonths | D12: 1 | E12: =SUM(C12:D12)-1
B16: Key Timing (derived)
B17: Construction Start | C17: =MS_Construction_Start
B18: Construction Maturity | C18: =ConStart+ConLoanTermMonths-1
B19: 1st Unit Delivery | C19: =MS_1st_Unit_Delivery_Start
B20: Stabilization Month | C20: =MS_Stabilization_Start
B21: Disposition Month | C21: =HoldPeriodMonths
B22: Growth Start Month | C22: =(YEAR(GrowthStartDate)-YEAR(InceptionDate))*12+MONTH(GrowthStartDate)-MONTH(InceptionDate)
B23: Refi Flag (1=refi,0=sell) | C23: =IF(DispoMonth>ConMaturity,1,0)
B24: Refi Month | C24: =IF(RefiFlag=1,MIN(ConMaturity,IF(RefiMonthOverride>0,RefiMonthOverride,MAX(StabMonth,ConEndMonth)+RefiLagMonths)),0)
B25: Con Payoff Month | C25: =IF(RefiFlag=1,RefiMonth,DispoMonth)
B27: Monthly Period Grid
B28: Period → | D28: Total | E28: 1 | F28: 2 | G28: 3 | H28: 4 | I28: 5 | J28: 6 | K28: 7 | L28: 8 | M28: 9 | N28: 10 | O28: 11 | P28: 12 | Q28: 13 | R28: 14 | S28: 15 | T28: 16 | U28: 17 | V28: 18 | W28: 19 | X28: 20 | Y28: 21 | Z28: 22 | AA28: 23 | AB28: 24 | AC28: 25 | AD28: 26 | AE28: 27 | AF28: 28 | AG28: 29 | AH28: 30 | AI28: 31 | AJ28: 32 | AK28: 33 | AL28: 34 | AM28: 35 | AN28: 36 | AO28: 37 | AP28: 38 | AQ28: 39 | AR28: 40 | AS28: 41 | AT28: 42 | AU28: 43 | AV28: 44 | AW28: 45 | AX28: 46 | AY28: 47 | AZ28: 48 | BA28: 49 | BB28: 50 | BC28: 51 | BD28: 52 | BE28: 53 | BF28: 54 | BG28: 55 | BH28: 56 | BI28: 57 | BJ28: 58 | BK28: 59 | BL28: 60 | BM28: 61 | BN28: 62 | BO28: 63 | BP28: 64 | BQ28: 65 | BR28: 66 | BS28: 67 | BT28: 68 | BU28: 69 | BV28: 70 | BW28: 71 | BX28: 72 | BY28: 73 | BZ28: 74 | CA28: 75 | CB28: 76 | CC28: 77 | CD28: 78 | CE28: 79 | CF28: 80 | CG28: 81 | CH28: 82 | CI28: 83 | CJ28: 84 | CK28: 85 | CL28: 86 | CM28: 87 | CN28: 88 | CO28: 89 | CP28: 90 | CQ28: 91 | CR28: 92 | CS28: 93 | CT28: 94 | CU28: 95 | CV28: 96 | CW28: 97 | CX28: 98 | CY28: 99 | CZ28: 100 | DA28: 101 | DB28: 102 | DC28: 103 | DD28: 104 | DE28: 105 | DF28: 106 | DG28: 107 | DH28: 108 | DI28: 109 | DJ28: 110 | DK28: 111 | DL28: 112 | DM28: 113 | DN28: 114 | DO28: 115 | DP28: 116 | DQ28: 117 | DR28: 118 | DS28: 119 | DT28: 120 | DU28: 121 | DV28: 122 | DW28: 123 | DX28: 124 | DY28: 125 | DZ28: 126 | EA28: 127 | EB28: 128 | EC28: 129 | ED28: 130 | EE28: 131 | EF28: 132 | EG28: 133 | EH28: 134 | EI28: 135 | EJ28: 136 | EK28: 137 | EL28: 138 | EM28: 139 | EN28: 140 | EO28: 141 | EP28: 142 | EQ28: 143 | ER28: 144 | ES28: 145 | ET28: 146 | EU28: 147 | EV28: 148 | EW28: 149 | EX28: 150 | EY28: 151 | EZ28: 152 | FA28: 153 | FB28: 154 | FC28: 155 | FD28: 156 | FE28: 157 | FF28: 158 | FG28: 159 | FH28: 160 | FI28: 161 | FJ28: 162 | FK28: 163 | FL28: 164 | FM28: 165 | FN28: 166 | FO28: 167 | FP28: 168 | FQ28: 169 | FR28: 170 | FS28: 171 | FT28: 172 | FU28: 173 | FV28: 174 | FW28: 175 | FX28: 176 | FY28: 177 | FZ28: 178 | GA28: 179 | GB28: 180 | GC28: 181 | GD28: 182 | GE28: 183 | GF28: 184 | GG28: 185 | GH28: 186 | GI28: 187 | GJ28: 188 | GK28: 189 | GL28: 190 | GM28: 191 | GN28: 192 | GO28: 193 | GP28: 194 | GQ28: 195 | GR28: 196 | GS28: 197 | GT28: 198 | GU28: 199 | GV28: 200 | GW28: 201 | GX28: 202 | GY28: 203 | GZ28: 204 | HA28: 205 | HB28: 206 | HC28: 207 | HD28: 208 | HE28: 209 | HF28: 210 | HG28: 211 | HH28: 212 | HI28: 213 | HJ28: 214 | HK28: 215 | HL28: 216 | HM28: 217 | HN28: 218 | HO28: 219 | HP28: 220 | HQ28: 221 | HR28: 222 | HS28: 223 | HT28: 224 | HU28: 225 | HV28: 226 | HW28: 227 | HX28: 228 | HY28: 229 | HZ28: 230 | IA28: 231 | IB28: 232 | IC28: 233 | ID28: 234 | IE28: 235 | IF28: 236 | IG28: 237 | IH28: 238 | II28: 239 | IJ28: 240 | IK28: 241 | IL28: 242 | IM28: 243 | IN28: 244 | IO28: 245 | IP28: 246 | IQ28: 247 | IR28: 248 | IS28: 249 | IT28: 250 | IU28: 251 | IV28: 252 | IW28: 253 | IX28: 254 | IY28: 255 | IZ28: 256 | JA28: 257 | JB28: 258 | JC28: 259 | JD28: 260 | JE28: 261 | JF28: 262 | JG28: 263 | JH28: 264 | JI28: 265 | JJ28: 266 | JK28: 267 | JL28: 268 | JM28: 269 | JN28: 270 | JO28: 271 | JP28: 272 | JQ28: 273 | JR28: 274 | JS28: 275 | JT28: 276 | JU28: 277 | JV28: 278 | JW28: 279 | JX28: 280 | JY28: 281 | JZ28: 282 | KA28: 283 | KB28: 284 | KC28: 285 | KD28: 286 | KE28: 287 | KF28: 288 | KG28: 289 | KH28: 290 | KI28: 291 | KJ28: 292 | KK28: 293 | KL28: 294 | KM28: 295 | KN28: 296 | KO28: 297 | KP28: 298 | KQ28: 299 | KR28: 300 | KS28: 301 | KT28: 302 | KU28: 303 | KV28: 304 | KW28: 305 | KX28: 306 | KY28: 307 | KZ28: 308 | LA28: 309 | LB28: 310 | LC28: 311 | LD28: 312 | LE28: 313 | LF28: 314 | LG28: 315 | LH28: 316 | LI28: 317 | LJ28: 318 | LK28: 319 | LL28: 320 | LM28: 321 | LN28: 322 | LO28: 323 | LP28: 324 | LQ28: 325 | LR28: 326 | LS28: 327 | LT28: 328 | LU28: 329 | LV28: 330 | LW28: 331 | LX28: 332 | LY28: 333 | LZ28: 334 | MA28: 335 | MB28: 336 | MC28: 337 | MD28: 338 | ME28: 339 | MF28: 340 | MG28: 341 | MH28: 342 | MI28: 343 | MJ28: 344 | MK28: 345 | ML28: 346 | MM28: 347 | MN28: 348 | MO28: 349 | MP28: 350 | MQ28: 351 | MR28: 352 | MS28: 353 | MT28: 354 | MU28: 355 | MV28: 356 | MW28: 357 | MX28: 358 | MY28: 359 | MZ28: 360 | NA28: 361 | NB28: 362 | NC28: 363 | ND28: 364 | NE28: 365 | NF28: 366 | NG28: 367 | NH28: 368 | NI28: 369 | NJ28: 370 | NK28: 371 | NL28: 372
B29: Month Start | E29: =EDATE(InceptionDate,0) | F29: =EDATE(InceptionDate,1) | G29: =EDATE(InceptionDate,2) | H29: =EDATE(InceptionDate,3) | I29: =EDATE(InceptionDate,4) | J29: =EDATE(InceptionDate,5) | K29: =EDATE(InceptionDate,6) | L29: =EDATE(InceptionDate,7) | M29: =EDATE(InceptionDate,8) | N29: =EDATE(InceptionDate,9) | O29: =EDATE(InceptionDate,10) | P29: =EDATE(InceptionDate,11) | Q29: =EDATE(InceptionDate,12) | R29: =EDATE(InceptionDate,13) | S29: =EDATE(InceptionDate,14) | T29: =EDATE(InceptionDate,15) | U29: =EDATE(InceptionDate,16) | V29: =EDATE(InceptionDate,17) | W29: =EDATE(InceptionDate,18) | X29: =EDATE(InceptionDate,19) | Y29: =EDATE(InceptionDate,20) | Z29: =EDATE(InceptionDate,21) | AA29: =EDATE(InceptionDate,22) | AB29: =EDATE(InceptionDate,23) | AC29: =EDATE(InceptionDate,24) | AD29: =EDATE(InceptionDate,25) | AE29: =EDATE(InceptionDate,26) | AF29: =EDATE(InceptionDate,27) | AG29: =EDATE(InceptionDate,28) | AH29: =EDATE(InceptionDate,29) | AI29: =EDATE(InceptionDate,30) | AJ29: =EDATE(InceptionDate,31) | AK29: =EDATE(InceptionDate,32) | AL29: =EDATE(InceptionDate,33) | AM29: =EDATE(InceptionDate,34) | AN29: =EDATE(InceptionDate,35) | AO29: =EDATE(InceptionDate,36) | AP29: =EDATE(InceptionDate,37) | AQ29: =EDATE(InceptionDate,38) | AR29: =EDATE(InceptionDate,39) | AS29: =EDATE(InceptionDate,40) | AT29: =EDATE(InceptionDate,41) | AU29: =EDATE(InceptionDate,42) | AV29: =EDATE(InceptionDate,43) | AW29: =EDATE(InceptionDate,44) | AX29: =EDATE(InceptionDate,45) | AY29: =EDATE(InceptionDate,46) | AZ29: =EDATE(InceptionDate,47) | BA29: =EDATE(InceptionDate,48) | BB29: =EDATE(InceptionDate,49) | BC29: =EDATE(InceptionDate,50) | BD29: =EDATE(InceptionDate,51) | BE29: =EDATE(InceptionDate,52) | BF29: =EDATE(InceptionDate,53) | BG29: =EDATE(InceptionDate,54) | BH29: =EDATE(InceptionDate,55) | BI29: =EDATE(InceptionDate,56) | BJ29: =EDATE(InceptionDate,57) | BK29: =EDATE(InceptionDate,58) | BL29: =EDATE(InceptionDate,59) | BM29: =EDATE(InceptionDate,60) | BN29: =EDATE(InceptionDate,61) | BO29: =EDATE(InceptionDate,62) | BP29: =EDATE(InceptionDate,63) | BQ29: =EDATE(InceptionDate,64) | BR29: =EDATE(InceptionDate,65) | BS29: =EDATE(InceptionDate,66) | BT29: =EDATE(InceptionDate,67) | BU29: =EDATE(InceptionDate,68) | BV29: =EDATE(InceptionDate,69) | BW29: =EDATE(InceptionDate,70) | BX29: =EDATE(InceptionDate,71) | BY29: =EDATE(InceptionDate,72) | BZ29: =EDATE(InceptionDate,73) | CA29: =EDATE(InceptionDate,74) | CB29: =EDATE(InceptionDate,75) | CC29: =EDATE(InceptionDate,76) | CD29: =EDATE(InceptionDate,77) | CE29: =EDATE(InceptionDate,78) | CF29: =EDATE(InceptionDate,79) | CG29: =EDATE(InceptionDate,80) | CH29: =EDATE(InceptionDate,81) | CI29: =EDATE(InceptionDate,82) | CJ29: =EDATE(InceptionDate,83) | CK29: =EDATE(InceptionDate,84) | CL29: =EDATE(InceptionDate,85) | CM29: =EDATE(InceptionDate,86) | CN29: =EDATE(InceptionDate,87) | CO29: =EDATE(InceptionDate,88) | CP29: =EDATE(InceptionDate,89) | CQ29: =EDATE(InceptionDate,90) | CR29: =EDATE(InceptionDate,91) | CS29: =EDATE(InceptionDate,92) | CT29: =EDATE(InceptionDate,93) | CU29: =EDATE(InceptionDate,94) | CV29: =EDATE(InceptionDate,95) | CW29: =EDATE(InceptionDate,96) | CX29: =EDATE(InceptionDate,97) | CY29: =EDATE(InceptionDate,98) | CZ29: =EDATE(InceptionDate,99) | DA29: =EDATE(InceptionDate,100) | DB29: =EDATE(InceptionDate,101) | DC29: =EDATE(InceptionDate,102) | DD29: =EDATE(InceptionDate,103) | DE29: =EDATE(InceptionDate,104) | DF29: =EDATE(InceptionDate,105) | DG29: =EDATE(InceptionDate,106) | DH29: =EDATE(InceptionDate,107) | DI29: =EDATE(InceptionDate,108) | DJ29: =EDATE(InceptionDate,109) | DK29: =EDATE(InceptionDate,110) | DL29: =EDATE(InceptionDate,111) | DM29: =EDATE(InceptionDate,112) | DN29: =EDATE(InceptionDate,113) | DO29: =EDATE(InceptionDate,114) | DP29: =EDATE(InceptionDate,115) | DQ29: =EDATE(InceptionDate,116) | DR29: =EDATE(InceptionDate,117) | DS29: =EDATE(InceptionDate,118) | DT29: =EDATE(InceptionDate,119) | DU29: =EDATE(InceptionDate,120) | DV29: =EDATE(InceptionDate,121) | DW29: =EDATE(InceptionDate,122) | DX29: =EDATE(InceptionDate,123) | DY29: =EDATE(InceptionDate,124) | DZ29: =EDATE(InceptionDate,125) | EA29: =EDATE(InceptionDate,126) | EB29: =EDATE(InceptionDate,127) | EC29: =EDATE(InceptionDate,128) | ED29: =EDATE(InceptionDate,129) | EE29: =EDATE(InceptionDate,130) | EF29: =EDATE(InceptionDate,131) | EG29: =EDATE(InceptionDate,132) | EH29: =EDATE(InceptionDate,133) | EI29: =EDATE(InceptionDate,134) | EJ29: =EDATE(InceptionDate,135) | EK29: =EDATE(InceptionDate,136) | EL29: =EDATE(InceptionDate,137) | EM29: =EDATE(InceptionDate,138) | EN29: =EDATE(InceptionDate,139) | EO29: =EDATE(InceptionDate,140) | EP29: =EDATE(InceptionDate,141) | EQ29: =EDATE(InceptionDate,142) | ER29: =EDATE(InceptionDate,143) | ES29: =EDATE(InceptionDate,144) | ET29: =EDATE(InceptionDate,145) | EU29: =EDATE(InceptionDate,146) | EV29: =EDATE(InceptionDate,147) | EW29: =EDATE(InceptionDate,148) | EX29: =EDATE(InceptionDate,149) | EY29: =EDATE(InceptionDate,150) | EZ29: =EDATE(InceptionDate,151) | FA29: =EDATE(InceptionDate,152) | FB29: =EDATE(InceptionDate,153) | FC29: =EDATE(InceptionDate,154) | FD29: =EDATE(InceptionDate,155) | FE29: =EDATE(InceptionDate,156) | FF29: =EDATE(InceptionDate,157) | FG29: =EDATE(InceptionDate,158) | FH29: =EDATE(InceptionDate,159) | FI29: =EDATE(InceptionDate,160) | FJ29: =EDATE(InceptionDate,161) | FK29: =EDATE(InceptionDate,162) | FL29: =EDATE(InceptionDate,163) | FM29: =EDATE(InceptionDate,164) | FN29: =EDATE(InceptionDate,165) | FO29: =EDATE(InceptionDate,166) | FP29: =EDATE(InceptionDate,167) | FQ29: =EDATE(InceptionDate,168) | FR29: =EDATE(InceptionDate,169) | FS29: =EDATE(InceptionDate,170) | FT29: =EDATE(InceptionDate,171) | FU29: =EDATE(InceptionDate,172) | FV29: =EDATE(InceptionDate,173) | FW29: =EDATE(InceptionDate,174) | FX29: =EDATE(InceptionDate,175) | FY29: =EDATE(InceptionDate,176) | FZ29: =EDATE(InceptionDate,177) | GA29: =EDATE(InceptionDate,178) | GB29: =EDATE(InceptionDate,179) | GC29: =EDATE(InceptionDate,180) | GD29: =EDATE(InceptionDate,181) | GE29: =EDATE(InceptionDate,182) | GF29: =EDATE(InceptionDate,183) | GG29: =EDATE(InceptionDate,184) | GH29: =EDATE(InceptionDate,185) | GI29: =EDATE(InceptionDate,186) | GJ29: =EDATE(InceptionDate,187) | GK29: =EDATE(InceptionDate,188) | GL29: =EDATE(InceptionDate,189) | GM29: =EDATE(InceptionDate,190) | GN29: =EDATE(InceptionDate,191) | GO29: =EDATE(InceptionDate,192) | GP29: =EDATE(InceptionDate,193) | GQ29: =EDATE(InceptionDate,194) | GR29: =EDATE(InceptionDate,195) | GS29: =EDATE(InceptionDate,196) | GT29: =EDATE(InceptionDate,197) | GU29: =EDATE(InceptionDate,198) | GV29: =EDATE(InceptionDate,199) | GW29: =EDATE(InceptionDate,200) | GX29: =EDATE(InceptionDate,201) | GY29: =EDATE(InceptionDate,202) | GZ29: =EDATE(InceptionDate,203) | HA29: =EDATE(InceptionDate,204) | HB29: =EDATE(InceptionDate,205) | HC29: =EDATE(InceptionDate,206) | HD29: =EDATE(InceptionDate,207) | HE29: =EDATE(InceptionDate,208) | HF29: =EDATE(InceptionDate,209) | HG29: =EDATE(InceptionDate,210) | HH29: =EDATE(InceptionDate,211) | HI29: =EDATE(InceptionDate,212) | HJ29: =EDATE(InceptionDate,213) | HK29: =EDATE(InceptionDate,214) | HL29: =EDATE(InceptionDate,215) | HM29: =EDATE(InceptionDate,216) | HN29: =EDATE(InceptionDate,217) | HO29: =EDATE(InceptionDate,218) | HP29: =EDATE(InceptionDate,219) | HQ29: =EDATE(InceptionDate,220) | HR29: =EDATE(InceptionDate,221) | HS29: =EDATE(InceptionDate,222) | HT29: =EDATE(InceptionDate,223) | HU29: =EDATE(InceptionDate,224) | HV29: =EDATE(InceptionDate,225) | HW29: =EDATE(InceptionDate,226) | HX29: =EDATE(InceptionDate,227) | HY29: =EDATE(InceptionDate,228) | HZ29: =EDATE(InceptionDate,229) | IA29: =EDATE(InceptionDate,230) | IB29: =EDATE(InceptionDate,231) | IC29: =EDATE(InceptionDate,232) | ID29: =EDATE(InceptionDate,233) | IE29: =EDATE(InceptionDate,234) | IF29: =EDATE(InceptionDate,235) | IG29: =EDATE(InceptionDate,236) | IH29: =EDATE(InceptionDate,237) | II29: =EDATE(InceptionDate,238) | IJ29: =EDATE(InceptionDate,239) | IK29: =EDATE(InceptionDate,240) | IL29: =EDATE(InceptionDate,241) | IM29: =EDATE(InceptionDate,242) | IN29: =EDATE(InceptionDate,243) | IO29: =EDATE(InceptionDate,244) | IP29: =EDATE(InceptionDate,245) | IQ29: =EDATE(InceptionDate,246) | IR29: =EDATE(InceptionDate,247) | IS29: =EDATE(InceptionDate,248) | IT29: =EDATE(InceptionDate,249) | IU29: =EDATE(InceptionDate,250) | IV29: =EDATE(InceptionDate,251) | IW29: =EDATE(InceptionDate,252) | IX29: =EDATE(InceptionDate,253) | IY29: =EDATE(InceptionDate,254) | IZ29: =EDATE(InceptionDate,255) | JA29: =EDATE(InceptionDate,256) | JB29: =EDATE(InceptionDate,257) | JC29: =EDATE(InceptionDate,258) | JD29: =EDATE(InceptionDate,259) | JE29: =EDATE(InceptionDate,260) | JF29: =EDATE(InceptionDate,261) | JG29: =EDATE(InceptionDate,262) | JH29: =EDATE(InceptionDate,263) | JI29: =EDATE(InceptionDate,264) | JJ29: =EDATE(InceptionDate,265) | JK29: =EDATE(InceptionDate,266) | JL29: =EDATE(InceptionDate,267) | JM29: =EDATE(InceptionDate,268) | JN29: =EDATE(InceptionDate,269) | JO29: =EDATE(InceptionDate,270) | JP29: =EDATE(InceptionDate,271) | JQ29: =EDATE(InceptionDate,272) | JR29: =EDATE(InceptionDate,273) | JS29: =EDATE(InceptionDate,274) | JT29: =EDATE(InceptionDate,275) | JU29: =EDATE(InceptionDate,276) | JV29: =EDATE(InceptionDate,277) | JW29: =EDATE(InceptionDate,278) | JX29: =EDATE(InceptionDate,279) | JY29: =EDATE(InceptionDate,280) | JZ29: =EDATE(InceptionDate,281) | KA29: =EDATE(InceptionDate,282) | KB29: =EDATE(InceptionDate,283) | KC29: =EDATE(InceptionDate,284) | KD29: =EDATE(InceptionDate,285) | KE29: =EDATE(InceptionDate,286) | KF29: =EDATE(InceptionDate,287) | KG29: =EDATE(InceptionDate,288) | KH29: =EDATE(InceptionDate,289) | KI29: =EDATE(InceptionDate,290) | KJ29: =EDATE(InceptionDate,291) | KK29: =EDATE(InceptionDate,292) | KL29: =EDATE(InceptionDate,293) | KM29: =EDATE(InceptionDate,294) | KN29: =EDATE(InceptionDate,295) | KO29: =EDATE(InceptionDate,296) | KP29: =EDATE(InceptionDate,297) | KQ29: =EDATE(InceptionDate,298) | KR29: =EDATE(InceptionDate,299) | KS29: =EDATE(InceptionDate,300) | KT29: =EDATE(InceptionDate,301) | KU29: =EDATE(InceptionDate,302) | KV29: =EDATE(InceptionDate,303) | KW29: =EDATE(InceptionDate,304) | KX29: =EDATE(InceptionDate,305) | KY29: =EDATE(InceptionDate,306) | KZ29: =EDATE(InceptionDate,307) | LA29: =EDATE(InceptionDate,308) | LB29: =EDATE(InceptionDate,309) | LC29: =EDATE(InceptionDate,310) | LD29: =EDATE(InceptionDate,311) | LE29: =EDATE(InceptionDate,312) | LF29: =EDATE(InceptionDate,313) | LG29: =EDATE(InceptionDate,314) | LH29: =EDATE(InceptionDate,315) | LI29: =EDATE(InceptionDate,316) | LJ29: =EDATE(InceptionDate,317) | LK29: =EDATE(InceptionDate,318) | LL29: =EDATE(InceptionDate,319) | LM29: =EDATE(InceptionDate,320) | LN29: =EDATE(InceptionDate,321) | LO29: =EDATE(InceptionDate,322) | LP29: =EDATE(InceptionDate,323) | LQ29: =EDATE(InceptionDate,324) | LR29: =EDATE(InceptionDate,325) | LS29: =EDATE(InceptionDate,326) | LT29: =EDATE(InceptionDate,327) | LU29: =EDATE(InceptionDate,328) | LV29: =EDATE(InceptionDate,329) | LW29: =EDATE(InceptionDate,330) | LX29: =EDATE(InceptionDate,331) | LY29: =EDATE(InceptionDate,332) | LZ29: =EDATE(InceptionDate,333) | MA29: =EDATE(InceptionDate,334) | MB29: =EDATE(InceptionDate,335) | MC29: =EDATE(InceptionDate,336) | MD29: =EDATE(InceptionDate,337) | ME29: =EDATE(InceptionDate,338) | MF29: =EDATE(InceptionDate,339) | MG29: =EDATE(InceptionDate,340) | MH29: =EDATE(InceptionDate,341) | MI29: =EDATE(InceptionDate,342) | MJ29: =EDATE(InceptionDate,343) | MK29: =EDATE(InceptionDate,344) | ML29: =EDATE(InceptionDate,345) | MM29: =EDATE(InceptionDate,346) | MN29: =EDATE(InceptionDate,347) | MO29: =EDATE(InceptionDate,348) | MP29: =EDATE(InceptionDate,349) | MQ29: =EDATE(InceptionDate,350) | MR29: =EDATE(InceptionDate,351) | MS29: =EDATE(InceptionDate,352) | MT29: =EDATE(InceptionDate,353) | MU29: =EDATE(InceptionDate,354) | MV29: =EDATE(InceptionDate,355) | MW29: =EDATE(InceptionDate,356) | MX29: =EDATE(InceptionDate,357) | MY29: =EDATE(InceptionDate,358) | MZ29: =EDATE(InceptionDate,359) | NA29: =EDATE(InceptionDate,360) | NB29: =EDATE(InceptionDate,361) | NC29: =EDATE(InceptionDate,362) | ND29: =EDATE(InceptionDate,363) | NE29: =EDATE(InceptionDate,364) | NF29: =EDATE(InceptionDate,365) | NG29: =EDATE(InceptionDate,366) | NH29: =EDATE(InceptionDate,367) | NI29: =EDATE(InceptionDate,368) | NJ29: =EDATE(InceptionDate,369) | NK29: =EDATE(InceptionDate,370) | NL29: =EDATE(InceptionDate,371)
B30: Flag: Open Escrow | E30: =IF(AND(1>=$C$4,1<=$E$4),1,0) | F30: =IF(AND(2>=$C$4,2<=$E$4),1,0) | G30: =IF(AND(3>=$C$4,3<=$E$4),1,0) | H30: =IF(AND(4>=$C$4,4<=$E$4),1,0) | I30: =IF(AND(5>=$C$4,5<=$E$4),1,0) | J30: =IF(AND(6>=$C$4,6<=$E$4),1,0) | K30: =IF(AND(7>=$C$4,7<=$E$4),1,0) | L30: =IF(AND(8>=$C$4,8<=$E$4),1,0) | M30: =IF(AND(9>=$C$4,9<=$E$4),1,0) | N30: =IF(AND(10>=$C$4,10<=$E$4),1,0) | O30: =IF(AND(11>=$C$4,11<=$E$4),1,0) | P30: =IF(AND(12>=$C$4,12<=$E$4),1,0) | Q30: =IF(AND(13>=$C$4,13<=$E$4),1,0) | R30: =IF(AND(14>=$C$4,14<=$E$4),1,0) | S30: =IF(AND(15>=$C$4,15<=$E$4),1,0) | T30: =IF(AND(16>=$C$4,16<=$E$4),1,0) | U30: =IF(AND(17>=$C$4,17<=$E$4),1,0) | V30: =IF(AND(18>=$C$4,18<=$E$4),1,0) | W30: =IF(AND(19>=$C$4,19<=$E$4),1,0) | X30: =IF(AND(20>=$C$4,20<=$E$4),1,0) | Y30: =IF(AND(21>=$C$4,21<=$E$4),1,0) | Z30: =IF(AND(22>=$C$4,22<=$E$4),1,0) | AA30: =IF(AND(23>=$C$4,23<=$E$4),1,0) | AB30: =IF(AND(24>=$C$4,24<=$E$4),1,0) | AC30: =IF(AND(25>=$C$4,25<=$E$4),1,0) | AD30: =IF(AND(26>=$C$4,26<=$E$4),1,0) | AE30: =IF(AND(27>=$C$4,27<=$E$4),1,0) | AF30: =IF(AND(28>=$C$4,28<=$E$4),1,0) | AG30: =IF(AND(29>=$C$4,29<=$E$4),1,0) | AH30: =IF(AND(30>=$C$4,30<=$E$4),1,0) | AI30: =IF(AND(31>=$C$4,31<=$E$4),1,0) | AJ30: =IF(AND(32>=$C$4,32<=$E$4),1,0) | AK30: =IF(AND(33>=$C$4,33<=$E$4),1,0) | AL30: =IF(AND(34>=$C$4,34<=$E$4),1,0) | AM30: =IF(AND(35>=$C$4,35<=$E$4),1,0) | AN30: =IF(AND(36>=$C$4,36<=$E$4),1,0) | AO30: =IF(AND(37>=$C$4,37<=$E$4),1,0) | AP30: =IF(AND(38>=$C$4,38<=$E$4),1,0) | AQ30: =IF(AND(39>=$C$4,39<=$E$4),1,0) | AR30: =IF(AND(40>=$C$4,40<=$E$4),1,0) | AS30: =IF(AND(41>=$C$4,41<=$E$4),1,0) | AT30: =IF(AND(42>=$C$4,42<=$E$4),1,0) | AU30: =IF(AND(43>=$C$4,43<=$E$4),1,0) | AV30: =IF(AND(44>=$C$4,44<=$E$4),1,0) | AW30: =IF(AND(45>=$C$4,45<=$E$4),1,0) | AX30: =IF(AND(46>=$C$4,46<=$E$4),1,0) | AY30: =IF(AND(47>=$C$4,47<=$E$4),1,0) | AZ30: =IF(AND(48>=$C$4,48<=$E$4),1,0) | BA30: =IF(AND(49>=$C$4,49<=$E$4),1,0) | BB30: =IF(AND(50>=$C$4,50<=$E$4),1,0) | BC30: =IF(AND(51>=$C$4,51<=$E$4),1,0) | BD30: =IF(AND(52>=$C$4,52<=$E$4),1,0) | BE30: =IF(AND(53>=$C$4,53<=$E$4),1,0) | BF30: =IF(AND(54>=$C$4,54<=$E$4),1,0) | BG30: =IF(AND(55>=$C$4,55<=$E$4),1,0) | BH30: =IF(AND(56>=$C$4,56<=$E$4),1,0) | BI30: =IF(AND(57>=$C$4,57<=$E$4),1,0) | BJ30: =IF(AND(58>=$C$4,58<=$E$4),1,0) | BK30: =IF(AND(59>=$C$4,59<=$E$4),1,0) | BL30: =IF(AND(60>=$C$4,60<=$E$4),1,0) | BM30: =IF(AND(61>=$C$4,61<=$E$4),1,0) | BN30: =IF(AND(62>=$C$4,62<=$E$4),1,0) | BO30: =IF(AND(63>=$C$4,63<=$E$4),1,0) | BP30: =IF(AND(64>=$C$4,64<=$E$4),1,0) | BQ30: =IF(AND(65>=$C$4,65<=$E$4),1,0) | BR30: =IF(AND(66>=$C$4,66<=$E$4),1,0) | BS30: =IF(AND(67>=$C$4,67<=$E$4),1,0) | BT30: =IF(AND(68>=$C$4,68<=$E$4),1,0) | BU30: =IF(AND(69>=$C$4,69<=$E$4),1,0) | BV30: =IF(AND(70>=$C$4,70<=$E$4),1,0) | BW30: =IF(AND(71>=$C$4,71<=$E$4),1,0) | BX30: =IF(AND(72>=$C$4,72<=$E$4),1,0) | BY30: =IF(AND(73>=$C$4,73<=$E$4),1,0) | BZ30: =IF(AND(74>=$C$4,74<=$E$4),1,0) | CA30: =IF(AND(75>=$C$4,75<=$E$4),1,0) | CB30: =IF(AND(76>=$C$4,76<=$E$4),1,0) | CC30: =IF(AND(77>=$C$4,77<=$E$4),1,0) | CD30: =IF(AND(78>=$C$4,78<=$E$4),1,0) | CE30: =IF(AND(79>=$C$4,79<=$E$4),1,0) | CF30: =IF(AND(80>=$C$4,80<=$E$4),1,0) | CG30: =IF(AND(81>=$C$4,81<=$E$4),1,0) | CH30: =IF(AND(82>=$C$4,82<=$E$4),1,0) | CI30: =IF(AND(83>=$C$4,83<=$E$4),1,0) | CJ30: =IF(AND(84>=$C$4,84<=$E$4),1,0) | CK30: =IF(AND(85>=$C$4,85<=$E$4),1,0) | CL30: =IF(AND(86>=$C$4,86<=$E$4),1,0) | CM30: =IF(AND(87>=$C$4,87<=$E$4),1,0) | CN30: =IF(AND(88>=$C$4,88<=$E$4),1,0) | CO30: =IF(AND(89>=$C$4,89<=$E$4),1,0) | CP30: =IF(AND(90>=$C$4,90<=$E$4),1,0) | CQ30: =IF(AND(91>=$C$4,91<=$E$4),1,0) | CR30: =IF(AND(92>=$C$4,92<=$E$4),1,0) | CS30: =IF(AND(93>=$C$4,93<=$E$4),1,0) | CT30: =IF(AND(94>=$C$4,94<=$E$4),1,0) | CU30: =IF(AND(95>=$C$4,95<=$E$4),1,0) | CV30: =IF(AND(96>=$C$4,96<=$E$4),1,0) | CW30: =IF(AND(97>=$C$4,97<=$E$4),1,0) | CX30: =IF(AND(98>=$C$4,98<=$E$4),1,0) | CY30: =IF(AND(99>=$C$4,99<=$E$4),1,0) | CZ30: =IF(AND(100>=$C$4,100<=$E$4),1,0) | DA30: =IF(AND(101>=$C$4,101<=$E$4),1,0) | DB30: =IF(AND(102>=$C$4,102<=$E$4),1,0) | DC30: =IF(AND(103>=$C$4,103<=$E$4),1,0) | DD30: =IF(AND(104>=$C$4,104<=$E$4),1,0) | DE30: =IF(AND(105>=$C$4,105<=$E$4),1,0) | DF30: =IF(AND(106>=$C$4,106<=$E$4),1,0) | DG30: =IF(AND(107>=$C$4,107<=$E$4),1,0) | DH30: =IF(AND(108>=$C$4,108<=$E$4),1,0) | DI30: =IF(AND(109>=$C$4,109<=$E$4),1,0) | DJ30: =IF(AND(110>=$C$4,110<=$E$4),1,0) | DK30: =IF(AND(111>=$C$4,111<=$E$4),1,0) | DL30: =IF(AND(112>=$C$4,112<=$E$4),1,0) | DM30: =IF(AND(113>=$C$4,113<=$E$4),1,0) | DN30: =IF(AND(114>=$C$4,114<=$E$4),1,0) | DO30: =IF(AND(115>=$C$4,115<=$E$4),1,0) | DP30: =IF(AND(116>=$C$4,116<=$E$4),1,0) | DQ30: =IF(AND(117>=$C$4,117<=$E$4),1,0) | DR30: =IF(AND(118>=$C$4,118<=$E$4),1,0) | DS30: =IF(AND(119>=$C$4,119<=$E$4),1,0) | DT30: =IF(AND(120>=$C$4,120<=$E$4),1,0) | DU30: =IF(AND(121>=$C$4,121<=$E$4),1,0) | DV30: =IF(AND(122>=$C$4,122<=$E$4),1,0) | DW30: =IF(AND(123>=$C$4,123<=$E$4),1,0) | DX30: =IF(AND(124>=$C$4,124<=$E$4),1,0) | DY30: =IF(AND(125>=$C$4,125<=$E$4),1,0) | DZ30: =IF(AND(126>=$C$4,126<=$E$4),1,0) | EA30: =IF(AND(127>=$C$4,127<=$E$4),1,0) | EB30: =IF(AND(128>=$C$4,128<=$E$4),1,0) | EC30: =IF(AND(129>=$C$4,129<=$E$4),1,0) | ED30: =IF(AND(130>=$C$4,130<=$E$4),1,0) | EE30: =IF(AND(131>=$C$4,131<=$E$4),1,0) | EF30: =IF(AND(132>=$C$4,132<=$E$4),1,0) | EG30: =IF(AND(133>=$C$4,133<=$E$4),1,0) | EH30: =IF(AND(134>=$C$4,134<=$E$4),1,0) | EI30: =IF(AND(135>=$C$4,135<=$E$4),1,0) | EJ30: =IF(AND(136>=$C$4,136<=$E$4),1,0) | EK30: =IF(AND(137>=$C$4,137<=$E$4),1,0) | EL30: =IF(AND(138>=$C$4,138<=$E$4),1,0) | EM30: =IF(AND(139>=$C$4,139<=$E$4),1,0) | EN30: =IF(AND(140>=$C$4,140<=$E$4),1,0) | EO30: =IF(AND(141>=$C$4,141<=$E$4),1,0) | EP30: =IF(AND(142>=$C$4,142<=$E$4),1,0) | EQ30: =IF(AND(143>=$C$4,143<=$E$4),1,0) | ER30: =IF(AND(144>=$C$4,144<=$E$4),1,0) | ES30: =IF(AND(145>=$C$4,145<=$E$4),1,0) | ET30: =IF(AND(146>=$C$4,146<=$E$4),1,0) | EU30: =IF(AND(147>=$C$4,147<=$E$4),1,0) | EV30: =IF(AND(148>=$C$4,148<=$E$4),1,0) | EW30: =IF(AND(149>=$C$4,149<=$E$4),1,0) | EX30: =IF(AND(150>=$C$4,150<=$E$4),1,0) | EY30: =IF(AND(151>=$C$4,151<=$E$4),1,0) | EZ30: =IF(AND(152>=$C$4,152<=$E$4),1,0) | FA30: =IF(AND(153>=$C$4,153<=$E$4),1,0) | FB30: =IF(AND(154>=$C$4,154<=$E$4),1,0) | FC30: =IF(AND(155>=$C$4,155<=$E$4),1,0) | FD30: =IF(AND(156>=$C$4,156<=$E$4),1,0) | FE30: =IF(AND(157>=$C$4,157<=$E$4),1,0) | FF30: =IF(AND(158>=$C$4,158<=$E$4),1,0) | FG30: =IF(AND(159>=$C$4,159<=$E$4),1,0) | FH30: =IF(AND(160>=$C$4,160<=$E$4),1,0) | FI30: =IF(AND(161>=$C$4,161<=$E$4),1,0) | FJ30: =IF(AND(162>=$C$4,162<=$E$4),1,0) | FK30: =IF(AND(163>=$C$4,163<=$E$4),1,0) | FL30: =IF(AND(164>=$C$4,164<=$E$4),1,0) | FM30: =IF(AND(165>=$C$4,165<=$E$4),1,0) | FN30: =IF(AND(166>=$C$4,166<=$E$4),1,0) | FO30: =IF(AND(167>=$C$4,167<=$E$4),1,0) | FP30: =IF(AND(168>=$C$4,168<=$E$4),1,0) | FQ30: =IF(AND(169>=$C$4,169<=$E$4),1,0) | FR30: =IF(AND(170>=$C$4,170<=$E$4),1,0) | FS30: =IF(AND(171>=$C$4,171<=$E$4),1,0) | FT30: =IF(AND(172>=$C$4,172<=$E$4),1,0) | FU30: =IF(AND(173>=$C$4,173<=$E$4),1,0) | FV30: =IF(AND(174>=$C$4,174<=$E$4),1,0) | FW30: =IF(AND(175>=$C$4,175<=$E$4),1,0) | FX30: =IF(AND(176>=$C$4,176<=$E$4),1,0) | FY30: =IF(AND(177>=$C$4,177<=$E$4),1,0) | FZ30: =IF(AND(178>=$C$4,178<=$E$4),1,0) | GA30: =IF(AND(179>=$C$4,179<=$E$4),1,0) | GB30: =IF(AND(180>=$C$4,180<=$E$4),1,0) | GC30: =IF(AND(181>=$C$4,181<=$E$4),1,0) | GD30: =IF(AND(182>=$C$4,182<=$E$4),1,0) | GE30: =IF(AND(183>=$C$4,183<=$E$4),1,0) | GF30: =IF(AND(184>=$C$4,184<=$E$4),1,0) | GG30: =IF(AND(185>=$C$4,185<=$E$4),1,0) | GH30: =IF(AND(186>=$C$4,186<=$E$4),1,0) | GI30: =IF(AND(187>=$C$4,187<=$E$4),1,0) | GJ30: =IF(AND(188>=$C$4,188<=$E$4),1,0) | GK30: =IF(AND(189>=$C$4,189<=$E$4),1,0) | GL30: =IF(AND(190>=$C$4,190<=$E$4),1,0) | GM30: =IF(AND(191>=$C$4,191<=$E$4),1,0) | GN30: =IF(AND(192>=$C$4,192<=$E$4),1,0) | GO30: =IF(AND(193>=$C$4,193<=$E$4),1,0) | GP30: =IF(AND(194>=$C$4,194<=$E$4),1,0) | GQ30: =IF(AND(195>=$C$4,195<=$E$4),1,0) | GR30: =IF(AND(196>=$C$4,196<=$E$4),1,0) | GS30: =IF(AND(197>=$C$4,197<=$E$4),1,0) | GT30: =IF(AND(198>=$C$4,198<=$E$4),1,0) | GU30: =IF(AND(199>=$C$4,199<=$E$4),1,0) | GV30: =IF(AND(200>=$C$4,200<=$E$4),1,0) | GW30: =IF(AND(201>=$C$4,201<=$E$4),1,0) | GX30: =IF(AND(202>=$C$4,202<=$E$4),1,0) | GY30: =IF(AND(203>=$C$4,203<=$E$4),1,0) | GZ30: =IF(AND(204>=$C$4,204<=$E$4),1,0) | HA30: =IF(AND(205>=$C$4,205<=$E$4),1,0) | HB30: =IF(AND(206>=$C$4,206<=$E$4),1,0) | HC30: =IF(AND(207>=$C$4,207<=$E$4),1,0) | HD30: =IF(AND(208>=$C$4,208<=$E$4),1,0) | HE30: =IF(AND(209>=$C$4,209<=$E$4),1,0) | HF30: =IF(AND(210>=$C$4,210<=$E$4),1,0) | HG30: =IF(AND(211>=$C$4,211<=$E$4),1,0) | HH30: =IF(AND(212>=$C$4,212<=$E$4),1,0) | HI30: =IF(AND(213>=$C$4,213<=$E$4),1,0) | HJ30: =IF(AND(214>=$C$4,214<=$E$4),1,0) | HK30: =IF(AND(215>=$C$4,215<=$E$4),1,0) | HL30: =IF(AND(216>=$C$4,216<=$E$4),1,0) | HM30: =IF(AND(217>=$C$4,217<=$E$4),1,0) | HN30: =IF(AND(218>=$C$4,218<=$E$4),1,0) | HO30: =IF(AND(219>=$C$4,219<=$E$4),1,0) | HP30: =IF(AND(220>=$C$4,220<=$E$4),1,0) | HQ30: =IF(AND(221>=$C$4,221<=$E$4),1,0) | HR30: =IF(AND(222>=$C$4,222<=$E$4),1,0) | HS30: =IF(AND(223>=$C$4,223<=$E$4),1,0) | HT30: =IF(AND(224>=$C$4,224<=$E$4),1,0) | HU30: =IF(AND(225>=$C$4,225<=$E$4),1,0) | HV30: =IF(AND(226>=$C$4,226<=$E$4),1,0) | HW30: =IF(AND(227>=$C$4,227<=$E$4),1,0) | HX30: =IF(AND(228>=$C$4,228<=$E$4),1,0) | HY30: =IF(AND(229>=$C$4,229<=$E$4),1,0) | HZ30: =IF(AND(230>=$C$4,230<=$E$4),1,0) | IA30: =IF(AND(231>=$C$4,231<=$E$4),1,0) | IB30: =IF(AND(232>=$C$4,232<=$E$4),1,0) | IC30: =IF(AND(233>=$C$4,233<=$E$4),1,0) | ID30: =IF(AND(234>=$C$4,234<=$E$4),1,0) | IE30: =IF(AND(235>=$C$4,235<=$E$4),1,0) | IF30: =IF(AND(236>=$C$4,236<=$E$4),1,0) | IG30: =IF(AND(237>=$C$4,237<=$E$4),1,0) | IH30: =IF(AND(238>=$C$4,238<=$E$4),1,0) | II30: =IF(AND(239>=$C$4,239<=$E$4),1,0) | IJ30: =IF(AND(240>=$C$4,240<=$E$4),1,0) | IK30: =IF(AND(241>=$C$4,241<=$E$4),1,0) | IL30: =IF(AND(242>=$C$4,242<=$E$4),1,0) | IM30: =IF(AND(243>=$C$4,243<=$E$4),1,0) | IN30: =IF(AND(244>=$C$4,244<=$E$4),1,0) | IO30: =IF(AND(245>=$C$4,245<=$E$4),1,0) | IP30: =IF(AND(246>=$C$4,246<=$E$4),1,0) | IQ30: =IF(AND(247>=$C$4,247<=$E$4),1,0) | IR30: =IF(AND(248>=$C$4,248<=$E$4),1,0) | IS30: =IF(AND(249>=$C$4,249<=$E$4),1,0) | IT30: =IF(AND(250>=$C$4,250<=$E$4),1,0) | IU30: =IF(AND(251>=$C$4,251<=$E$4),1,0) | IV30: =IF(AND(252>=$C$4,252<=$E$4),1,0) | IW30: =IF(AND(253>=$C$4,253<=$E$4),1,0) | IX30: =IF(AND(254>=$C$4,254<=$E$4),1,0) | IY30: =IF(AND(255>=$C$4,255<=$E$4),1,0) | IZ30: =IF(AND(256>=$C$4,256<=$E$4),1,0) | JA30: =IF(AND(257>=$C$4,257<=$E$4),1,0) | JB30: =IF(AND(258>=$C$4,258<=$E$4),1,0) | JC30: =IF(AND(259>=$C$4,259<=$E$4),1,0) | JD30: =IF(AND(260>=$C$4,260<=$E$4),1,0) | JE30: =IF(AND(261>=$C$4,261<=$E$4),1,0) | JF30: =IF(AND(262>=$C$4,262<=$E$4),1,0) | JG30: =IF(AND(263>=$C$4,263<=$E$4),1,0) | JH30: =IF(AND(264>=$C$4,264<=$E$4),1,0) | JI30: =IF(AND(265>=$C$4,265<=$E$4),1,0) | JJ30: =IF(AND(266>=$C$4,266<=$E$4),1,0) | JK30: =IF(AND(267>=$C$4,267<=$E$4),1,0) | JL30: =IF(AND(268>=$C$4,268<=$E$4),1,0) | JM30: =IF(AND(269>=$C$4,269<=$E$4),1,0) | JN30: =IF(AND(270>=$C$4,270<=$E$4),1,0) | JO30: =IF(AND(271>=$C$4,271<=$E$4),1,0) | JP30: =IF(AND(272>=$C$4,272<=$E$4),1,0) | JQ30: =IF(AND(273>=$C$4,273<=$E$4),1,0) | JR30: =IF(AND(274>=$C$4,274<=$E$4),1,0) | JS30: =IF(AND(275>=$C$4,275<=$E$4),1,0) | JT30: =IF(AND(276>=$C$4,276<=$E$4),1,0) | JU30: =IF(AND(277>=$C$4,277<=$E$4),1,0) | JV30: =IF(AND(278>=$C$4,278<=$E$4),1,0) | JW30: =IF(AND(279>=$C$4,279<=$E$4),1,0) | JX30: =IF(AND(280>=$C$4,280<=$E$4),1,0) | JY30: =IF(AND(281>=$C$4,281<=$E$4),1,0) | JZ30: =IF(AND(282>=$C$4,282<=$E$4),1,0) | KA30: =IF(AND(283>=$C$4,283<=$E$4),1,0) | KB30: =IF(AND(284>=$C$4,284<=$E$4),1,0) | KC30: =IF(AND(285>=$C$4,285<=$E$4),1,0) | KD30: =IF(AND(286>=$C$4,286<=$E$4),1,0) | KE30: =IF(AND(287>=$C$4,287<=$E$4),1,0) | KF30: =IF(AND(288>=$C$4,288<=$E$4),1,0) | KG30: =IF(AND(289>=$C$4,289<=$E$4),1,0) | KH30: =IF(AND(290>=$C$4,290<=$E$4),1,0) | KI30: =IF(AND(291>=$C$4,291<=$E$4),1,0) | KJ30: =IF(AND(292>=$C$4,292<=$E$4),1,0) | KK30: =IF(AND(293>=$C$4,293<=$E$4),1,0) | KL30: =IF(AND(294>=$C$4,294<=$E$4),1,0) | KM30: =IF(AND(295>=$C$4,295<=$E$4),1,0) | KN30: =IF(AND(296>=$C$4,296<=$E$4),1,0) | KO30: =IF(AND(297>=$C$4,297<=$E$4),1,0) | KP30: =IF(AND(298>=$C$4,298<=$E$4),1,0) | KQ30: =IF(AND(299>=$C$4,299<=$E$4),1,0) | KR30: =IF(AND(300>=$C$4,300<=$E$4),1,0) | KS30: =IF(AND(301>=$C$4,301<=$E$4),1,0) | KT30: =IF(AND(302>=$C$4,302<=$E$4),1,0) | KU30: =IF(AND(303>=$C$4,303<=$E$4),1,0) | KV30: =IF(AND(304>=$C$4,304<=$E$4),1,0) | KW30: =IF(AND(305>=$C$4,305<=$E$4),1,0) | KX30: =IF(AND(306>=$C$4,306<=$E$4),1,0) | KY30: =IF(AND(307>=$C$4,307<=$E$4),1,0) | KZ30: =IF(AND(308>=$C$4,308<=$E$4),1,0) | LA30: =IF(AND(309>=$C$4,309<=$E$4),1,0) | LB30: =IF(AND(310>=$C$4,310<=$E$4),1,0) | LC30: =IF(AND(311>=$C$4,311<=$E$4),1,0) | LD30: =IF(AND(312>=$C$4,312<=$E$4),1,0) | LE30: =IF(AND(313>=$C$4,313<=$E$4),1,0) | LF30: =IF(AND(314>=$C$4,314<=$E$4),1,0) | LG30: =IF(AND(315>=$C$4,315<=$E$4),1,0) | LH30: =IF(AND(316>=$C$4,316<=$E$4),1,0) | LI30: =IF(AND(317>=$C$4,317<=$E$4),1,0) | LJ30: =IF(AND(318>=$C$4,318<=$E$4),1,0) | LK30: =IF(AND(319>=$C$4,319<=$E$4),1,0) | LL30: =IF(AND(320>=$C$4,320<=$E$4),1,0) | LM30: =IF(AND(321>=$C$4,321<=$E$4),1,0) | LN30: =IF(AND(322>=$C$4,322<=$E$4),1,0) | LO30: =IF(AND(323>=$C$4,323<=$E$4),1,0) | LP30: =IF(AND(324>=$C$4,324<=$E$4),1,0) | LQ30: =IF(AND(325>=$C$4,325<=$E$4),1,0) | LR30: =IF(AND(326>=$C$4,326<=$E$4),1,0) | LS30: =IF(AND(327>=$C$4,327<=$E$4),1,0) | LT30: =IF(AND(328>=$C$4,328<=$E$4),1,0) | LU30: =IF(AND(329>=$C$4,329<=$E$4),1,0) | LV30: =IF(AND(330>=$C$4,330<=$E$4),1,0) | LW30: =IF(AND(331>=$C$4,331<=$E$4),1,0) | LX30: =IF(AND(332>=$C$4,332<=$E$4),1,0) | LY30: =IF(AND(333>=$C$4,333<=$E$4),1,0) | LZ30: =IF(AND(334>=$C$4,334<=$E$4),1,0) | MA30: =IF(AND(335>=$C$4,335<=$E$4),1,0) | MB30: =IF(AND(336>=$C$4,336<=$E$4),1,0) | MC30: =IF(AND(337>=$C$4,337<=$E$4),1,0) | MD30: =IF(AND(338>=$C$4,338<=$E$4),1,0) | ME30: =IF(AND(339>=$C$4,339<=$E$4),1,0) | MF30: =IF(AND(340>=$C$4,340<=$E$4),1,0) | MG30: =IF(AND(341>=$C$4,341<=$E$4),1,0) | MH30: =IF(AND(342>=$C$4,342<=$E$4),1,0) | MI30: =IF(AND(343>=$C$4,343<=$E$4),1,0) | MJ30: =IF(AND(344>=$C$4,344<=$E$4),1,0) | MK30: =IF(AND(345>=$C$4,345<=$E$4),1,0) | ML30: =IF(AND(346>=$C$4,346<=$E$4),1,0) | MM30: =IF(AND(347>=$C$4,347<=$E$4),1,0) | MN30: =IF(AND(348>=$C$4,348<=$E$4),1,0) | MO30: =IF(AND(349>=$C$4,349<=$E$4),1,0) | MP30: =IF(AND(350>=$C$4,350<=$E$4),1,0) | MQ30: =IF(AND(351>=$C$4,351<=$E$4),1,0) | MR30: =IF(AND(352>=$C$4,352<=$E$4),1,0) | MS30: =IF(AND(353>=$C$4,353<=$E$4),1,0) | MT30: =IF(AND(354>=$C$4,354<=$E$4),1,0) | MU30: =IF(AND(355>=$C$4,355<=$E$4),1,0) | MV30: =IF(AND(356>=$C$4,356<=$E$4),1,0) | MW30: =IF(AND(357>=$C$4,357<=$E$4),1,0) | MX30: =IF(AND(358>=$C$4,358<=$E$4),1,0) | MY30: =IF(AND(359>=$C$4,359<=$E$4),1,0) | MZ30: =IF(AND(360>=$C$4,360<=$E$4),1,0) | NA30: =IF(AND(361>=$C$4,361<=$E$4),1,0) | NB30: =IF(AND(362>=$C$4,362<=$E$4),1,0) | NC30: =IF(AND(363>=$C$4,363<=$E$4),1,0) | ND30: =IF(AND(364>=$C$4,364<=$E$4),1,0) | NE30: =IF(AND(365>=$C$4,365<=$E$4),1,0) | NF30: =IF(AND(366>=$C$4,366<=$E$4),1,0) | NG30: =IF(AND(367>=$C$4,367<=$E$4),1,0) | NH30: =IF(AND(368>=$C$4,368<=$E$4),1,0) | NI30: =IF(AND(369>=$C$4,369<=$E$4),1,0) | NJ30: =IF(AND(370>=$C$4,370<=$E$4),1,0) | NK30: =IF(AND(371>=$C$4,371<=$E$4),1,0) | NL30: =IF(AND(372>=$C$4,372<=$E$4),1,0)
B31: Flag: Due Diligence | E31: =IF(AND(1>=$C$5,1<=$E$5),1,0) | F31: =IF(AND(2>=$C$5,2<=$E$5),1,0) | G31: =IF(AND(3>=$C$5,3<=$E$5),1,0) | H31: =IF(AND(4>=$C$5,4<=$E$5),1,0) | I31: =IF(AND(5>=$C$5,5<=$E$5),1,0) | J31: =IF(AND(6>=$C$5,6<=$E$5),1,0) | K31: =IF(AND(7>=$C$5,7<=$E$5),1,0) | L31: =IF(AND(8>=$C$5,8<=$E$5),1,0) | M31: =IF(AND(9>=$C$5,9<=$E$5),1,0) | N31: =IF(AND(10>=$C$5,10<=$E$5),1,0) | O31: =IF(AND(11>=$C$5,11<=$E$5),1,0) | P31: =IF(AND(12>=$C$5,12<=$E$5),1,0) | Q31: =IF(AND(13>=$C$5,13<=$E$5),1,0) | R31: =IF(AND(14>=$C$5,14<=$E$5),1,0) | S31: =IF(AND(15>=$C$5,15<=$E$5),1,0) | T31: =IF(AND(16>=$C$5,16<=$E$5),1,0) | U31: =IF(AND(17>=$C$5,17<=$E$5),1,0) | V31: =IF(AND(18>=$C$5,18<=$E$5),1,0) | W31: =IF(AND(19>=$C$5,19<=$E$5),1,0) | X31: =IF(AND(20>=$C$5,20<=$E$5),1,0) | Y31: =IF(AND(21>=$C$5,21<=$E$5),1,0) | Z31: =IF(AND(22>=$C$5,22<=$E$5),1,0) | AA31: =IF(AND(23>=$C$5,23<=$E$5),1,0) | AB31: =IF(AND(24>=$C$5,24<=$E$5),1,0) | AC31: =IF(AND(25>=$C$5,25<=$E$5),1,0) | AD31: =IF(AND(26>=$C$5,26<=$E$5),1,0) | AE31: =IF(AND(27>=$C$5,27<=$E$5),1,0) | AF31: =IF(AND(28>=$C$5,28<=$E$5),1,0) | AG31: =IF(AND(29>=$C$5,29<=$E$5),1,0) | AH31: =IF(AND(30>=$C$5,30<=$E$5),1,0) | AI31: =IF(AND(31>=$C$5,31<=$E$5),1,0) | AJ31: =IF(AND(32>=$C$5,32<=$E$5),1,0) | AK31: =IF(AND(33>=$C$5,33<=$E$5),1,0) | AL31: =IF(AND(34>=$C$5,34<=$E$5),1,0) | AM31: =IF(AND(35>=$C$5,35<=$E$5),1,0) | AN31: =IF(AND(36>=$C$5,36<=$E$5),1,0) | AO31: =IF(AND(37>=$C$5,37<=$E$5),1,0) | AP31: =IF(AND(38>=$C$5,38<=$E$5),1,0) | AQ31: =IF(AND(39>=$C$5,39<=$E$5),1,0) | AR31: =IF(AND(40>=$C$5,40<=$E$5),1,0) | AS31: =IF(AND(41>=$C$5,41<=$E$5),1,0) | AT31: =IF(AND(42>=$C$5,42<=$E$5),1,0) | AU31: =IF(AND(43>=$C$5,43<=$E$5),1,0) | AV31: =IF(AND(44>=$C$5,44<=$E$5),1,0) | AW31: =IF(AND(45>=$C$5,45<=$E$5),1,0) | AX31: =IF(AND(46>=$C$5,46<=$E$5),1,0) | AY31: =IF(AND(47>=$C$5,47<=$E$5),1,0) | AZ31: =IF(AND(48>=$C$5,48<=$E$5),1,0) | BA31: =IF(AND(49>=$C$5,49<=$E$5),1,0) | BB31: =IF(AND(50>=$C$5,50<=$E$5),1,0) | BC31: =IF(AND(51>=$C$5,51<=$E$5),1,0) | BD31: =IF(AND(52>=$C$5,52<=$E$5),1,0) | BE31: =IF(AND(53>=$C$5,53<=$E$5),1,0) | BF31: =IF(AND(54>=$C$5,54<=$E$5),1,0) | BG31: =IF(AND(55>=$C$5,55<=$E$5),1,0) | BH31: =IF(AND(56>=$C$5,56<=$E$5),1,0) | BI31: =IF(AND(57>=$C$5,57<=$E$5),1,0) | BJ31: =IF(AND(58>=$C$5,58<=$E$5),1,0) | BK31: =IF(AND(59>=$C$5,59<=$E$5),1,0) | BL31: =IF(AND(60>=$C$5,60<=$E$5),1,0) | BM31: =IF(AND(61>=$C$5,61<=$E$5),1,0) | BN31: =IF(AND(62>=$C$5,62<=$E$5),1,0) | BO31: =IF(AND(63>=$C$5,63<=$E$5),1,0) | BP31: =IF(AND(64>=$C$5,64<=$E$5),1,0) | BQ31: =IF(AND(65>=$C$5,65<=$E$5),1,0) | BR31: =IF(AND(66>=$C$5,66<=$E$5),1,0) | BS31: =IF(AND(67>=$C$5,67<=$E$5),1,0) | BT31: =IF(AND(68>=$C$5,68<=$E$5),1,0) | BU31: =IF(AND(69>=$C$5,69<=$E$5),1,0) | BV31: =IF(AND(70>=$C$5,70<=$E$5),1,0) | BW31: =IF(AND(71>=$C$5,71<=$E$5),1,0) | BX31: =IF(AND(72>=$C$5,72<=$E$5),1,0) | BY31: =IF(AND(73>=$C$5,73<=$E$5),1,0) | BZ31: =IF(AND(74>=$C$5,74<=$E$5),1,0) | CA31: =IF(AND(75>=$C$5,75<=$E$5),1,0) | CB31: =IF(AND(76>=$C$5,76<=$E$5),1,0) | CC31: =IF(AND(77>=$C$5,77<=$E$5),1,0) | CD31: =IF(AND(78>=$C$5,78<=$E$5),1,0) | CE31: =IF(AND(79>=$C$5,79<=$E$5),1,0) | CF31: =IF(AND(80>=$C$5,80<=$E$5),1,0) | CG31: =IF(AND(81>=$C$5,81<=$E$5),1,0) | CH31: =IF(AND(82>=$C$5,82<=$E$5),1,0) | CI31: =IF(AND(83>=$C$5,83<=$E$5),1,0) | CJ31: =IF(AND(84>=$C$5,84<=$E$5),1,0) | CK31: =IF(AND(85>=$C$5,85<=$E$5),1,0) | CL31: =IF(AND(86>=$C$5,86<=$E$5),1,0) | CM31: =IF(AND(87>=$C$5,87<=$E$5),1,0) | CN31: =IF(AND(88>=$C$5,88<=$E$5),1,0) | CO31: =IF(AND(89>=$C$5,89<=$E$5),1,0) | CP31: =IF(AND(90>=$C$5,90<=$E$5),1,0) | CQ31: =IF(AND(91>=$C$5,91<=$E$5),1,0) | CR31: =IF(AND(92>=$C$5,92<=$E$5),1,0) | CS31: =IF(AND(93>=$C$5,93<=$E$5),1,0) | CT31: =IF(AND(94>=$C$5,94<=$E$5),1,0) | CU31: =IF(AND(95>=$C$5,95<=$E$5),1,0) | CV31: =IF(AND(96>=$C$5,96<=$E$5),1,0) | CW31: =IF(AND(97>=$C$5,97<=$E$5),1,0) | CX31: =IF(AND(98>=$C$5,98<=$E$5),1,0) | CY31: =IF(AND(99>=$C$5,99<=$E$5),1,0) | CZ31: =IF(AND(100>=$C$5,100<=$E$5),1,0) | DA31: =IF(AND(101>=$C$5,101<=$E$5),1,0) | DB31: =IF(AND(102>=$C$5,102<=$E$5),1,0) | DC31: =IF(AND(103>=$C$5,103<=$E$5),1,0) | DD31: =IF(AND(104>=$C$5,104<=$E$5),1,0) | DE31: =IF(AND(105>=$C$5,105<=$E$5),1,0) | DF31: =IF(AND(106>=$C$5,106<=$E$5),1,0) | DG31: =IF(AND(107>=$C$5,107<=$E$5),1,0) | DH31: =IF(AND(108>=$C$5,108<=$E$5),1,0) | DI31: =IF(AND(109>=$C$5,109<=$E$5),1,0) | DJ31: =IF(AND(110>=$C$5,110<=$E$5),1,0) | DK31: =IF(AND(111>=$C$5,111<=$E$5),1,0) | DL31: =IF(AND(112>=$C$5,112<=$E$5),1,0) | DM31: =IF(AND(113>=$C$5,113<=$E$5),1,0) | DN31: =IF(AND(114>=$C$5,114<=$E$5),1,0) | DO31: =IF(AND(115>=$C$5,115<=$E$5),1,0) | DP31: =IF(AND(116>=$C$5,116<=$E$5),1,0) | DQ31: =IF(AND(117>=$C$5,117<=$E$5),1,0) | DR31: =IF(AND(118>=$C$5,118<=$E$5),1,0) | DS31: =IF(AND(119>=$C$5,119<=$E$5),1,0) | DT31: =IF(AND(120>=$C$5,120<=$E$5),1,0) | DU31: =IF(AND(121>=$C$5,121<=$E$5),1,0) | DV31: =IF(AND(122>=$C$5,122<=$E$5),1,0) | DW31: =IF(AND(123>=$C$5,123<=$E$5),1,0) | DX31: =IF(AND(124>=$C$5,124<=$E$5),1,0) | DY31: =IF(AND(125>=$C$5,125<=$E$5),1,0) | DZ31: =IF(AND(126>=$C$5,126<=$E$5),1,0) | EA31: =IF(AND(127>=$C$5,127<=$E$5),1,0) | EB31: =IF(AND(128>=$C$5,128<=$E$5),1,0) | EC31: =IF(AND(129>=$C$5,129<=$E$5),1,0) | ED31: =IF(AND(130>=$C$5,130<=$E$5),1,0) | EE31: =IF(AND(131>=$C$5,131<=$E$5),1,0) | EF31: =IF(AND(132>=$C$5,132<=$E$5),1,0) | EG31: =IF(AND(133>=$C$5,133<=$E$5),1,0) | EH31: =IF(AND(134>=$C$5,134<=$E$5),1,0) | EI31: =IF(AND(135>=$C$5,135<=$E$5),1,0) | EJ31: =IF(AND(136>=$C$5,136<=$E$5),1,0) | EK31: =IF(AND(137>=$C$5,137<=$E$5),1,0) | EL31: =IF(AND(138>=$C$5,138<=$E$5),1,0) | EM31: =IF(AND(139>=$C$5,139<=$E$5),1,0) | EN31: =IF(AND(140>=$C$5,140<=$E$5),1,0) | EO31: =IF(AND(141>=$C$5,141<=$E$5),1,0) | EP31: =IF(AND(142>=$C$5,142<=$E$5),1,0) | EQ31: =IF(AND(143>=$C$5,143<=$E$5),1,0) | ER31: =IF(AND(144>=$C$5,144<=$E$5),1,0) | ES31: =IF(AND(145>=$C$5,145<=$E$5),1,0) | ET31: =IF(AND(146>=$C$5,146<=$E$5),1,0) | EU31: =IF(AND(147>=$C$5,147<=$E$5),1,0) | EV31: =IF(AND(148>=$C$5,148<=$E$5),1,0) | EW31: =IF(AND(149>=$C$5,149<=$E$5),1,0) | EX31: =IF(AND(150>=$C$5,150<=$E$5),1,0) | EY31: =IF(AND(151>=$C$5,151<=$E$5),1,0) | EZ31: =IF(AND(152>=$C$5,152<=$E$5),1,0) | FA31: =IF(AND(153>=$C$5,153<=$E$5),1,0) | FB31: =IF(AND(154>=$C$5,154<=$E$5),1,0) | FC31: =IF(AND(155>=$C$5,155<=$E$5),1,0) | FD31: =IF(AND(156>=$C$5,156<=$E$5),1,0) | FE31: =IF(AND(157>=$C$5,157<=$E$5),1,0) | FF31: =IF(AND(158>=$C$5,158<=$E$5),1,0) | FG31: =IF(AND(159>=$C$5,159<=$E$5),1,0) | FH31: =IF(AND(160>=$C$5,160<=$E$5),1,0) | FI31: =IF(AND(161>=$C$5,161<=$E$5),1,0) | FJ31: =IF(AND(162>=$C$5,162<=$E$5),1,0) | FK31: =IF(AND(163>=$C$5,163<=$E$5),1,0) | FL31: =IF(AND(164>=$C$5,164<=$E$5),1,0) | FM31: =IF(AND(165>=$C$5,165<=$E$5),1,0) | FN31: =IF(AND(166>=$C$5,166<=$E$5),1,0) | FO31: =IF(AND(167>=$C$5,167<=$E$5),1,0) | FP31: =IF(AND(168>=$C$5,168<=$E$5),1,0) | FQ31: =IF(AND(169>=$C$5,169<=$E$5),1,0) | FR31: =IF(AND(170>=$C$5,170<=$E$5),1,0) | FS31: =IF(AND(171>=$C$5,171<=$E$5),1,0) | FT31: =IF(AND(172>=$C$5,172<=$E$5),1,0) | FU31: =IF(AND(173>=$C$5,173<=$E$5),1,0) | FV31: =IF(AND(174>=$C$5,174<=$E$5),1,0) | FW31: =IF(AND(175>=$C$5,175<=$E$5),1,0) | FX31: =IF(AND(176>=$C$5,176<=$E$5),1,0) | FY31: =IF(AND(177>=$C$5,177<=$E$5),1,0) | FZ31: =IF(AND(178>=$C$5,178<=$E$5),1,0) | GA31: =IF(AND(179>=$C$5,179<=$E$5),1,0) | GB31: =IF(AND(180>=$C$5,180<=$E$5),1,0) | GC31: =IF(AND(181>=$C$5,181<=$E$5),1,0) | GD31: =IF(AND(182>=$C$5,182<=$E$5),1,0) | GE31: =IF(AND(183>=$C$5,183<=$E$5),1,0) | GF31: =IF(AND(184>=$C$5,184<=$E$5),1,0) | GG31: =IF(AND(185>=$C$5,185<=$E$5),1,0) | GH31: =IF(AND(186>=$C$5,186<=$E$5),1,0) | GI31: =IF(AND(187>=$C$5,187<=$E$5),1,0) | GJ31: =IF(AND(188>=$C$5,188<=$E$5),1,0) | GK31: =IF(AND(189>=$C$5,189<=$E$5),1,0) | GL31: =IF(AND(190>=$C$5,190<=$E$5),1,0) | GM31: =IF(AND(191>=$C$5,191<=$E$5),1,0) | GN31: =IF(AND(192>=$C$5,192<=$E$5),1,0) | GO31: =IF(AND(193>=$C$5,193<=$E$5),1,0) | GP31: =IF(AND(194>=$C$5,194<=$E$5),1,0) | GQ31: =IF(AND(195>=$C$5,195<=$E$5),1,0) | GR31: =IF(AND(196>=$C$5,196<=$E$5),1,0) | GS31: =IF(AND(197>=$C$5,197<=$E$5),1,0) | GT31: =IF(AND(198>=$C$5,198<=$E$5),1,0) | GU31: =IF(AND(199>=$C$5,199<=$E$5),1,0) | GV31: =IF(AND(200>=$C$5,200<=$E$5),1,0) | GW31: =IF(AND(201>=$C$5,201<=$E$5),1,0) | GX31: =IF(AND(202>=$C$5,202<=$E$5),1,0) | GY31: =IF(AND(203>=$C$5,203<=$E$5),1,0) | GZ31: =IF(AND(204>=$C$5,204<=$E$5),1,0) | HA31: =IF(AND(205>=$C$5,205<=$E$5),1,0) | HB31: =IF(AND(206>=$C$5,206<=$E$5),1,0) | HC31: =IF(AND(207>=$C$5,207<=$E$5),1,0) | HD31: =IF(AND(208>=$C$5,208<=$E$5),1,0) | HE31: =IF(AND(209>=$C$5,209<=$E$5),1,0) | HF31: =IF(AND(210>=$C$5,210<=$E$5),1,0) | HG31: =IF(AND(211>=$C$5,211<=$E$5),1,0) | HH31: =IF(AND(212>=$C$5,212<=$E$5),1,0) | HI31: =IF(AND(213>=$C$5,213<=$E$5),1,0) | HJ31: =IF(AND(214>=$C$5,214<=$E$5),1,0) | HK31: =IF(AND(215>=$C$5,215<=$E$5),1,0) | HL31: =IF(AND(216>=$C$5,216<=$E$5),1,0) | HM31: =IF(AND(217>=$C$5,217<=$E$5),1,0) | HN31: =IF(AND(218>=$C$5,218<=$E$5),1,0) | HO31: =IF(AND(219>=$C$5,219<=$E$5),1,0) | HP31: =IF(AND(220>=$C$5,220<=$E$5),1,0) | HQ31: =IF(AND(221>=$C$5,221<=$E$5),1,0) | HR31: =IF(AND(222>=$C$5,222<=$E$5),1,0) | HS31: =IF(AND(223>=$C$5,223<=$E$5),1,0) | HT31: =IF(AND(224>=$C$5,224<=$E$5),1,0) | HU31: =IF(AND(225>=$C$5,225<=$E$5),1,0) | HV31: =IF(AND(226>=$C$5,226<=$E$5),1,0) | HW31: =IF(AND(227>=$C$5,227<=$E$5),1,0) | HX31: =IF(AND(228>=$C$5,228<=$E$5),1,0) | HY31: =IF(AND(229>=$C$5,229<=$E$5),1,0) | HZ31: =IF(AND(230>=$C$5,230<=$E$5),1,0) | IA31: =IF(AND(231>=$C$5,231<=$E$5),1,0) | IB31: =IF(AND(232>=$C$5,232<=$E$5),1,0) | IC31: =IF(AND(233>=$C$5,233<=$E$5),1,0) | ID31: =IF(AND(234>=$C$5,234<=$E$5),1,0) | IE31: =IF(AND(235>=$C$5,235<=$E$5),1,0) | IF31: =IF(AND(236>=$C$5,236<=$E$5),1,0) | IG31: =IF(AND(237>=$C$5,237<=$E$5),1,0) | IH31: =IF(AND(238>=$C$5,238<=$E$5),1,0) | II31: =IF(AND(239>=$C$5,239<=$E$5),1,0) | IJ31: =IF(AND(240>=$C$5,240<=$E$5),1,0) | IK31: =IF(AND(241>=$C$5,241<=$E$5),1,0) | IL31: =IF(AND(242>=$C$5,242<=$E$5),1,0) | IM31: =IF(AND(243>=$C$5,243<=$E$5),1,0) | IN31: =IF(AND(244>=$C$5,244<=$E$5),1,0) | IO31: =IF(AND(245>=$C$5,245<=$E$5),1,0) | IP31: =IF(AND(246>=$C$5,246<=$E$5),1,0) | IQ31: =IF(AND(247>=$C$5,247<=$E$5),1,0) | IR31: =IF(AND(248>=$C$5,248<=$E$5),1,0) | IS31: =IF(AND(249>=$C$5,249<=$E$5),1,0) | IT31: =IF(AND(250>=$C$5,250<=$E$5),1,0) | IU31: =IF(AND(251>=$C$5,251<=$E$5),1,0) | IV31: =IF(AND(252>=$C$5,252<=$E$5),1,0) | IW31: =IF(AND(253>=$C$5,253<=$E$5),1,0) | IX31: =IF(AND(254>=$C$5,254<=$E$5),1,0) | IY31: =IF(AND(255>=$C$5,255<=$E$5),1,0) | IZ31: =IF(AND(256>=$C$5,256<=$E$5),1,0) | JA31: =IF(AND(257>=$C$5,257<=$E$5),1,0) | JB31: =IF(AND(258>=$C$5,258<=$E$5),1,0) | JC31: =IF(AND(259>=$C$5,259<=$E$5),1,0) | JD31: =IF(AND(260>=$C$5,260<=$E$5),1,0) | JE31: =IF(AND(261>=$C$5,261<=$E$5),1,0) | JF31: =IF(AND(262>=$C$5,262<=$E$5),1,0) | JG31: =IF(AND(263>=$C$5,263<=$E$5),1,0) | JH31: =IF(AND(264>=$C$5,264<=$E$5),1,0) | JI31: =IF(AND(265>=$C$5,265<=$E$5),1,0) | JJ31: =IF(AND(266>=$C$5,266<=$E$5),1,0) | JK31: =IF(AND(267>=$C$5,267<=$E$5),1,0) | JL31: =IF(AND(268>=$C$5,268<=$E$5),1,0) | JM31: =IF(AND(269>=$C$5,269<=$E$5),1,0) | JN31: =IF(AND(270>=$C$5,270<=$E$5),1,0) | JO31: =IF(AND(271>=$C$5,271<=$E$5),1,0) | JP31: =IF(AND(272>=$C$5,272<=$E$5),1,0) | JQ31: =IF(AND(273>=$C$5,273<=$E$5),1,0) | JR31: =IF(AND(274>=$C$5,274<=$E$5),1,0) | JS31: =IF(AND(275>=$C$5,275<=$E$5),1,0) | JT31: =IF(AND(276>=$C$5,276<=$E$5),1,0) | JU31: =IF(AND(277>=$C$5,277<=$E$5),1,0) | JV31: =IF(AND(278>=$C$5,278<=$E$5),1,0) | JW31: =IF(AND(279>=$C$5,279<=$E$5),1,0) | JX31: =IF(AND(280>=$C$5,280<=$E$5),1,0) | JY31: =IF(AND(281>=$C$5,281<=$E$5),1,0) | JZ31: =IF(AND(282>=$C$5,282<=$E$5),1,0) | KA31: =IF(AND(283>=$C$5,283<=$E$5),1,0) | KB31: =IF(AND(284>=$C$5,284<=$E$5),1,0) | KC31: =IF(AND(285>=$C$5,285<=$E$5),1,0) | KD31: =IF(AND(286>=$C$5,286<=$E$5),1,0) | KE31: =IF(AND(287>=$C$5,287<=$E$5),1,0) | KF31: =IF(AND(288>=$C$5,288<=$E$5),1,0) | KG31: =IF(AND(289>=$C$5,289<=$E$5),1,0) | KH31: =IF(AND(290>=$C$5,290<=$E$5),1,0) | KI31: =IF(AND(291>=$C$5,291<=$E$5),1,0) | KJ31: =IF(AND(292>=$C$5,292<=$E$5),1,0) | KK31: =IF(AND(293>=$C$5,293<=$E$5),1,0) | KL31: =IF(AND(294>=$C$5,294<=$E$5),1,0) | KM31: =IF(AND(295>=$C$5,295<=$E$5),1,0) | KN31: =IF(AND(296>=$C$5,296<=$E$5),1,0) | KO31: =IF(AND(297>=$C$5,297<=$E$5),1,0) | KP31: =IF(AND(298>=$C$5,298<=$E$5),1,0) | KQ31: =IF(AND(299>=$C$5,299<=$E$5),1,0) | KR31: =IF(AND(300>=$C$5,300<=$E$5),1,0) | KS31: =IF(AND(301>=$C$5,301<=$E$5),1,0) | KT31: =IF(AND(302>=$C$5,302<=$E$5),1,0) | KU31: =IF(AND(303>=$C$5,303<=$E$5),1,0) | KV31: =IF(AND(304>=$C$5,304<=$E$5),1,0) | KW31: =IF(AND(305>=$C$5,305<=$E$5),1,0) | KX31: =IF(AND(306>=$C$5,306<=$E$5),1,0) | KY31: =IF(AND(307>=$C$5,307<=$E$5),1,0) | KZ31: =IF(AND(308>=$C$5,308<=$E$5),1,0) | LA31: =IF(AND(309>=$C$5,309<=$E$5),1,0) | LB31: =IF(AND(310>=$C$5,310<=$E$5),1,0) | LC31: =IF(AND(311>=$C$5,311<=$E$5),1,0) | LD31: =IF(AND(312>=$C$5,312<=$E$5),1,0) | LE31: =IF(AND(313>=$C$5,313<=$E$5),1,0) | LF31: =IF(AND(314>=$C$5,314<=$E$5),1,0) | LG31: =IF(AND(315>=$C$5,315<=$E$5),1,0) | LH31: =IF(AND(316>=$C$5,316<=$E$5),1,0) | LI31: =IF(AND(317>=$C$5,317<=$E$5),1,0) | LJ31: =IF(AND(318>=$C$5,318<=$E$5),1,0) | LK31: =IF(AND(319>=$C$5,319<=$E$5),1,0) | LL31: =IF(AND(320>=$C$5,320<=$E$5),1,0) | LM31: =IF(AND(321>=$C$5,321<=$E$5),1,0) | LN31: =IF(AND(322>=$C$5,322<=$E$5),1,0) | LO31: =IF(AND(323>=$C$5,323<=$E$5),1,0) | LP31: =IF(AND(324>=$C$5,324<=$E$5),1,0) | LQ31: =IF(AND(325>=$C$5,325<=$E$5),1,0) | LR31: =IF(AND(326>=$C$5,326<=$E$5),1,0) | LS31: =IF(AND(327>=$C$5,327<=$E$5),1,0) | LT31: =IF(AND(328>=$C$5,328<=$E$5),1,0) | LU31: =IF(AND(329>=$C$5,329<=$E$5),1,0) | LV31: =IF(AND(330>=$C$5,330<=$E$5),1,0) | LW31: =IF(AND(331>=$C$5,331<=$E$5),1,0) | LX31: =IF(AND(332>=$C$5,332<=$E$5),1,0) | LY31: =IF(AND(333>=$C$5,333<=$E$5),1,0) | LZ31: =IF(AND(334>=$C$5,334<=$E$5),1,0) | MA31: =IF(AND(335>=$C$5,335<=$E$5),1,0) | MB31: =IF(AND(336>=$C$5,336<=$E$5),1,0) | MC31: =IF(AND(337>=$C$5,337<=$E$5),1,0) | MD31: =IF(AND(338>=$C$5,338<=$E$5),1,0) | ME31: =IF(AND(339>=$C$5,339<=$E$5),1,0) | MF31: =IF(AND(340>=$C$5,340<=$E$5),1,0) | MG31: =IF(AND(341>=$C$5,341<=$E$5),1,0) | MH31: =IF(AND(342>=$C$5,342<=$E$5),1,0) | MI31: =IF(AND(343>=$C$5,343<=$E$5),1,0) | MJ31: =IF(AND(344>=$C$5,344<=$E$5),1,0) | MK31: =IF(AND(345>=$C$5,345<=$E$5),1,0) | ML31: =IF(AND(346>=$C$5,346<=$E$5),1,0) | MM31: =IF(AND(347>=$C$5,347<=$E$5),1,0) | MN31: =IF(AND(348>=$C$5,348<=$E$5),1,0) | MO31: =IF(AND(349>=$C$5,349<=$E$5),1,0) | MP31: =IF(AND(350>=$C$5,350<=$E$5),1,0) | MQ31: =IF(AND(351>=$C$5,351<=$E$5),1,0) | MR31: =IF(AND(352>=$C$5,352<=$E$5),1,0) | MS31: =IF(AND(353>=$C$5,353<=$E$5),1,0) | MT31: =IF(AND(354>=$C$5,354<=$E$5),1,0) | MU31: =IF(AND(355>=$C$5,355<=$E$5),1,0) | MV31: =IF(AND(356>=$C$5,356<=$E$5),1,0) | MW31: =IF(AND(357>=$C$5,357<=$E$5),1,0) | MX31: =IF(AND(358>=$C$5,358<=$E$5),1,0) | MY31: =IF(AND(359>=$C$5,359<=$E$5),1,0) | MZ31: =IF(AND(360>=$C$5,360<=$E$5),1,0) | NA31: =IF(AND(361>=$C$5,361<=$E$5),1,0) | NB31: =IF(AND(362>=$C$5,362<=$E$5),1,0) | NC31: =IF(AND(363>=$C$5,363<=$E$5),1,0) | ND31: =IF(AND(364>=$C$5,364<=$E$5),1,0) | NE31: =IF(AND(365>=$C$5,365<=$E$5),1,0) | NF31: =IF(AND(366>=$C$5,366<=$E$5),1,0) | NG31: =IF(AND(367>=$C$5,367<=$E$5),1,0) | NH31: =IF(AND(368>=$C$5,368<=$E$5),1,0) | NI31: =IF(AND(369>=$C$5,369<=$E$5),1,0) | NJ31: =IF(AND(370>=$C$5,370<=$E$5),1,0) | NK31: =IF(AND(371>=$C$5,371<=$E$5),1,0) | NL31: =IF(AND(372>=$C$5,372<=$E$5),1,0)
B32: Flag: Entitlement | E32: =IF(AND(1>=$C$6,1<=$E$6),1,0) | F32: =IF(AND(2>=$C$6,2<=$E$6),1,0) | G32: =IF(AND(3>=$C$6,3<=$E$6),1,0) | H32: =IF(AND(4>=$C$6,4<=$E$6),1,0) | I32: =IF(AND(5>=$C$6,5<=$E$6),1,0) | J32: =IF(AND(6>=$C$6,6<=$E$6),1,0) | K32: =IF(AND(7>=$C$6,7<=$E$6),1,0) | L32: =IF(AND(8>=$C$6,8<=$E$6),1,0) | M32: =IF(AND(9>=$C$6,9<=$E$6),1,0) | N32: =IF(AND(10>=$C$6,10<=$E$6),1,0) | O32: =IF(AND(11>=$C$6,11<=$E$6),1,0) | P32: =IF(AND(12>=$C$6,12<=$E$6),1,0) | Q32: =IF(AND(13>=$C$6,13<=$E$6),1,0) | R32: =IF(AND(14>=$C$6,14<=$E$6),1,0) | S32: =IF(AND(15>=$C$6,15<=$E$6),1,0) | T32: =IF(AND(16>=$C$6,16<=$E$6),1,0) | U32: =IF(AND(17>=$C$6,17<=$E$6),1,0) | V32: =IF(AND(18>=$C$6,18<=$E$6),1,0) | W32: =IF(AND(19>=$C$6,19<=$E$6),1,0) | X32: =IF(AND(20>=$C$6,20<=$E$6),1,0) | Y32: =IF(AND(21>=$C$6,21<=$E$6),1,0) | Z32: =IF(AND(22>=$C$6,22<=$E$6),1,0) | AA32: =IF(AND(23>=$C$6,23<=$E$6),1,0) | AB32: =IF(AND(24>=$C$6,24<=$E$6),1,0) | AC32: =IF(AND(25>=$C$6,25<=$E$6),1,0) | AD32: =IF(AND(26>=$C$6,26<=$E$6),1,0) | AE32: =IF(AND(27>=$C$6,27<=$E$6),1,0) | AF32: =IF(AND(28>=$C$6,28<=$E$6),1,0) | AG32: =IF(AND(29>=$C$6,29<=$E$6),1,0) | AH32: =IF(AND(30>=$C$6,30<=$E$6),1,0) | AI32: =IF(AND(31>=$C$6,31<=$E$6),1,0) | AJ32: =IF(AND(32>=$C$6,32<=$E$6),1,0) | AK32: =IF(AND(33>=$C$6,33<=$E$6),1,0) | AL32: =IF(AND(34>=$C$6,34<=$E$6),1,0) | AM32: =IF(AND(35>=$C$6,35<=$E$6),1,0) | AN32: =IF(AND(36>=$C$6,36<=$E$6),1,0) | AO32: =IF(AND(37>=$C$6,37<=$E$6),1,0) | AP32: =IF(AND(38>=$C$6,38<=$E$6),1,0) | AQ32: =IF(AND(39>=$C$6,39<=$E$6),1,0) | AR32: =IF(AND(40>=$C$6,40<=$E$6),1,0) | AS32: =IF(AND(41>=$C$6,41<=$E$6),1,0) | AT32: =IF(AND(42>=$C$6,42<=$E$6),1,0) | AU32: =IF(AND(43>=$C$6,43<=$E$6),1,0) | AV32: =IF(AND(44>=$C$6,44<=$E$6),1,0) | AW32: =IF(AND(45>=$C$6,45<=$E$6),1,0) | AX32: =IF(AND(46>=$C$6,46<=$E$6),1,0) | AY32: =IF(AND(47>=$C$6,47<=$E$6),1,0) | AZ32: =IF(AND(48>=$C$6,48<=$E$6),1,0) | BA32: =IF(AND(49>=$C$6,49<=$E$6),1,0) | BB32: =IF(AND(50>=$C$6,50<=$E$6),1,0) | BC32: =IF(AND(51>=$C$6,51<=$E$6),1,0) | BD32: =IF(AND(52>=$C$6,52<=$E$6),1,0) | BE32: =IF(AND(53>=$C$6,53<=$E$6),1,0) | BF32: =IF(AND(54>=$C$6,54<=$E$6),1,0) | BG32: =IF(AND(55>=$C$6,55<=$E$6),1,0) | BH32: =IF(AND(56>=$C$6,56<=$E$6),1,0) | BI32: =IF(AND(57>=$C$6,57<=$E$6),1,0) | BJ32: =IF(AND(58>=$C$6,58<=$E$6),1,0) | BK32: =IF(AND(59>=$C$6,59<=$E$6),1,0) | BL32: =IF(AND(60>=$C$6,60<=$E$6),1,0) | BM32: =IF(AND(61>=$C$6,61<=$E$6),1,0) | BN32: =IF(AND(62>=$C$6,62<=$E$6),1,0) | BO32: =IF(AND(63>=$C$6,63<=$E$6),1,0) | BP32: =IF(AND(64>=$C$6,64<=$E$6),1,0) | BQ32: =IF(AND(65>=$C$6,65<=$E$6),1,0) | BR32: =IF(AND(66>=$C$6,66<=$E$6),1,0) | BS32: =IF(AND(67>=$C$6,67<=$E$6),1,0) | BT32: =IF(AND(68>=$C$6,68<=$E$6),1,0) | BU32: =IF(AND(69>=$C$6,69<=$E$6),1,0) | BV32: =IF(AND(70>=$C$6,70<=$E$6),1,0) | BW32: =IF(AND(71>=$C$6,71<=$E$6),1,0) | BX32: =IF(AND(72>=$C$6,72<=$E$6),1,0) | BY32: =IF(AND(73>=$C$6,73<=$E$6),1,0) | BZ32: =IF(AND(74>=$C$6,74<=$E$6),1,0) | CA32: =IF(AND(75>=$C$6,75<=$E$6),1,0) | CB32: =IF(AND(76>=$C$6,76<=$E$6),1,0) | CC32: =IF(AND(77>=$C$6,77<=$E$6),1,0) | CD32: =IF(AND(78>=$C$6,78<=$E$6),1,0) | CE32: =IF(AND(79>=$C$6,79<=$E$6),1,0) | CF32: =IF(AND(80>=$C$6,80<=$E$6),1,0) | CG32: =IF(AND(81>=$C$6,81<=$E$6),1,0) | CH32: =IF(AND(82>=$C$6,82<=$E$6),1,0) | CI32: =IF(AND(83>=$C$6,83<=$E$6),1,0) | CJ32: =IF(AND(84>=$C$6,84<=$E$6),1,0) | CK32: =IF(AND(85>=$C$6,85<=$E$6),1,0) | CL32: =IF(AND(86>=$C$6,86<=$E$6),1,0) | CM32: =IF(AND(87>=$C$6,87<=$E$6),1,0) | CN32: =IF(AND(88>=$C$6,88<=$E$6),1,0) | CO32: =IF(AND(89>=$C$6,89<=$E$6),1,0) | CP32: =IF(AND(90>=$C$6,90<=$E$6),1,0) | CQ32: =IF(AND(91>=$C$6,91<=$E$6),1,0) | CR32: =IF(AND(92>=$C$6,92<=$E$6),1,0) | CS32: =IF(AND(93>=$C$6,93<=$E$6),1,0) | CT32: =IF(AND(94>=$C$6,94<=$E$6),1,0) | CU32: =IF(AND(95>=$C$6,95<=$E$6),1,0) | CV32: =IF(AND(96>=$C$6,96<=$E$6),1,0) | CW32: =IF(AND(97>=$C$6,97<=$E$6),1,0) | CX32: =IF(AND(98>=$C$6,98<=$E$6),1,0) | CY32: =IF(AND(99>=$C$6,99<=$E$6),1,0) | CZ32: =IF(AND(100>=$C$6,100<=$E$6),1,0) | DA32: =IF(AND(101>=$C$6,101<=$E$6),1,0) | DB32: =IF(AND(102>=$C$6,102<=$E$6),1,0) | DC32: =IF(AND(103>=$C$6,103<=$E$6),1,0) | DD32: =IF(AND(104>=$C$6,104<=$E$6),1,0) | DE32: =IF(AND(105>=$C$6,105<=$E$6),1,0) | DF32: =IF(AND(106>=$C$6,106<=$E$6),1,0) | DG32: =IF(AND(107>=$C$6,107<=$E$6),1,0) | DH32: =IF(AND(108>=$C$6,108<=$E$6),1,0) | DI32: =IF(AND(109>=$C$6,109<=$E$6),1,0) | DJ32: =IF(AND(110>=$C$6,110<=$E$6),1,0) | DK32: =IF(AND(111>=$C$6,111<=$E$6),1,0) | DL32: =IF(AND(112>=$C$6,112<=$E$6),1,0) | DM32: =IF(AND(113>=$C$6,113<=$E$6),1,0) | DN32: =IF(AND(114>=$C$6,114<=$E$6),1,0) | DO32: =IF(AND(115>=$C$6,115<=$E$6),1,0) | DP32: =IF(AND(116>=$C$6,116<=$E$6),1,0) | DQ32: =IF(AND(117>=$C$6,117<=$E$6),1,0) | DR32: =IF(AND(118>=$C$6,118<=$E$6),1,0) | DS32: =IF(AND(119>=$C$6,119<=$E$6),1,0) | DT32: =IF(AND(120>=$C$6,120<=$E$6),1,0) | DU32: =IF(AND(121>=$C$6,121<=$E$6),1,0) | DV32: =IF(AND(122>=$C$6,122<=$E$6),1,0) | DW32: =IF(AND(123>=$C$6,123<=$E$6),1,0) | DX32: =IF(AND(124>=$C$6,124<=$E$6),1,0) | DY32: =IF(AND(125>=$C$6,125<=$E$6),1,0) | DZ32: =IF(AND(126>=$C$6,126<=$E$6),1,0) | EA32: =IF(AND(127>=$C$6,127<=$E$6),1,0) | EB32: =IF(AND(128>=$C$6,128<=$E$6),1,0) | EC32: =IF(AND(129>=$C$6,129<=$E$6),1,0) | ED32: =IF(AND(130>=$C$6,130<=$E$6),1,0) | EE32: =IF(AND(131>=$C$6,131<=$E$6),1,0) | EF32: =IF(AND(132>=$C$6,132<=$E$6),1,0) | EG32: =IF(AND(133>=$C$6,133<=$E$6),1,0) | EH32: =IF(AND(134>=$C$6,134<=$E$6),1,0) | EI32: =IF(AND(135>=$C$6,135<=$E$6),1,0) | EJ32: =IF(AND(136>=$C$6,136<=$E$6),1,0) | EK32: =IF(AND(137>=$C$6,137<=$E$6),1,0) | EL32: =IF(AND(138>=$C$6,138<=$E$6),1,0) | EM32: =IF(AND(139>=$C$6,139<=$E$6),1,0) | EN32: =IF(AND(140>=$C$6,140<=$E$6),1,0) | EO32: =IF(AND(141>=$C$6,141<=$E$6),1,0) | EP32: =IF(AND(142>=$C$6,142<=$E$6),1,0) | EQ32: =IF(AND(143>=$C$6,143<=$E$6),1,0) | ER32: =IF(AND(144>=$C$6,144<=$E$6),1,0) | ES32: =IF(AND(145>=$C$6,145<=$E$6),1,0) | ET32: =IF(AND(146>=$C$6,146<=$E$6),1,0) | EU32: =IF(AND(147>=$C$6,147<=$E$6),1,0) | EV32: =IF(AND(148>=$C$6,148<=$E$6),1,0) | EW32: =IF(AND(149>=$C$6,149<=$E$6),1,0) | EX32: =IF(AND(150>=$C$6,150<=$E$6),1,0) | EY32: =IF(AND(151>=$C$6,151<=$E$6),1,0) | EZ32: =IF(AND(152>=$C$6,152<=$E$6),1,0) | FA32: =IF(AND(153>=$C$6,153<=$E$6),1,0) | FB32: =IF(AND(154>=$C$6,154<=$E$6),1,0) | FC32: =IF(AND(155>=$C$6,155<=$E$6),1,0) | FD32: =IF(AND(156>=$C$6,156<=$E$6),1,0) | FE32: =IF(AND(157>=$C$6,157<=$E$6),1,0) | FF32: =IF(AND(158>=$C$6,158<=$E$6),1,0) | FG32: =IF(AND(159>=$C$6,159<=$E$6),1,0) | FH32: =IF(AND(160>=$C$6,160<=$E$6),1,0) | FI32: =IF(AND(161>=$C$6,161<=$E$6),1,0) | FJ32: =IF(AND(162>=$C$6,162<=$E$6),1,0) | FK32: =IF(AND(163>=$C$6,163<=$E$6),1,0) | FL32: =IF(AND(164>=$C$6,164<=$E$6),1,0) | FM32: =IF(AND(165>=$C$6,165<=$E$6),1,0) | FN32: =IF(AND(166>=$C$6,166<=$E$6),1,0) | FO32: =IF(AND(167>=$C$6,167<=$E$6),1,0) | FP32: =IF(AND(168>=$C$6,168<=$E$6),1,0) | FQ32: =IF(AND(169>=$C$6,169<=$E$6),1,0) | FR32: =IF(AND(170>=$C$6,170<=$E$6),1,0) | FS32: =IF(AND(171>=$C$6,171<=$E$6),1,0) | FT32: =IF(AND(172>=$C$6,172<=$E$6),1,0) | FU32: =IF(AND(173>=$C$6,173<=$E$6),1,0) | FV32: =IF(AND(174>=$C$6,174<=$E$6),1,0) | FW32: =IF(AND(175>=$C$6,175<=$E$6),1,0) | FX32: =IF(AND(176>=$C$6,176<=$E$6),1,0) | FY32: =IF(AND(177>=$C$6,177<=$E$6),1,0) | FZ32: =IF(AND(178>=$C$6,178<=$E$6),1,0) | GA32: =IF(AND(179>=$C$6,179<=$E$6),1,0) | GB32: =IF(AND(180>=$C$6,180<=$E$6),1,0) | GC32: =IF(AND(181>=$C$6,181<=$E$6),1,0) | GD32: =IF(AND(182>=$C$6,182<=$E$6),1,0) | GE32: =IF(AND(183>=$C$6,183<=$E$6),1,0) | GF32: =IF(AND(184>=$C$6,184<=$E$6),1,0) | GG32: =IF(AND(185>=$C$6,185<=$E$6),1,0) | GH32: =IF(AND(186>=$C$6,186<=$E$6),1,0) | GI32: =IF(AND(187>=$C$6,187<=$E$6),1,0) | GJ32: =IF(AND(188>=$C$6,188<=$E$6),1,0) | GK32: =IF(AND(189>=$C$6,189<=$E$6),1,0) | GL32: =IF(AND(190>=$C$6,190<=$E$6),1,0) | GM32: =IF(AND(191>=$C$6,191<=$E$6),1,0) | GN32: =IF(AND(192>=$C$6,192<=$E$6),1,0) | GO32: =IF(AND(193>=$C$6,193<=$E$6),1,0) | GP32: =IF(AND(194>=$C$6,194<=$E$6),1,0) | GQ32: =IF(AND(195>=$C$6,195<=$E$6),1,0) | GR32: =IF(AND(196>=$C$6,196<=$E$6),1,0) | GS32: =IF(AND(197>=$C$6,197<=$E$6),1,0) | GT32: =IF(AND(198>=$C$6,198<=$E$6),1,0) | GU32: =IF(AND(199>=$C$6,199<=$E$6),1,0) | GV32: =IF(AND(200>=$C$6,200<=$E$6),1,0) | GW32: =IF(AND(201>=$C$6,201<=$E$6),1,0) | GX32: =IF(AND(202>=$C$6,202<=$E$6),1,0) | GY32: =IF(AND(203>=$C$6,203<=$E$6),1,0) | GZ32: =IF(AND(204>=$C$6,204<=$E$6),1,0) | HA32: =IF(AND(205>=$C$6,205<=$E$6),1,0) | HB32: =IF(AND(206>=$C$6,206<=$E$6),1,0) | HC32: =IF(AND(207>=$C$6,207<=$E$6),1,0) | HD32: =IF(AND(208>=$C$6,208<=$E$6),1,0) | HE32: =IF(AND(209>=$C$6,209<=$E$6),1,0) | HF32: =IF(AND(210>=$C$6,210<=$E$6),1,0) | HG32: =IF(AND(211>=$C$6,211<=$E$6),1,0) | HH32: =IF(AND(212>=$C$6,212<=$E$6),1,0) | HI32: =IF(AND(213>=$C$6,213<=$E$6),1,0) | HJ32: =IF(AND(214>=$C$6,214<=$E$6),1,0) | HK32: =IF(AND(215>=$C$6,215<=$E$6),1,0) | HL32: =IF(AND(216>=$C$6,216<=$E$6),1,0) | HM32: =IF(AND(217>=$C$6,217<=$E$6),1,0) | HN32: =IF(AND(218>=$C$6,218<=$E$6),1,0) | HO32: =IF(AND(219>=$C$6,219<=$E$6),1,0) | HP32: =IF(AND(220>=$C$6,220<=$E$6),1,0) | HQ32: =IF(AND(221>=$C$6,221<=$E$6),1,0) | HR32: =IF(AND(222>=$C$6,222<=$E$6),1,0) | HS32: =IF(AND(223>=$C$6,223<=$E$6),1,0) | HT32: =IF(AND(224>=$C$6,224<=$E$6),1,0) | HU32: =IF(AND(225>=$C$6,225<=$E$6),1,0) | HV32: =IF(AND(226>=$C$6,226<=$E$6),1,0) | HW32: =IF(AND(227>=$C$6,227<=$E$6),1,0) | HX32: =IF(AND(228>=$C$6,228<=$E$6),1,0) | HY32: =IF(AND(229>=$C$6,229<=$E$6),1,0) | HZ32: =IF(AND(230>=$C$6,230<=$E$6),1,0) | IA32: =IF(AND(231>=$C$6,231<=$E$6),1,0) | IB32: =IF(AND(232>=$C$6,232<=$E$6),1,0) | IC32: =IF(AND(233>=$C$6,233<=$E$6),1,0) | ID32: =IF(AND(234>=$C$6,234<=$E$6),1,0) | IE32: =IF(AND(235>=$C$6,235<=$E$6),1,0) | IF32: =IF(AND(236>=$C$6,236<=$E$6),1,0) | IG32: =IF(AND(237>=$C$6,237<=$E$6),1,0) | IH32: =IF(AND(238>=$C$6,238<=$E$6),1,0) | II32: =IF(AND(239>=$C$6,239<=$E$6),1,0) | IJ32: =IF(AND(240>=$C$6,240<=$E$6),1,0) | IK32: =IF(AND(241>=$C$6,241<=$E$6),1,0) | IL32: =IF(AND(242>=$C$6,242<=$E$6),1,0) | IM32: =IF(AND(243>=$C$6,243<=$E$6),1,0) | IN32: =IF(AND(244>=$C$6,244<=$E$6),1,0) | IO32: =IF(AND(245>=$C$6,245<=$E$6),1,0) | IP32: =IF(AND(246>=$C$6,246<=$E$6),1,0) | IQ32: =IF(AND(247>=$C$6,247<=$E$6),1,0) | IR32: =IF(AND(248>=$C$6,248<=$E$6),1,0) | IS32: =IF(AND(249>=$C$6,249<=$E$6),1,0) | IT32: =IF(AND(250>=$C$6,250<=$E$6),1,0) | IU32: =IF(AND(251>=$C$6,251<=$E$6),1,0) | IV32: =IF(AND(252>=$C$6,252<=$E$6),1,0) | IW32: =IF(AND(253>=$C$6,253<=$E$6),1,0) | IX32: =IF(AND(254>=$C$6,254<=$E$6),1,0) | IY32: =IF(AND(255>=$C$6,255<=$E$6),1,0) | IZ32: =IF(AND(256>=$C$6,256<=$E$6),1,0) | JA32: =IF(AND(257>=$C$6,257<=$E$6),1,0) | JB32: =IF(AND(258>=$C$6,258<=$E$6),1,0) | JC32: =IF(AND(259>=$C$6,259<=$E$6),1,0) | JD32: =IF(AND(260>=$C$6,260<=$E$6),1,0) | JE32: =IF(AND(261>=$C$6,261<=$E$6),1,0) | JF32: =IF(AND(262>=$C$6,262<=$E$6),1,0) | JG32: =IF(AND(263>=$C$6,263<=$E$6),1,0) | JH32: =IF(AND(264>=$C$6,264<=$E$6),1,0) | JI32: =IF(AND(265>=$C$6,265<=$E$6),1,0) | JJ32: =IF(AND(266>=$C$6,266<=$E$6),1,0) | JK32: =IF(AND(267>=$C$6,267<=$E$6),1,0) | JL32: =IF(AND(268>=$C$6,268<=$E$6),1,0) | JM32: =IF(AND(269>=$C$6,269<=$E$6),1,0) | JN32: =IF(AND(270>=$C$6,270<=$E$6),1,0) | JO32: =IF(AND(271>=$C$6,271<=$E$6),1,0) | JP32: =IF(AND(272>=$C$6,272<=$E$6),1,0) | JQ32: =IF(AND(273>=$C$6,273<=$E$6),1,0) | JR32: =IF(AND(274>=$C$6,274<=$E$6),1,0) | JS32: =IF(AND(275>=$C$6,275<=$E$6),1,0) | JT32: =IF(AND(276>=$C$6,276<=$E$6),1,0) | JU32: =IF(AND(277>=$C$6,277<=$E$6),1,0) | JV32: =IF(AND(278>=$C$6,278<=$E$6),1,0) | JW32: =IF(AND(279>=$C$6,279<=$E$6),1,0) | JX32: =IF(AND(280>=$C$6,280<=$E$6),1,0) | JY32: =IF(AND(281>=$C$6,281<=$E$6),1,0) | JZ32: =IF(AND(282>=$C$6,282<=$E$6),1,0) | KA32: =IF(AND(283>=$C$6,283<=$E$6),1,0) | KB32: =IF(AND(284>=$C$6,284<=$E$6),1,0) | KC32: =IF(AND(285>=$C$6,285<=$E$6),1,0) | KD32: =IF(AND(286>=$C$6,286<=$E$6),1,0) | KE32: =IF(AND(287>=$C$6,287<=$E$6),1,0) | KF32: =IF(AND(288>=$C$6,288<=$E$6),1,0) | KG32: =IF(AND(289>=$C$6,289<=$E$6),1,0) | KH32: =IF(AND(290>=$C$6,290<=$E$6),1,0) | KI32: =IF(AND(291>=$C$6,291<=$E$6),1,0) | KJ32: =IF(AND(292>=$C$6,292<=$E$6),1,0) | KK32: =IF(AND(293>=$C$6,293<=$E$6),1,0) | KL32: =IF(AND(294>=$C$6,294<=$E$6),1,0) | KM32: =IF(AND(295>=$C$6,295<=$E$6),1,0) | KN32: =IF(AND(296>=$C$6,296<=$E$6),1,0) | KO32: =IF(AND(297>=$C$6,297<=$E$6),1,0) | KP32: =IF(AND(298>=$C$6,298<=$E$6),1,0) | KQ32: =IF(AND(299>=$C$6,299<=$E$6),1,0) | KR32: =IF(AND(300>=$C$6,300<=$E$6),1,0) | KS32: =IF(AND(301>=$C$6,301<=$E$6),1,0) | KT32: =IF(AND(302>=$C$6,302<=$E$6),1,0) | KU32: =IF(AND(303>=$C$6,303<=$E$6),1,0) | KV32: =IF(AND(304>=$C$6,304<=$E$6),1,0) | KW32: =IF(AND(305>=$C$6,305<=$E$6),1,0) | KX32: =IF(AND(306>=$C$6,306<=$E$6),1,0) | KY32: =IF(AND(307>=$C$6,307<=$E$6),1,0) | KZ32: =IF(AND(308>=$C$6,308<=$E$6),1,0) | LA32: =IF(AND(309>=$C$6,309<=$E$6),1,0) | LB32: =IF(AND(310>=$C$6,310<=$E$6),1,0) | LC32: =IF(AND(311>=$C$6,311<=$E$6),1,0) | LD32: =IF(AND(312>=$C$6,312<=$E$6),1,0) | LE32: =IF(AND(313>=$C$6,313<=$E$6),1,0) | LF32: =IF(AND(314>=$C$6,314<=$E$6),1,0) | LG32: =IF(AND(315>=$C$6,315<=$E$6),1,0) | LH32: =IF(AND(316>=$C$6,316<=$E$6),1,0) | LI32: =IF(AND(317>=$C$6,317<=$E$6),1,0) | LJ32: =IF(AND(318>=$C$6,318<=$E$6),1,0) | LK32: =IF(AND(319>=$C$6,319<=$E$6),1,0) | LL32: =IF(AND(320>=$C$6,320<=$E$6),1,0) | LM32: =IF(AND(321>=$C$6,321<=$E$6),1,0) | LN32: =IF(AND(322>=$C$6,322<=$E$6),1,0) | LO32: =IF(AND(323>=$C$6,323<=$E$6),1,0) | LP32: =IF(AND(324>=$C$6,324<=$E$6),1,0) | LQ32: =IF(AND(325>=$C$6,325<=$E$6),1,0) | LR32: =IF(AND(326>=$C$6,326<=$E$6),1,0) | LS32: =IF(AND(327>=$C$6,327<=$E$6),1,0) | LT32: =IF(AND(328>=$C$6,328<=$E$6),1,0) | LU32: =IF(AND(329>=$C$6,329<=$E$6),1,0) | LV32: =IF(AND(330>=$C$6,330<=$E$6),1,0) | LW32: =IF(AND(331>=$C$6,331<=$E$6),1,0) | LX32: =IF(AND(332>=$C$6,332<=$E$6),1,0) | LY32: =IF(AND(333>=$C$6,333<=$E$6),1,0) | LZ32: =IF(AND(334>=$C$6,334<=$E$6),1,0) | MA32: =IF(AND(335>=$C$6,335<=$E$6),1,0) | MB32: =IF(AND(336>=$C$6,336<=$E$6),1,0) | MC32: =IF(AND(337>=$C$6,337<=$E$6),1,0) | MD32: =IF(AND(338>=$C$6,338<=$E$6),1,0) | ME32: =IF(AND(339>=$C$6,339<=$E$6),1,0) | MF32: =IF(AND(340>=$C$6,340<=$E$6),1,0) | MG32: =IF(AND(341>=$C$6,341<=$E$6),1,0) | MH32: =IF(AND(342>=$C$6,342<=$E$6),1,0) | MI32: =IF(AND(343>=$C$6,343<=$E$6),1,0) | MJ32: =IF(AND(344>=$C$6,344<=$E$6),1,0) | MK32: =IF(AND(345>=$C$6,345<=$E$6),1,0) | ML32: =IF(AND(346>=$C$6,346<=$E$6),1,0) | MM32: =IF(AND(347>=$C$6,347<=$E$6),1,0) | MN32: =IF(AND(348>=$C$6,348<=$E$6),1,0) | MO32: =IF(AND(349>=$C$6,349<=$E$6),1,0) | MP32: =IF(AND(350>=$C$6,350<=$E$6),1,0) | MQ32: =IF(AND(351>=$C$6,351<=$E$6),1,0) | MR32: =IF(AND(352>=$C$6,352<=$E$6),1,0) | MS32: =IF(AND(353>=$C$6,353<=$E$6),1,0) | MT32: =IF(AND(354>=$C$6,354<=$E$6),1,0) | MU32: =IF(AND(355>=$C$6,355<=$E$6),1,0) | MV32: =IF(AND(356>=$C$6,356<=$E$6),1,0) | MW32: =IF(AND(357>=$C$6,357<=$E$6),1,0) | MX32: =IF(AND(358>=$C$6,358<=$E$6),1,0) | MY32: =IF(AND(359>=$C$6,359<=$E$6),1,0) | MZ32: =IF(AND(360>=$C$6,360<=$E$6),1,0) | NA32: =IF(AND(361>=$C$6,361<=$E$6),1,0) | NB32: =IF(AND(362>=$C$6,362<=$E$6),1,0) | NC32: =IF(AND(363>=$C$6,363<=$E$6),1,0) | ND32: =IF(AND(364>=$C$6,364<=$E$6),1,0) | NE32: =IF(AND(365>=$C$6,365<=$E$6),1,0) | NF32: =IF(AND(366>=$C$6,366<=$E$6),1,0) | NG32: =IF(AND(367>=$C$6,367<=$E$6),1,0) | NH32: =IF(AND(368>=$C$6,368<=$E$6),1,0) | NI32: =IF(AND(369>=$C$6,369<=$E$6),1,0) | NJ32: =IF(AND(370>=$C$6,370<=$E$6),1,0) | NK32: =IF(AND(371>=$C$6,371<=$E$6),1,0) | NL32: =IF(AND(372>=$C$6,372<=$E$6),1,0)
B33: Flag: Pre-Construction | E33: =IF(AND(1>=$C$7,1<=$E$7),1,0) | F33: =IF(AND(2>=$C$7,2<=$E$7),1,0) | G33: =IF(AND(3>=$C$7,3<=$E$7),1,0) | H33: =IF(AND(4>=$C$7,4<=$E$7),1,0) | I33: =IF(AND(5>=$C$7,5<=$E$7),1,0) | J33: =IF(AND(6>=$C$7,6<=$E$7),1,0) | K33: =IF(AND(7>=$C$7,7<=$E$7),1,0) | L33: =IF(AND(8>=$C$7,8<=$E$7),1,0) | M33: =IF(AND(9>=$C$7,9<=$E$7),1,0) | N33: =IF(AND(10>=$C$7,10<=$E$7),1,0) | O33: =IF(AND(11>=$C$7,11<=$E$7),1,0) | P33: =IF(AND(12>=$C$7,12<=$E$7),1,0) | Q33: =IF(AND(13>=$C$7,13<=$E$7),1,0) | R33: =IF(AND(14>=$C$7,14<=$E$7),1,0) | S33: =IF(AND(15>=$C$7,15<=$E$7),1,0) | T33: =IF(AND(16>=$C$7,16<=$E$7),1,0) | U33: =IF(AND(17>=$C$7,17<=$E$7),1,0) | V33: =IF(AND(18>=$C$7,18<=$E$7),1,0) | W33: =IF(AND(19>=$C$7,19<=$E$7),1,0) | X33: =IF(AND(20>=$C$7,20<=$E$7),1,0) | Y33: =IF(AND(21>=$C$7,21<=$E$7),1,0) | Z33: =IF(AND(22>=$C$7,22<=$E$7),1,0) | AA33: =IF(AND(23>=$C$7,23<=$E$7),1,0) | AB33: =IF(AND(24>=$C$7,24<=$E$7),1,0) | AC33: =IF(AND(25>=$C$7,25<=$E$7),1,0) | AD33: =IF(AND(26>=$C$7,26<=$E$7),1,0) | AE33: =IF(AND(27>=$C$7,27<=$E$7),1,0) | AF33: =IF(AND(28>=$C$7,28<=$E$7),1,0) | AG33: =IF(AND(29>=$C$7,29<=$E$7),1,0) | AH33: =IF(AND(30>=$C$7,30<=$E$7),1,0) | AI33: =IF(AND(31>=$C$7,31<=$E$7),1,0) | AJ33: =IF(AND(32>=$C$7,32<=$E$7),1,0) | AK33: =IF(AND(33>=$C$7,33<=$E$7),1,0) | AL33: =IF(AND(34>=$C$7,34<=$E$7),1,0) | AM33: =IF(AND(35>=$C$7,35<=$E$7),1,0) | AN33: =IF(AND(36>=$C$7,36<=$E$7),1,0) | AO33: =IF(AND(37>=$C$7,37<=$E$7),1,0) | AP33: =IF(AND(38>=$C$7,38<=$E$7),1,0) | AQ33: =IF(AND(39>=$C$7,39<=$E$7),1,0) | AR33: =IF(AND(40>=$C$7,40<=$E$7),1,0) | AS33: =IF(AND(41>=$C$7,41<=$E$7),1,0) | AT33: =IF(AND(42>=$C$7,42<=$E$7),1,0) | AU33: =IF(AND(43>=$C$7,43<=$E$7),1,0) | AV33: =IF(AND(44>=$C$7,44<=$E$7),1,0) | AW33: =IF(AND(45>=$C$7,45<=$E$7),1,0) | AX33: =IF(AND(46>=$C$7,46<=$E$7),1,0) | AY33: =IF(AND(47>=$C$7,47<=$E$7),1,0) | AZ33: =IF(AND(48>=$C$7,48<=$E$7),1,0) | BA33: =IF(AND(49>=$C$7,49<=$E$7),1,0) | BB33: =IF(AND(50>=$C$7,50<=$E$7),1,0) | BC33: =IF(AND(51>=$C$7,51<=$E$7),1,0) | BD33: =IF(AND(52>=$C$7,52<=$E$7),1,0) | BE33: =IF(AND(53>=$C$7,53<=$E$7),1,0) | BF33: =IF(AND(54>=$C$7,54<=$E$7),1,0) | BG33: =IF(AND(55>=$C$7,55<=$E$7),1,0) | BH33: =IF(AND(56>=$C$7,56<=$E$7),1,0) | BI33: =IF(AND(57>=$C$7,57<=$E$7),1,0) | BJ33: =IF(AND(58>=$C$7,58<=$E$7),1,0) | BK33: =IF(AND(59>=$C$7,59<=$E$7),1,0) | BL33: =IF(AND(60>=$C$7,60<=$E$7),1,0) | BM33: =IF(AND(61>=$C$7,61<=$E$7),1,0) | BN33: =IF(AND(62>=$C$7,62<=$E$7),1,0) | BO33: =IF(AND(63>=$C$7,63<=$E$7),1,0) | BP33: =IF(AND(64>=$C$7,64<=$E$7),1,0) | BQ33: =IF(AND(65>=$C$7,65<=$E$7),1,0) | BR33: =IF(AND(66>=$C$7,66<=$E$7),1,0) | BS33: =IF(AND(67>=$C$7,67<=$E$7),1,0) | BT33: =IF(AND(68>=$C$7,68<=$E$7),1,0) | BU33: =IF(AND(69>=$C$7,69<=$E$7),1,0) | BV33: =IF(AND(70>=$C$7,70<=$E$7),1,0) | BW33: =IF(AND(71>=$C$7,71<=$E$7),1,0) | BX33: =IF(AND(72>=$C$7,72<=$E$7),1,0) | BY33: =IF(AND(73>=$C$7,73<=$E$7),1,0) | BZ33: =IF(AND(74>=$C$7,74<=$E$7),1,0) | CA33: =IF(AND(75>=$C$7,75<=$E$7),1,0) | CB33: =IF(AND(76>=$C$7,76<=$E$7),1,0) | CC33: =IF(AND(77>=$C$7,77<=$E$7),1,0) | CD33: =IF(AND(78>=$C$7,78<=$E$7),1,0) | CE33: =IF(AND(79>=$C$7,79<=$E$7),1,0) | CF33: =IF(AND(80>=$C$7,80<=$E$7),1,0) | CG33: =IF(AND(81>=$C$7,81<=$E$7),1,0) | CH33: =IF(AND(82>=$C$7,82<=$E$7),1,0) | CI33: =IF(AND(83>=$C$7,83<=$E$7),1,0) | CJ33: =IF(AND(84>=$C$7,84<=$E$7),1,0) | CK33: =IF(AND(85>=$C$7,85<=$E$7),1,0) | CL33: =IF(AND(86>=$C$7,86<=$E$7),1,0) | CM33: =IF(AND(87>=$C$7,87<=$E$7),1,0) | CN33: =IF(AND(88>=$C$7,88<=$E$7),1,0) | CO33: =IF(AND(89>=$C$7,89<=$E$7),1,0) | CP33: =IF(AND(90>=$C$7,90<=$E$7),1,0) | CQ33: =IF(AND(91>=$C$7,91<=$E$7),1,0) | CR33: =IF(AND(92>=$C$7,92<=$E$7),1,0) | CS33: =IF(AND(93>=$C$7,93<=$E$7),1,0) | CT33: =IF(AND(94>=$C$7,94<=$E$7),1,0) | CU33: =IF(AND(95>=$C$7,95<=$E$7),1,0) | CV33: =IF(AND(96>=$C$7,96<=$E$7),1,0) | CW33: =IF(AND(97>=$C$7,97<=$E$7),1,0) | CX33: =IF(AND(98>=$C$7,98<=$E$7),1,0) | CY33: =IF(AND(99>=$C$7,99<=$E$7),1,0) | CZ33: =IF(AND(100>=$C$7,100<=$E$7),1,0) | DA33: =IF(AND(101>=$C$7,101<=$E$7),1,0) | DB33: =IF(AND(102>=$C$7,102<=$E$7),1,0) | DC33: =IF(AND(103>=$C$7,103<=$E$7),1,0) | DD33: =IF(AND(104>=$C$7,104<=$E$7),1,0) | DE33: =IF(AND(105>=$C$7,105<=$E$7),1,0) | DF33: =IF(AND(106>=$C$7,106<=$E$7),1,0) | DG33: =IF(AND(107>=$C$7,107<=$E$7),1,0) | DH33: =IF(AND(108>=$C$7,108<=$E$7),1,0) | DI33: =IF(AND(109>=$C$7,109<=$E$7),1,0) | DJ33: =IF(AND(110>=$C$7,110<=$E$7),1,0) | DK33: =IF(AND(111>=$C$7,111<=$E$7),1,0) | DL33: =IF(AND(112>=$C$7,112<=$E$7),1,0) | DM33: =IF(AND(113>=$C$7,113<=$E$7),1,0) | DN33: =IF(AND(114>=$C$7,114<=$E$7),1,0) | DO33: =IF(AND(115>=$C$7,115<=$E$7),1,0) | DP33: =IF(AND(116>=$C$7,116<=$E$7),1,0) | DQ33: =IF(AND(117>=$C$7,117<=$E$7),1,0) | DR33: =IF(AND(118>=$C$7,118<=$E$7),1,0) | DS33: =IF(AND(119>=$C$7,119<=$E$7),1,0) | DT33: =IF(AND(120>=$C$7,120<=$E$7),1,0) | DU33: =IF(AND(121>=$C$7,121<=$E$7),1,0) | DV33: =IF(AND(122>=$C$7,122<=$E$7),1,0) | DW33: =IF(AND(123>=$C$7,123<=$E$7),1,0) | DX33: =IF(AND(124>=$C$7,124<=$E$7),1,0) | DY33: =IF(AND(125>=$C$7,125<=$E$7),1,0) | DZ33: =IF(AND(126>=$C$7,126<=$E$7),1,0) | EA33: =IF(AND(127>=$C$7,127<=$E$7),1,0) | EB33: =IF(AND(128>=$C$7,128<=$E$7),1,0) | EC33: =IF(AND(129>=$C$7,129<=$E$7),1,0) | ED33: =IF(AND(130>=$C$7,130<=$E$7),1,0) | EE33: =IF(AND(131>=$C$7,131<=$E$7),1,0) | EF33: =IF(AND(132>=$C$7,132<=$E$7),1,0) | EG33: =IF(AND(133>=$C$7,133<=$E$7),1,0) | EH33: =IF(AND(134>=$C$7,134<=$E$7),1,0) | EI33: =IF(AND(135>=$C$7,135<=$E$7),1,0) | EJ33: =IF(AND(136>=$C$7,136<=$E$7),1,0) | EK33: =IF(AND(137>=$C$7,137<=$E$7),1,0) | EL33: =IF(AND(138>=$C$7,138<=$E$7),1,0) | EM33: =IF(AND(139>=$C$7,139<=$E$7),1,0) | EN33: =IF(AND(140>=$C$7,140<=$E$7),1,0) | EO33: =IF(AND(141>=$C$7,141<=$E$7),1,0) | EP33: =IF(AND(142>=$C$7,142<=$E$7),1,0) | EQ33: =IF(AND(143>=$C$7,143<=$E$7),1,0) | ER33: =IF(AND(144>=$C$7,144<=$E$7),1,0) | ES33: =IF(AND(145>=$C$7,145<=$E$7),1,0) | ET33: =IF(AND(146>=$C$7,146<=$E$7),1,0) | EU33: =IF(AND(147>=$C$7,147<=$E$7),1,0) | EV33: =IF(AND(148>=$C$7,148<=$E$7),1,0) | EW33: =IF(AND(149>=$C$7,149<=$E$7),1,0) | EX33: =IF(AND(150>=$C$7,150<=$E$7),1,0) | EY33: =IF(AND(151>=$C$7,151<=$E$7),1,0) | EZ33: =IF(AND(152>=$C$7,152<=$E$7),1,0) | FA33: =IF(AND(153>=$C$7,153<=$E$7),1,0) | FB33: =IF(AND(154>=$C$7,154<=$E$7),1,0) | FC33: =IF(AND(155>=$C$7,155<=$E$7),1,0) | FD33: =IF(AND(156>=$C$7,156<=$E$7),1,0) | FE33: =IF(AND(157>=$C$7,157<=$E$7),1,0) | FF33: =IF(AND(158>=$C$7,158<=$E$7),1,0) | FG33: =IF(AND(159>=$C$7,159<=$E$7),1,0) | FH33: =IF(AND(160>=$C$7,160<=$E$7),1,0) | FI33: =IF(AND(161>=$C$7,161<=$E$7),1,0) | FJ33: =IF(AND(162>=$C$7,162<=$E$7),1,0) | FK33: =IF(AND(163>=$C$7,163<=$E$7),1,0) | FL33: =IF(AND(164>=$C$7,164<=$E$7),1,0) | FM33: =IF(AND(165>=$C$7,165<=$E$7),1,0) | FN33: =IF(AND(166>=$C$7,166<=$E$7),1,0) | FO33: =IF(AND(167>=$C$7,167<=$E$7),1,0) | FP33: =IF(AND(168>=$C$7,168<=$E$7),1,0) | FQ33: =IF(AND(169>=$C$7,169<=$E$7),1,0) | FR33: =IF(AND(170>=$C$7,170<=$E$7),1,0) | FS33: =IF(AND(171>=$C$7,171<=$E$7),1,0) | FT33: =IF(AND(172>=$C$7,172<=$E$7),1,0) | FU33: =IF(AND(173>=$C$7,173<=$E$7),1,0) | FV33: =IF(AND(174>=$C$7,174<=$E$7),1,0) | FW33: =IF(AND(175>=$C$7,175<=$E$7),1,0) | FX33: =IF(AND(176>=$C$7,176<=$E$7),1,0) | FY33: =IF(AND(177>=$C$7,177<=$E$7),1,0) | FZ33: =IF(AND(178>=$C$7,178<=$E$7),1,0) | GA33: =IF(AND(179>=$C$7,179<=$E$7),1,0) | GB33: =IF(AND(180>=$C$7,180<=$E$7),1,0) | GC33: =IF(AND(181>=$C$7,181<=$E$7),1,0) | GD33: =IF(AND(182>=$C$7,182<=$E$7),1,0) | GE33: =IF(AND(183>=$C$7,183<=$E$7),1,0) | GF33: =IF(AND(184>=$C$7,184<=$E$7),1,0) | GG33: =IF(AND(185>=$C$7,185<=$E$7),1,0) | GH33: =IF(AND(186>=$C$7,186<=$E$7),1,0) | GI33: =IF(AND(187>=$C$7,187<=$E$7),1,0) | GJ33: =IF(AND(188>=$C$7,188<=$E$7),1,0) | GK33: =IF(AND(189>=$C$7,189<=$E$7),1,0) | GL33: =IF(AND(190>=$C$7,190<=$E$7),1,0) | GM33: =IF(AND(191>=$C$7,191<=$E$7),1,0) | GN33: =IF(AND(192>=$C$7,192<=$E$7),1,0) | GO33: =IF(AND(193>=$C$7,193<=$E$7),1,0) | GP33: =IF(AND(194>=$C$7,194<=$E$7),1,0) | GQ33: =IF(AND(195>=$C$7,195<=$E$7),1,0) | GR33: =IF(AND(196>=$C$7,196<=$E$7),1,0) | GS33: =IF(AND(197>=$C$7,197<=$E$7),1,0) | GT33: =IF(AND(198>=$C$7,198<=$E$7),1,0) | GU33: =IF(AND(199>=$C$7,199<=$E$7),1,0) | GV33: =IF(AND(200>=$C$7,200<=$E$7),1,0) | GW33: =IF(AND(201>=$C$7,201<=$E$7),1,0) | GX33: =IF(AND(202>=$C$7,202<=$E$7),1,0) | GY33: =IF(AND(203>=$C$7,203<=$E$7),1,0) | GZ33: =IF(AND(204>=$C$7,204<=$E$7),1,0) | HA33: =IF(AND(205>=$C$7,205<=$E$7),1,0) | HB33: =IF(AND(206>=$C$7,206<=$E$7),1,0) | HC33: =IF(AND(207>=$C$7,207<=$E$7),1,0) | HD33: =IF(AND(208>=$C$7,208<=$E$7),1,0) | HE33: =IF(AND(209>=$C$7,209<=$E$7),1,0) | HF33: =IF(AND(210>=$C$7,210<=$E$7),1,0) | HG33: =IF(AND(211>=$C$7,211<=$E$7),1,0) | HH33: =IF(AND(212>=$C$7,212<=$E$7),1,0) | HI33: =IF(AND(213>=$C$7,213<=$E$7),1,0) | HJ33: =IF(AND(214>=$C$7,214<=$E$7),1,0) | HK33: =IF(AND(215>=$C$7,215<=$E$7),1,0) | HL33: =IF(AND(216>=$C$7,216<=$E$7),1,0) | HM33: =IF(AND(217>=$C$7,217<=$E$7),1,0) | HN33: =IF(AND(218>=$C$7,218<=$E$7),1,0) | HO33: =IF(AND(219>=$C$7,219<=$E$7),1,0) | HP33: =IF(AND(220>=$C$7,220<=$E$7),1,0) | HQ33: =IF(AND(221>=$C$7,221<=$E$7),1,0) | HR33: =IF(AND(222>=$C$7,222<=$E$7),1,0) | HS33: =IF(AND(223>=$C$7,223<=$E$7),1,0) | HT33: =IF(AND(224>=$C$7,224<=$E$7),1,0) | HU33: =IF(AND(225>=$C$7,225<=$E$7),1,0) | HV33: =IF(AND(226>=$C$7,226<=$E$7),1,0) | HW33: =IF(AND(227>=$C$7,227<=$E$7),1,0) | HX33: =IF(AND(228>=$C$7,228<=$E$7),1,0) | HY33: =IF(AND(229>=$C$7,229<=$E$7),1,0) | HZ33: =IF(AND(230>=$C$7,230<=$E$7),1,0) | IA33: =IF(AND(231>=$C$7,231<=$E$7),1,0) | IB33: =IF(AND(232>=$C$7,232<=$E$7),1,0) | IC33: =IF(AND(233>=$C$7,233<=$E$7),1,0) | ID33: =IF(AND(234>=$C$7,234<=$E$7),1,0) | IE33: =IF(AND(235>=$C$7,235<=$E$7),1,0) | IF33: =IF(AND(236>=$C$7,236<=$E$7),1,0) | IG33: =IF(AND(237>=$C$7,237<=$E$7),1,0) | IH33: =IF(AND(238>=$C$7,238<=$E$7),1,0) | II33: =IF(AND(239>=$C$7,239<=$E$7),1,0) | IJ33: =IF(AND(240>=$C$7,240<=$E$7),1,0) | IK33: =IF(AND(241>=$C$7,241<=$E$7),1,0) | IL33: =IF(AND(242>=$C$7,242<=$E$7),1,0) | IM33: =IF(AND(243>=$C$7,243<=$E$7),1,0) | IN33: =IF(AND(244>=$C$7,244<=$E$7),1,0) | IO33: =IF(AND(245>=$C$7,245<=$E$7),1,0) | IP33: =IF(AND(246>=$C$7,246<=$E$7),1,0) | IQ33: =IF(AND(247>=$C$7,247<=$E$7),1,0) | IR33: =IF(AND(248>=$C$7,248<=$E$7),1,0) | IS33: =IF(AND(249>=$C$7,249<=$E$7),1,0) | IT33: =IF(AND(250>=$C$7,250<=$E$7),1,0) | IU33: =IF(AND(251>=$C$7,251<=$E$7),1,0) | IV33: =IF(AND(252>=$C$7,252<=$E$7),1,0) | IW33: =IF(AND(253>=$C$7,253<=$E$7),1,0) | IX33: =IF(AND(254>=$C$7,254<=$E$7),1,0) | IY33: =IF(AND(255>=$C$7,255<=$E$7),1,0) | IZ33: =IF(AND(256>=$C$7,256<=$E$7),1,0) | JA33: =IF(AND(257>=$C$7,257<=$E$7),1,0) | JB33: =IF(AND(258>=$C$7,258<=$E$7),1,0) | JC33: =IF(AND(259>=$C$7,259<=$E$7),1,0) | JD33: =IF(AND(260>=$C$7,260<=$E$7),1,0) | JE33: =IF(AND(261>=$C$7,261<=$E$7),1,0) | JF33: =IF(AND(262>=$C$7,262<=$E$7),1,0) | JG33: =IF(AND(263>=$C$7,263<=$E$7),1,0) | JH33: =IF(AND(264>=$C$7,264<=$E$7),1,0) | JI33: =IF(AND(265>=$C$7,265<=$E$7),1,0) | JJ33: =IF(AND(266>=$C$7,266<=$E$7),1,0) | JK33: =IF(AND(267>=$C$7,267<=$E$7),1,0) | JL33: =IF(AND(268>=$C$7,268<=$E$7),1,0) | JM33: =IF(AND(269>=$C$7,269<=$E$7),1,0) | JN33: =IF(AND(270>=$C$7,270<=$E$7),1,0) | JO33: =IF(AND(271>=$C$7,271<=$E$7),1,0) | JP33: =IF(AND(272>=$C$7,272<=$E$7),1,0) | JQ33: =IF(AND(273>=$C$7,273<=$E$7),1,0) | JR33: =IF(AND(274>=$C$7,274<=$E$7),1,0) | JS33: =IF(AND(275>=$C$7,275<=$E$7),1,0) | JT33: =IF(AND(276>=$C$7,276<=$E$7),1,0) | JU33: =IF(AND(277>=$C$7,277<=$E$7),1,0) | JV33: =IF(AND(278>=$C$7,278<=$E$7),1,0) | JW33: =IF(AND(279>=$C$7,279<=$E$7),1,0) | JX33: =IF(AND(280>=$C$7,280<=$E$7),1,0) | JY33: =IF(AND(281>=$C$7,281<=$E$7),1,0) | JZ33: =IF(AND(282>=$C$7,282<=$E$7),1,0) | KA33: =IF(AND(283>=$C$7,283<=$E$7),1,0) | KB33: =IF(AND(284>=$C$7,284<=$E$7),1,0) | KC33: =IF(AND(285>=$C$7,285<=$E$7),1,0) | KD33: =IF(AND(286>=$C$7,286<=$E$7),1,0) | KE33: =IF(AND(287>=$C$7,287<=$E$7),1,0) | KF33: =IF(AND(288>=$C$7,288<=$E$7),1,0) | KG33: =IF(AND(289>=$C$7,289<=$E$7),1,0) | KH33: =IF(AND(290>=$C$7,290<=$E$7),1,0) | KI33: =IF(AND(291>=$C$7,291<=$E$7),1,0) | KJ33: =IF(AND(292>=$C$7,292<=$E$7),1,0) | KK33: =IF(AND(293>=$C$7,293<=$E$7),1,0) | KL33: =IF(AND(294>=$C$7,294<=$E$7),1,0) | KM33: =IF(AND(295>=$C$7,295<=$E$7),1,0) | KN33: =IF(AND(296>=$C$7,296<=$E$7),1,0) | KO33: =IF(AND(297>=$C$7,297<=$E$7),1,0) | KP33: =IF(AND(298>=$C$7,298<=$E$7),1,0) | KQ33: =IF(AND(299>=$C$7,299<=$E$7),1,0) | KR33: =IF(AND(300>=$C$7,300<=$E$7),1,0) | KS33: =IF(AND(301>=$C$7,301<=$E$7),1,0) | KT33: =IF(AND(302>=$C$7,302<=$E$7),1,0) | KU33: =IF(AND(303>=$C$7,303<=$E$7),1,0) | KV33: =IF(AND(304>=$C$7,304<=$E$7),1,0) | KW33: =IF(AND(305>=$C$7,305<=$E$7),1,0) | KX33: =IF(AND(306>=$C$7,306<=$E$7),1,0) | KY33: =IF(AND(307>=$C$7,307<=$E$7),1,0) | KZ33: =IF(AND(308>=$C$7,308<=$E$7),1,0) | LA33: =IF(AND(309>=$C$7,309<=$E$7),1,0) | LB33: =IF(AND(310>=$C$7,310<=$E$7),1,0) | LC33: =IF(AND(311>=$C$7,311<=$E$7),1,0) | LD33: =IF(AND(312>=$C$7,312<=$E$7),1,0) | LE33: =IF(AND(313>=$C$7,313<=$E$7),1,0) | LF33: =IF(AND(314>=$C$7,314<=$E$7),1,0) | LG33: =IF(AND(315>=$C$7,315<=$E$7),1,0) | LH33: =IF(AND(316>=$C$7,316<=$E$7),1,0) | LI33: =IF(AND(317>=$C$7,317<=$E$7),1,0) | LJ33: =IF(AND(318>=$C$7,318<=$E$7),1,0) | LK33: =IF(AND(319>=$C$7,319<=$E$7),1,0) | LL33: =IF(AND(320>=$C$7,320<=$E$7),1,0) | LM33: =IF(AND(321>=$C$7,321<=$E$7),1,0) | LN33: =IF(AND(322>=$C$7,322<=$E$7),1,0) | LO33: =IF(AND(323>=$C$7,323<=$E$7),1,0) | LP33: =IF(AND(324>=$C$7,324<=$E$7),1,0) | LQ33: =IF(AND(325>=$C$7,325<=$E$7),1,0) | LR33: =IF(AND(326>=$C$7,326<=$E$7),1,0) | LS33: =IF(AND(327>=$C$7,327<=$E$7),1,0) | LT33: =IF(AND(328>=$C$7,328<=$E$7),1,0) | LU33: =IF(AND(329>=$C$7,329<=$E$7),1,0) | LV33: =IF(AND(330>=$C$7,330<=$E$7),1,0) | LW33: =IF(AND(331>=$C$7,331<=$E$7),1,0) | LX33: =IF(AND(332>=$C$7,332<=$E$7),1,0) | LY33: =IF(AND(333>=$C$7,333<=$E$7),1,0) | LZ33: =IF(AND(334>=$C$7,334<=$E$7),1,0) | MA33: =IF(AND(335>=$C$7,335<=$E$7),1,0) | MB33: =IF(AND(336>=$C$7,336<=$E$7),1,0) | MC33: =IF(AND(337>=$C$7,337<=$E$7),1,0) | MD33: =IF(AND(338>=$C$7,338<=$E$7),1,0) | ME33: =IF(AND(339>=$C$7,339<=$E$7),1,0) | MF33: =IF(AND(340>=$C$7,340<=$E$7),1,0) | MG33: =IF(AND(341>=$C$7,341<=$E$7),1,0) | MH33: =IF(AND(342>=$C$7,342<=$E$7),1,0) | MI33: =IF(AND(343>=$C$7,343<=$E$7),1,0) | MJ33: =IF(AND(344>=$C$7,344<=$E$7),1,0) | MK33: =IF(AND(345>=$C$7,345<=$E$7),1,0) | ML33: =IF(AND(346>=$C$7,346<=$E$7),1,0) | MM33: =IF(AND(347>=$C$7,347<=$E$7),1,0) | MN33: =IF(AND(348>=$C$7,348<=$E$7),1,0) | MO33: =IF(AND(349>=$C$7,349<=$E$7),1,0) | MP33: =IF(AND(350>=$C$7,350<=$E$7),1,0) | MQ33: =IF(AND(351>=$C$7,351<=$E$7),1,0) | MR33: =IF(AND(352>=$C$7,352<=$E$7),1,0) | MS33: =IF(AND(353>=$C$7,353<=$E$7),1,0) | MT33: =IF(AND(354>=$C$7,354<=$E$7),1,0) | MU33: =IF(AND(355>=$C$7,355<=$E$7),1,0) | MV33: =IF(AND(356>=$C$7,356<=$E$7),1,0) | MW33: =IF(AND(357>=$C$7,357<=$E$7),1,0) | MX33: =IF(AND(358>=$C$7,358<=$E$7),1,0) | MY33: =IF(AND(359>=$C$7,359<=$E$7),1,0) | MZ33: =IF(AND(360>=$C$7,360<=$E$7),1,0) | NA33: =IF(AND(361>=$C$7,361<=$E$7),1,0) | NB33: =IF(AND(362>=$C$7,362<=$E$7),1,0) | NC33: =IF(AND(363>=$C$7,363<=$E$7),1,0) | ND33: =IF(AND(364>=$C$7,364<=$E$7),1,0) | NE33: =IF(AND(365>=$C$7,365<=$E$7),1,0) | NF33: =IF(AND(366>=$C$7,366<=$E$7),1,0) | NG33: =IF(AND(367>=$C$7,367<=$E$7),1,0) | NH33: =IF(AND(368>=$C$7,368<=$E$7),1,0) | NI33: =IF(AND(369>=$C$7,369<=$E$7),1,0) | NJ33: =IF(AND(370>=$C$7,370<=$E$7),1,0) | NK33: =IF(AND(371>=$C$7,371<=$E$7),1,0) | NL33: =IF(AND(372>=$C$7,372<=$E$7),1,0)
B34: Flag: Initial Closing | E34: =IF(AND(1>=$C$8,1<=$E$8),1,0) | F34: =IF(AND(2>=$C$8,2<=$E$8),1,0) | G34: =IF(AND(3>=$C$8,3<=$E$8),1,0) | H34: =IF(AND(4>=$C$8,4<=$E$8),1,0) | I34: =IF(AND(5>=$C$8,5<=$E$8),1,0) | J34: =IF(AND(6>=$C$8,6<=$E$8),1,0) | K34: =IF(AND(7>=$C$8,7<=$E$8),1,0) | L34: =IF(AND(8>=$C$8,8<=$E$8),1,0) | M34: =IF(AND(9>=$C$8,9<=$E$8),1,0) | N34: =IF(AND(10>=$C$8,10<=$E$8),1,0) | O34: =IF(AND(11>=$C$8,11<=$E$8),1,0) | P34: =IF(AND(12>=$C$8,12<=$E$8),1,0) | Q34: =IF(AND(13>=$C$8,13<=$E$8),1,0) | R34: =IF(AND(14>=$C$8,14<=$E$8),1,0) | S34: =IF(AND(15>=$C$8,15<=$E$8),1,0) | T34: =IF(AND(16>=$C$8,16<=$E$8),1,0) | U34: =IF(AND(17>=$C$8,17<=$E$8),1,0) | V34: =IF(AND(18>=$C$8,18<=$E$8),1,0) | W34: =IF(AND(19>=$C$8,19<=$E$8),1,0) | X34: =IF(AND(20>=$C$8,20<=$E$8),1,0) | Y34: =IF(AND(21>=$C$8,21<=$E$8),1,0) | Z34: =IF(AND(22>=$C$8,22<=$E$8),1,0) | AA34: =IF(AND(23>=$C$8,23<=$E$8),1,0) | AB34: =IF(AND(24>=$C$8,24<=$E$8),1,0) | AC34: =IF(AND(25>=$C$8,25<=$E$8),1,0) | AD34: =IF(AND(26>=$C$8,26<=$E$8),1,0) | AE34: =IF(AND(27>=$C$8,27<=$E$8),1,0) | AF34: =IF(AND(28>=$C$8,28<=$E$8),1,0) | AG34: =IF(AND(29>=$C$8,29<=$E$8),1,0) | AH34: =IF(AND(30>=$C$8,30<=$E$8),1,0) | AI34: =IF(AND(31>=$C$8,31<=$E$8),1,0) | AJ34: =IF(AND(32>=$C$8,32<=$E$8),1,0) | AK34: =IF(AND(33>=$C$8,33<=$E$8),1,0) | AL34: =IF(AND(34>=$C$8,34<=$E$8),1,0) | AM34: =IF(AND(35>=$C$8,35<=$E$8),1,0) | AN34: =IF(AND(36>=$C$8,36<=$E$8),1,0) | AO34: =IF(AND(37>=$C$8,37<=$E$8),1,0) | AP34: =IF(AND(38>=$C$8,38<=$E$8),1,0) | AQ34: =IF(AND(39>=$C$8,39<=$E$8),1,0) | AR34: =IF(AND(40>=$C$8,40<=$E$8),1,0) | AS34: =IF(AND(41>=$C$8,41<=$E$8),1,0) | AT34: =IF(AND(42>=$C$8,42<=$E$8),1,0) | AU34: =IF(AND(43>=$C$8,43<=$E$8),1,0) | AV34: =IF(AND(44>=$C$8,44<=$E$8),1,0) | AW34: =IF(AND(45>=$C$8,45<=$E$8),1,0) | AX34: =IF(AND(46>=$C$8,46<=$E$8),1,0) | AY34: =IF(AND(47>=$C$8,47<=$E$8),1,0) | AZ34: =IF(AND(48>=$C$8,48<=$E$8),1,0) | BA34: =IF(AND(49>=$C$8,49<=$E$8),1,0) | BB34: =IF(AND(50>=$C$8,50<=$E$8),1,0) | BC34: =IF(AND(51>=$C$8,51<=$E$8),1,0) | BD34: =IF(AND(52>=$C$8,52<=$E$8),1,0) | BE34: =IF(AND(53>=$C$8,53<=$E$8),1,0) | BF34: =IF(AND(54>=$C$8,54<=$E$8),1,0) | BG34: =IF(AND(55>=$C$8,55<=$E$8),1,0) | BH34: =IF(AND(56>=$C$8,56<=$E$8),1,0) | BI34: =IF(AND(57>=$C$8,57<=$E$8),1,0) | BJ34: =IF(AND(58>=$C$8,58<=$E$8),1,0) | BK34: =IF(AND(59>=$C$8,59<=$E$8),1,0) | BL34: =IF(AND(60>=$C$8,60<=$E$8),1,0) | BM34: =IF(AND(61>=$C$8,61<=$E$8),1,0) | BN34: =IF(AND(62>=$C$8,62<=$E$8),1,0) | BO34: =IF(AND(63>=$C$8,63<=$E$8),1,0) | BP34: =IF(AND(64>=$C$8,64<=$E$8),1,0) | BQ34: =IF(AND(65>=$C$8,65<=$E$8),1,0) | BR34: =IF(AND(66>=$C$8,66<=$E$8),1,0) | BS34: =IF(AND(67>=$C$8,67<=$E$8),1,0) | BT34: =IF(AND(68>=$C$8,68<=$E$8),1,0) | BU34: =IF(AND(69>=$C$8,69<=$E$8),1,0) | BV34: =IF(AND(70>=$C$8,70<=$E$8),1,0) | BW34: =IF(AND(71>=$C$8,71<=$E$8),1,0) | BX34: =IF(AND(72>=$C$8,72<=$E$8),1,0) | BY34: =IF(AND(73>=$C$8,73<=$E$8),1,0) | BZ34: =IF(AND(74>=$C$8,74<=$E$8),1,0) | CA34: =IF(AND(75>=$C$8,75<=$E$8),1,0) | CB34: =IF(AND(76>=$C$8,76<=$E$8),1,0) | CC34: =IF(AND(77>=$C$8,77<=$E$8),1,0) | CD34: =IF(AND(78>=$C$8,78<=$E$8),1,0) | CE34: =IF(AND(79>=$C$8,79<=$E$8),1,0) | CF34: =IF(AND(80>=$C$8,80<=$E$8),1,0) | CG34: =IF(AND(81>=$C$8,81<=$E$8),1,0) | CH34: =IF(AND(82>=$C$8,82<=$E$8),1,0) | CI34: =IF(AND(83>=$C$8,83<=$E$8),1,0) | CJ34: =IF(AND(84>=$C$8,84<=$E$8),1,0) | CK34: =IF(AND(85>=$C$8,85<=$E$8),1,0) | CL34: =IF(AND(86>=$C$8,86<=$E$8),1,0) | CM34: =IF(AND(87>=$C$8,87<=$E$8),1,0) | CN34: =IF(AND(88>=$C$8,88<=$E$8),1,0) | CO34: =IF(AND(89>=$C$8,89<=$E$8),1,0) | CP34: =IF(AND(90>=$C$8,90<=$E$8),1,0) | CQ34: =IF(AND(91>=$C$8,91<=$E$8),1,0) | CR34: =IF(AND(92>=$C$8,92<=$E$8),1,0) | CS34: =IF(AND(93>=$C$8,93<=$E$8),1,0) | CT34: =IF(AND(94>=$C$8,94<=$E$8),1,0) | CU34: =IF(AND(95>=$C$8,95<=$E$8),1,0) | CV34: =IF(AND(96>=$C$8,96<=$E$8),1,0) | CW34: =IF(AND(97>=$C$8,97<=$E$8),1,0) | CX34: =IF(AND(98>=$C$8,98<=$E$8),1,0) | CY34: =IF(AND(99>=$C$8,99<=$E$8),1,0) | CZ34: =IF(AND(100>=$C$8,100<=$E$8),1,0) | DA34: =IF(AND(101>=$C$8,101<=$E$8),1,0) | DB34: =IF(AND(102>=$C$8,102<=$E$8),1,0) | DC34: =IF(AND(103>=$C$8,103<=$E$8),1,0) | DD34: =IF(AND(104>=$C$8,104<=$E$8),1,0) | DE34: =IF(AND(105>=$C$8,105<=$E$8),1,0) | DF34: =IF(AND(106>=$C$8,106<=$E$8),1,0) | DG34: =IF(AND(107>=$C$8,107<=$E$8),1,0) | DH34: =IF(AND(108>=$C$8,108<=$E$8),1,0) | DI34: =IF(AND(109>=$C$8,109<=$E$8),1,0) | DJ34: =IF(AND(110>=$C$8,110<=$E$8),1,0) | DK34: =IF(AND(111>=$C$8,111<=$E$8),1,0) | DL34: =IF(AND(112>=$C$8,112<=$E$8),1,0) | DM34: =IF(AND(113>=$C$8,113<=$E$8),1,0) | DN34: =IF(AND(114>=$C$8,114<=$E$8),1,0) | DO34: =IF(AND(115>=$C$8,115<=$E$8),1,0) | DP34: =IF(AND(116>=$C$8,116<=$E$8),1,0) | DQ34: =IF(AND(117>=$C$8,117<=$E$8),1,0) | DR34: =IF(AND(118>=$C$8,118<=$E$8),1,0) | DS34: =IF(AND(119>=$C$8,119<=$E$8),1,0) | DT34: =IF(AND(120>=$C$8,120<=$E$8),1,0) | DU34: =IF(AND(121>=$C$8,121<=$E$8),1,0) | DV34: =IF(AND(122>=$C$8,122<=$E$8),1,0) | DW34: =IF(AND(123>=$C$8,123<=$E$8),1,0) | DX34: =IF(AND(124>=$C$8,124<=$E$8),1,0) | DY34: =IF(AND(125>=$C$8,125<=$E$8),1,0) | DZ34: =IF(AND(126>=$C$8,126<=$E$8),1,0) | EA34: =IF(AND(127>=$C$8,127<=$E$8),1,0) | EB34: =IF(AND(128>=$C$8,128<=$E$8),1,0) | EC34: =IF(AND(129>=$C$8,129<=$E$8),1,0) | ED34: =IF(AND(130>=$C$8,130<=$E$8),1,0) | EE34: =IF(AND(131>=$C$8,131<=$E$8),1,0) | EF34: =IF(AND(132>=$C$8,132<=$E$8),1,0) | EG34: =IF(AND(133>=$C$8,133<=$E$8),1,0) | EH34: =IF(AND(134>=$C$8,134<=$E$8),1,0) | EI34: =IF(AND(135>=$C$8,135<=$E$8),1,0) | EJ34: =IF(AND(136>=$C$8,136<=$E$8),1,0) | EK34: =IF(AND(137>=$C$8,137<=$E$8),1,0) | EL34: =IF(AND(138>=$C$8,138<=$E$8),1,0) | EM34: =IF(AND(139>=$C$8,139<=$E$8),1,0) | EN34: =IF(AND(140>=$C$8,140<=$E$8),1,0) | EO34: =IF(AND(141>=$C$8,141<=$E$8),1,0) | EP34: =IF(AND(142>=$C$8,142<=$E$8),1,0) | EQ34: =IF(AND(143>=$C$8,143<=$E$8),1,0) | ER34: =IF(AND(144>=$C$8,144<=$E$8),1,0) | ES34: =IF(AND(145>=$C$8,145<=$E$8),1,0) | ET34: =IF(AND(146>=$C$8,146<=$E$8),1,0) | EU34: =IF(AND(147>=$C$8,147<=$E$8),1,0) | EV34: =IF(AND(148>=$C$8,148<=$E$8),1,0) | EW34: =IF(AND(149>=$C$8,149<=$E$8),1,0) | EX34: =IF(AND(150>=$C$8,150<=$E$8),1,0) | EY34: =IF(AND(151>=$C$8,151<=$E$8),1,0) | EZ34: =IF(AND(152>=$C$8,152<=$E$8),1,0) | FA34: =IF(AND(153>=$C$8,153<=$E$8),1,0) | FB34: =IF(AND(154>=$C$8,154<=$E$8),1,0) | FC34: =IF(AND(155>=$C$8,155<=$E$8),1,0) | FD34: =IF(AND(156>=$C$8,156<=$E$8),1,0) | FE34: =IF(AND(157>=$C$8,157<=$E$8),1,0) | FF34: =IF(AND(158>=$C$8,158<=$E$8),1,0) | FG34: =IF(AND(159>=$C$8,159<=$E$8),1,0) | FH34: =IF(AND(160>=$C$8,160<=$E$8),1,0) | FI34: =IF(AND(161>=$C$8,161<=$E$8),1,0) | FJ34: =IF(AND(162>=$C$8,162<=$E$8),1,0) | FK34: =IF(AND(163>=$C$8,163<=$E$8),1,0) | FL34: =IF(AND(164>=$C$8,164<=$E$8),1,0) | FM34: =IF(AND(165>=$C$8,165<=$E$8),1,0) | FN34: =IF(AND(166>=$C$8,166<=$E$8),1,0) | FO34: =IF(AND(167>=$C$8,167<=$E$8),1,0) | FP34: =IF(AND(168>=$C$8,168<=$E$8),1,0) | FQ34: =IF(AND(169>=$C$8,169<=$E$8),1,0) | FR34: =IF(AND(170>=$C$8,170<=$E$8),1,0) | FS34: =IF(AND(171>=$C$8,171<=$E$8),1,0) | FT34: =IF(AND(172>=$C$8,172<=$E$8),1,0) | FU34: =IF(AND(173>=$C$8,173<=$E$8),1,0) | FV34: =IF(AND(174>=$C$8,174<=$E$8),1,0) | FW34: =IF(AND(175>=$C$8,175<=$E$8),1,0) | FX34: =IF(AND(176>=$C$8,176<=$E$8),1,0) | FY34: =IF(AND(177>=$C$8,177<=$E$8),1,0) | FZ34: =IF(AND(178>=$C$8,178<=$E$8),1,0) | GA34: =IF(AND(179>=$C$8,179<=$E$8),1,0) | GB34: =IF(AND(180>=$C$8,180<=$E$8),1,0) | GC34: =IF(AND(181>=$C$8,181<=$E$8),1,0) | GD34: =IF(AND(182>=$C$8,182<=$E$8),1,0) | GE34: =IF(AND(183>=$C$8,183<=$E$8),1,0) | GF34: =IF(AND(184>=$C$8,184<=$E$8),1,0) | GG34: =IF(AND(185>=$C$8,185<=$E$8),1,0) | GH34: =IF(AND(186>=$C$8,186<=$E$8),1,0) | GI34: =IF(AND(187>=$C$8,187<=$E$8),1,0) | GJ34: =IF(AND(188>=$C$8,188<=$E$8),1,0) | GK34: =IF(AND(189>=$C$8,189<=$E$8),1,0) | GL34: =IF(AND(190>=$C$8,190<=$E$8),1,0) | GM34: =IF(AND(191>=$C$8,191<=$E$8),1,0) | GN34: =IF(AND(192>=$C$8,192<=$E$8),1,0) | GO34: =IF(AND(193>=$C$8,193<=$E$8),1,0) | GP34: =IF(AND(194>=$C$8,194<=$E$8),1,0) | GQ34: =IF(AND(195>=$C$8,195<=$E$8),1,0) | GR34: =IF(AND(196>=$C$8,196<=$E$8),1,0) | GS34: =IF(AND(197>=$C$8,197<=$E$8),1,0) | GT34: =IF(AND(198>=$C$8,198<=$E$8),1,0) | GU34: =IF(AND(199>=$C$8,199<=$E$8),1,0) | GV34: =IF(AND(200>=$C$8,200<=$E$8),1,0) | GW34: =IF(AND(201>=$C$8,201<=$E$8),1,0) | GX34: =IF(AND(202>=$C$8,202<=$E$8),1,0) | GY34: =IF(AND(203>=$C$8,203<=$E$8),1,0) | GZ34: =IF(AND(204>=$C$8,204<=$E$8),1,0) | HA34: =IF(AND(205>=$C$8,205<=$E$8),1,0) | HB34: =IF(AND(206>=$C$8,206<=$E$8),1,0) | HC34: =IF(AND(207>=$C$8,207<=$E$8),1,0) | HD34: =IF(AND(208>=$C$8,208<=$E$8),1,0) | HE34: =IF(AND(209>=$C$8,209<=$E$8),1,0) | HF34: =IF(AND(210>=$C$8,210<=$E$8),1,0) | HG34: =IF(AND(211>=$C$8,211<=$E$8),1,0) | HH34: =IF(AND(212>=$C$8,212<=$E$8),1,0) | HI34: =IF(AND(213>=$C$8,213<=$E$8),1,0) | HJ34: =IF(AND(214>=$C$8,214<=$E$8),1,0) | HK34: =IF(AND(215>=$C$8,215<=$E$8),1,0) | HL34: =IF(AND(216>=$C$8,216<=$E$8),1,0) | HM34: =IF(AND(217>=$C$8,217<=$E$8),1,0) | HN34: =IF(AND(218>=$C$8,218<=$E$8),1,0) | HO34: =IF(AND(219>=$C$8,219<=$E$8),1,0) | HP34: =IF(AND(220>=$C$8,220<=$E$8),1,0) | HQ34: =IF(AND(221>=$C$8,221<=$E$8),1,0) | HR34: =IF(AND(222>=$C$8,222<=$E$8),1,0) | HS34: =IF(AND(223>=$C$8,223<=$E$8),1,0) | HT34: =IF(AND(224>=$C$8,224<=$E$8),1,0) | HU34: =IF(AND(225>=$C$8,225<=$E$8),1,0) | HV34: =IF(AND(226>=$C$8,226<=$E$8),1,0) | HW34: =IF(AND(227>=$C$8,227<=$E$8),1,0) | HX34: =IF(AND(228>=$C$8,228<=$E$8),1,0) | HY34: =IF(AND(229>=$C$8,229<=$E$8),1,0) | HZ34: =IF(AND(230>=$C$8,230<=$E$8),1,0) | IA34: =IF(AND(231>=$C$8,231<=$E$8),1,0) | IB34: =IF(AND(232>=$C$8,232<=$E$8),1,0) | IC34: =IF(AND(233>=$C$8,233<=$E$8),1,0) | ID34: =IF(AND(234>=$C$8,234<=$E$8),1,0) | IE34: =IF(AND(235>=$C$8,235<=$E$8),1,0) | IF34: =IF(AND(236>=$C$8,236<=$E$8),1,0) | IG34: =IF(AND(237>=$C$8,237<=$E$8),1,0) | IH34: =IF(AND(238>=$C$8,238<=$E$8),1,0) | II34: =IF(AND(239>=$C$8,239<=$E$8),1,0) | IJ34: =IF(AND(240>=$C$8,240<=$E$8),1,0) | IK34: =IF(AND(241>=$C$8,241<=$E$8),1,0) | IL34: =IF(AND(242>=$C$8,242<=$E$8),1,0) | IM34: =IF(AND(243>=$C$8,243<=$E$8),1,0) | IN34: =IF(AND(244>=$C$8,244<=$E$8),1,0) | IO34: =IF(AND(245>=$C$8,245<=$E$8),1,0) | IP34: =IF(AND(246>=$C$8,246<=$E$8),1,0) | IQ34: =IF(AND(247>=$C$8,247<=$E$8),1,0) | IR34: =IF(AND(248>=$C$8,248<=$E$8),1,0) | IS34: =IF(AND(249>=$C$8,249<=$E$8),1,0) | IT34: =IF(AND(250>=$C$8,250<=$E$8),1,0) | IU34: =IF(AND(251>=$C$8,251<=$E$8),1,0) | IV34: =IF(AND(252>=$C$8,252<=$E$8),1,0) | IW34: =IF(AND(253>=$C$8,253<=$E$8),1,0) | IX34: =IF(AND(254>=$C$8,254<=$E$8),1,0) | IY34: =IF(AND(255>=$C$8,255<=$E$8),1,0) | IZ34: =IF(AND(256>=$C$8,256<=$E$8),1,0) | JA34: =IF(AND(257>=$C$8,257<=$E$8),1,0) | JB34: =IF(AND(258>=$C$8,258<=$E$8),1,0) | JC34: =IF(AND(259>=$C$8,259<=$E$8),1,0) | JD34: =IF(AND(260>=$C$8,260<=$E$8),1,0) | JE34: =IF(AND(261>=$C$8,261<=$E$8),1,0) | JF34: =IF(AND(262>=$C$8,262<=$E$8),1,0) | JG34: =IF(AND(263>=$C$8,263<=$E$8),1,0) | JH34: =IF(AND(264>=$C$8,264<=$E$8),1,0) | JI34: =IF(AND(265>=$C$8,265<=$E$8),1,0) | JJ34: =IF(AND(266>=$C$8,266<=$E$8),1,0) | JK34: =IF(AND(267>=$C$8,267<=$E$8),1,0) | JL34: =IF(AND(268>=$C$8,268<=$E$8),1,0) | JM34: =IF(AND(269>=$C$8,269<=$E$8),1,0) | JN34: =IF(AND(270>=$C$8,270<=$E$8),1,0) | JO34: =IF(AND(271>=$C$8,271<=$E$8),1,0) | JP34: =IF(AND(272>=$C$8,272<=$E$8),1,0) | JQ34: =IF(AND(273>=$C$8,273<=$E$8),1,0) | JR34: =IF(AND(274>=$C$8,274<=$E$8),1,0) | JS34: =IF(AND(275>=$C$8,275<=$E$8),1,0) | JT34: =IF(AND(276>=$C$8,276<=$E$8),1,0) | JU34: =IF(AND(277>=$C$8,277<=$E$8),1,0) | JV34: =IF(AND(278>=$C$8,278<=$E$8),1,0) | JW34: =IF(AND(279>=$C$8,279<=$E$8),1,0) | JX34: =IF(AND(280>=$C$8,280<=$E$8),1,0) | JY34: =IF(AND(281>=$C$8,281<=$E$8),1,0) | JZ34: =IF(AND(282>=$C$8,282<=$E$8),1,0) | KA34: =IF(AND(283>=$C$8,283<=$E$8),1,0) | KB34: =IF(AND(284>=$C$8,284<=$E$8),1,0) | KC34: =IF(AND(285>=$C$8,285<=$E$8),1,0) | KD34: =IF(AND(286>=$C$8,286<=$E$8),1,0) | KE34: =IF(AND(287>=$C$8,287<=$E$8),1,0) | KF34: =IF(AND(288>=$C$8,288<=$E$8),1,0) | KG34: =IF(AND(289>=$C$8,289<=$E$8),1,0) | KH34: =IF(AND(290>=$C$8,290<=$E$8),1,0) | KI34: =IF(AND(291>=$C$8,291<=$E$8),1,0) | KJ34: =IF(AND(292>=$C$8,292<=$E$8),1,0) | KK34: =IF(AND(293>=$C$8,293<=$E$8),1,0) | KL34: =IF(AND(294>=$C$8,294<=$E$8),1,0) | KM34: =IF(AND(295>=$C$8,295<=$E$8),1,0) | KN34: =IF(AND(296>=$C$8,296<=$E$8),1,0) | KO34: =IF(AND(297>=$C$8,297<=$E$8),1,0) | KP34: =IF(AND(298>=$C$8,298<=$E$8),1,0) | KQ34: =IF(AND(299>=$C$8,299<=$E$8),1,0) | KR34: =IF(AND(300>=$C$8,300<=$E$8),1,0) | KS34: =IF(AND(301>=$C$8,301<=$E$8),1,0) | KT34: =IF(AND(302>=$C$8,302<=$E$8),1,0) | KU34: =IF(AND(303>=$C$8,303<=$E$8),1,0) | KV34: =IF(AND(304>=$C$8,304<=$E$8),1,0) | KW34: =IF(AND(305>=$C$8,305<=$E$8),1,0) | KX34: =IF(AND(306>=$C$8,306<=$E$8),1,0) | KY34: =IF(AND(307>=$C$8,307<=$E$8),1,0) | KZ34: =IF(AND(308>=$C$8,308<=$E$8),1,0) | LA34: =IF(AND(309>=$C$8,309<=$E$8),1,0) | LB34: =IF(AND(310>=$C$8,310<=$E$8),1,0) | LC34: =IF(AND(311>=$C$8,311<=$E$8),1,0) | LD34: =IF(AND(312>=$C$8,312<=$E$8),1,0) | LE34: =IF(AND(313>=$C$8,313<=$E$8),1,0) | LF34: =IF(AND(314>=$C$8,314<=$E$8),1,0) | LG34: =IF(AND(315>=$C$8,315<=$E$8),1,0) | LH34: =IF(AND(316>=$C$8,316<=$E$8),1,0) | LI34: =IF(AND(317>=$C$8,317<=$E$8),1,0) | LJ34: =IF(AND(318>=$C$8,318<=$E$8),1,0) | LK34: =IF(AND(319>=$C$8,319<=$E$8),1,0) | LL34: =IF(AND(320>=$C$8,320<=$E$8),1,0) | LM34: =IF(AND(321>=$C$8,321<=$E$8),1,0) | LN34: =IF(AND(322>=$C$8,322<=$E$8),1,0) | LO34: =IF(AND(323>=$C$8,323<=$E$8),1,0) | LP34: =IF(AND(324>=$C$8,324<=$E$8),1,0) | LQ34: =IF(AND(325>=$C$8,325<=$E$8),1,0) | LR34: =IF(AND(326>=$C$8,326<=$E$8),1,0) | LS34: =IF(AND(327>=$C$8,327<=$E$8),1,0) | LT34: =IF(AND(328>=$C$8,328<=$E$8),1,0) | LU34: =IF(AND(329>=$C$8,329<=$E$8),1,0) | LV34: =IF(AND(330>=$C$8,330<=$E$8),1,0) | LW34: =IF(AND(331>=$C$8,331<=$E$8),1,0) | LX34: =IF(AND(332>=$C$8,332<=$E$8),1,0) | LY34: =IF(AND(333>=$C$8,333<=$E$8),1,0) | LZ34: =IF(AND(334>=$C$8,334<=$E$8),1,0) | MA34: =IF(AND(335>=$C$8,335<=$E$8),1,0) | MB34: =IF(AND(336>=$C$8,336<=$E$8),1,0) | MC34: =IF(AND(337>=$C$8,337<=$E$8),1,0) | MD34: =IF(AND(338>=$C$8,338<=$E$8),1,0) | ME34: =IF(AND(339>=$C$8,339<=$E$8),1,0) | MF34: =IF(AND(340>=$C$8,340<=$E$8),1,0) | MG34: =IF(AND(341>=$C$8,341<=$E$8),1,0) | MH34: =IF(AND(342>=$C$8,342<=$E$8),1,0) | MI34: =IF(AND(343>=$C$8,343<=$E$8),1,0) | MJ34: =IF(AND(344>=$C$8,344<=$E$8),1,0) | MK34: =IF(AND(345>=$C$8,345<=$E$8),1,0) | ML34: =IF(AND(346>=$C$8,346<=$E$8),1,0) | MM34: =IF(AND(347>=$C$8,347<=$E$8),1,0) | MN34: =IF(AND(348>=$C$8,348<=$E$8),1,0) | MO34: =IF(AND(349>=$C$8,349<=$E$8),1,0) | MP34: =IF(AND(350>=$C$8,350<=$E$8),1,0) | MQ34: =IF(AND(351>=$C$8,351<=$E$8),1,0) | MR34: =IF(AND(352>=$C$8,352<=$E$8),1,0) | MS34: =IF(AND(353>=$C$8,353<=$E$8),1,0) | MT34: =IF(AND(354>=$C$8,354<=$E$8),1,0) | MU34: =IF(AND(355>=$C$8,355<=$E$8),1,0) | MV34: =IF(AND(356>=$C$8,356<=$E$8),1,0) | MW34: =IF(AND(357>=$C$8,357<=$E$8),1,0) | MX34: =IF(AND(358>=$C$8,358<=$E$8),1,0) | MY34: =IF(AND(359>=$C$8,359<=$E$8),1,0) | MZ34: =IF(AND(360>=$C$8,360<=$E$8),1,0) | NA34: =IF(AND(361>=$C$8,361<=$E$8),1,0) | NB34: =IF(AND(362>=$C$8,362<=$E$8),1,0) | NC34: =IF(AND(363>=$C$8,363<=$E$8),1,0) | ND34: =IF(AND(364>=$C$8,364<=$E$8),1,0) | NE34: =IF(AND(365>=$C$8,365<=$E$8),1,0) | NF34: =IF(AND(366>=$C$8,366<=$E$8),1,0) | NG34: =IF(AND(367>=$C$8,367<=$E$8),1,0) | NH34: =IF(AND(368>=$C$8,368<=$E$8),1,0) | NI34: =IF(AND(369>=$C$8,369<=$E$8),1,0) | NJ34: =IF(AND(370>=$C$8,370<=$E$8),1,0) | NK34: =IF(AND(371>=$C$8,371<=$E$8),1,0) | NL34: =IF(AND(372>=$C$8,372<=$E$8),1,0)
B35: Flag: Construction | E35: =IF(AND(1>=$C$9,1<=$E$9),1,0) | F35: =IF(AND(2>=$C$9,2<=$E$9),1,0) | G35: =IF(AND(3>=$C$9,3<=$E$9),1,0) | H35: =IF(AND(4>=$C$9,4<=$E$9),1,0) | I35: =IF(AND(5>=$C$9,5<=$E$9),1,0) | J35: =IF(AND(6>=$C$9,6<=$E$9),1,0) | K35: =IF(AND(7>=$C$9,7<=$E$9),1,0) | L35: =IF(AND(8>=$C$9,8<=$E$9),1,0) | M35: =IF(AND(9>=$C$9,9<=$E$9),1,0) | N35: =IF(AND(10>=$C$9,10<=$E$9),1,0) | O35: =IF(AND(11>=$C$9,11<=$E$9),1,0) | P35: =IF(AND(12>=$C$9,12<=$E$9),1,0) | Q35: =IF(AND(13>=$C$9,13<=$E$9),1,0) | R35: =IF(AND(14>=$C$9,14<=$E$9),1,0) | S35: =IF(AND(15>=$C$9,15<=$E$9),1,0) | T35: =IF(AND(16>=$C$9,16<=$E$9),1,0) | U35: =IF(AND(17>=$C$9,17<=$E$9),1,0) | V35: =IF(AND(18>=$C$9,18<=$E$9),1,0) | W35: =IF(AND(19>=$C$9,19<=$E$9),1,0) | X35: =IF(AND(20>=$C$9,20<=$E$9),1,0) | Y35: =IF(AND(21>=$C$9,21<=$E$9),1,0) | Z35: =IF(AND(22>=$C$9,22<=$E$9),1,0) | AA35: =IF(AND(23>=$C$9,23<=$E$9),1,0) | AB35: =IF(AND(24>=$C$9,24<=$E$9),1,0) | AC35: =IF(AND(25>=$C$9,25<=$E$9),1,0) | AD35: =IF(AND(26>=$C$9,26<=$E$9),1,0) | AE35: =IF(AND(27>=$C$9,27<=$E$9),1,0) | AF35: =IF(AND(28>=$C$9,28<=$E$9),1,0) | AG35: =IF(AND(29>=$C$9,29<=$E$9),1,0) | AH35: =IF(AND(30>=$C$9,30<=$E$9),1,0) | AI35: =IF(AND(31>=$C$9,31<=$E$9),1,0) | AJ35: =IF(AND(32>=$C$9,32<=$E$9),1,0) | AK35: =IF(AND(33>=$C$9,33<=$E$9),1,0) | AL35: =IF(AND(34>=$C$9,34<=$E$9),1,0) | AM35: =IF(AND(35>=$C$9,35<=$E$9),1,0) | AN35: =IF(AND(36>=$C$9,36<=$E$9),1,0) | AO35: =IF(AND(37>=$C$9,37<=$E$9),1,0) | AP35: =IF(AND(38>=$C$9,38<=$E$9),1,0) | AQ35: =IF(AND(39>=$C$9,39<=$E$9),1,0) | AR35: =IF(AND(40>=$C$9,40<=$E$9),1,0) | AS35: =IF(AND(41>=$C$9,41<=$E$9),1,0) | AT35: =IF(AND(42>=$C$9,42<=$E$9),1,0) | AU35: =IF(AND(43>=$C$9,43<=$E$9),1,0) | AV35: =IF(AND(44>=$C$9,44<=$E$9),1,0) | AW35: =IF(AND(45>=$C$9,45<=$E$9),1,0) | AX35: =IF(AND(46>=$C$9,46<=$E$9),1,0) | AY35: =IF(AND(47>=$C$9,47<=$E$9),1,0) | AZ35: =IF(AND(48>=$C$9,48<=$E$9),1,0) | BA35: =IF(AND(49>=$C$9,49<=$E$9),1,0) | BB35: =IF(AND(50>=$C$9,50<=$E$9),1,0) | BC35: =IF(AND(51>=$C$9,51<=$E$9),1,0) | BD35: =IF(AND(52>=$C$9,52<=$E$9),1,0) | BE35: =IF(AND(53>=$C$9,53<=$E$9),1,0) | BF35: =IF(AND(54>=$C$9,54<=$E$9),1,0) | BG35: =IF(AND(55>=$C$9,55<=$E$9),1,0) | BH35: =IF(AND(56>=$C$9,56<=$E$9),1,0) | BI35: =IF(AND(57>=$C$9,57<=$E$9),1,0) | BJ35: =IF(AND(58>=$C$9,58<=$E$9),1,0) | BK35: =IF(AND(59>=$C$9,59<=$E$9),1,0) | BL35: =IF(AND(60>=$C$9,60<=$E$9),1,0) | BM35: =IF(AND(61>=$C$9,61<=$E$9),1,0) | BN35: =IF(AND(62>=$C$9,62<=$E$9),1,0) | BO35: =IF(AND(63>=$C$9,63<=$E$9),1,0) | BP35: =IF(AND(64>=$C$9,64<=$E$9),1,0) | BQ35: =IF(AND(65>=$C$9,65<=$E$9),1,0) | BR35: =IF(AND(66>=$C$9,66<=$E$9),1,0) | BS35: =IF(AND(67>=$C$9,67<=$E$9),1,0) | BT35: =IF(AND(68>=$C$9,68<=$E$9),1,0) | BU35: =IF(AND(69>=$C$9,69<=$E$9),1,0) | BV35: =IF(AND(70>=$C$9,70<=$E$9),1,0) | BW35: =IF(AND(71>=$C$9,71<=$E$9),1,0) | BX35: =IF(AND(72>=$C$9,72<=$E$9),1,0) | BY35: =IF(AND(73>=$C$9,73<=$E$9),1,0) | BZ35: =IF(AND(74>=$C$9,74<=$E$9),1,0) | CA35: =IF(AND(75>=$C$9,75<=$E$9),1,0) | CB35: =IF(AND(76>=$C$9,76<=$E$9),1,0) | CC35: =IF(AND(77>=$C$9,77<=$E$9),1,0) | CD35: =IF(AND(78>=$C$9,78<=$E$9),1,0) | CE35: =IF(AND(79>=$C$9,79<=$E$9),1,0) | CF35: =IF(AND(80>=$C$9,80<=$E$9),1,0) | CG35: =IF(AND(81>=$C$9,81<=$E$9),1,0) | CH35: =IF(AND(82>=$C$9,82<=$E$9),1,0) | CI35: =IF(AND(83>=$C$9,83<=$E$9),1,0) | CJ35: =IF(AND(84>=$C$9,84<=$E$9),1,0) | CK35: =IF(AND(85>=$C$9,85<=$E$9),1,0) | CL35: =IF(AND(86>=$C$9,86<=$E$9),1,0) | CM35: =IF(AND(87>=$C$9,87<=$E$9),1,0) | CN35: =IF(AND(88>=$C$9,88<=$E$9),1,0) | CO35: =IF(AND(89>=$C$9,89<=$E$9),1,0) | CP35: =IF(AND(90>=$C$9,90<=$E$9),1,0) | CQ35: =IF(AND(91>=$C$9,91<=$E$9),1,0) | CR35: =IF(AND(92>=$C$9,92<=$E$9),1,0) | CS35: =IF(AND(93>=$C$9,93<=$E$9),1,0) | CT35: =IF(AND(94>=$C$9,94<=$E$9),1,0) | CU35: =IF(AND(95>=$C$9,95<=$E$9),1,0) | CV35: =IF(AND(96>=$C$9,96<=$E$9),1,0) | CW35: =IF(AND(97>=$C$9,97<=$E$9),1,0) | CX35: =IF(AND(98>=$C$9,98<=$E$9),1,0) | CY35: =IF(AND(99>=$C$9,99<=$E$9),1,0) | CZ35: =IF(AND(100>=$C$9,100<=$E$9),1,0) | DA35: =IF(AND(101>=$C$9,101<=$E$9),1,0) | DB35: =IF(AND(102>=$C$9,102<=$E$9),1,0) | DC35: =IF(AND(103>=$C$9,103<=$E$9),1,0) | DD35: =IF(AND(104>=$C$9,104<=$E$9),1,0) | DE35: =IF(AND(105>=$C$9,105<=$E$9),1,0) | DF35: =IF(AND(106>=$C$9,106<=$E$9),1,0) | DG35: =IF(AND(107>=$C$9,107<=$E$9),1,0) | DH35: =IF(AND(108>=$C$9,108<=$E$9),1,0) | DI35: =IF(AND(109>=$C$9,109<=$E$9),1,0) | DJ35: =IF(AND(110>=$C$9,110<=$E$9),1,0) | DK35: =IF(AND(111>=$C$9,111<=$E$9),1,0) | DL35: =IF(AND(112>=$C$9,112<=$E$9),1,0) | DM35: =IF(AND(113>=$C$9,113<=$E$9),1,0) | DN35: =IF(AND(114>=$C$9,114<=$E$9),1,0) | DO35: =IF(AND(115>=$C$9,115<=$E$9),1,0) | DP35: =IF(AND(116>=$C$9,116<=$E$9),1,0) | DQ35: =IF(AND(117>=$C$9,117<=$E$9),1,0) | DR35: =IF(AND(118>=$C$9,118<=$E$9),1,0) | DS35: =IF(AND(119>=$C$9,119<=$E$9),1,0) | DT35: =IF(AND(120>=$C$9,120<=$E$9),1,0) | DU35: =IF(AND(121>=$C$9,121<=$E$9),1,0) | DV35: =IF(AND(122>=$C$9,122<=$E$9),1,0) | DW35: =IF(AND(123>=$C$9,123<=$E$9),1,0) | DX35: =IF(AND(124>=$C$9,124<=$E$9),1,0) | DY35: =IF(AND(125>=$C$9,125<=$E$9),1,0) | DZ35: =IF(AND(126>=$C$9,126<=$E$9),1,0) | EA35: =IF(AND(127>=$C$9,127<=$E$9),1,0) | EB35: =IF(AND(128>=$C$9,128<=$E$9),1,0) | EC35: =IF(AND(129>=$C$9,129<=$E$9),1,0) | ED35: =IF(AND(130>=$C$9,130<=$E$9),1,0) | EE35: =IF(AND(131>=$C$9,131<=$E$9),1,0) | EF35: =IF(AND(132>=$C$9,132<=$E$9),1,0) | EG35: =IF(AND(133>=$C$9,133<=$E$9),1,0) | EH35: =IF(AND(134>=$C$9,134<=$E$9),1,0) | EI35: =IF(AND(135>=$C$9,135<=$E$9),1,0) | EJ35: =IF(AND(136>=$C$9,136<=$E$9),1,0) | EK35: =IF(AND(137>=$C$9,137<=$E$9),1,0) | EL35: =IF(AND(138>=$C$9,138<=$E$9),1,0) | EM35: =IF(AND(139>=$C$9,139<=$E$9),1,0) | EN35: =IF(AND(140>=$C$9,140<=$E$9),1,0) | EO35: =IF(AND(141>=$C$9,141<=$E$9),1,0) | EP35: =IF(AND(142>=$C$9,142<=$E$9),1,0) | EQ35: =IF(AND(143>=$C$9,143<=$E$9),1,0) | ER35: =IF(AND(144>=$C$9,144<=$E$9),1,0) | ES35: =IF(AND(145>=$C$9,145<=$E$9),1,0) | ET35: =IF(AND(146>=$C$9,146<=$E$9),1,0) | EU35: =IF(AND(147>=$C$9,147<=$E$9),1,0) | EV35: =IF(AND(148>=$C$9,148<=$E$9),1,0) | EW35: =IF(AND(149>=$C$9,149<=$E$9),1,0) | EX35: =IF(AND(150>=$C$9,150<=$E$9),1,0) | EY35: =IF(AND(151>=$C$9,151<=$E$9),1,0) | EZ35: =IF(AND(152>=$C$9,152<=$E$9),1,0) | FA35: =IF(AND(153>=$C$9,153<=$E$9),1,0) | FB35: =IF(AND(154>=$C$9,154<=$E$9),1,0) | FC35: =IF(AND(155>=$C$9,155<=$E$9),1,0) | FD35: =IF(AND(156>=$C$9,156<=$E$9),1,0) | FE35: =IF(AND(157>=$C$9,157<=$E$9),1,0) | FF35: =IF(AND(158>=$C$9,158<=$E$9),1,0) | FG35: =IF(AND(159>=$C$9,159<=$E$9),1,0) | FH35: =IF(AND(160>=$C$9,160<=$E$9),1,0) | FI35: =IF(AND(161>=$C$9,161<=$E$9),1,0) | FJ35: =IF(AND(162>=$C$9,162<=$E$9),1,0) | FK35: =IF(AND(163>=$C$9,163<=$E$9),1,0) | FL35: =IF(AND(164>=$C$9,164<=$E$9),1,0) | FM35: =IF(AND(165>=$C$9,165<=$E$9),1,0) | FN35: =IF(AND(166>=$C$9,166<=$E$9),1,0) | FO35: =IF(AND(167>=$C$9,167<=$E$9),1,0) | FP35: =IF(AND(168>=$C$9,168<=$E$9),1,0) | FQ35: =IF(AND(169>=$C$9,169<=$E$9),1,0) | FR35: =IF(AND(170>=$C$9,170<=$E$9),1,0) | FS35: =IF(AND(171>=$C$9,171<=$E$9),1,0) | FT35: =IF(AND(172>=$C$9,172<=$E$9),1,0) | FU35: =IF(AND(173>=$C$9,173<=$E$9),1,0) | FV35: =IF(AND(174>=$C$9,174<=$E$9),1,0) | FW35: =IF(AND(175>=$C$9,175<=$E$9),1,0) | FX35: =IF(AND(176>=$C$9,176<=$E$9),1,0) | FY35: =IF(AND(177>=$C$9,177<=$E$9),1,0) | FZ35: =IF(AND(178>=$C$9,178<=$E$9),1,0) | GA35: =IF(AND(179>=$C$9,179<=$E$9),1,0) | GB35: =IF(AND(180>=$C$9,180<=$E$9),1,0) | GC35: =IF(AND(181>=$C$9,181<=$E$9),1,0) | GD35: =IF(AND(182>=$C$9,182<=$E$9),1,0) | GE35: =IF(AND(183>=$C$9,183<=$E$9),1,0) | GF35: =IF(AND(184>=$C$9,184<=$E$9),1,0) | GG35: =IF(AND(185>=$C$9,185<=$E$9),1,0) | GH35: =IF(AND(186>=$C$9,186<=$E$9),1,0) | GI35: =IF(AND(187>=$C$9,187<=$E$9),1,0) | GJ35: =IF(AND(188>=$C$9,188<=$E$9),1,0) | GK35: =IF(AND(189>=$C$9,189<=$E$9),1,0) | GL35: =IF(AND(190>=$C$9,190<=$E$9),1,0) | GM35: =IF(AND(191>=$C$9,191<=$E$9),1,0) | GN35: =IF(AND(192>=$C$9,192<=$E$9),1,0) | GO35: =IF(AND(193>=$C$9,193<=$E$9),1,0) | GP35: =IF(AND(194>=$C$9,194<=$E$9),1,0) | GQ35: =IF(AND(195>=$C$9,195<=$E$9),1,0) | GR35: =IF(AND(196>=$C$9,196<=$E$9),1,0) | GS35: =IF(AND(197>=$C$9,197<=$E$9),1,0) | GT35: =IF(AND(198>=$C$9,198<=$E$9),1,0) | GU35: =IF(AND(199>=$C$9,199<=$E$9),1,0) | GV35: =IF(AND(200>=$C$9,200<=$E$9),1,0) | GW35: =IF(AND(201>=$C$9,201<=$E$9),1,0) | GX35: =IF(AND(202>=$C$9,202<=$E$9),1,0) | GY35: =IF(AND(203>=$C$9,203<=$E$9),1,0) | GZ35: =IF(AND(204>=$C$9,204<=$E$9),1,0) | HA35: =IF(AND(205>=$C$9,205<=$E$9),1,0) | HB35: =IF(AND(206>=$C$9,206<=$E$9),1,0) | HC35: =IF(AND(207>=$C$9,207<=$E$9),1,0) | HD35: =IF(AND(208>=$C$9,208<=$E$9),1,0) | HE35: =IF(AND(209>=$C$9,209<=$E$9),1,0) | HF35: =IF(AND(210>=$C$9,210<=$E$9),1,0) | HG35: =IF(AND(211>=$C$9,211<=$E$9),1,0) | HH35: =IF(AND(212>=$C$9,212<=$E$9),1,0) | HI35: =IF(AND(213>=$C$9,213<=$E$9),1,0) | HJ35: =IF(AND(214>=$C$9,214<=$E$9),1,0) | HK35: =IF(AND(215>=$C$9,215<=$E$9),1,0) | HL35: =IF(AND(216>=$C$9,216<=$E$9),1,0) | HM35: =IF(AND(217>=$C$9,217<=$E$9),1,0) | HN35: =IF(AND(218>=$C$9,218<=$E$9),1,0) | HO35: =IF(AND(219>=$C$9,219<=$E$9),1,0) | HP35: =IF(AND(220>=$C$9,220<=$E$9),1,0) | HQ35: =IF(AND(221>=$C$9,221<=$E$9),1,0) | HR35: =IF(AND(222>=$C$9,222<=$E$9),1,0) | HS35: =IF(AND(223>=$C$9,223<=$E$9),1,0) | HT35: =IF(AND(224>=$C$9,224<=$E$9),1,0) | HU35: =IF(AND(225>=$C$9,225<=$E$9),1,0) | HV35: =IF(AND(226>=$C$9,226<=$E$9),1,0) | HW35: =IF(AND(227>=$C$9,227<=$E$9),1,0) | HX35: =IF(AND(228>=$C$9,228<=$E$9),1,0) | HY35: =IF(AND(229>=$C$9,229<=$E$9),1,0) | HZ35: =IF(AND(230>=$C$9,230<=$E$9),1,0) | IA35: =IF(AND(231>=$C$9,231<=$E$9),1,0) | IB35: =IF(AND(232>=$C$9,232<=$E$9),1,0) | IC35: =IF(AND(233>=$C$9,233<=$E$9),1,0) | ID35: =IF(AND(234>=$C$9,234<=$E$9),1,0) | IE35: =IF(AND(235>=$C$9,235<=$E$9),1,0) | IF35: =IF(AND(236>=$C$9,236<=$E$9),1,0) | IG35: =IF(AND(237>=$C$9,237<=$E$9),1,0) | IH35: =IF(AND(238>=$C$9,238<=$E$9),1,0) | II35: =IF(AND(239>=$C$9,239<=$E$9),1,0) | IJ35: =IF(AND(240>=$C$9,240<=$E$9),1,0) | IK35: =IF(AND(241>=$C$9,241<=$E$9),1,0) | IL35: =IF(AND(242>=$C$9,242<=$E$9),1,0) | IM35: =IF(AND(243>=$C$9,243<=$E$9),1,0) | IN35: =IF(AND(244>=$C$9,244<=$E$9),1,0) | IO35: =IF(AND(245>=$C$9,245<=$E$9),1,0) | IP35: =IF(AND(246>=$C$9,246<=$E$9),1,0) | IQ35: =IF(AND(247>=$C$9,247<=$E$9),1,0) | IR35: =IF(AND(248>=$C$9,248<=$E$9),1,0) | IS35: =IF(AND(249>=$C$9,249<=$E$9),1,0) | IT35: =IF(AND(250>=$C$9,250<=$E$9),1,0) | IU35: =IF(AND(251>=$C$9,251<=$E$9),1,0) | IV35: =IF(AND(252>=$C$9,252<=$E$9),1,0) | IW35: =IF(AND(253>=$C$9,253<=$E$9),1,0) | IX35: =IF(AND(254>=$C$9,254<=$E$9),1,0) | IY35: =IF(AND(255>=$C$9,255<=$E$9),1,0) | IZ35: =IF(AND(256>=$C$9,256<=$E$9),1,0) | JA35: =IF(AND(257>=$C$9,257<=$E$9),1,0) | JB35: =IF(AND(258>=$C$9,258<=$E$9),1,0) | JC35: =IF(AND(259>=$C$9,259<=$E$9),1,0) | JD35: =IF(AND(260>=$C$9,260<=$E$9),1,0) | JE35: =IF(AND(261>=$C$9,261<=$E$9),1,0) | JF35: =IF(AND(262>=$C$9,262<=$E$9),1,0) | JG35: =IF(AND(263>=$C$9,263<=$E$9),1,0) | JH35: =IF(AND(264>=$C$9,264<=$E$9),1,0) | JI35: =IF(AND(265>=$C$9,265<=$E$9),1,0) | JJ35: =IF(AND(266>=$C$9,266<=$E$9),1,0) | JK35: =IF(AND(267>=$C$9,267<=$E$9),1,0) | JL35: =IF(AND(268>=$C$9,268<=$E$9),1,0) | JM35: =IF(AND(269>=$C$9,269<=$E$9),1,0) | JN35: =IF(AND(270>=$C$9,270<=$E$9),1,0) | JO35: =IF(AND(271>=$C$9,271<=$E$9),1,0) | JP35: =IF(AND(272>=$C$9,272<=$E$9),1,0) | JQ35: =IF(AND(273>=$C$9,273<=$E$9),1,0) | JR35: =IF(AND(274>=$C$9,274<=$E$9),1,0) | JS35: =IF(AND(275>=$C$9,275<=$E$9),1,0) | JT35: =IF(AND(276>=$C$9,276<=$E$9),1,0) | JU35: =IF(AND(277>=$C$9,277<=$E$9),1,0) | JV35: =IF(AND(278>=$C$9,278<=$E$9),1,0) | JW35: =IF(AND(279>=$C$9,279<=$E$9),1,0) | JX35: =IF(AND(280>=$C$9,280<=$E$9),1,0) | JY35: =IF(AND(281>=$C$9,281<=$E$9),1,0) | JZ35: =IF(AND(282>=$C$9,282<=$E$9),1,0) | KA35: =IF(AND(283>=$C$9,283<=$E$9),1,0) | KB35: =IF(AND(284>=$C$9,284<=$E$9),1,0) | KC35: =IF(AND(285>=$C$9,285<=$E$9),1,0) | KD35: =IF(AND(286>=$C$9,286<=$E$9),1,0) | KE35: =IF(AND(287>=$C$9,287<=$E$9),1,0) | KF35: =IF(AND(288>=$C$9,288<=$E$9),1,0) | KG35: =IF(AND(289>=$C$9,289<=$E$9),1,0) | KH35: =IF(AND(290>=$C$9,290<=$E$9),1,0) | KI35: =IF(AND(291>=$C$9,291<=$E$9),1,0) | KJ35: =IF(AND(292>=$C$9,292<=$E$9),1,0) | KK35: =IF(AND(293>=$C$9,293<=$E$9),1,0) | KL35: =IF(AND(294>=$C$9,294<=$E$9),1,0) | KM35: =IF(AND(295>=$C$9,295<=$E$9),1,0) | KN35: =IF(AND(296>=$C$9,296<=$E$9),1,0) | KO35: =IF(AND(297>=$C$9,297<=$E$9),1,0) | KP35: =IF(AND(298>=$C$9,298<=$E$9),1,0) | KQ35: =IF(AND(299>=$C$9,299<=$E$9),1,0) | KR35: =IF(AND(300>=$C$9,300<=$E$9),1,0) | KS35: =IF(AND(301>=$C$9,301<=$E$9),1,0) | KT35: =IF(AND(302>=$C$9,302<=$E$9),1,0) | KU35: =IF(AND(303>=$C$9,303<=$E$9),1,0) | KV35: =IF(AND(304>=$C$9,304<=$E$9),1,0) | KW35: =IF(AND(305>=$C$9,305<=$E$9),1,0) | KX35: =IF(AND(306>=$C$9,306<=$E$9),1,0) | KY35: =IF(AND(307>=$C$9,307<=$E$9),1,0) | KZ35: =IF(AND(308>=$C$9,308<=$E$9),1,0) | LA35: =IF(AND(309>=$C$9,309<=$E$9),1,0) | LB35: =IF(AND(310>=$C$9,310<=$E$9),1,0) | LC35: =IF(AND(311>=$C$9,311<=$E$9),1,0) | LD35: =IF(AND(312>=$C$9,312<=$E$9),1,0) | LE35: =IF(AND(313>=$C$9,313<=$E$9),1,0) | LF35: =IF(AND(314>=$C$9,314<=$E$9),1,0) | LG35: =IF(AND(315>=$C$9,315<=$E$9),1,0) | LH35: =IF(AND(316>=$C$9,316<=$E$9),1,0) | LI35: =IF(AND(317>=$C$9,317<=$E$9),1,0) | LJ35: =IF(AND(318>=$C$9,318<=$E$9),1,0) | LK35: =IF(AND(319>=$C$9,319<=$E$9),1,0) | LL35: =IF(AND(320>=$C$9,320<=$E$9),1,0) | LM35: =IF(AND(321>=$C$9,321<=$E$9),1,0) | LN35: =IF(AND(322>=$C$9,322<=$E$9),1,0) | LO35: =IF(AND(323>=$C$9,323<=$E$9),1,0) | LP35: =IF(AND(324>=$C$9,324<=$E$9),1,0) | LQ35: =IF(AND(325>=$C$9,325<=$E$9),1,0) | LR35: =IF(AND(326>=$C$9,326<=$E$9),1,0) | LS35: =IF(AND(327>=$C$9,327<=$E$9),1,0) | LT35: =IF(AND(328>=$C$9,328<=$E$9),1,0) | LU35: =IF(AND(329>=$C$9,329<=$E$9),1,0) | LV35: =IF(AND(330>=$C$9,330<=$E$9),1,0) | LW35: =IF(AND(331>=$C$9,331<=$E$9),1,0) | LX35: =IF(AND(332>=$C$9,332<=$E$9),1,0) | LY35: =IF(AND(333>=$C$9,333<=$E$9),1,0) | LZ35: =IF(AND(334>=$C$9,334<=$E$9),1,0) | MA35: =IF(AND(335>=$C$9,335<=$E$9),1,0) | MB35: =IF(AND(336>=$C$9,336<=$E$9),1,0) | MC35: =IF(AND(337>=$C$9,337<=$E$9),1,0) | MD35: =IF(AND(338>=$C$9,338<=$E$9),1,0) | ME35: =IF(AND(339>=$C$9,339<=$E$9),1,0) | MF35: =IF(AND(340>=$C$9,340<=$E$9),1,0) | MG35: =IF(AND(341>=$C$9,341<=$E$9),1,0) | MH35: =IF(AND(342>=$C$9,342<=$E$9),1,0) | MI35: =IF(AND(343>=$C$9,343<=$E$9),1,0) | MJ35: =IF(AND(344>=$C$9,344<=$E$9),1,0) | MK35: =IF(AND(345>=$C$9,345<=$E$9),1,0) | ML35: =IF(AND(346>=$C$9,346<=$E$9),1,0) | MM35: =IF(AND(347>=$C$9,347<=$E$9),1,0) | MN35: =IF(AND(348>=$C$9,348<=$E$9),1,0) | MO35: =IF(AND(349>=$C$9,349<=$E$9),1,0) | MP35: =IF(AND(350>=$C$9,350<=$E$9),1,0) | MQ35: =IF(AND(351>=$C$9,351<=$E$9),1,0) | MR35: =IF(AND(352>=$C$9,352<=$E$9),1,0) | MS35: =IF(AND(353>=$C$9,353<=$E$9),1,0) | MT35: =IF(AND(354>=$C$9,354<=$E$9),1,0) | MU35: =IF(AND(355>=$C$9,355<=$E$9),1,0) | MV35: =IF(AND(356>=$C$9,356<=$E$9),1,0) | MW35: =IF(AND(357>=$C$9,357<=$E$9),1,0) | MX35: =IF(AND(358>=$C$9,358<=$E$9),1,0) | MY35: =IF(AND(359>=$C$9,359<=$E$9),1,0) | MZ35: =IF(AND(360>=$C$9,360<=$E$9),1,0) | NA35: =IF(AND(361>=$C$9,361<=$E$9),1,0) | NB35: =IF(AND(362>=$C$9,362<=$E$9),1,0) | NC35: =IF(AND(363>=$C$9,363<=$E$9),1,0) | ND35: =IF(AND(364>=$C$9,364<=$E$9),1,0) | NE35: =IF(AND(365>=$C$9,365<=$E$9),1,0) | NF35: =IF(AND(366>=$C$9,366<=$E$9),1,0) | NG35: =IF(AND(367>=$C$9,367<=$E$9),1,0) | NH35: =IF(AND(368>=$C$9,368<=$E$9),1,0) | NI35: =IF(AND(369>=$C$9,369<=$E$9),1,0) | NJ35: =IF(AND(370>=$C$9,370<=$E$9),1,0) | NK35: =IF(AND(371>=$C$9,371<=$E$9),1,0) | NL35: =IF(AND(372>=$C$9,372<=$E$9),1,0)
B36: Flag: 1st Unit Delivery | E36: =IF(AND(1>=$C$10,1<=$E$10),1,0) | F36: =IF(AND(2>=$C$10,2<=$E$10),1,0) | G36: =IF(AND(3>=$C$10,3<=$E$10),1,0) | H36: =IF(AND(4>=$C$10,4<=$E$10),1,0) | I36: =IF(AND(5>=$C$10,5<=$E$10),1,0) | J36: =IF(AND(6>=$C$10,6<=$E$10),1,0) | K36: =IF(AND(7>=$C$10,7<=$E$10),1,0) | L36: =IF(AND(8>=$C$10,8<=$E$10),1,0) | M36: =IF(AND(9>=$C$10,9<=$E$10),1,0) | N36: =IF(AND(10>=$C$10,10<=$E$10),1,0) | O36: =IF(AND(11>=$C$10,11<=$E$10),1,0) | P36: =IF(AND(12>=$C$10,12<=$E$10),1,0) | Q36: =IF(AND(13>=$C$10,13<=$E$10),1,0) | R36: =IF(AND(14>=$C$10,14<=$E$10),1,0) | S36: =IF(AND(15>=$C$10,15<=$E$10),1,0) | T36: =IF(AND(16>=$C$10,16<=$E$10),1,0) | U36: =IF(AND(17>=$C$10,17<=$E$10),1,0) | V36: =IF(AND(18>=$C$10,18<=$E$10),1,0) | W36: =IF(AND(19>=$C$10,19<=$E$10),1,0) | X36: =IF(AND(20>=$C$10,20<=$E$10),1,0) | Y36: =IF(AND(21>=$C$10,21<=$E$10),1,0) | Z36: =IF(AND(22>=$C$10,22<=$E$10),1,0) | AA36: =IF(AND(23>=$C$10,23<=$E$10),1,0) | AB36: =IF(AND(24>=$C$10,24<=$E$10),1,0) | AC36: =IF(AND(25>=$C$10,25<=$E$10),1,0) | AD36: =IF(AND(26>=$C$10,26<=$E$10),1,0) | AE36: =IF(AND(27>=$C$10,27<=$E$10),1,0) | AF36: =IF(AND(28>=$C$10,28<=$E$10),1,0) | AG36: =IF(AND(29>=$C$10,29<=$E$10),1,0) | AH36: =IF(AND(30>=$C$10,30<=$E$10),1,0) | AI36: =IF(AND(31>=$C$10,31<=$E$10),1,0) | AJ36: =IF(AND(32>=$C$10,32<=$E$10),1,0) | AK36: =IF(AND(33>=$C$10,33<=$E$10),1,0) | AL36: =IF(AND(34>=$C$10,34<=$E$10),1,0) | AM36: =IF(AND(35>=$C$10,35<=$E$10),1,0) | AN36: =IF(AND(36>=$C$10,36<=$E$10),1,0) | AO36: =IF(AND(37>=$C$10,37<=$E$10),1,0) | AP36: =IF(AND(38>=$C$10,38<=$E$10),1,0) | AQ36: =IF(AND(39>=$C$10,39<=$E$10),1,0) | AR36: =IF(AND(40>=$C$10,40<=$E$10),1,0) | AS36: =IF(AND(41>=$C$10,41<=$E$10),1,0) | AT36: =IF(AND(42>=$C$10,42<=$E$10),1,0) | AU36: =IF(AND(43>=$C$10,43<=$E$10),1,0) | AV36: =IF(AND(44>=$C$10,44<=$E$10),1,0) | AW36: =IF(AND(45>=$C$10,45<=$E$10),1,0) | AX36: =IF(AND(46>=$C$10,46<=$E$10),1,0) | AY36: =IF(AND(47>=$C$10,47<=$E$10),1,0) | AZ36: =IF(AND(48>=$C$10,48<=$E$10),1,0) | BA36: =IF(AND(49>=$C$10,49<=$E$10),1,0) | BB36: =IF(AND(50>=$C$10,50<=$E$10),1,0) | BC36: =IF(AND(51>=$C$10,51<=$E$10),1,0) | BD36: =IF(AND(52>=$C$10,52<=$E$10),1,0) | BE36: =IF(AND(53>=$C$10,53<=$E$10),1,0) | BF36: =IF(AND(54>=$C$10,54<=$E$10),1,0) | BG36: =IF(AND(55>=$C$10,55<=$E$10),1,0) | BH36: =IF(AND(56>=$C$10,56<=$E$10),1,0) | BI36: =IF(AND(57>=$C$10,57<=$E$10),1,0) | BJ36: =IF(AND(58>=$C$10,58<=$E$10),1,0) | BK36: =IF(AND(59>=$C$10,59<=$E$10),1,0) | BL36: =IF(AND(60>=$C$10,60<=$E$10),1,0) | BM36: =IF(AND(61>=$C$10,61<=$E$10),1,0) | BN36: =IF(AND(62>=$C$10,62<=$E$10),1,0) | BO36: =IF(AND(63>=$C$10,63<=$E$10),1,0) | BP36: =IF(AND(64>=$C$10,64<=$E$10),1,0) | BQ36: =IF(AND(65>=$C$10,65<=$E$10),1,0) | BR36: =IF(AND(66>=$C$10,66<=$E$10),1,0) | BS36: =IF(AND(67>=$C$10,67<=$E$10),1,0) | BT36: =IF(AND(68>=$C$10,68<=$E$10),1,0) | BU36: =IF(AND(69>=$C$10,69<=$E$10),1,0) | BV36: =IF(AND(70>=$C$10,70<=$E$10),1,0) | BW36: =IF(AND(71>=$C$10,71<=$E$10),1,0) | BX36: =IF(AND(72>=$C$10,72<=$E$10),1,0) | BY36: =IF(AND(73>=$C$10,73<=$E$10),1,0) | BZ36: =IF(AND(74>=$C$10,74<=$E$10),1,0) | CA36: =IF(AND(75>=$C$10,75<=$E$10),1,0) | CB36: =IF(AND(76>=$C$10,76<=$E$10),1,0) | CC36: =IF(AND(77>=$C$10,77<=$E$10),1,0) | CD36: =IF(AND(78>=$C$10,78<=$E$10),1,0) | CE36: =IF(AND(79>=$C$10,79<=$E$10),1,0) | CF36: =IF(AND(80>=$C$10,80<=$E$10),1,0) | CG36: =IF(AND(81>=$C$10,81<=$E$10),1,0) | CH36: =IF(AND(82>=$C$10,82<=$E$10),1,0) | CI36: =IF(AND(83>=$C$10,83<=$E$10),1,0) | CJ36: =IF(AND(84>=$C$10,84<=$E$10),1,0) | CK36: =IF(AND(85>=$C$10,85<=$E$10),1,0) | CL36: =IF(AND(86>=$C$10,86<=$E$10),1,0) | CM36: =IF(AND(87>=$C$10,87<=$E$10),1,0) | CN36: =IF(AND(88>=$C$10,88<=$E$10),1,0) | CO36: =IF(AND(89>=$C$10,89<=$E$10),1,0) | CP36: =IF(AND(90>=$C$10,90<=$E$10),1,0) | CQ36: =IF(AND(91>=$C$10,91<=$E$10),1,0) | CR36: =IF(AND(92>=$C$10,92<=$E$10),1,0) | CS36: =IF(AND(93>=$C$10,93<=$E$10),1,0) | CT36: =IF(AND(94>=$C$10,94<=$E$10),1,0) | CU36: =IF(AND(95>=$C$10,95<=$E$10),1,0) | CV36: =IF(AND(96>=$C$10,96<=$E$10),1,0) | CW36: =IF(AND(97>=$C$10,97<=$E$10),1,0) | CX36: =IF(AND(98>=$C$10,98<=$E$10),1,0) | CY36: =IF(AND(99>=$C$10,99<=$E$10),1,0) | CZ36: =IF(AND(100>=$C$10,100<=$E$10),1,0) | DA36: =IF(AND(101>=$C$10,101<=$E$10),1,0) | DB36: =IF(AND(102>=$C$10,102<=$E$10),1,0) | DC36: =IF(AND(103>=$C$10,103<=$E$10),1,0) | DD36: =IF(AND(104>=$C$10,104<=$E$10),1,0) | DE36: =IF(AND(105>=$C$10,105<=$E$10),1,0) | DF36: =IF(AND(106>=$C$10,106<=$E$10),1,0) | DG36: =IF(AND(107>=$C$10,107<=$E$10),1,0) | DH36: =IF(AND(108>=$C$10,108<=$E$10),1,0) | DI36: =IF(AND(109>=$C$10,109<=$E$10),1,0) | DJ36: =IF(AND(110>=$C$10,110<=$E$10),1,0) | DK36: =IF(AND(111>=$C$10,111<=$E$10),1,0) | DL36: =IF(AND(112>=$C$10,112<=$E$10),1,0) | DM36: =IF(AND(113>=$C$10,113<=$E$10),1,0) | DN36: =IF(AND(114>=$C$10,114<=$E$10),1,0) | DO36: =IF(AND(115>=$C$10,115<=$E$10),1,0) | DP36: =IF(AND(116>=$C$10,116<=$E$10),1,0) | DQ36: =IF(AND(117>=$C$10,117<=$E$10),1,0) | DR36: =IF(AND(118>=$C$10,118<=$E$10),1,0) | DS36: =IF(AND(119>=$C$10,119<=$E$10),1,0) | DT36: =IF(AND(120>=$C$10,120<=$E$10),1,0) | DU36: =IF(AND(121>=$C$10,121<=$E$10),1,0) | DV36: =IF(AND(122>=$C$10,122<=$E$10),1,0) | DW36: =IF(AND(123>=$C$10,123<=$E$10),1,0) | DX36: =IF(AND(124>=$C$10,124<=$E$10),1,0) | DY36: =IF(AND(125>=$C$10,125<=$E$10),1,0) | DZ36: =IF(AND(126>=$C$10,126<=$E$10),1,0) | EA36: =IF(AND(127>=$C$10,127<=$E$10),1,0) | EB36: =IF(AND(128>=$C$10,128<=$E$10),1,0) | EC36: =IF(AND(129>=$C$10,129<=$E$10),1,0) | ED36: =IF(AND(130>=$C$10,130<=$E$10),1,0) | EE36: =IF(AND(131>=$C$10,131<=$E$10),1,0) | EF36: =IF(AND(132>=$C$10,132<=$E$10),1,0) | EG36: =IF(AND(133>=$C$10,133<=$E$10),1,0) | EH36: =IF(AND(134>=$C$10,134<=$E$10),1,0) | EI36: =IF(AND(135>=$C$10,135<=$E$10),1,0) | EJ36: =IF(AND(136>=$C$10,136<=$E$10),1,0) | EK36: =IF(AND(137>=$C$10,137<=$E$10),1,0) | EL36: =IF(AND(138>=$C$10,138<=$E$10),1,0) | EM36: =IF(AND(139>=$C$10,139<=$E$10),1,0) | EN36: =IF(AND(140>=$C$10,140<=$E$10),1,0) | EO36: =IF(AND(141>=$C$10,141<=$E$10),1,0) | EP36: =IF(AND(142>=$C$10,142<=$E$10),1,0) | EQ36: =IF(AND(143>=$C$10,143<=$E$10),1,0) | ER36: =IF(AND(144>=$C$10,144<=$E$10),1,0) | ES36: =IF(AND(145>=$C$10,145<=$E$10),1,0) | ET36: =IF(AND(146>=$C$10,146<=$E$10),1,0) | EU36: =IF(AND(147>=$C$10,147<=$E$10),1,0) | EV36: =IF(AND(148>=$C$10,148<=$E$10),1,0) | EW36: =IF(AND(149>=$C$10,149<=$E$10),1,0) | EX36: =IF(AND(150>=$C$10,150<=$E$10),1,0) | EY36: =IF(AND(151>=$C$10,151<=$E$10),1,0) | EZ36: =IF(AND(152>=$C$10,152<=$E$10),1,0) | FA36: =IF(AND(153>=$C$10,153<=$E$10),1,0) | FB36: =IF(AND(154>=$C$10,154<=$E$10),1,0) | FC36: =IF(AND(155>=$C$10,155<=$E$10),1,0) | FD36: =IF(AND(156>=$C$10,156<=$E$10),1,0) | FE36: =IF(AND(157>=$C$10,157<=$E$10),1,0) | FF36: =IF(AND(158>=$C$10,158<=$E$10),1,0) | FG36: =IF(AND(159>=$C$10,159<=$E$10),1,0) | FH36: =IF(AND(160>=$C$10,160<=$E$10),1,0) | FI36: =IF(AND(161>=$C$10,161<=$E$10),1,0) | FJ36: =IF(AND(162>=$C$10,162<=$E$10),1,0) | FK36: =IF(AND(163>=$C$10,163<=$E$10),1,0) | FL36: =IF(AND(164>=$C$10,164<=$E$10),1,0) | FM36: =IF(AND(165>=$C$10,165<=$E$10),1,0) | FN36: =IF(AND(166>=$C$10,166<=$E$10),1,0) | FO36: =IF(AND(167>=$C$10,167<=$E$10),1,0) | FP36: =IF(AND(168>=$C$10,168<=$E$10),1,0) | FQ36: =IF(AND(169>=$C$10,169<=$E$10),1,0) | FR36: =IF(AND(170>=$C$10,170<=$E$10),1,0) | FS36: =IF(AND(171>=$C$10,171<=$E$10),1,0) | FT36: =IF(AND(172>=$C$10,172<=$E$10),1,0) | FU36: =IF(AND(173>=$C$10,173<=$E$10),1,0) | FV36: =IF(AND(174>=$C$10,174<=$E$10),1,0) | FW36: =IF(AND(175>=$C$10,175<=$E$10),1,0) | FX36: =IF(AND(176>=$C$10,176<=$E$10),1,0) | FY36: =IF(AND(177>=$C$10,177<=$E$10),1,0) | FZ36: =IF(AND(178>=$C$10,178<=$E$10),1,0) | GA36: =IF(AND(179>=$C$10,179<=$E$10),1,0) | GB36: =IF(AND(180>=$C$10,180<=$E$10),1,0) | GC36: =IF(AND(181>=$C$10,181<=$E$10),1,0) | GD36: =IF(AND(182>=$C$10,182<=$E$10),1,0) | GE36: =IF(AND(183>=$C$10,183<=$E$10),1,0) | GF36: =IF(AND(184>=$C$10,184<=$E$10),1,0) | GG36: =IF(AND(185>=$C$10,185<=$E$10),1,0) | GH36: =IF(AND(186>=$C$10,186<=$E$10),1,0) | GI36: =IF(AND(187>=$C$10,187<=$E$10),1,0) | GJ36: =IF(AND(188>=$C$10,188<=$E$10),1,0) | GK36: =IF(AND(189>=$C$10,189<=$E$10),1,0) | GL36: =IF(AND(190>=$C$10,190<=$E$10),1,0) | GM36: =IF(AND(191>=$C$10,191<=$E$10),1,0) | GN36: =IF(AND(192>=$C$10,192<=$E$10),1,0) | GO36: =IF(AND(193>=$C$10,193<=$E$10),1,0) | GP36: =IF(AND(194>=$C$10,194<=$E$10),1,0) | GQ36: =IF(AND(195>=$C$10,195<=$E$10),1,0) | GR36: =IF(AND(196>=$C$10,196<=$E$10),1,0) | GS36: =IF(AND(197>=$C$10,197<=$E$10),1,0) | GT36: =IF(AND(198>=$C$10,198<=$E$10),1,0) | GU36: =IF(AND(199>=$C$10,199<=$E$10),1,0) | GV36: =IF(AND(200>=$C$10,200<=$E$10),1,0) | GW36: =IF(AND(201>=$C$10,201<=$E$10),1,0) | GX36: =IF(AND(202>=$C$10,202<=$E$10),1,0) | GY36: =IF(AND(203>=$C$10,203<=$E$10),1,0) | GZ36: =IF(AND(204>=$C$10,204<=$E$10),1,0) | HA36: =IF(AND(205>=$C$10,205<=$E$10),1,0) | HB36: =IF(AND(206>=$C$10,206<=$E$10),1,0) | HC36: =IF(AND(207>=$C$10,207<=$E$10),1,0) | HD36: =IF(AND(208>=$C$10,208<=$E$10),1,0) | HE36: =IF(AND(209>=$C$10,209<=$E$10),1,0) | HF36: =IF(AND(210>=$C$10,210<=$E$10),1,0) | HG36: =IF(AND(211>=$C$10,211<=$E$10),1,0) | HH36: =IF(AND(212>=$C$10,212<=$E$10),1,0) | HI36: =IF(AND(213>=$C$10,213<=$E$10),1,0) | HJ36: =IF(AND(214>=$C$10,214<=$E$10),1,0) | HK36: =IF(AND(215>=$C$10,215<=$E$10),1,0) | HL36: =IF(AND(216>=$C$10,216<=$E$10),1,0) | HM36: =IF(AND(217>=$C$10,217<=$E$10),1,0) | HN36: =IF(AND(218>=$C$10,218<=$E$10),1,0) | HO36: =IF(AND(219>=$C$10,219<=$E$10),1,0) | HP36: =IF(AND(220>=$C$10,220<=$E$10),1,0) | HQ36: =IF(AND(221>=$C$10,221<=$E$10),1,0) | HR36: =IF(AND(222>=$C$10,222<=$E$10),1,0) | HS36: =IF(AND(223>=$C$10,223<=$E$10),1,0) | HT36: =IF(AND(224>=$C$10,224<=$E$10),1,0) | HU36: =IF(AND(225>=$C$10,225<=$E$10),1,0) | HV36: =IF(AND(226>=$C$10,226<=$E$10),1,0) | HW36: =IF(AND(227>=$C$10,227<=$E$10),1,0) | HX36: =IF(AND(228>=$C$10,228<=$E$10),1,0) | HY36: =IF(AND(229>=$C$10,229<=$E$10),1,0) | HZ36: =IF(AND(230>=$C$10,230<=$E$10),1,0) | IA36: =IF(AND(231>=$C$10,231<=$E$10),1,0) | IB36: =IF(AND(232>=$C$10,232<=$E$10),1,0) | IC36: =IF(AND(233>=$C$10,233<=$E$10),1,0) | ID36: =IF(AND(234>=$C$10,234<=$E$10),1,0) | IE36: =IF(AND(235>=$C$10,235<=$E$10),1,0) | IF36: =IF(AND(236>=$C$10,236<=$E$10),1,0) | IG36: =IF(AND(237>=$C$10,237<=$E$10),1,0) | IH36: =IF(AND(238>=$C$10,238<=$E$10),1,0) | II36: =IF(AND(239>=$C$10,239<=$E$10),1,0) | IJ36: =IF(AND(240>=$C$10,240<=$E$10),1,0) | IK36: =IF(AND(241>=$C$10,241<=$E$10),1,0) | IL36: =IF(AND(242>=$C$10,242<=$E$10),1,0) | IM36: =IF(AND(243>=$C$10,243<=$E$10),1,0) | IN36: =IF(AND(244>=$C$10,244<=$E$10),1,0) | IO36: =IF(AND(245>=$C$10,245<=$E$10),1,0) | IP36: =IF(AND(246>=$C$10,246<=$E$10),1,0) | IQ36: =IF(AND(247>=$C$10,247<=$E$10),1,0) | IR36: =IF(AND(248>=$C$10,248<=$E$10),1,0) | IS36: =IF(AND(249>=$C$10,249<=$E$10),1,0) | IT36: =IF(AND(250>=$C$10,250<=$E$10),1,0) | IU36: =IF(AND(251>=$C$10,251<=$E$10),1,0) | IV36: =IF(AND(252>=$C$10,252<=$E$10),1,0) | IW36: =IF(AND(253>=$C$10,253<=$E$10),1,0) | IX36: =IF(AND(254>=$C$10,254<=$E$10),1,0) | IY36: =IF(AND(255>=$C$10,255<=$E$10),1,0) | IZ36: =IF(AND(256>=$C$10,256<=$E$10),1,0) | JA36: =IF(AND(257>=$C$10,257<=$E$10),1,0) | JB36: =IF(AND(258>=$C$10,258<=$E$10),1,0) | JC36: =IF(AND(259>=$C$10,259<=$E$10),1,0) | JD36: =IF(AND(260>=$C$10,260<=$E$10),1,0) | JE36: =IF(AND(261>=$C$10,261<=$E$10),1,0) | JF36: =IF(AND(262>=$C$10,262<=$E$10),1,0) | JG36: =IF(AND(263>=$C$10,263<=$E$10),1,0) | JH36: =IF(AND(264>=$C$10,264<=$E$10),1,0) | JI36: =IF(AND(265>=$C$10,265<=$E$10),1,0) | JJ36: =IF(AND(266>=$C$10,266<=$E$10),1,0) | JK36: =IF(AND(267>=$C$10,267<=$E$10),1,0) | JL36: =IF(AND(268>=$C$10,268<=$E$10),1,0) | JM36: =IF(AND(269>=$C$10,269<=$E$10),1,0) | JN36: =IF(AND(270>=$C$10,270<=$E$10),1,0) | JO36: =IF(AND(271>=$C$10,271<=$E$10),1,0) | JP36: =IF(AND(272>=$C$10,272<=$E$10),1,0) | JQ36: =IF(AND(273>=$C$10,273<=$E$10),1,0) | JR36: =IF(AND(274>=$C$10,274<=$E$10),1,0) | JS36: =IF(AND(275>=$C$10,275<=$E$10),1,0) | JT36: =IF(AND(276>=$C$10,276<=$E$10),1,0) | JU36: =IF(AND(277>=$C$10,277<=$E$10),1,0) | JV36: =IF(AND(278>=$C$10,278<=$E$10),1,0) | JW36: =IF(AND(279>=$C$10,279<=$E$10),1,0) | JX36: =IF(AND(280>=$C$10,280<=$E$10),1,0) | JY36: =IF(AND(281>=$C$10,281<=$E$10),1,0) | JZ36: =IF(AND(282>=$C$10,282<=$E$10),1,0) | KA36: =IF(AND(283>=$C$10,283<=$E$10),1,0) | KB36: =IF(AND(284>=$C$10,284<=$E$10),1,0) | KC36: =IF(AND(285>=$C$10,285<=$E$10),1,0) | KD36: =IF(AND(286>=$C$10,286<=$E$10),1,0) | KE36: =IF(AND(287>=$C$10,287<=$E$10),1,0) | KF36: =IF(AND(288>=$C$10,288<=$E$10),1,0) | KG36: =IF(AND(289>=$C$10,289<=$E$10),1,0) | KH36: =IF(AND(290>=$C$10,290<=$E$10),1,0) | KI36: =IF(AND(291>=$C$10,291<=$E$10),1,0) | KJ36: =IF(AND(292>=$C$10,292<=$E$10),1,0) | KK36: =IF(AND(293>=$C$10,293<=$E$10),1,0) | KL36: =IF(AND(294>=$C$10,294<=$E$10),1,0) | KM36: =IF(AND(295>=$C$10,295<=$E$10),1,0) | KN36: =IF(AND(296>=$C$10,296<=$E$10),1,0) | KO36: =IF(AND(297>=$C$10,297<=$E$10),1,0) | KP36: =IF(AND(298>=$C$10,298<=$E$10),1,0) | KQ36: =IF(AND(299>=$C$10,299<=$E$10),1,0) | KR36: =IF(AND(300>=$C$10,300<=$E$10),1,0) | KS36: =IF(AND(301>=$C$10,301<=$E$10),1,0) | KT36: =IF(AND(302>=$C$10,302<=$E$10),1,0) | KU36: =IF(AND(303>=$C$10,303<=$E$10),1,0) | KV36: =IF(AND(304>=$C$10,304<=$E$10),1,0) | KW36: =IF(AND(305>=$C$10,305<=$E$10),1,0) | KX36: =IF(AND(306>=$C$10,306<=$E$10),1,0) | KY36: =IF(AND(307>=$C$10,307<=$E$10),1,0) | KZ36: =IF(AND(308>=$C$10,308<=$E$10),1,0) | LA36: =IF(AND(309>=$C$10,309<=$E$10),1,0) | LB36: =IF(AND(310>=$C$10,310<=$E$10),1,0) | LC36: =IF(AND(311>=$C$10,311<=$E$10),1,0) | LD36: =IF(AND(312>=$C$10,312<=$E$10),1,0) | LE36: =IF(AND(313>=$C$10,313<=$E$10),1,0) | LF36: =IF(AND(314>=$C$10,314<=$E$10),1,0) | LG36: =IF(AND(315>=$C$10,315<=$E$10),1,0) | LH36: =IF(AND(316>=$C$10,316<=$E$10),1,0) | LI36: =IF(AND(317>=$C$10,317<=$E$10),1,0) | LJ36: =IF(AND(318>=$C$10,318<=$E$10),1,0) | LK36: =IF(AND(319>=$C$10,319<=$E$10),1,0) | LL36: =IF(AND(320>=$C$10,320<=$E$10),1,0) | LM36: =IF(AND(321>=$C$10,321<=$E$10),1,0) | LN36: =IF(AND(322>=$C$10,322<=$E$10),1,0) | LO36: =IF(AND(323>=$C$10,323<=$E$10),1,0) | LP36: =IF(AND(324>=$C$10,324<=$E$10),1,0) | LQ36: =IF(AND(325>=$C$10,325<=$E$10),1,0) | LR36: =IF(AND(326>=$C$10,326<=$E$10),1,0) | LS36: =IF(AND(327>=$C$10,327<=$E$10),1,0) | LT36: =IF(AND(328>=$C$10,328<=$E$10),1,0) | LU36: =IF(AND(329>=$C$10,329<=$E$10),1,0) | LV36: =IF(AND(330>=$C$10,330<=$E$10),1,0) | LW36: =IF(AND(331>=$C$10,331<=$E$10),1,0) | LX36: =IF(AND(332>=$C$10,332<=$E$10),1,0) | LY36: =IF(AND(333>=$C$10,333<=$E$10),1,0) | LZ36: =IF(AND(334>=$C$10,334<=$E$10),1,0) | MA36: =IF(AND(335>=$C$10,335<=$E$10),1,0) | MB36: =IF(AND(336>=$C$10,336<=$E$10),1,0) | MC36: =IF(AND(337>=$C$10,337<=$E$10),1,0) | MD36: =IF(AND(338>=$C$10,338<=$E$10),1,0) | ME36: =IF(AND(339>=$C$10,339<=$E$10),1,0) | MF36: =IF(AND(340>=$C$10,340<=$E$10),1,0) | MG36: =IF(AND(341>=$C$10,341<=$E$10),1,0) | MH36: =IF(AND(342>=$C$10,342<=$E$10),1,0) | MI36: =IF(AND(343>=$C$10,343<=$E$10),1,0) | MJ36: =IF(AND(344>=$C$10,344<=$E$10),1,0) | MK36: =IF(AND(345>=$C$10,345<=$E$10),1,0) | ML36: =IF(AND(346>=$C$10,346<=$E$10),1,0) | MM36: =IF(AND(347>=$C$10,347<=$E$10),1,0) | MN36: =IF(AND(348>=$C$10,348<=$E$10),1,0) | MO36: =IF(AND(349>=$C$10,349<=$E$10),1,0) | MP36: =IF(AND(350>=$C$10,350<=$E$10),1,0) | MQ36: =IF(AND(351>=$C$10,351<=$E$10),1,0) | MR36: =IF(AND(352>=$C$10,352<=$E$10),1,0) | MS36: =IF(AND(353>=$C$10,353<=$E$10),1,0) | MT36: =IF(AND(354>=$C$10,354<=$E$10),1,0) | MU36: =IF(AND(355>=$C$10,355<=$E$10),1,0) | MV36: =IF(AND(356>=$C$10,356<=$E$10),1,0) | MW36: =IF(AND(357>=$C$10,357<=$E$10),1,0) | MX36: =IF(AND(358>=$C$10,358<=$E$10),1,0) | MY36: =IF(AND(359>=$C$10,359<=$E$10),1,0) | MZ36: =IF(AND(360>=$C$10,360<=$E$10),1,0) | NA36: =IF(AND(361>=$C$10,361<=$E$10),1,0) | NB36: =IF(AND(362>=$C$10,362<=$E$10),1,0) | NC36: =IF(AND(363>=$C$10,363<=$E$10),1,0) | ND36: =IF(AND(364>=$C$10,364<=$E$10),1,0) | NE36: =IF(AND(365>=$C$10,365<=$E$10),1,0) | NF36: =IF(AND(366>=$C$10,366<=$E$10),1,0) | NG36: =IF(AND(367>=$C$10,367<=$E$10),1,0) | NH36: =IF(AND(368>=$C$10,368<=$E$10),1,0) | NI36: =IF(AND(369>=$C$10,369<=$E$10),1,0) | NJ36: =IF(AND(370>=$C$10,370<=$E$10),1,0) | NK36: =IF(AND(371>=$C$10,371<=$E$10),1,0) | NL36: =IF(AND(372>=$C$10,372<=$E$10),1,0)
B37: Flag: Lease-Up | E37: =IF(AND(1>=$C$11,1<=$E$11),1,0) | F37: =IF(AND(2>=$C$11,2<=$E$11),1,0) | G37: =IF(AND(3>=$C$11,3<=$E$11),1,0) | H37: =IF(AND(4>=$C$11,4<=$E$11),1,0) | I37: =IF(AND(5>=$C$11,5<=$E$11),1,0) | J37: =IF(AND(6>=$C$11,6<=$E$11),1,0) | K37: =IF(AND(7>=$C$11,7<=$E$11),1,0) | L37: =IF(AND(8>=$C$11,8<=$E$11),1,0) | M37: =IF(AND(9>=$C$11,9<=$E$11),1,0) | N37: =IF(AND(10>=$C$11,10<=$E$11),1,0) | O37: =IF(AND(11>=$C$11,11<=$E$11),1,0) | P37: =IF(AND(12>=$C$11,12<=$E$11),1,0) | Q37: =IF(AND(13>=$C$11,13<=$E$11),1,0) | R37: =IF(AND(14>=$C$11,14<=$E$11),1,0) | S37: =IF(AND(15>=$C$11,15<=$E$11),1,0) | T37: =IF(AND(16>=$C$11,16<=$E$11),1,0) | U37: =IF(AND(17>=$C$11,17<=$E$11),1,0) | V37: =IF(AND(18>=$C$11,18<=$E$11),1,0) | W37: =IF(AND(19>=$C$11,19<=$E$11),1,0) | X37: =IF(AND(20>=$C$11,20<=$E$11),1,0) | Y37: =IF(AND(21>=$C$11,21<=$E$11),1,0) | Z37: =IF(AND(22>=$C$11,22<=$E$11),1,0) | AA37: =IF(AND(23>=$C$11,23<=$E$11),1,0) | AB37: =IF(AND(24>=$C$11,24<=$E$11),1,0) | AC37: =IF(AND(25>=$C$11,25<=$E$11),1,0) | AD37: =IF(AND(26>=$C$11,26<=$E$11),1,0) | AE37: =IF(AND(27>=$C$11,27<=$E$11),1,0) | AF37: =IF(AND(28>=$C$11,28<=$E$11),1,0) | AG37: =IF(AND(29>=$C$11,29<=$E$11),1,0) | AH37: =IF(AND(30>=$C$11,30<=$E$11),1,0) | AI37: =IF(AND(31>=$C$11,31<=$E$11),1,0) | AJ37: =IF(AND(32>=$C$11,32<=$E$11),1,0) | AK37: =IF(AND(33>=$C$11,33<=$E$11),1,0) | AL37: =IF(AND(34>=$C$11,34<=$E$11),1,0) | AM37: =IF(AND(35>=$C$11,35<=$E$11),1,0) | AN37: =IF(AND(36>=$C$11,36<=$E$11),1,0) | AO37: =IF(AND(37>=$C$11,37<=$E$11),1,0) | AP37: =IF(AND(38>=$C$11,38<=$E$11),1,0) | AQ37: =IF(AND(39>=$C$11,39<=$E$11),1,0) | AR37: =IF(AND(40>=$C$11,40<=$E$11),1,0) | AS37: =IF(AND(41>=$C$11,41<=$E$11),1,0) | AT37: =IF(AND(42>=$C$11,42<=$E$11),1,0) | AU37: =IF(AND(43>=$C$11,43<=$E$11),1,0) | AV37: =IF(AND(44>=$C$11,44<=$E$11),1,0) | AW37: =IF(AND(45>=$C$11,45<=$E$11),1,0) | AX37: =IF(AND(46>=$C$11,46<=$E$11),1,0) | AY37: =IF(AND(47>=$C$11,47<=$E$11),1,0) | AZ37: =IF(AND(48>=$C$11,48<=$E$11),1,0) | BA37: =IF(AND(49>=$C$11,49<=$E$11),1,0) | BB37: =IF(AND(50>=$C$11,50<=$E$11),1,0) | BC37: =IF(AND(51>=$C$11,51<=$E$11),1,0) | BD37: =IF(AND(52>=$C$11,52<=$E$11),1,0) | BE37: =IF(AND(53>=$C$11,53<=$E$11),1,0) | BF37: =IF(AND(54>=$C$11,54<=$E$11),1,0) | BG37: =IF(AND(55>=$C$11,55<=$E$11),1,0) | BH37: =IF(AND(56>=$C$11,56<=$E$11),1,0) | BI37: =IF(AND(57>=$C$11,57<=$E$11),1,0) | BJ37: =IF(AND(58>=$C$11,58<=$E$11),1,0) | BK37: =IF(AND(59>=$C$11,59<=$E$11),1,0) | BL37: =IF(AND(60>=$C$11,60<=$E$11),1,0) | BM37: =IF(AND(61>=$C$11,61<=$E$11),1,0) | BN37: =IF(AND(62>=$C$11,62<=$E$11),1,0) | BO37: =IF(AND(63>=$C$11,63<=$E$11),1,0) | BP37: =IF(AND(64>=$C$11,64<=$E$11),1,0) | BQ37: =IF(AND(65>=$C$11,65<=$E$11),1,0) | BR37: =IF(AND(66>=$C$11,66<=$E$11),1,0) | BS37: =IF(AND(67>=$C$11,67<=$E$11),1,0) | BT37: =IF(AND(68>=$C$11,68<=$E$11),1,0) | BU37: =IF(AND(69>=$C$11,69<=$E$11),1,0) | BV37: =IF(AND(70>=$C$11,70<=$E$11),1,0) | BW37: =IF(AND(71>=$C$11,71<=$E$11),1,0) | BX37: =IF(AND(72>=$C$11,72<=$E$11),1,0) | BY37: =IF(AND(73>=$C$11,73<=$E$11),1,0) | BZ37: =IF(AND(74>=$C$11,74<=$E$11),1,0) | CA37: =IF(AND(75>=$C$11,75<=$E$11),1,0) | CB37: =IF(AND(76>=$C$11,76<=$E$11),1,0) | CC37: =IF(AND(77>=$C$11,77<=$E$11),1,0) | CD37: =IF(AND(78>=$C$11,78<=$E$11),1,0) | CE37: =IF(AND(79>=$C$11,79<=$E$11),1,0) | CF37: =IF(AND(80>=$C$11,80<=$E$11),1,0) | CG37: =IF(AND(81>=$C$11,81<=$E$11),1,0) | CH37: =IF(AND(82>=$C$11,82<=$E$11),1,0) | CI37: =IF(AND(83>=$C$11,83<=$E$11),1,0) | CJ37: =IF(AND(84>=$C$11,84<=$E$11),1,0) | CK37: =IF(AND(85>=$C$11,85<=$E$11),1,0) | CL37: =IF(AND(86>=$C$11,86<=$E$11),1,0) | CM37: =IF(AND(87>=$C$11,87<=$E$11),1,0) | CN37: =IF(AND(88>=$C$11,88<=$E$11),1,0) | CO37: =IF(AND(89>=$C$11,89<=$E$11),1,0) | CP37: =IF(AND(90>=$C$11,90<=$E$11),1,0) | CQ37: =IF(AND(91>=$C$11,91<=$E$11),1,0) | CR37: =IF(AND(92>=$C$11,92<=$E$11),1,0) | CS37: =IF(AND(93>=$C$11,93<=$E$11),1,0) | CT37: =IF(AND(94>=$C$11,94<=$E$11),1,0) | CU37: =IF(AND(95>=$C$11,95<=$E$11),1,0) | CV37: =IF(AND(96>=$C$11,96<=$E$11),1,0) | CW37: =IF(AND(97>=$C$11,97<=$E$11),1,0) | CX37: =IF(AND(98>=$C$11,98<=$E$11),1,0) | CY37: =IF(AND(99>=$C$11,99<=$E$11),1,0) | CZ37: =IF(AND(100>=$C$11,100<=$E$11),1,0) | DA37: =IF(AND(101>=$C$11,101<=$E$11),1,0) | DB37: =IF(AND(102>=$C$11,102<=$E$11),1,0) | DC37: =IF(AND(103>=$C$11,103<=$E$11),1,0) | DD37: =IF(AND(104>=$C$11,104<=$E$11),1,0) | DE37: =IF(AND(105>=$C$11,105<=$E$11),1,0) | DF37: =IF(AND(106>=$C$11,106<=$E$11),1,0) | DG37: =IF(AND(107>=$C$11,107<=$E$11),1,0) | DH37: =IF(AND(108>=$C$11,108<=$E$11),1,0) | DI37: =IF(AND(109>=$C$11,109<=$E$11),1,0) | DJ37: =IF(AND(110>=$C$11,110<=$E$11),1,0) | DK37: =IF(AND(111>=$C$11,111<=$E$11),1,0) | DL37: =IF(AND(112>=$C$11,112<=$E$11),1,0) | DM37: =IF(AND(113>=$C$11,113<=$E$11),1,0) | DN37: =IF(AND(114>=$C$11,114<=$E$11),1,0) | DO37: =IF(AND(115>=$C$11,115<=$E$11),1,0) | DP37: =IF(AND(116>=$C$11,116<=$E$11),1,0) | DQ37: =IF(AND(117>=$C$11,117<=$E$11),1,0) | DR37: =IF(AND(118>=$C$11,118<=$E$11),1,0) | DS37: =IF(AND(119>=$C$11,119<=$E$11),1,0) | DT37: =IF(AND(120>=$C$11,120<=$E$11),1,0) | DU37: =IF(AND(121>=$C$11,121<=$E$11),1,0) | DV37: =IF(AND(122>=$C$11,122<=$E$11),1,0) | DW37: =IF(AND(123>=$C$11,123<=$E$11),1,0) | DX37: =IF(AND(124>=$C$11,124<=$E$11),1,0) | DY37: =IF(AND(125>=$C$11,125<=$E$11),1,0) | DZ37: =IF(AND(126>=$C$11,126<=$E$11),1,0) | EA37: =IF(AND(127>=$C$11,127<=$E$11),1,0) | EB37: =IF(AND(128>=$C$11,128<=$E$11),1,0) | EC37: =IF(AND(129>=$C$11,129<=$E$11),1,0) | ED37: =IF(AND(130>=$C$11,130<=$E$11),1,0) | EE37: =IF(AND(131>=$C$11,131<=$E$11),1,0) | EF37: =IF(AND(132>=$C$11,132<=$E$11),1,0) | EG37: =IF(AND(133>=$C$11,133<=$E$11),1,0) | EH37: =IF(AND(134>=$C$11,134<=$E$11),1,0) | EI37: =IF(AND(135>=$C$11,135<=$E$11),1,0) | EJ37: =IF(AND(136>=$C$11,136<=$E$11),1,0) | EK37: =IF(AND(137>=$C$11,137<=$E$11),1,0) | EL37: =IF(AND(138>=$C$11,138<=$E$11),1,0) | EM37: =IF(AND(139>=$C$11,139<=$E$11),1,0) | EN37: =IF(AND(140>=$C$11,140<=$E$11),1,0) | EO37: =IF(AND(141>=$C$11,141<=$E$11),1,0) | EP37: =IF(AND(142>=$C$11,142<=$E$11),1,0) | EQ37: =IF(AND(143>=$C$11,143<=$E$11),1,0) | ER37: =IF(AND(144>=$C$11,144<=$E$11),1,0) | ES37: =IF(AND(145>=$C$11,145<=$E$11),1,0) | ET37: =IF(AND(146>=$C$11,146<=$E$11),1,0) | EU37: =IF(AND(147>=$C$11,147<=$E$11),1,0) | EV37: =IF(AND(148>=$C$11,148<=$E$11),1,0) | EW37: =IF(AND(149>=$C$11,149<=$E$11),1,0) | EX37: =IF(AND(150>=$C$11,150<=$E$11),1,0) | EY37: =IF(AND(151>=$C$11,151<=$E$11),1,0) | EZ37: =IF(AND(152>=$C$11,152<=$E$11),1,0) | FA37: =IF(AND(153>=$C$11,153<=$E$11),1,0) | FB37: =IF(AND(154>=$C$11,154<=$E$11),1,0) | FC37: =IF(AND(155>=$C$11,155<=$E$11),1,0) | FD37: =IF(AND(156>=$C$11,156<=$E$11),1,0) | FE37: =IF(AND(157>=$C$11,157<=$E$11),1,0) | FF37: =IF(AND(158>=$C$11,158<=$E$11),1,0) | FG37: =IF(AND(159>=$C$11,159<=$E$11),1,0) | FH37: =IF(AND(160>=$C$11,160<=$E$11),1,0) | FI37: =IF(AND(161>=$C$11,161<=$E$11),1,0) | FJ37: =IF(AND(162>=$C$11,162<=$E$11),1,0) | FK37: =IF(AND(163>=$C$11,163<=$E$11),1,0) | FL37: =IF(AND(164>=$C$11,164<=$E$11),1,0) | FM37: =IF(AND(165>=$C$11,165<=$E$11),1,0) | FN37: =IF(AND(166>=$C$11,166<=$E$11),1,0) | FO37: =IF(AND(167>=$C$11,167<=$E$11),1,0) | FP37: =IF(AND(168>=$C$11,168<=$E$11),1,0) | FQ37: =IF(AND(169>=$C$11,169<=$E$11),1,0) | FR37: =IF(AND(170>=$C$11,170<=$E$11),1,0) | FS37: =IF(AND(171>=$C$11,171<=$E$11),1,0) | FT37: =IF(AND(172>=$C$11,172<=$E$11),1,0) | FU37: =IF(AND(173>=$C$11,173<=$E$11),1,0) | FV37: =IF(AND(174>=$C$11,174<=$E$11),1,0) | FW37: =IF(AND(175>=$C$11,175<=$E$11),1,0) | FX37: =IF(AND(176>=$C$11,176<=$E$11),1,0) | FY37: =IF(AND(177>=$C$11,177<=$E$11),1,0) | FZ37: =IF(AND(178>=$C$11,178<=$E$11),1,0) | GA37: =IF(AND(179>=$C$11,179<=$E$11),1,0) | GB37: =IF(AND(180>=$C$11,180<=$E$11),1,0) | GC37: =IF(AND(181>=$C$11,181<=$E$11),1,0) | GD37: =IF(AND(182>=$C$11,182<=$E$11),1,0) | GE37: =IF(AND(183>=$C$11,183<=$E$11),1,0) | GF37: =IF(AND(184>=$C$11,184<=$E$11),1,0) | GG37: =IF(AND(185>=$C$11,185<=$E$11),1,0) | GH37: =IF(AND(186>=$C$11,186<=$E$11),1,0) | GI37: =IF(AND(187>=$C$11,187<=$E$11),1,0) | GJ37: =IF(AND(188>=$C$11,188<=$E$11),1,0) | GK37: =IF(AND(189>=$C$11,189<=$E$11),1,0) | GL37: =IF(AND(190>=$C$11,190<=$E$11),1,0) | GM37: =IF(AND(191>=$C$11,191<=$E$11),1,0) | GN37: =IF(AND(192>=$C$11,192<=$E$11),1,0) | GO37: =IF(AND(193>=$C$11,193<=$E$11),1,0) | GP37: =IF(AND(194>=$C$11,194<=$E$11),1,0) | GQ37: =IF(AND(195>=$C$11,195<=$E$11),1,0) | GR37: =IF(AND(196>=$C$11,196<=$E$11),1,0) | GS37: =IF(AND(197>=$C$11,197<=$E$11),1,0) | GT37: =IF(AND(198>=$C$11,198<=$E$11),1,0) | GU37: =IF(AND(199>=$C$11,199<=$E$11),1,0) | GV37: =IF(AND(200>=$C$11,200<=$E$11),1,0) | GW37: =IF(AND(201>=$C$11,201<=$E$11),1,0) | GX37: =IF(AND(202>=$C$11,202<=$E$11),1,0) | GY37: =IF(AND(203>=$C$11,203<=$E$11),1,0) | GZ37: =IF(AND(204>=$C$11,204<=$E$11),1,0) | HA37: =IF(AND(205>=$C$11,205<=$E$11),1,0) | HB37: =IF(AND(206>=$C$11,206<=$E$11),1,0) | HC37: =IF(AND(207>=$C$11,207<=$E$11),1,0) | HD37: =IF(AND(208>=$C$11,208<=$E$11),1,0) | HE37: =IF(AND(209>=$C$11,209<=$E$11),1,0) | HF37: =IF(AND(210>=$C$11,210<=$E$11),1,0) | HG37: =IF(AND(211>=$C$11,211<=$E$11),1,0) | HH37: =IF(AND(212>=$C$11,212<=$E$11),1,0) | HI37: =IF(AND(213>=$C$11,213<=$E$11),1,0) | HJ37: =IF(AND(214>=$C$11,214<=$E$11),1,0) | HK37: =IF(AND(215>=$C$11,215<=$E$11),1,0) | HL37: =IF(AND(216>=$C$11,216<=$E$11),1,0) | HM37: =IF(AND(217>=$C$11,217<=$E$11),1,0) | HN37: =IF(AND(218>=$C$11,218<=$E$11),1,0) | HO37: =IF(AND(219>=$C$11,219<=$E$11),1,0) | HP37: =IF(AND(220>=$C$11,220<=$E$11),1,0) | HQ37: =IF(AND(221>=$C$11,221<=$E$11),1,0) | HR37: =IF(AND(222>=$C$11,222<=$E$11),1,0) | HS37: =IF(AND(223>=$C$11,223<=$E$11),1,0) | HT37: =IF(AND(224>=$C$11,224<=$E$11),1,0) | HU37: =IF(AND(225>=$C$11,225<=$E$11),1,0) | HV37: =IF(AND(226>=$C$11,226<=$E$11),1,0) | HW37: =IF(AND(227>=$C$11,227<=$E$11),1,0) | HX37: =IF(AND(228>=$C$11,228<=$E$11),1,0) | HY37: =IF(AND(229>=$C$11,229<=$E$11),1,0) | HZ37: =IF(AND(230>=$C$11,230<=$E$11),1,0) | IA37: =IF(AND(231>=$C$11,231<=$E$11),1,0) | IB37: =IF(AND(232>=$C$11,232<=$E$11),1,0) | IC37: =IF(AND(233>=$C$11,233<=$E$11),1,0) | ID37: =IF(AND(234>=$C$11,234<=$E$11),1,0) | IE37: =IF(AND(235>=$C$11,235<=$E$11),1,0) | IF37: =IF(AND(236>=$C$11,236<=$E$11),1,0) | IG37: =IF(AND(237>=$C$11,237<=$E$11),1,0) | IH37: =IF(AND(238>=$C$11,238<=$E$11),1,0) | II37: =IF(AND(239>=$C$11,239<=$E$11),1,0) | IJ37: =IF(AND(240>=$C$11,240<=$E$11),1,0) | IK37: =IF(AND(241>=$C$11,241<=$E$11),1,0) | IL37: =IF(AND(242>=$C$11,242<=$E$11),1,0) | IM37: =IF(AND(243>=$C$11,243<=$E$11),1,0) | IN37: =IF(AND(244>=$C$11,244<=$E$11),1,0) | IO37: =IF(AND(245>=$C$11,245<=$E$11),1,0) | IP37: =IF(AND(246>=$C$11,246<=$E$11),1,0) | IQ37: =IF(AND(247>=$C$11,247<=$E$11),1,0) | IR37: =IF(AND(248>=$C$11,248<=$E$11),1,0) | IS37: =IF(AND(249>=$C$11,249<=$E$11),1,0) | IT37: =IF(AND(250>=$C$11,250<=$E$11),1,0) | IU37: =IF(AND(251>=$C$11,251<=$E$11),1,0) | IV37: =IF(AND(252>=$C$11,252<=$E$11),1,0) | IW37: =IF(AND(253>=$C$11,253<=$E$11),1,0) | IX37: =IF(AND(254>=$C$11,254<=$E$11),1,0) | IY37: =IF(AND(255>=$C$11,255<=$E$11),1,0) | IZ37: =IF(AND(256>=$C$11,256<=$E$11),1,0) | JA37: =IF(AND(257>=$C$11,257<=$E$11),1,0) | JB37: =IF(AND(258>=$C$11,258<=$E$11),1,0) | JC37: =IF(AND(259>=$C$11,259<=$E$11),1,0) | JD37: =IF(AND(260>=$C$11,260<=$E$11),1,0) | JE37: =IF(AND(261>=$C$11,261<=$E$11),1,0) | JF37: =IF(AND(262>=$C$11,262<=$E$11),1,0) | JG37: =IF(AND(263>=$C$11,263<=$E$11),1,0) | JH37: =IF(AND(264>=$C$11,264<=$E$11),1,0) | JI37: =IF(AND(265>=$C$11,265<=$E$11),1,0) | JJ37: =IF(AND(266>=$C$11,266<=$E$11),1,0) | JK37: =IF(AND(267>=$C$11,267<=$E$11),1,0) | JL37: =IF(AND(268>=$C$11,268<=$E$11),1,0) | JM37: =IF(AND(269>=$C$11,269<=$E$11),1,0) | JN37: =IF(AND(270>=$C$11,270<=$E$11),1,0) | JO37: =IF(AND(271>=$C$11,271<=$E$11),1,0) | JP37: =IF(AND(272>=$C$11,272<=$E$11),1,0) | JQ37: =IF(AND(273>=$C$11,273<=$E$11),1,0) | JR37: =IF(AND(274>=$C$11,274<=$E$11),1,0) | JS37: =IF(AND(275>=$C$11,275<=$E$11),1,0) | JT37: =IF(AND(276>=$C$11,276<=$E$11),1,0) | JU37: =IF(AND(277>=$C$11,277<=$E$11),1,0) | JV37: =IF(AND(278>=$C$11,278<=$E$11),1,0) | JW37: =IF(AND(279>=$C$11,279<=$E$11),1,0) | JX37: =IF(AND(280>=$C$11,280<=$E$11),1,0) | JY37: =IF(AND(281>=$C$11,281<=$E$11),1,0) | JZ37: =IF(AND(282>=$C$11,282<=$E$11),1,0) | KA37: =IF(AND(283>=$C$11,283<=$E$11),1,0) | KB37: =IF(AND(284>=$C$11,284<=$E$11),1,0) | KC37: =IF(AND(285>=$C$11,285<=$E$11),1,0) | KD37: =IF(AND(286>=$C$11,286<=$E$11),1,0) | KE37: =IF(AND(287>=$C$11,287<=$E$11),1,0) | KF37: =IF(AND(288>=$C$11,288<=$E$11),1,0) | KG37: =IF(AND(289>=$C$11,289<=$E$11),1,0) | KH37: =IF(AND(290>=$C$11,290<=$E$11),1,0) | KI37: =IF(AND(291>=$C$11,291<=$E$11),1,0) | KJ37: =IF(AND(292>=$C$11,292<=$E$11),1,0) | KK37: =IF(AND(293>=$C$11,293<=$E$11),1,0) | KL37: =IF(AND(294>=$C$11,294<=$E$11),1,0) | KM37: =IF(AND(295>=$C$11,295<=$E$11),1,0) | KN37: =IF(AND(296>=$C$11,296<=$E$11),1,0) | KO37: =IF(AND(297>=$C$11,297<=$E$11),1,0) | KP37: =IF(AND(298>=$C$11,298<=$E$11),1,0) | KQ37: =IF(AND(299>=$C$11,299<=$E$11),1,0) | KR37: =IF(AND(300>=$C$11,300<=$E$11),1,0) | KS37: =IF(AND(301>=$C$11,301<=$E$11),1,0) | KT37: =IF(AND(302>=$C$11,302<=$E$11),1,0) | KU37: =IF(AND(303>=$C$11,303<=$E$11),1,0) | KV37: =IF(AND(304>=$C$11,304<=$E$11),1,0) | KW37: =IF(AND(305>=$C$11,305<=$E$11),1,0) | KX37: =IF(AND(306>=$C$11,306<=$E$11),1,0) | KY37: =IF(AND(307>=$C$11,307<=$E$11),1,0) | KZ37: =IF(AND(308>=$C$11,308<=$E$11),1,0) | LA37: =IF(AND(309>=$C$11,309<=$E$11),1,0) | LB37: =IF(AND(310>=$C$11,310<=$E$11),1,0) | LC37: =IF(AND(311>=$C$11,311<=$E$11),1,0) | LD37: =IF(AND(312>=$C$11,312<=$E$11),1,0) | LE37: =IF(AND(313>=$C$11,313<=$E$11),1,0) | LF37: =IF(AND(314>=$C$11,314<=$E$11),1,0) | LG37: =IF(AND(315>=$C$11,315<=$E$11),1,0) | LH37: =IF(AND(316>=$C$11,316<=$E$11),1,0) | LI37: =IF(AND(317>=$C$11,317<=$E$11),1,0) | LJ37: =IF(AND(318>=$C$11,318<=$E$11),1,0) | LK37: =IF(AND(319>=$C$11,319<=$E$11),1,0) | LL37: =IF(AND(320>=$C$11,320<=$E$11),1,0) | LM37: =IF(AND(321>=$C$11,321<=$E$11),1,0) | LN37: =IF(AND(322>=$C$11,322<=$E$11),1,0) | LO37: =IF(AND(323>=$C$11,323<=$E$11),1,0) | LP37: =IF(AND(324>=$C$11,324<=$E$11),1,0) | LQ37: =IF(AND(325>=$C$11,325<=$E$11),1,0) | LR37: =IF(AND(326>=$C$11,326<=$E$11),1,0) | LS37: =IF(AND(327>=$C$11,327<=$E$11),1,0) | LT37: =IF(AND(328>=$C$11,328<=$E$11),1,0) | LU37: =IF(AND(329>=$C$11,329<=$E$11),1,0) | LV37: =IF(AND(330>=$C$11,330<=$E$11),1,0) | LW37: =IF(AND(331>=$C$11,331<=$E$11),1,0) | LX37: =IF(AND(332>=$C$11,332<=$E$11),1,0) | LY37: =IF(AND(333>=$C$11,333<=$E$11),1,0) | LZ37: =IF(AND(334>=$C$11,334<=$E$11),1,0) | MA37: =IF(AND(335>=$C$11,335<=$E$11),1,0) | MB37: =IF(AND(336>=$C$11,336<=$E$11),1,0) | MC37: =IF(AND(337>=$C$11,337<=$E$11),1,0) | MD37: =IF(AND(338>=$C$11,338<=$E$11),1,0) | ME37: =IF(AND(339>=$C$11,339<=$E$11),1,0) | MF37: =IF(AND(340>=$C$11,340<=$E$11),1,0) | MG37: =IF(AND(341>=$C$11,341<=$E$11),1,0) | MH37: =IF(AND(342>=$C$11,342<=$E$11),1,0) | MI37: =IF(AND(343>=$C$11,343<=$E$11),1,0) | MJ37: =IF(AND(344>=$C$11,344<=$E$11),1,0) | MK37: =IF(AND(345>=$C$11,345<=$E$11),1,0) | ML37: =IF(AND(346>=$C$11,346<=$E$11),1,0) | MM37: =IF(AND(347>=$C$11,347<=$E$11),1,0) | MN37: =IF(AND(348>=$C$11,348<=$E$11),1,0) | MO37: =IF(AND(349>=$C$11,349<=$E$11),1,0) | MP37: =IF(AND(350>=$C$11,350<=$E$11),1,0) | MQ37: =IF(AND(351>=$C$11,351<=$E$11),1,0) | MR37: =IF(AND(352>=$C$11,352<=$E$11),1,0) | MS37: =IF(AND(353>=$C$11,353<=$E$11),1,0) | MT37: =IF(AND(354>=$C$11,354<=$E$11),1,0) | MU37: =IF(AND(355>=$C$11,355<=$E$11),1,0) | MV37: =IF(AND(356>=$C$11,356<=$E$11),1,0) | MW37: =IF(AND(357>=$C$11,357<=$E$11),1,0) | MX37: =IF(AND(358>=$C$11,358<=$E$11),1,0) | MY37: =IF(AND(359>=$C$11,359<=$E$11),1,0) | MZ37: =IF(AND(360>=$C$11,360<=$E$11),1,0) | NA37: =IF(AND(361>=$C$11,361<=$E$11),1,0) | NB37: =IF(AND(362>=$C$11,362<=$E$11),1,0) | NC37: =IF(AND(363>=$C$11,363<=$E$11),1,0) | ND37: =IF(AND(364>=$C$11,364<=$E$11),1,0) | NE37: =IF(AND(365>=$C$11,365<=$E$11),1,0) | NF37: =IF(AND(366>=$C$11,366<=$E$11),1,0) | NG37: =IF(AND(367>=$C$11,367<=$E$11),1,0) | NH37: =IF(AND(368>=$C$11,368<=$E$11),1,0) | NI37: =IF(AND(369>=$C$11,369<=$E$11),1,0) | NJ37: =IF(AND(370>=$C$11,370<=$E$11),1,0) | NK37: =IF(AND(371>=$C$11,371<=$E$11),1,0) | NL37: =IF(AND(372>=$C$11,372<=$E$11),1,0)
