Workbook
Name InvestmentType: 'Inputs'!$B$5
Name PropertyName: 'Inputs'!$B$6
Name City: 'Inputs'!$B$7
Name State: 'Inputs'!$B$8
Name Market: 'Inputs'!$B$9
Name ProductType: 'Inputs'!$B$10
Name Location: 'Inputs'!$B$11
Name InceptionDate: 'Inputs'!$B$12
Name HoldPeriodMonths: 'Inputs'!$B$15
Name EntryCapRate: 'Inputs'!$B$16
Name CapAdjLocation: 'Inputs'!$B$17
Name CapAdjSize: 'Inputs'!$B$18
Name CapAdjAging: 'Inputs'!$B$19
Name ExitCapResidential: 'Inputs'!$B$20
Name ExitCapRetail: 'Inputs'!$B$21
Name GrowthRent: 'Inputs'!$B$22
Name GrowthLowIncRent: 'Inputs'!$B$23
Name GrowthExpense: 'Inputs'!$B$24
Name GrowthUtility: 'Inputs'!$B$25
Name GrowthTax: 'Inputs'!$B$26
Name GrowthOther: 'Inputs'!$B$27
Name GrowthStartDate: 'Inputs'!$B$28
Name LeaseUpIncomeOffset: 'Inputs'!$B$31
Name UnitsDeliveredPerMo: 'Inputs'!$B$32
Name UnitsLeasedPerMo: 'Inputs'!$B$33
Name LeaseUpRampPct: 'Inputs'!$B$34
Name LeaseUpElevationPct: 'Inputs'!$B$35
Name StabilizedOccupancy: 'Inputs'!$B$36
Name LandCost: 'Inputs'!$B$39
Name GrossAcres: 'Inputs'!$B$40
Name NetAcres: 'Inputs'!$B$41
Name FARRatio: 'Inputs'!$B$42
Name EfficiencyRatio: 'Inputs'!$B$43
Name ExistingStructureCost: 'Inputs'!$B$44
Name TaxLevyPct: 'Inputs'!$B$47
Name TaxAssessmentPct: 'Inputs'!$B$48
Name TaxValueAdjFactor: 'Inputs'!$B$49
Name TaxMethodValue: 'Inputs'!$B$50
Name TaxYear1Override: 'Inputs'!$B$51
Name ReassessOnSale: 'Inputs'!$B$52
Name DispoTaxRatePct: 'Inputs'!$B$53
Name FundingOrderPari: 'Inputs'!$B$56
Name TargetLTC: 'Inputs'!$B$57
Name OpReserveCoverage: 'Inputs'!$B$58
Name OpReserveMinMonths: 'Inputs'!$B$59
Name ConLoanTermMonths: 'Inputs'!$B$62
Name ConRate: 'Inputs'!$B$63
Name ConActual360: 'Inputs'!$B$64
Name ConPointsPct: 'Inputs'!$B$65
Name ConOtherCosts: 'Inputs'!$B$66
Name ConMinDebtYield: 'Inputs'!$B$67
Name ConMinDSCR: 'Inputs'!$B$68
Name LenderReqReserveOverride: 'Inputs'!$B$69
Name PermMaxLTV: 'Inputs'!$B$72
Name PermRate: 'Inputs'!$B$73
Name PermTermMonths: 'Inputs'!$B$74
Name PermIOMonths: 'Inputs'!$B$75
Name PermAmortMonths: 'Inputs'!$B$76
Name PermActual360: 'Inputs'!$B$77
Name PermPointsPct: 'Inputs'!$B$78

Sheet Dashboard

Sheet Inputs
A1: Institutional Multifamily Development Model — Inputs
A2: Blue = hard-keyed input. Every value below is a workbook named range.
A4: Property Details
A5: Investment Type | B5: Ground-Up Development | C5: Investment type
A6: Property Name | B6: Meridian Apartments | C6: Deal name
A7: City | B7: Austin
A8: State | B8: TX
A9: Market | B9: Austin-Round Rock | C9: MSA
A10: Product Type | B10: Garden / Mid-Rise
A11: Location | B11: Suburban Infill
A12: Inception Date | B12: 46023 | C12: Model period 1 = this month
A14: Investment Details
A15: Hold Period Months | B15: 84 | C15: Disposition month (1-360 toggle)
A16: Entry Cap Rate | B16: 0.0475 | C16: Market / entry cap rate
A17: Cap Adj Location | B17: 0 | C17: Location adjustment (+/-)
A18: Cap Adj Size | B18: 0 | C18: Size adjustment (+/-)
A19: Cap Adj Aging | B19: 0.0025 | C19: Aging adjustment (+/-)
A20: Exit Cap Residential | B20: 0.05 | C20: Exit cap - residential
A21: Exit Cap Retail | B21: 0.065 | C21: Exit cap - retail
A22: Growth Rent | B22: 0.03 | C22: Annual market-rent growth
A23: Growth Low Inc Rent | B23: 0.02 | C23: Annual low-income-rent growth
A24: Growth Expense | B24: 0.03 | C24: Annual expense growth
A25: Growth Utility | B25: 0.035 | C25: Annual utility growth
A26: Growth Tax | B26: 0.02 | C26: Annual tax growth
... A28: Growth Start Date | B28: 46054 | C28: Date all growth trending begins (override)
A30: Unit Delivery & Lease-Up
A31: Lease Up Income Offset | B31: 1 | C31: 1=offset lease-up income vs equity, 0=no
A32: Units Delivered Per Mo | B32: 30 | C32: Units delivered per month
A33: Units Leased Per Mo | B33: 18 | C33: Units absorbed (leased) per month
A34: Lease Up Ramp Pct | B34: 0.6 | C34: Variable-opex ramp: % of stabilized during lease-up
A35: Lease Up Elevation Pct | B35: 0.25 | C35: Elevated-opex uplift over stabilized during lease-up
A36: Stabilized Occupancy | B36: 0.93 | C36: Physical occupancy at stabilization
A38: Site Details
A39: Land Cost | B39: 14000000 | C39: Total land cost
A40: Gross Acres | B40: 9.5 | C40: Gross site acres
A41: Net Acres | B41: 8 | C41: Net developable acres
A42: FARRatio | B42: 1.75 | C42: Floor-area ratio
A43: Efficiency Ratio | B43: 0.85 | C43: Net rentable / gross buildable
A44: Existing Structure Cost | B44: 0 | C44: Demo / existing structure
A46: Property Taxes
A47: Tax Levy Pct | B47: 0.0185 | C47: Levy / mill rate (% of assessed)
A48: Tax Assessment Pct | B48: 1 | C48: Assessment ratio (% of value)
A49: Tax Value Adj Factor | B49: 0.5 | C49: Value-adjustment / abatement factor (1.0 = full unabated tax)
A50: Tax Method Value | B50: 1 | C50: Post-stab method: 1=value approach, 0=income approach
A51: Tax Year1 Override | B51: 0 | C51: Year-1 stabilized tax: 0=dynamic (stab value x rate), >0=manual
A52: Reassess On Sale | B52: 1 | C52: 1=reassess buyer taxes on sale value, 0=in-place
A53: Dispo Tax Rate Pct | B53: 0 | C53: Buyer tax rate at sale: 0=use operating effective rate (consistent)
A55: Capitalization & Funding
A56: Funding Order Pari | B56: 0 | C56: 1=pari-passu, 0=equity-first
A57: Target LTC | B57: 0.65 | C57: Target construction loan-to-cost
A58: Op Reserve Coverage | B58: 1.1 | C58: Operating reserve coverage multiple on peak shortfall
A59: Op Reserve Min Months | B59: 3 | C59: Minimum months of stabilized opex floor for reserve
A61: Construction Loan
A62: Con Loan Term Months | B62: 36 | C62: Construction loan term
A63: Con Rate | B63: 0.085 | C63: Construction interest rate (annual)
A64: Con Actual360 | B64: 1 | C64: 1=Actual/360, 0=30/360
A65: Con Points Pct | B65: 0.01 | C65: Origination points
A66: Con Other Costs | B66: 250000 | C66: Other construction loan costs
A67: Con Min Debt Yield | B67: 0.07 | C67: Min stabilized debt yield (sizing)
A68: Con Min DSCR | B68: 1.2 | C68: Min DSCR at target (sizing)
A69: Lender Req Reserve Override | B69: 0 | C69: If >0, overrides computed interest reserve
A71: Permanent Loan (Refinance)
A72: Perm Max LTV | B72: 0.65 | C72: Max permanent loan-to-value
A73: Perm Rate | B73: 0.0625 | C73: Permanent interest rate (annual)
A74: Perm Term Months | B74: 360 | C74: Permanent loan term
A75: Perm IOMonths | B75: 24 | C75: Permanent interest-only period
A76: Perm Amort Months | B76: 360 | C76: Permanent amortization period
A77: Perm Actual360 | B77: 0 | C77: 1=Actual/360, 0=30/360
A78: Perm Points Pct | B78: 0.0075 | C78: Permanent loan points
A79: Perm Min Debt Yield | B79: 0.08 | C79: Min debt yield at refi (sizing)
A80: Perm Min DSCR | B80: 1.15 | C80: Min DSCR at refi (sizing)
A81: No Cash Out | B81: 0 | C81: 1=size perm so net cash at refi = 0
A82: Refi Month Override | B82: 0 | C82: If >0, override refi month (else = con maturity)
A84: Sponsor Fees
A85: Dev Fee Pct Direct | B85: 0.04 | C85: Development fee % of direct costs
A86: Dev Fee Third Party Split | B86: 0 | C86: Portion of dev fee paid to 3rd party
A87: Sponsor Dispo Fee Pct | B87: 0.01 | C87: Sponsor disposition fee % of sale
A88: Recourse Fee Pct | B88: 0.0025 | C88: Loan recourse / indemnity fee % of loan
A90: Disposition & Sale
A91: Broker Cost Pct | B91: 0.015 | C91: Broker / sale cost % of gross sale
A92: Sales Tax Pct | B92: 0 | C92: Transfer / sales tax % of gross sale
A93: Tax Proration Months | B93: 2 | C93: Property-tax proration at sale (months)
A95: Stabilized Revenue (other income)
A96: Bad Debt Pct | B96: 0.005 | C96: Bad debt % of GPR
A97: Concessions Pct | B97: 0.01 | C97: Concessions % of GPR
A98: Loss To Lease Pct | B98: 0.01 | C98: Gain/loss-to-lease % of GPR
A99: Model Units | B99: 1 | C99: Down / model units (non-revenue)
A100: Parking Per Unit Mo | B100: 35 | C100: Parking & storage income $/unit/mo
A101: Retail Income Mo | B101: 18000 | C101: Retail income $/mo (stabilized)
A102: Util Reimb Per Unit Mo | B102: 45 | C102: Utility reimbursement $/unit/mo
A103: Other Inc Per Unit Mo | B103: 25 | C103: Other income $/unit/mo
A105: Stabilized Operating Expenses (annual)
A106: Exp Insurance Per Unit | B106: 425 | C106: Insurance $/unit/yr
A107: Exp Utilities Per Unit | B107: 900 | C107: Utilities $/unit/yr (variable)
A108: Exp Payroll Per Unit | B108: 1300 | C108: Payroll $/unit/yr (elevated in lease-up)
A109: Exp RMPer Unit | B109: 650 | C109: Repairs & maintenance $/unit/yr (variable)
A110: Exp Turnover Per Unit | B110: 250 | C110: Turnover $/unit/yr (variable)
A111: Exp Contract Per Unit | B111: 500 | C111: Contract services $/unit/yr (variable)
A112: Exp Admin Per Unit | B112: 300 | C112: Admin & legal $/unit/yr
A113: Exp Advertising Per Unit | B113: 200 | C113: Advertising $/unit/yr (elevated in lease-up)
...

Sheet UnitMatrix
A1: Unit Matrix — Residential & Retail
A3: Plan | B3: Class | C3: Units | D3: Avg SF | E3: Total SF | F3: Market Rent | G3: Net Eff. Rent | H3: Annual Rent | I3: Rent / SF | J3: % of Total
A4: Studio | B4: Market | C4: 40 | D4: 540 | E4: =C4*D4 | F4: 1895 | G4: 1845 | H4: =C4*F4*12 | I4: =IF(D4=0,0,F4/D4) | J4: =IF(TotalUnits=0,0,C4/TotalUnits)
A5: 1BR-A | B5: Market | C5: 60 | D5: 720 | E5: =C5*D5 | F5: 2245 | G5: 2195 | H5: =C5*F5*12 | I5: =IF(D5=0,0,F5/D5) | J5: =IF(TotalUnits=0,0,C5/TotalUnits)
A6: 1BR-B | B6: Market | C6: 30 | D6: 780 | E6: =C6*D6 | F6: 2360 | G6: 2300 | H6: =C6*F6*12 | I6: =IF(D6=0,0,F6/D6) | J6: =IF(TotalUnits=0,0,C6/TotalUnits)
A7: 2BR-A | B7: Market | C7: 40 | D7: 1050 | E7: =C7*D7 | F7: 3050 | G7: 2975 | H7: =C7*F7*12 | I7: =IF(D7=0,0,F7/D7) | J7: =IF(TotalUnits=0,0,C7/TotalUnits)
A8: 2BR-B | B8: Market | C8: 10 | D8: 1150 | E8: =C8*D8 | F8: 3220 | G8: 3140 | H8: =C8*F8*12 | I8: =IF(D8=0,0,F8/D8) | J8: =IF(TotalUnits=0,0,C8/TotalUnits)
A9: 1BR-LI | B9: Low | C9: 12 | D9: 720 | E9: =C9*D9 | F9: 1350 | G9: 1350 | H9: =C9*F9*12 | I9: =IF(D9=0,0,F9/D9) | J9: =IF(TotalUnits=0,0,C9/TotalUnits)
A10: 2BR-LI | B10: Low | C10: 8 | D10: 1050 | E10: =C10*D10 | F10: 1625 | G10: 1625 | H10: =C10*F10*12 | I10: =IF(D10=0,0,F10/D10) | J10: =IF(TotalUnits=0,0,C10/TotalUnits)
A11: Total / Weighted | C11: =SUM(C4:C10) | E11: =SUM(E4:E10) | H11: =SUM(H4:H10)
A13: Derived Unit Metrics
A14: Total Units | B14: =SUM(C4:C10)
A15: Market-Rate Units | B15: =SUMIF(B4:B10,"Market",C4:C10)
A16: Low-Income Units | B16: =SUMIF(B4:B10,"Low",C4:C10)
A17: Net Rentable SF (NRSF) | B17: =SUM(E4:E10)
A18: Buildable SF | B18: =NRSF/EfficiencyRatio
A19: Avg Unit SF | B19: =IF(TotalUnits=0,0,NRSF/TotalUnits)
A20: Base Market Rent / mo | B20: =SUMPRODUCT((B4:B10="Market")*C4:C10*F4:F10)
A21: Base Low-Income Rent / mo | B21: =SUMPRODUCT((B4:B10="Low")*C4:C10*F4:F10)
A23: Retail Matrix
A24: Suite | B24: SF | C24: Rent / SF / yr | D24: Annual Rent | E24: Monthly Rent
A25: Retail-1 | B25: 4200 | C25: 34 | D25: =B25*C25 | E25: =B25*C25/12
A26: Retail-2 | B26: 3100 | C26: 32 | D26: =B26*C26 | E26: =B26*C26/12
A27: Retail Rent / mo | B27: =SUM(E25:E26)

Sheet Budget
A1: Development Budget & Cost Assumptions
A2: Basis: abs=$ unit=$/unit sf=$/NRSF. Modeled Total drives the cost-curve engine.
A4: Line Item | B4: Group | C4: Type | D4: Basis | E4: Amount | F4: Phase | G4: Cost Curve | H4: Modifier | I4: Modeled Total | J4: Per Unit | K4: Per SF
A5: Land Acquisition | B5: Land | C5: Land | D5: abs | E5: =LandCost | F5: Initial Closing | G5: Single_Point | H5: 0 | I5: =IF(D5="abs",E5,IF(D5="unit",E5*TotalUnits,IF(D5="sf",E5*NRSF,E5))) | J5: =IF(TotalUnits=0,0,I5/TotalUnits) | K5: =IF(NRSF=0,0,I5/NRSF)
A6: Existing Structure/Demo | B6: Land | C6: Land | D6: abs | E6: =ExistingStructureCost | F6: Pre-Construction | G6: Straight_Line | H6: 0 | I6: =IF(D6="abs",E6,IF(D6="unit",E6*TotalUnits,IF(D6="sf",E6*NRSF,E6))) | J6: =IF(TotalUnits=0,0,I6/TotalUnits) | K6: =IF(NRSF=0,0,I6/NRSF)
A7: Due Diligence | B7: Soft | C7: Soft | D7: abs | E7: 150000 | F7: Due Diligence | G7: Straight_Line | H7: 0 | I7: =IF(D7="abs",E7,IF(D7="unit",E7*TotalUnits,IF(D7="sf",E7*NRSF,E7))) | J7: =IF(TotalUnits=0,0,I7/TotalUnits) | K7: =IF(NRSF=0,0,I7/NRSF)
A8: Entitlements | B8: Soft | C8: Soft | D8: abs | E8: 600000 | F8: Entitlement | G8: Straight_Line | H8: 0 | I8: =IF(D8="abs",E8,IF(D8="unit",E8*TotalUnits,IF(D8="sf",E8*NRSF,E8))) | J8: =IF(TotalUnits=0,0,I8/TotalUnits) | K8: =IF(NRSF=0,0,I8/NRSF)
A9: Architecture & Eng. | B9: Soft | C9: Soft | D9: sf | E9: 6.5 | F9: Pre-Construction | G9: Straight_Line | H9: 0 | I9: =IF(D9="abs",E9,IF(D9="unit",E9*TotalUnits,IF(D9="sf",E9*NRSF,E9))) | J9: =IF(TotalUnits=0,0,I9/TotalUnits) | K9: =IF(NRSF=0,0,I9/NRSF)
A10: Consultants | B10: Soft | C10: Soft | D10: abs | E10: 400000 | F10: Entitlement | G10: Straight_Line | H10: 0 | I10: =IF(D10="abs",E10,IF(D10="unit",E10*TotalUnits,IF(D10="sf",E10*NRSF,E10))) | J10: =IF(TotalUnits=0,0,I10/TotalUnits) | K10: =IF(NRSF=0,0,I10/NRSF)
A11: Legal & Org. | B11: Soft | C11: Soft | D11: abs | E11: 300000 | F11: Due Diligence | G11: Straight_Line | H11: 0 | I11: =IF(D11="abs",E11,IF(D11="unit",E11*TotalUnits,IF(D11="sf",E11*NRSF,E11))) | J11: =IF(TotalUnits=0,0,I11/TotalUnits) | K11: =IF(NRSF=0,0,I11/NRSF)
A12: Marketing & Lease-Up | B12: Soft | C12: Soft | D12: unit | E12: 1200 | F12: Lease-Up | G12: Straight_Line | H12: 0 | I12: =IF(D12="abs",E12,IF(D12="unit",E12*TotalUnits,IF(D12="sf",E12*NRSF,E12))) | J12: =IF(TotalUnits=0,0,I12/TotalUnits) | K12: =IF(NRSF=0,0,I12/NRSF)
A13: Insurance (Dev) | B13: Soft | C13: Soft | D13: abs | E13: 500000 | F13: Construction | G13: Straight_Line | H13: 0 | I13: =IF(D13="abs",E13,IF(D13="unit",E13*TotalUnits,IF(D13="sf",E13*NRSF,E13))) | J13: =IF(TotalUnits=0,0,I13/TotalUnits) | K13: =IF(NRSF=0,0,I13/NRSF)
A14: GC Contract (Hard) | B14: Hard | C14: Hard | D14: sf | E14: 200 | F14: Construction | G14: Bell_Curve | H14: 0 | I14: =IF(D14="abs",E14,IF(D14="unit",E14*TotalUnits,IF(D14="sf",E14*NRSF,E14))) | J14: =IF(TotalUnits=0,0,I14/TotalUnits) | K14: =IF(NRSF=0,0,I14/NRSF)
A15: Off-Site Improvements | B15: Hard | C15: Hard | D15: abs | E15: 1200000 | F15: Construction | G15: Straight_Line | H15: 0 | I15: =IF(D15="abs",E15,IF(D15="unit",E15*TotalUnits,IF(D15="sf",E15*NRSF,E15))) | J15: =IF(TotalUnits=0,0,I15/TotalUnits) | K15: =IF(NRSF=0,0,I15/NRSF)
A16: Utilities & Hookups | B16: Hard | C16: Hard | D16: abs | E16: 900000 | F16: Construction | G16: Straight_Line | H16: 0 | I16: =IF(D16="abs",E16,IF(D16="unit",E16*TotalUnits,IF(D16="sf",E16*NRSF,E16))) | J16: =IF(TotalUnits=0,0,I16/TotalUnits) | K16: =IF(NRSF=0,0,I16/NRSF)
A17: Builder's Risk | B17: Hard | C17: Hard | D17: abs | E17: 350000 | F17: Construction | G17: Straight_Line | H17: 0 | I17: =IF(D17="abs",E17,IF(D17="unit",E17*TotalUnits,IF(D17="sf",E17*NRSF,E17))) | J17: =IF(TotalUnits=0,0,I17/TotalUnits) | K17: =IF(NRSF=0,0,I17/NRSF)
A18: Hard Cost Contingency | B18: Hard | C18: Hard | D18: sf | E18: 10 | F18: Construction | G18: Bell_Curve | H18: 0 | I18: =IF(D18="abs",E18,IF(D18="unit",E18*TotalUnits,IF(D18="sf",E18*NRSF,E18))) | J18: =IF(TotalUnits=0,0,I18/TotalUnits) | K18: =IF(NRSF=0,0,I18/NRSF)
... A31: Other Hard Cost 6 | B31: Hard | C31: Hard | D31: abs | E31: 0 | F31: Construction | G31: Bell_Curve | H31: 0 | I31: =IF(D31="abs",E31,IF(D31="unit",E31*TotalUnits,IF(D31="sf",E31*NRSF,E31))) | J31: =IF(TotalUnits=0,0,I31/TotalUnits) | K31: =IF(NRSF=0,0,I31/NRSF)
A33: Budget Summary
A34: Land | I34: =SUMIF(B5:B31,"Land",I5:I31)
A35: Soft Costs | I35: =SUMIF(B5:B31,"Soft",I5:I31)
A36: Hard Costs | I36: =SUMIF(B5:B31,"Hard",I5:I31)
A37: Direct Costs (subtotal) | I37: =SUM(I5:I31)
A38: Sponsor Development Fee | I38: =DevFeePctDirect*DirectCosts
A39: Total Development Cost (per Diagnostics) | I39: =TDC_Total

Sheet Timeline
A1: Timeline Engine — Milestones & Monthly Period Grid
A3: Milestone | B3: Start (mo) | C3: Duration (mo) | D3: End (mo)
A4: Open Escrow | B4: 1 | C4: 1 | D4: =B4+C4-1
A5: Due Diligence | B5: 1 | C5: 3 | D5: =B5+C5-1
A6: Entitlement | B6: 2 | C6: 5 | D6: =B6+C6-1
A7: Pre-Construction | B7: 5 | C7: 3 | D7: =B7+C7-1
A8: Initial Closing | B8: 7 | C8: 1 | D8: =B8+C8-1
A9: Construction | B9: 7 | C9: 20 | D9: =B9+C9-1
A10: 1st Unit Delivery | B10: 21 | C10: 1 | D10: =B10+C10-1
A11: Lease-Up | B11: 21 | C11: 12 | D11: =B11+C11-1
A12: Stabilization | B12: 33 | C12: 1 | D12: =B12+C12-1
A13: Recapitalization/Refinance | B13: 43 | C13: 1 | D13: =B13+C13-1
A14: Disposition | B14: =HoldPeriodMonths | C14: 1 | D14: =B14+C14-1
A16: Key Timing (derived)
A17: Construction Start | B17: =MS_Construction_Start
A18: Construction Maturity | B18: =ConStart+ConLoanTermMonths-1
A19: 1st Unit Delivery | B19: =MS_1st_Unit_Delivery_Start
A20: Stabilization Month | B20: =MS_Stabilization_Start
A21: Disposition Month | B21: =HoldPeriodMonths
A22: Growth Start Month | B22: =(YEAR(GrowthStartDate)-YEAR(InceptionDate))*12+MONTH(GrowthStartDate)-MONTH(InceptionDate)+1
A23: Refi Flag (1=refi,0=sell) | B23: =IF(DispoMonth>ConMaturity,1,0)
A24: Refi Month | B24: =IF(RefiFlag=1,MIN(ConMaturity,IF(RefiMonthOverride>0,RefiMonthOverride,ConMaturity)),0)
A25: Con Payoff Month | B25: =IF(RefiFlag=1,RefiMonth,DispoMonth)
A27: Monthly Period Grid
A28: Period → | C28: Total | D28: 1 | E28: 2 | F28: 3 | G28: 4 | H28: 5 | I28: 6 | J28: 7 | K28: 8 | L28: 9 | M28: 10 | N28: 11 | O28: 12 | P28: 13 | Q28: 14 | R28: 15 | S28: 16 | T28: 17 | U28: 18 | V28: 19 | W28: 20 | X28: 21 | Y28: 22 | Z28: 23 | AA28: 24 | AB28: 25 | AC28: 26 | AD28: 27 | AE28: 28 | AF28: 29 | AG28: 30 | AH28: 31 | AI28: 32 | AJ28: 33 | AK28: 34 | AL28: 35 | AM28: 36 | AN28: 37 | AO28: 38 | AP28: 39 | AQ28: 40 | AR28: 41 | AS28: 42 | AT28: 43 | AU28: 44 | AV28: 45 | AW28: 46 | AX28: 47 | AY28: 48 | AZ28: 49 | BA28: 50 | BB28: 51 | BC28: 52 | BD28: 53 | BE28: 54 | BF28: 55 | BG28: 56 | BH28: 57 | BI28: 58 | BJ28: 59 | BK28: 60 | BL28: 61 | BM28: 62 | BN28: 63 | BO28: 64 | BP28: 65 | BQ28: 66 | BR28: 67 | BS28: 68 | BT28: 69 | BU28: 70 | BV28: 71 | BW28: 72 | BX28: 73 | BY28: 74 | BZ28: 75 | CA28: 76 | CB28: 77 | CC28: 78 | CD28: 79 | CE28: 80 | CF28: 81 | CG28: 82 | CH28: 83 | CI28: 84 | CJ28: 85 | CK28: 86 | CL28: 87 | CM28: 88 | CN28: 89 | CO28: 90 | CP28: 91 | CQ28: 92 | CR28: 93 | CS28: 94 | CT28: 95 | CU28: 96 | CV28: 97 | CW28: 98 | CX28: 99 | CY28: 100 | CZ28: 101 | DA28: 102 | DB28: 103 | DC28: 104 | DD28: 105 | DE28: 106 | DF28: 107 | DG28: 108 | DH28: 109 | DI28: 110 | DJ28: 111 | DK28: 112 | DL28: 113 | DM28: 114 | DN28: 115 | DO28: 116 | DP28: 117 | DQ28: 118 | DR28: 119 | DS28: 120 | DT28: 121 | DU28: 122 | DV28: 123 | DW28: 124 | DX28: 125 | DY28: 126 | DZ28: 127 | EA28: 128 | EB28: 129 | EC28: 130 | ED28: 131 | EE28: 132 | EF28: 133 | EG28: 134 | EH28: 135 | EI28: 136 | EJ28: 137 | EK28: 138 | EL28: 139 | EM28: 140 | EN28: 141 | EO28: 142 | EP28: 143 | EQ28: 144 | ER28: 145 | ES28: 146 | ET28: 147 | EU28: 148 | EV28: 149 | EW28: 150 | EX28: 151 | EY28: 152 | EZ28: 153 | FA28: 154 | FB28: 155 | FC28: 156 | FD28: 157 | FE28: 158 | FF28: 159 | FG28: 160 | FH28: 161 | FI28: 162 | FJ28: 163 | FK28: 164 | FL28: 165 | FM28: 166 | FN28: 167 | FO28: 168 | FP28: 169 | FQ28: 170 | FR28: 171 | FS28: 172 | FT28: 173 | FU28: 174 | FV28: 175 | FW28: 176 | FX28: 177 | FY28: 178 | FZ28: 179 | GA28: 180 | GB28: 181 | GC28: 182 | GD28: 183 | GE28: 184 | GF28: 185 | GG28: 186 | GH28: 187 | GI28: 188 | GJ28: 189 | GK28: 190 | GL28: 191 | GM28: 192 | GN28: 193 | GO28: 194 | GP28: 195 | GQ28: 196 | GR28: 197 | GS28: 198 | GT28: 199 | GU28: 200 | GV28: 201 | GW28: 202 | GX28: 203 | GY28: 204 | GZ28: 205 | HA28: 206 | HB28: 207 | HC28: 208 | HD28: 209 | HE28: 210 | HF28: 211 | HG28: 212 | HH28: 213 | HI28: 214 | HJ28: 215 | HK28: 216 | HL28: 217 | HM28: 218 | HN28: 219 | HO28: 220 | HP28: 221 | HQ28: 222 | HR28: 223 | HS28: 224 | HT28: 225 | HU28: 226 | HV28: 227 | HW28: 228 | HX28: 229 | HY28: 230 | HZ28: 231 | IA28: 232 | IB28: 233 | IC28: 234 | ID28: 235 | IE28: 236 | IF28: 237 | IG28: 238 | IH28: 239 | II28: 240 | IJ28: 241 | IK28: 242 | IL28: 243 | IM28: 244 | IN28: 245 | IO28: 246 | IP28: 247 | IQ28: 248 | IR28: 249 | IS28: 250 | IT28: 251 | IU28: 252 | IV28: 253 | IW28: 254 | IX28: 255 | IY28: 256 | IZ28: 257 | JA28: 258 | JB28: 259 | JC28: 260 | JD28: 261 | JE28: 262 | JF28: 263 | JG28: 264 | JH28: 265 | JI28: 266 | JJ28: 267 | JK28: 268 | JL28: 269 | JM28: 270 | JN28: 271 | JO28: 272 | JP28: 273 | JQ28: 274 | JR28: 275 | JS28: 276 | JT28: 277 | JU28: 278 | JV28: 279 | JW28: 280 | JX28: 281 | JY28: 282 | JZ28: 283 | KA28: 284 | KB28: 285 | KC28: 286 | KD28: 287 | KE28: 288 | KF28: 289 | KG28: 290 | KH28: 291 | KI28: 292 | KJ28: 293 | KK28: 294 | KL28: 295 | KM28: 296 | KN28: 297 | KO28: 298 | KP28: 299 | KQ28: 300 | KR28: 301 | KS28: 302 | KT28: 303 | KU28: 304 | KV28: 305 | KW28: 306 | KX28: 307 | KY28: 308 | KZ28: 309 | LA28: 310 | LB28: 311 | LC28: 312 | LD28: 313 | LE28: 314 | LF28: 315 | LG28: 316 | LH28: 317 | LI28: 318 | LJ28: 319 | LK28: 320 | LL28: 321 | LM28: 322 | LN28: 323 | LO28: 324 | LP28: 325 | LQ28: 326 | LR28: 327 | LS28: 328 | LT28: 329 | LU28: 330 | LV28: 331 | LW28: 332 | LX28: 333 | LY28: 334 | LZ28: 335 | MA28: 336 | MB28: 337 | MC28: 338 | MD28: 339 | ME28: 340 | MF28: 341 | MG28: 342 | MH28: 343 | MI28: 344 | MJ28: 345 | MK28: 346 | ML28: 347 | MM28: 348 | MN28: 349 | MO28: 350 | MP28: 351 | MQ28: 352 | MR28: 353 | MS28: 354 | MT28: 355 | MU28: 356 | MV28: 357 | MW28: 358 | MX28: 359 | MY28: 360 | MZ28: 361 | NA28: 362 | NB28: 363 | NC28: 364 | ND28: 365 | NE28: 366 | NF28: 367 | NG28: 368 | NH28: 369 | NI28: 370 | NJ28: 371 | NK28: 372
A29: Month Start | D29: =EDATE(InceptionDate,0) | E29: =EDATE(InceptionDate,1) | F29: =EDATE(InceptionDate,2) | G29: =EDATE(InceptionDate,3) | H29: =EDATE(InceptionDate,4) | I29: =EDATE(InceptionDate,5) | J29: =EDATE(InceptionDate,6) | K29: =EDATE(InceptionDate,7) | L29: =EDATE(InceptionDate,8) | M29: =EDATE(InceptionDate,9) | N29: =EDATE(InceptionDate,10) | O29: =EDATE(InceptionDate,11) | P29: =EDATE(InceptionDate,12) | Q29: =EDATE(InceptionDate,13) | R29: =EDATE(InceptionDate,14) | S29: =EDATE(InceptionDate,15) | T29: =EDATE(InceptionDate,16) | U29: =EDATE(InceptionDate,17) | V29: =EDATE(InceptionDate,18) | W29: =EDATE(InceptionDate,19) | X29: =EDATE(InceptionDate,20) | Y29: =EDATE(InceptionDate,21) | Z29: =EDATE(InceptionDate,22) | AA29: =EDATE(InceptionDate,23) | AB29: =EDATE(InceptionDate,24) | AC29: =EDATE(InceptionDate,25) | AD29: =EDATE(InceptionDate,26) | AE29: =EDATE(InceptionDate,27) | AF29: =EDATE(InceptionDate,28) | AG29: =EDATE(InceptionDate,29) | AH29: =EDATE(InceptionDate,30) | AI29: =EDATE(InceptionDate,31) | AJ29: =EDATE(InceptionDate,32) | AK29: =EDATE(InceptionDate,33) | AL29: =EDATE(InceptionDate,34) | AM29: =EDATE(InceptionDate,35) | AN29: =EDATE(InceptionDate,36) | AO29: =EDATE(InceptionDate,37) | AP29: =EDATE(InceptionDate,38) | AQ29: =EDATE(InceptionDate,39) | AR29: =EDATE(InceptionDate,40) | AS29: =EDATE(InceptionDate,41) | AT29: =EDATE(InceptionDate,42) | AU29: =EDATE(InceptionDate,43) | AV29: =EDATE(InceptionDate,44) | AW29: =EDATE(InceptionDate,45) | AX29: =EDATE(InceptionDate,46) | AY29: =EDATE(InceptionDate,47) | AZ29: =EDATE(InceptionDate,48) | BA29: =EDATE(InceptionDate,49) | BB29: =EDATE(InceptionDate,50) | BC29: =EDATE(InceptionDate,51) | BD29: =EDATE(InceptionDate,52) | BE29: =EDATE(InceptionDate,53) | BF29: =EDATE(InceptionDate,54) | BG29: =EDATE(InceptionDate,55) | BH29: =EDATE(InceptionDate,56) | BI29: =EDATE(InceptionDate,57) | BJ29: =EDATE(InceptionDate,58) | BK29: =EDATE(InceptionDate,59) | BL29: =EDATE(InceptionDate,60) | BM29: =EDATE(InceptionDate,61) | BN29: =EDATE(InceptionDate,62) | BO29: =EDATE(InceptionDate,63) | BP29: =EDATE(InceptionDate,64) | BQ29: =EDATE(InceptionDate,65) | BR29: =EDATE(InceptionDate,66) | BS29: =EDATE(InceptionDate,67) | BT29: =EDATE(InceptionDate,68) | BU29: =EDATE(InceptionDate,69) | BV29: =EDATE(InceptionDate,70) | BW29: =EDATE(InceptionDate,71) | BX29: =EDATE(InceptionDate,72) | BY29: =EDATE(InceptionDate,73) | BZ29: =EDATE(InceptionDate,74) | CA29: =EDATE(InceptionDate,75) | CB29: =EDATE(InceptionDate,76) | CC29: =EDATE(InceptionDate,77) | CD29: =EDATE(InceptionDate,78) | CE29: =EDATE(InceptionDate,79) | CF29: =EDATE(InceptionDate,80) | CG29: =EDATE(InceptionDate,81) | CH29: =EDATE(InceptionDate,82) | CI29: =EDATE(InceptionDate,83) | CJ29: =EDATE(InceptionDate,84) | CK29: =EDATE(InceptionDate,85) | CL29: =EDATE(InceptionDate,86) | CM29: =EDATE(InceptionDate,87) | CN29: =EDATE(InceptionDate,88) | CO29: =EDATE(InceptionDate,89) | CP29: =EDATE(InceptionDate,90) | CQ29: =EDATE(InceptionDate,91) | CR29: =EDATE(InceptionDate,92) | CS29: =EDATE(InceptionDate,93) | CT29: =EDATE(InceptionDate,94) | CU29: =EDATE(InceptionDate,95) | CV29: =EDATE(InceptionDate,96) | CW29: =EDATE(InceptionDate,97) | CX29: =EDATE(InceptionDate,98) | CY29: =EDATE(InceptionDate,99) | CZ29: =EDATE(InceptionDate,100) | DA29: =EDATE(InceptionDate,101) | DB29: =EDATE(InceptionDate,102) | DC29: =EDATE(InceptionDate,103) | DD29: =EDATE(InceptionDate,104) | DE29: =EDATE(InceptionDate,105) | DF29: =EDATE(InceptionDate,106) | DG29: =EDATE(InceptionDate,107) | DH29: =EDATE(InceptionDate,108) | DI29: =EDATE(InceptionDate,109) | DJ29: =EDATE(InceptionDate,110) | DK29: =EDATE(InceptionDate,111) | DL29: =EDATE(InceptionDate,112) | DM29: =EDATE(InceptionDate,113) | DN29: =EDATE(InceptionDate,114) | DO29: =EDATE(InceptionDate,115) | DP29: =EDATE(InceptionDate,116) | DQ29: =EDATE(InceptionDate,117) | DR29: =EDATE(InceptionDate,118) | DS29: =EDATE(InceptionDate,119) | DT29: =EDATE(InceptionDate,120) | DU29: =EDATE(InceptionDate,121) | DV29: =EDATE(InceptionDate,122) | DW29: =EDATE(InceptionDate,123) | DX29: =EDATE(InceptionDate,124) | DY29: =EDATE(InceptionDate,125) | DZ29: =EDATE(InceptionDate,126) | EA29: =EDATE(InceptionDate,127) | EB29: =EDATE(InceptionDate,128) | EC29: =EDATE(InceptionDate,129) | ED29: =EDATE(InceptionDate,130) | EE29: =EDATE(InceptionDate,131) | EF29: =EDATE(InceptionDate,132) | EG29: =EDATE(InceptionDate,133) | EH29: =EDATE(InceptionDate,134) | EI29: =EDATE(InceptionDate,135) | EJ29: =EDATE(InceptionDate,136) | EK29: =EDATE(InceptionDate,137) | EL29: =EDATE(InceptionDate,138) | EM29: =EDATE(InceptionDate,139) | EN29: =EDATE(InceptionDate,140) | EO29: =EDATE(InceptionDate,141) | EP29: =EDATE(InceptionDate,142) | EQ29: =EDATE(InceptionDate,143) | ER29: =EDATE(InceptionDate,144) | ES29: =EDATE(InceptionDate,145) | ET29: =EDATE(InceptionDate,146) | EU29: =EDATE(InceptionDate,147) | EV29: =EDATE(InceptionDate,148) | EW29: =EDATE(InceptionDate,149) | EX29: =EDATE(InceptionDate,150) | EY29: =EDATE(InceptionDate,151) | EZ29: =EDATE(InceptionDate,152) | FA29: =EDATE(InceptionDate,153) | FB29: =EDATE(InceptionDate,154) | FC29: =EDATE(InceptionDate,155) | FD29: =EDATE(InceptionDate,156) | FE29: =EDATE(InceptionDate,157) | FF29: =EDATE(InceptionDate,158) | FG29: =EDATE(InceptionDate,159) | FH29: =EDATE(InceptionDate,160) | FI29: =EDATE(InceptionDate,161) | FJ29: =EDATE(InceptionDate,162) | FK29: =EDATE(InceptionDate,163) | FL29: =EDATE(InceptionDate,164) | FM29: =EDATE(InceptionDate,165) | FN29: =EDATE(InceptionDate,166) | FO29: =EDATE(InceptionDate,167) | FP29: =EDATE(InceptionDate,168) | FQ29: =EDATE(InceptionDate,169) | FR29: =EDATE(InceptionDate,170) | FS29: =EDATE(InceptionDate,171) | FT29: =EDATE(InceptionDate,172) | FU29: =EDATE(InceptionDate,173) | FV29: =EDATE(InceptionDate,174) | FW29: =EDATE(InceptionDate,175) | FX29: =EDATE(InceptionDate,176) | FY29: =EDATE(InceptionDate,177) | FZ29: =EDATE(InceptionDate,178) | GA29: =EDATE(InceptionDate,179) | GB29: =EDATE(InceptionDate,180) | GC29: =EDATE(InceptionDate,181) | GD29: =EDATE(InceptionDate,182) | GE29: =EDATE(InceptionDate,183) | GF29: =EDATE(InceptionDate,184) | GG29: =EDATE(InceptionDate,185) | GH29: =EDATE(InceptionDate,186) | GI29: =EDATE(InceptionDate,187) | GJ29: =EDATE(InceptionDate,188) | GK29: =EDATE(InceptionDate,189) | GL29: =EDATE(InceptionDate,190) | GM29: =EDATE(InceptionDate,191) | GN29: =EDATE(InceptionDate,192) | GO29: =EDATE(InceptionDate,193) | GP29: =EDATE(InceptionDate,194) | GQ29: =EDATE(InceptionDate,195) | GR29: =EDATE(InceptionDate,196) | GS29: =EDATE(InceptionDate,197) | GT29: =EDATE(InceptionDate,198) | GU29: =EDATE(InceptionDate,199) | GV29: =EDATE(InceptionDate,200) | GW29: =EDATE(InceptionDate,201) | GX29: =EDATE(InceptionDate,202) | GY29: =EDATE(InceptionDate,203) | GZ29: =EDATE(InceptionDate,204) | HA29: =EDATE(InceptionDate,205) | HB29: =EDATE(InceptionDate,206) | HC29: =EDATE(InceptionDate,207) | HD29: =EDATE(InceptionDate,208) | HE29: =EDATE(InceptionDate,209) | HF29: =EDATE(InceptionDate,210) | HG29: =EDATE(InceptionDate,211) | HH29: =EDATE(InceptionDate,212) | HI29: =EDATE(InceptionDate,213) | HJ29: =EDATE(InceptionDate,214) | HK29: =EDATE(InceptionDate,215) | HL29: =EDATE(InceptionDate,216) | HM29: =EDATE(InceptionDate,217) | HN29: =EDATE(InceptionDate,218) | HO29: =EDATE(InceptionDate,219) | HP29: =EDATE(InceptionDate,220) | HQ29: =EDATE(InceptionDate,221) | HR29: =EDATE(InceptionDate,222) | HS29: =EDATE(InceptionDate,223) | HT29: =EDATE(InceptionDate,224) | HU29: =EDATE(InceptionDate,225) | HV29: =EDATE(InceptionDate,226) | HW29: =EDATE(InceptionDate,227) | HX29: =EDATE(InceptionDate,228) | HY29: =EDATE(InceptionDate,229) | HZ29: =EDATE(InceptionDate,230) | IA29: =EDATE(InceptionDate,231) | IB29: =EDATE(InceptionDate,232) | IC29: =EDATE(InceptionDate,233) | ID29: =EDATE(InceptionDate,234) | IE29: =EDATE(InceptionDate,235) | IF29: =EDATE(InceptionDate,236) | IG29: =EDATE(InceptionDate,237) | IH29: =EDATE(InceptionDate,238) | II29: =EDATE(InceptionDate,239) | IJ29: =EDATE(InceptionDate,240) | IK29: =EDATE(InceptionDate,241) | IL29: =EDATE(InceptionDate,242) | IM29: =EDATE(InceptionDate,243) | IN29: =EDATE(InceptionDate,244) | IO29: =EDATE(InceptionDate,245) | IP29: =EDATE(InceptionDate,246) | IQ29: =EDATE(InceptionDate,247) | IR29: =EDATE(InceptionDate,248) | IS29: =EDATE(InceptionDate,249) | IT29: =EDATE(InceptionDate,250) | IU29: =EDATE(InceptionDate,251) | IV29: =EDATE(InceptionDate,252) | IW29: =EDATE(InceptionDate,253) | IX29: =EDATE(InceptionDate,254) | IY29: =EDATE(InceptionDate,255) | IZ29: =EDATE(InceptionDate,256) | JA29: =EDATE(InceptionDate,257) | JB29: =EDATE(InceptionDate,258) | JC29: =EDATE(InceptionDate,259) | JD29: =EDATE(InceptionDate,260) | JE29: =EDATE(InceptionDate,261) | JF29: =EDATE(InceptionDate,262) | JG29: =EDATE(InceptionDate,263) | JH29: =EDATE(InceptionDate,264) | JI29: =EDATE(InceptionDate,265) | JJ29: =EDATE(InceptionDate,266) | JK29: =EDATE(InceptionDate,267) | JL29: =EDATE(InceptionDate,268) | JM29: =EDATE(InceptionDate,269) | JN29: =EDATE(InceptionDate,270) | JO29: =EDATE(InceptionDate,271) | JP29: =EDATE(InceptionDate,272) | JQ29: =EDATE(InceptionDate,273) | JR29: =EDATE(InceptionDate,274) | JS29: =EDATE(InceptionDate,275) | JT29: =EDATE(InceptionDate,276) | JU29: =EDATE(InceptionDate,277) | JV29: =EDATE(InceptionDate,278) | JW29: =EDATE(InceptionDate,279) | JX29: =EDATE(InceptionDate,280) | JY29: =EDATE(InceptionDate,281) | JZ29: =EDATE(InceptionDate,282) | KA29: =EDATE(InceptionDate,283) | KB29: =EDATE(InceptionDate,284) | KC29: =EDATE(InceptionDate,285) | KD29: =EDATE(InceptionDate,286) | KE29: =EDATE(InceptionDate,287) | KF29: =EDATE(InceptionDate,288) | KG29: =EDATE(InceptionDate,289) | KH29: =EDATE(InceptionDate,290) | KI29: =EDATE(InceptionDate,291) | KJ29: =EDATE(InceptionDate,292) | KK29: =EDATE(InceptionDate,293) | KL29: =EDATE(InceptionDate,294) | KM29: =EDATE(InceptionDate,295) | KN29: =EDATE(InceptionDate,296) | KO29: =EDATE(InceptionDate,297) | KP29: =EDATE(InceptionDate,298) | KQ29: =EDATE(InceptionDate,299) | KR29: =EDATE(InceptionDate,300) | KS29: =EDATE(InceptionDate,301) | KT29: =EDATE(InceptionDate,302) | KU29: =EDATE(InceptionDate,303) | KV29: =EDATE(InceptionDate,304) | KW29: =EDATE(InceptionDate,305) | KX29: =EDATE(InceptionDate,306) | KY29: =EDATE(InceptionDate,307) | KZ29: =EDATE(InceptionDate,308) | LA29: =EDATE(InceptionDate,309) | LB29: =EDATE(InceptionDate,310) | LC29: =EDATE(InceptionDate,311) | LD29: =EDATE(InceptionDate,312) | LE29: =EDATE(InceptionDate,313) | LF29: =EDATE(InceptionDate,314) | LG29: =EDATE(InceptionDate,315) | LH29: =EDATE(InceptionDate,316) | LI29: =EDATE(InceptionDate,317) | LJ29: =EDATE(InceptionDate,318) | LK29: =EDATE(InceptionDate,319) | LL29: =EDATE(InceptionDate,320) | LM29: =EDATE(InceptionDate,321) | LN29: =EDATE(InceptionDate,322) | LO29: =EDATE(InceptionDate,323) | LP29: =EDATE(InceptionDate,324) | LQ29: =EDATE(InceptionDate,325) | LR29: =EDATE(InceptionDate,326) | LS29: =EDATE(InceptionDate,327) | LT29: =EDATE(InceptionDate,328) | LU29: =EDATE(InceptionDate,329) | LV29: =EDATE(InceptionDate,330) | LW29: =EDATE(InceptionDate,331) | LX29: =EDATE(InceptionDate,332) | LY29: =EDATE(InceptionDate,333) | LZ29: =EDATE(InceptionDate,334) | MA29: =EDATE(InceptionDate,335) | MB29: =EDATE(InceptionDate,336) | MC29: =EDATE(InceptionDate,337) | MD29: =EDATE(InceptionDate,338) | ME29: =EDATE(InceptionDate,339) | MF29: =EDATE(InceptionDate,340) | MG29: =EDATE(InceptionDate,341) | MH29: =EDATE(InceptionDate,342) | MI29: =EDATE(InceptionDate,343) | MJ29: =EDATE(InceptionDate,344) | MK29: =EDATE(InceptionDate,345) | ML29: =EDATE(InceptionDate,346) | MM29: =EDATE(InceptionDate,347) | MN29: =EDATE(InceptionDate,348) | MO29: =EDATE(InceptionDate,349) | MP29: =EDATE(InceptionDate,350) | MQ29: =EDATE(InceptionDate,351) | MR29: =EDATE(InceptionDate,352) | MS29: =EDATE(InceptionDate,353) | MT29: =EDATE(InceptionDate,354) | MU29: =EDATE(InceptionDate,355) | MV29: =EDATE(InceptionDate,356) | MW29: =EDATE(InceptionDate,357) | MX29: =EDATE(InceptionDate,358) | MY29: =EDATE(InceptionDate,359) | MZ29: =EDATE(InceptionDate,360) | NA29: =EDATE(InceptionDate,361) | NB29: =EDATE(InceptionDate,362) | NC29: =EDATE(InceptionDate,363) | ND29: =EDATE(InceptionDate,364) | NE29: =EDATE(InceptionDate,365) | NF29: =EDATE(InceptionDate,366) | NG29: =EDATE(InceptionDate,367) | NH29: =EDATE(InceptionDate,368) | NI29: =EDATE(InceptionDate,369) | NJ29: =EDATE(InceptionDate,370) | NK29: =EDATE(InceptionDate,371)
A30: Flag: Open Escrow | D30: =IF(AND(1>=$B$4,1<=$D$4),1,0) | E30: =IF(AND(2>=$B$4,2<=$D$4),1,0) | F30: =IF(AND(3>=$B$4,3<=$D$4),1,0) | G30: =IF(AND(4>=$B$4,4<=$D$4),1,0) | H30: =IF(AND(5>=$B$4,5<=$D$4),1,0) | I30: =IF(AND(6>=$B$4,6<=$D$4),1,0) | J30: =IF(AND(7>=$B$4,7<=$D$4),1,0) | K30: =IF(AND(8>=$B$4,8<=$D$4),1,0) | L30: =IF(AND(9>=$B$4,9<=$D$4),1,0) | M30: =IF(AND(10>=$B$4,10<=$D$4),1,0) | N30: =IF(AND(11>=$B$4,11<=$D$4),1,0) | O30: =IF(AND(12>=$B$4,12<=$D$4),1,0) | P30: =IF(AND(13>=$B$4,13<=$D$4),1,0) | Q30: =IF(AND(14>=$B$4,14<=$D$4),1,0) | R30: =IF(AND(15>=$B$4,15<=$D$4),1,0) | S30: =IF(AND(16>=$B$4,16<=$D$4),1,0) | T30: =IF(AND(17>=$B$4,17<=$D$4),1,0) | U30: =IF(AND(18>=$B$4,18<=$D$4),1,0) | V30: =IF(AND(19>=$B$4,19<=$D$4),1,0) | W30: =IF(AND(20>=$B$4,20<=$D$4),1,0) | X30: =IF(AND(21>=$B$4,21<=$D$4),1,0) | Y30: =IF(AND(22>=$B$4,22<=$D$4),1,0) | Z30: =IF(AND(23>=$B$4,23<=$D$4),1,0) | AA30: =IF(AND(24>=$B$4,24<=$D$4),1,0) | AB30: =IF(AND(25>=$B$4,25<=$D$4),1,0) | AC30: =IF(AND(26>=$B$4,26<=$D$4),1,0) | AD30: =IF(AND(27>=$B$4,27<=$D$4),1,0) | AE30: =IF(AND(28>=$B$4,28<=$D$4),1,0) | AF30: =IF(AND(29>=$B$4,29<=$D$4),1,0) | AG30: =IF(AND(30>=$B$4,30<=$D$4),1,0) | AH30: =IF(AND(31>=$B$4,31<=$D$4),1,0) | AI30: =IF(AND(32>=$B$4,32<=$D$4),1,0) | AJ30: =IF(AND(33>=$B$4,33<=$D$4),1,0) | AK30: =IF(AND(34>=$B$4,34<=$D$4),1,0) | AL30: =IF(AND(35>=$B$4,35<=$D$4),1,0) | AM30: =IF(AND(36>=$B$4,36<=$D$4),1,0) | AN30: =IF(AND(37>=$B$4,37<=$D$4),1,0) | AO30: =IF(AND(38>=$B$4,38<=$D$4),1,0) | AP30: =IF(AND(39>=$B$4,39<=$D$4),1,0) | AQ30: =IF(AND(40>=$B$4,40<=$D$4),1,0) | AR30: =IF(AND(41>=$B$4,41<=$D$4),1,0) | AS30: =IF(AND(42>=$B$4,42<=$D$4),1,0) | AT30: =IF(AND(43>=$B$4,43<=$D$4),1,0) | AU30: =IF(AND(44>=$B$4,44<=$D$4),1,0) | AV30: =IF(AND(45>=$B$4,45<=$D$4),1,0) | AW30: =IF(AND(46>=$B$4,46<=$D$4),1,0) | AX30: =IF(AND(47>=$B$4,47<=$D$4),1,0) | AY30: =IF(AND(48>=$B$4,48<=$D$4),1,0) | AZ30: =IF(AND(49>=$B$4,49<=$D$4),1,0) | BA30: =IF(AND(50>=$B$4,50<=$D$4),1,0) | BB30: =IF(AND(51>=$B$4,51<=$D$4),1,0) | BC30: =IF(AND(52>=$B$4,52<=$D$4),1,0) | BD30: =IF(AND(53>=$B$4,53<=$D$4),1,0) | BE30: =IF(AND(54>=$B$4,54<=$D$4),1,0) | BF30: =IF(AND(55>=$B$4,55<=$D$4),1,0) | BG30: =IF(AND(56>=$B$4,56<=$D$4),1,0) | BH30: =IF(AND(57>=$B$4,57<=$D$4),1,0) | BI30: =IF(AND(58>=$B$4,58<=$D$4),1,0) | BJ30: =IF(AND(59>=$B$4,59<=$D$4),1,0) | BK30: =IF(AND(60>=$B$4,60<=$D$4),1,0) | BL30: =IF(AND(61>=$B$4,61<=$D$4),1,0) | BM30: =IF(AND(62>=$B$4,62<=$D$4),1,0) | BN30: =IF(AND(63>=$B$4,63<=$D$4),1,0) | BO30: =IF(AND(64>=$B$4,64<=$D$4),1,0) | BP30: =IF(AND(65>=$B$4,65<=$D$4),1,0) | BQ30: =IF(AND(66>=$B$4,66<=$D$4),1,0) | BR30: =IF(AND(67>=$B$4,67<=$D$4),1,0) | BS30: =IF(AND(68>=$B$4,68<=$D$4),1,0) | BT30: =IF(AND(69>=$B$4,69<=$D$4),1,0) | BU30: =IF(AND(70>=$B$4,70<=$D$4),1,0) | BV30: =IF(AND(71>=$B$4,71<=$D$4),1,0) | BW30: =IF(AND(72>=$B$4,72<=$D$4),1,0) | BX30: =IF(AND(73>=$B$4,73<=$D$4),1,0) | BY30: =IF(AND(74>=$B$4,74<=$D$4),1,0) | BZ30: =IF(AND(75>=$B$4,75<=$D$4),1,0) | CA30: =IF(AND(76>=$B$4,76<=$D$4),1,0) | CB30: =IF(AND(77>=$B$4,77<=$D$4),1,0) | CC30: =IF(AND(78>=$B$4,78<=$D$4),1,0) | CD30: =IF(AND(79>=$B$4,79<=$D$4),1,0) | CE30: =IF(AND(80>=$B$4,80<=$D$4),1,0) | CF30: =IF(AND(81>=$B$4,81<=$D$4),1,0) | CG30: =IF(AND(82>=$B$4,82<=$D$4),1,0) | CH30: =IF(AND(83>=$B$4,83<=$D$4),1,0) | CI30: =IF(AND(84>=$B$4,84<=$D$4),1,0) | CJ30: =IF(AND(85>=$B$4,85<=$D$4),1,0) | CK30: =IF(AND(86>=$B$4,86<=$D$4),1,0) | CL30: =IF(AND(87>=$B$4,87<=$D$4),1,0) | CM30: =IF(AND(88>=$B$4,88<=$D$4),1,0) | CN30: =IF(AND(89>=$B$4,89<=$D$4),1,0) | CO30: =IF(AND(90>=$B$4,90<=$D$4),1,0) | CP30: =IF(AND(91>=$B$4,91<=$D$4),1,0) | CQ30: =IF(AND(92>=$B$4,92<=$D$4),1,0) | CR30: =IF(AND(93>=$B$4,93<=$D$4),1,0) | CS30: =IF(AND(94>=$B$4,94<=$D$4),1,0) | CT30: =IF(AND(95>=$B$4,95<=$D$4),1,0) | CU30: =IF(AND(96>=$B$4,96<=$D$4),1,0) | CV30: =IF(AND(97>=$B$4,97<=$D$4),1,0) | CW30: =IF(AND(98>=$B$4,98<=$D$4),1,0) | CX30: =IF(AND(99>=$B$4,99<=$D$4),1,0) | CY30: =IF(AND(100>=$B$4,100<=$D$4),1,0) | CZ30: =IF(AND(101>=$B$4,101<=$D$4),1,0) | DA30: =IF(AND(102>=$B$4,102<=$D$4),1,0) | DB30: =IF(AND(103>=$B$4,103<=$D$4),1,0) | DC30: =IF(AND(104>=$B$4,104<=$D$4),1,0) | DD30: =IF(AND(105>=$B$4,105<=$D$4),1,0) | DE30: =IF(AND(106>=$B$4,106<=$D$4),1,0) | DF30: =IF(AND(107>=$B$4,107<=$D$4),1,0) | DG30: =IF(AND(108>=$B$4,108<=$D$4),1,0) | DH30: =IF(AND(109>=$B$4,109<=$D$4),1,0) | DI30: =IF(AND(110>=$B$4,110<=$D$4),1,0) | DJ30: =IF(AND(111>=$B$4,111<=$D$4),1,0) | DK30: =IF(AND(112>=$B$4,112<=$D$4),1,0) | DL30: =IF(AND(113>=$B$4,113<=$D$4),1,0) | DM30: =IF(AND(114>=$B$4,114<=$D$4),1,0) | DN30: =IF(AND(115>=$B$4,115<=$D$4),1,0) | DO30: =IF(AND(116>=$B$4,116<=$D$4),1,0) | DP30: =IF(AND(117>=$B$4,117<=$D$4),1,0) | DQ30: =IF(AND(118>=$B$4,118<=$D$4),1,0) | DR30: =IF(AND(119>=$B$4,119<=$D$4),1,0) | DS30: =IF(AND(120>=$B$4,120<=$D$4),1,0) | DT30: =IF(AND(121>=$B$4,121<=$D$4),1,0) | DU30: =IF(AND(122>=$B$4,122<=$D$4),1,0) | DV30: =IF(AND(123>=$B$4,123<=$D$4),1,0) | DW30: =IF(AND(124>=$B$4,124<=$D$4),1,0) | DX30: =IF(AND(125>=$B$4,125<=$D$4),1,0) | DY30: =IF(AND(126>=$B$4,126<=$D$4),1,0) | DZ30: =IF(AND(127>=$B$4,127<=$D$4),1,0) | EA30: =IF(AND(128>=$B$4,128<=$D$4),1,0) | EB30: =IF(AND(129>=$B$4,129<=$D$4),1,0) | EC30: =IF(AND(130>=$B$4,130<=$D$4),1,0) | ED30: =IF(AND(131>=$B$4,131<=$D$4),1,0) | EE30: =IF(AND(132>=$B$4,132<=$D$4),1,0) | EF30: =IF(AND(133>=$B$4,133<=$D$4),1,0) | EG30: =IF(AND(134>=$B$4,134<=$D$4),1,0) | EH30: =IF(AND(135>=$B$4,135<=$D$4),1,0) | EI30: =IF(AND(136>=$B$4,136<=$D$4),1,0) | EJ30: =IF(AND(137>=$B$4,137<=$D$4),1,0) | EK30: =IF(AND(138>=$B$4,138<=$D$4),1,0) | EL30: =IF(AND(139>=$B$4,139<=$D$4),1,0) | EM30: =IF(AND(140>=$B$4,140<=$D$4),1,0) | EN30: =IF(AND(141>=$B$4,141<=$D$4),1,0) | EO30: =IF(AND(142>=$B$4,142<=$D$4),1,0) | EP30: =IF(AND(143>=$B$4,143<=$D$4),1,0) | EQ30: =IF(AND(144>=$B$4,144<=$D$4),1,0) | ER30: =IF(AND(145>=$B$4,145<=$D$4),1,0) | ES30: =IF(AND(146>=$B$4,146<=$D$4),1,0) | ET30: =IF(AND(147>=$B$4,147<=$D$4),1,0) | EU30: =IF(AND(148>=$B$4,148<=$D$4),1,0) | EV30: =IF(AND(149>=$B$4,149<=$D$4),1,0) | EW30: =IF(AND(150>=$B$4,150<=$D$4),1,0) | EX30: =IF(AND(151>=$B$4,151<=$D$4),1,0) | EY30: =IF(AND(152>=$B$4,152<=$D$4),1,0) | EZ30: =IF(AND(153>=$B$4,153<=$D$4),1,0) | FA30: =IF(AND(154>=$B$4,154<=$D$4),1,0) | FB30: =IF(AND(155>=$B$4,155<=$D$4),1,0) | FC30: =IF(AND(156>=$B$4,156<=$D$4),1,0) | FD30: =IF(AND(157>=$B$4,157<=$D$4),1,0) | FE30: =IF(AND(158>=$B$4,158<=$D$4),1,0) | FF30: =IF(AND(159>=$B$4,159<=$D$4),1,0) | FG30: =IF(AND(160>=$B$4,160<=$D$4),1,0) | FH30: =IF(AND(161>=$B$4,161<=$D$4),1,0) | FI30: =IF(AND(162>=$B$4,162<=$D$4),1,0) | FJ30: =IF(AND(163>=$B$4,163<=$D$4),1,0) | FK30: =IF(AND(164>=$B$4,164<=$D$4),1,0) | FL30: =IF(AND(165>=$B$4,165<=$D$4),1,0) | FM30: =IF(AND(166>=$B$4,166<=$D$4),1,0) | FN30: =IF(AND(167>=$B$4,167<=$D$4),1,0) | FO30: =IF(AND(168>=$B$4,168<=$D$4),1,0) | FP30: =IF(AND(169>=$B$4,169<=$D$4),1,0) | FQ30: =IF(AND(170>=$B$4,170<=$D$4),1,0) | FR30: =IF(AND(171>=$B$4,171<=$D$4),1,0) | FS30: =IF(AND(172>=$B$4,172<=$D$4),1,0) | FT30: =IF(AND(173>=$B$4,173<=$D$4),1,0) | FU30: =IF(AND(174>=$B$4,174<=$D$4),1,0) | FV30: =IF(AND(175>=$B$4,175<=$D$4),1,0) | FW30: =IF(AND(176>=$B$4,176<=$D$4),1,0) | FX30: =IF(AND(177>=$B$4,177<=$D$4),1,0) | FY30: =IF(AND(178>=$B$4,178<=$D$4),1,0) | FZ30: =IF(AND(179>=$B$4,179<=$D$4),1,0) | GA30: =IF(AND(180>=$B$4,180<=$D$4),1,0) | GB30: =IF(AND(181>=$B$4,181<=$D$4),1,0) | GC30: =IF(AND(182>=$B$4,182<=$D$4),1,0) | GD30: =IF(AND(183>=$B$4,183<=$D$4),1,0) | GE30: =IF(AND(184>=$B$4,184<=$D$4),1,0) | GF30: =IF(AND(185>=$B$4,185<=$D$4),1,0) | GG30: =IF(AND(186>=$B$4,186<=$D$4),1,0) | GH30: =IF(AND(187>=$B$4,187<=$D$4),1,0) | GI30: =IF(AND(188>=$B$4,188<=$D$4),1,0) | GJ30: =IF(AND(189>=$B$4,189<=$D$4),1,0) | GK30: =IF(AND(190>=$B$4,190<=$D$4),1,0) | GL30: =IF(AND(191>=$B$4,191<=$D$4),1,0) | GM30: =IF(AND(192>=$B$4,192<=$D$4),1,0) | GN30: =IF(AND(193>=$B$4,193<=$D$4),1,0) | GO30: =IF(AND(194>=$B$4,194<=$D$4),1,0) | GP30: =IF(AND(195>=$B$4,195<=$D$4),1,0) | GQ30: =IF(AND(196>=$B$4,196<=$D$4),1,0) | GR30: =IF(AND(197>=$B$4,197<=$D$4),1,0) | GS30: =IF(AND(198>=$B$4,198<=$D$4),1,0) | GT30: =IF(AND(199>=$B$4,199<=$D$4),1,0) | GU30: =IF(AND(200>=$B$4,200<=$D$4),1,0) | GV30: =IF(AND(201>=$B$4,201<=$D$4),1,0) | GW30: =IF(AND(202>=$B$4,202<=$D$4),1,0) | GX30: =IF(AND(203>=$B$4,203<=$D$4),1,0) | GY30: =IF(AND(204>=$B$4,204<=$D$4),1,0) | GZ30: =IF(AND(205>=$B$4,205<=$D$4),1,0) | HA30: =IF(AND(206>=$B$4,206<=$D$4),1,0) | HB30: =IF(AND(207>=$B$4,207<=$D$4),1,0) | HC30: =IF(AND(208>=$B$4,208<=$D$4),1,0) | HD30: =IF(AND(209>=$B$4,209<=$D$4),1,0) | HE30: =IF(AND(210>=$B$4,210<=$D$4),1,0) | HF30: =IF(AND(211>=$B$4,211<=$D$4),1,0) | HG30: =IF(AND(212>=$B$4,212<=$D$4),1,0) | HH30: =IF(AND(213>=$B$4,213<=$D$4),1,0) | HI30: =IF(AND(214>=$B$4,214<=$D$4),1,0) | HJ30: =IF(AND(215>=$B$4,215<=$D$4),1,0) | HK30: =IF(AND(216>=$B$4,216<=$D$4),1,0) | HL30: =IF(AND(217>=$B$4,217<=$D$4),1,0) | HM30: =IF(AND(218>=$B$4,218<=$D$4),1,0) | HN30: =IF(AND(219>=$B$4,219<=$D$4),1,0) | HO30: =IF(AND(220>=$B$4,220<=$D$4),1,0) | HP30: =IF(AND(221>=$B$4,221<=$D$4),1,0) | HQ30: =IF(AND(222>=$B$4,222<=$D$4),1,0) | HR30: =IF(AND(223>=$B$4,223<=$D$4),1,0) | HS30: =IF(AND(224>=$B$4,224<=$D$4),1,0) | HT30: =IF(AND(225>=$B$4,225<=$D$4),1,0) | HU30: =IF(AND(226>=$B$4,226<=$D$4),1,0) | HV30: =IF(AND(227>=$B$4,227<=$D$4),1,0) | HW30: =IF(AND(228>=$B$4,228<=$D$4),1,0) | HX30: =IF(AND(229>=$B$4,229<=$D$4),1,0) | HY30: =IF(AND(230>=$B$4,230<=$D$4),1,0) | HZ30: =IF(AND(231>=$B$4,231<=$D$4),1,0) | IA30: =IF(AND(232>=$B$4,232<=$D$4),1,0) | IB30: =IF(AND(233>=$B$4,233<=$D$4),1,0) | IC30: =IF(AND(234>=$B$4,234<=$D$4),1,0) | ID30: =IF(AND(235>=$B$4,235<=$D$4),1,0) | IE30: =IF(AND(236>=$B$4,236<=$D$4),1,0) | IF30: =IF(AND(237>=$B$4,237<=$D$4),1,0) | IG30: =IF(AND(238>=$B$4,238<=$D$4),1,0) | IH30: =IF(AND(239>=$B$4,239<=$D$4),1,0) | II30: =IF(AND(240>=$B$4,240<=$D$4),1,0) | IJ30: =IF(AND(241>=$B$4,241<=$D$4),1,0) | IK30: =IF(AND(242>=$B$4,242<=$D$4),1,0) | IL30: =IF(AND(243>=$B$4,243<=$D$4),1,0) | IM30: =IF(AND(244>=$B$4,244<=$D$4),1,0) | IN30: =IF(AND(245>=$B$4,245<=$D$4),1,0) | IO30: =IF(AND(246>=$B$4,246<=$D$4),1,0) | IP30: =IF(AND(247>=$B$4,247<=$D$4),1,0) | IQ30: =IF(AND(248>=$B$4,248<=$D$4),1,0) | IR30: =IF(AND(249>=$B$4,249<=$D$4),1,0) | IS30: =IF(AND(250>=$B$4,250<=$D$4),1,0) | IT30: =IF(AND(251>=$B$4,251<=$D$4),1,0) | IU30: =IF(AND(252>=$B$4,252<=$D$4),1,0) | IV30: =IF(AND(253>=$B$4,253<=$D$4),1,0) | IW30: =IF(AND(254>=$B$4,254<=$D$4),1,0) | IX30: =IF(AND(255>=$B$4,255<=$D$4),1,0) | IY30: =IF(AND(256>=$B$4,256<=$D$4),1,0) | IZ30: =IF(AND(257>=$B$4,257<=$D$4),1,0) | JA30: =IF(AND(258>=$B$4,258<=$D$4),1,0) | JB30: =IF(AND(259>=$B$4,259<=$D$4),1,0) | JC30: =IF(AND(260>=$B$4,260<=$D$4),1,0) | JD30: =IF(AND(261>=$B$4,261<=$D$4),1,0) | JE30: =IF(AND(262>=$B$4,262<=$D$4),1,0) | JF30: =IF(AND(263>=$B$4,263<=$D$4),1,0) | JG30: =IF(AND(264>=$B$4,264<=$D$4),1,0) | JH30: =IF(AND(265>=$B$4,265<=$D$4),1,0) | JI30: =IF(AND(266>=$B$4,266<=$D$4),1,0) | JJ30: =IF(AND(267>=$B$4,267<=$D$4),1,0) | JK30: =IF(AND(268>=$B$4,268<=$D$4),1,0) | JL30: =IF(AND(269>=$B$4,269<=$D$4),1,0) | JM30: =IF(AND(270>=$B$4,270<=$D$4),1,0) | JN30: =IF(AND(271>=$B$4,271<=$D$4),1,0) | JO30: =IF(AND(272>=$B$4,272<=$D$4),1,0) | JP30: =IF(AND(273>=$B$4,273<=$D$4),1,0) | JQ30: =IF(AND(274>=$B$4,274<=$D$4),1,0) | JR30: =IF(AND(275>=$B$4,275<=$D$4),1,0) | JS30: =IF(AND(276>=$B$4,276<=$D$4),1,0) | JT30: =IF(AND(277>=$B$4,277<=$D$4),1,0) | JU30: =IF(AND(278>=$B$4,278<=$D$4),1,0) | JV30: =IF(AND(279>=$B$4,279<=$D$4),1,0) | JW30: =IF(AND(280>=$B$4,280<=$D$4),1,0) | JX30: =IF(AND(281>=$B$4,281<=$D$4),1,0) | JY30: =IF(AND(282>=$B$4,282<=$D$4),1,0) | JZ30: =IF(AND(283>=$B$4,283<=$D$4),1,0) | KA30: =IF(AND(284>=$B$4,284<=$D$4),1,0) | KB30: =IF(AND(285>=$B$4,285<=$D$4),1,0) | KC30: =IF(AND(286>=$B$4,286<=$D$4),1,0) | KD30: =IF(AND(287>=$B$4,287<=$D$4),1,0) | KE30: =IF(AND(288>=$B$4,288<=$D$4),1,0) | KF30: =IF(AND(289>=$B$4,289<=$D$4),1,0) | KG30: =IF(AND(290>=$B$4,290<=$D$4),1,0) | KH30: =IF(AND(291>=$B$4,291<=$D$4),1,0) | KI30: =IF(AND(292>=$B$4,292<=$D$4),1,0) | KJ30: =IF(AND(293>=$B$4,293<=$D$4),1,0) | KK30: =IF(AND(294>=$B$4,294<=$D$4),1,0) | KL30: =IF(AND(295>=$B$4,295<=$D$4),1,0) | KM30: =IF(AND(296>=$B$4,296<=$D$4),1,0) | KN30: =IF(AND(297>=$B$4,297<=$D$4),1,0) | KO30: =IF(AND(298>=$B$4,298<=$D$4),1,0) | KP30: =IF(AND(299>=$B$4,299<=$D$4),1,0) | KQ30: =IF(AND(300>=$B$4,300<=$D$4),1,0) | KR30: =IF(AND(301>=$B$4,301<=$D$4),1,0) | KS30: =IF(AND(302>=$B$4,302<=$D$4),1,0) | KT30: =IF(AND(303>=$B$4,303<=$D$4),1,0) | KU30: =IF(AND(304>=$B$4,304<=$D$4),1,0) | KV30: =IF(AND(305>=$B$4,305<=$D$4),1,0) | KW30: =IF(AND(306>=$B$4,306<=$D$4),1,0) | KX30: =IF(AND(307>=$B$4,307<=$D$4),1,0) | KY30: =IF(AND(308>=$B$4,308<=$D$4),1,0) | KZ30: =IF(AND(309>=$B$4,309<=$D$4),1,0) | LA30: =IF(AND(310>=$B$4,310<=$D$4),1,0) | LB30: =IF(AND(311>=$B$4,311<=$D$4),1,0) | LC30: =IF(AND(312>=$B$4,312<=$D$4),1,0) | LD30: =IF(AND(313>=$B$4,313<=$D$4),1,0) | LE30: =IF(AND(314>=$B$4,314<=$D$4),1,0) | LF30: =IF(AND(315>=$B$4,315<=$D$4),1,0) | LG30: =IF(AND(316>=$B$4,316<=$D$4),1,0) | LH30: =IF(AND(317>=$B$4,317<=$D$4),1,0) | LI30: =IF(AND(318>=$B$4,318<=$D$4),1,0) | LJ30: =IF(AND(319>=$B$4,319<=$D$4),1,0) | LK30: =IF(AND(320>=$B$4,320<=$D$4),1,0) | LL30: =IF(AND(321>=$B$4,321<=$D$4),1,0) | LM30: =IF(AND(322>=$B$4,322<=$D$4),1,0) | LN30: =IF(AND(323>=$B$4,323<=$D$4),1,0) | LO30: =IF(AND(324>=$B$4,324<=$D$4),1,0) | LP30: =IF(AND(325>=$B$4,325<=$D$4),1,0) | LQ30: =IF(AND(326>=$B$4,326<=$D$4),1,0) | LR30: =IF(AND(327>=$B$4,327<=$D$4),1,0) | LS30: =IF(AND(328>=$B$4,328<=$D$4),1,0) | LT30: =IF(AND(329>=$B$4,329<=$D$4),1,0) | LU30: =IF(AND(330>=$B$4,330<=$D$4),1,0) | LV30: =IF(AND(331>=$B$4,331<=$D$4),1,0) | LW30: =IF(AND(332>=$B$4,332<=$D$4),1,0) | LX30: =IF(AND(333>=$B$4,333<=$D$4),1,0) | LY30: =IF(AND(334>=$B$4,334<=$D$4),1,0) | LZ30: =IF(AND(335>=$B$4,335<=$D$4),1,0) | MA30: =IF(AND(336>=$B$4,336<=$D$4),1,0) | MB30: =IF(AND(337>=$B$4,337<=$D$4),1,0) | MC30: =IF(AND(338>=$B$4,338<=$D$4),1,0) | MD30: =IF(AND(339>=$B$4,339<=$D$4),1,0) | ME30: =IF(AND(340>=$B$4,340<=$D$4),1,0) | MF30: =IF(AND(341>=$B$4,341<=$D$4),1,0) | MG30: =IF(AND(342>=$B$4,342<=$D$4),1,0) | MH30: =IF(AND(343>=$B$4,343<=$D$4),1,0) | MI30: =IF(AND(344>=$B$4,344<=$D$4),1,0) | MJ30: =IF(AND(345>=$B$4,345<=$D$4),1,0) | MK30: =IF(AND(346>=$B$4,346<=$D$4),1,0) | ML30: =IF(AND(347>=$B$4,347<=$D$4),1,0) | MM30: =IF(AND(348>=$B$4,348<=$D$4),1,0) | MN30: =IF(AND(349>=$B$4,349<=$D$4),1,0) | MO30: =IF(AND(350>=$B$4,350<=$D$4),1,0) | MP30: =IF(AND(351>=$B$4,351<=$D$4),1,0) | MQ30: =IF(AND(352>=$B$4,352<=$D$4),1,0) | MR30: =IF(AND(353>=$B$4,353<=$D$4),1,0) | MS30: =IF(AND(354>=$B$4,354<=$D$4),1,0) | MT30: =IF(AND(355>=$B$4,355<=$D$4),1,0) | MU30: =IF(AND(356>=$B$4,356<=$D$4),1,0) | MV30: =IF(AND(357>=$B$4,357<=$D$4),1,0) | MW30: =IF(AND(358>=$B$4,358<=$D$4),1,0) | MX30: =IF(AND(359>=$B$4,359<=$D$4),1,0) | MY30: =IF(AND(360>=$B$4,360<=$D$4),1,0) | MZ30: =IF(AND(361>=$B$4,361<=$D$4),1,0) | NA30: =IF(AND(362>=$B$4,362<=$D$4),1,0) | NB30: =IF(AND(363>=$B$4,363<=$D$4),1,0) | NC30: =IF(AND(364>=$B$4,364<=$D$4),1,0) | ND30: =IF(AND(365>=$B$4,365<=$D$4),1,0) | NE30: =IF(AND(366>=$B$4,366<=$D$4),1,0) | NF30: =IF(AND(367>=$B$4,367<=$D$4),1,0) | NG30: =IF(AND(368>=$B$4,368<=$D$4),1,0) | NH30: =IF(AND(369>=$B$4,369<=$D$4),1,0) | NI30: =IF(AND(370>=$B$4,370<=$D$4),1,0) | NJ30: =IF(AND(371>=$B$4,371<=$D$4),1,0) | NK30: =IF(AND(372>=$B$4,372<=$D$4),1,0)
A31: Flag: Due Diligence | D31: =IF(AND(1>=$B$5,1<=$D$5),1,0) | E31: =IF(AND(2>=$B$5,2<=$D$5),1,0) | F31: =IF(AND(3>=$B$5,3<=$D$5),1,0) | G31: =IF(AND(4>=$B$5,4<=$D$5),1,0) | H31: =IF(AND(5>=$B$5,5<=$D$5),1,0) | I31: =IF(AND(6>=$B$5,6<=$D$5),1,0) | J31: =IF(AND(7>=$B$5,7<=$D$5),1,0) | K31: =IF(AND(8>=$B$5,8<=$D$5),1,0) | L31: =IF(AND(9>=$B$5,9<=$D$5),1,0) | M31: =IF(AND(10>=$B$5,10<=$D$5),1,0) | N31: =IF(AND(11>=$B$5,11<=$D$5),1,0) | O31: =IF(AND(12>=$B$5,12<=$D$5),1,0) | P31: =IF(AND(13>=$B$5,13<=$D$5),1,0) | Q31: =IF(AND(14>=$B$5,14<=$D$5),1,0) | R31: =IF(AND(15>=$B$5,15<=$D$5),1,0) | S31: =IF(AND(16>=$B$5,16<=$D$5),1,0) | T31: =IF(AND(17>=$B$5,17<=$D$5),1,0) | U31: =IF(AND(18>=$B$5,18<=$D$5),1,0) | V31: =IF(AND(19>=$B$5,19<=$D$5),1,0) | W31: =IF(AND(20>=$B$5,20<=$D$5),1,0) | X31: =IF(AND(21>=$B$5,21<=$D$5),1,0) | Y31: =IF(AND(22>=$B$5,22<=$D$5),1,0) | Z31: =IF(AND(23>=$B$5,23<=$D$5),1,0) | AA31: =IF(AND(24>=$B$5,24<=$D$5),1,0) | AB31: =IF(AND(25>=$B$5,25<=$D$5),1,0) | AC31: =IF(AND(26>=$B$5,26<=$D$5),1,0) | AD31: =IF(AND(27>=$B$5,27<=$D$5),1,0) | AE31: =IF(AND(28>=$B$5,28<=$D$5),1,0) | AF31: =IF(AND(29>=$B$5,29<=$D$5),1,0) | AG31: =IF(AND(30>=$B$5,30<=$D$5),1,0) | AH31: =IF(AND(31>=$B$5,31<=$D$5),1,0) | AI31: =IF(AND(32>=$B$5,32<=$D$5),1,0) | AJ31: =IF(AND(33>=$B$5,33<=$D$5),1,0) | AK31: =IF(AND(34>=$B$5,34<=$D$5),1,0) | AL31: =IF(AND(35>=$B$5,35<=$D$5),1,0) | AM31: =IF(AND(36>=$B$5,36<=$D$5),1,0) | AN31: =IF(AND(37>=$B$5,37<=$D$5),1,0) | AO31: =IF(AND(38>=$B$5,38<=$D$5),1,0) | AP31: =IF(AND(39>=$B$5,39<=$D$5),1,0) | AQ31: =IF(AND(40>=$B$5,40<=$D$5),1,0) | AR31: =IF(AND(41>=$B$5,41<=$D$5),1,0) | AS31: =IF(AND(42>=$B$5,42<=$D$5),1,0) | AT31: =IF(AND(43>=$B$5,43<=$D$5),1,0) | AU31: =IF(AND(44>=$B$5,44<=$D$5),1,0) | AV31: =IF(AND(45>=$B$5,45<=$D$5),1,0) | AW31: =IF(AND(46>=$B$5,46<=$D$5),1,0) | AX31: =IF(AND(47>=$B$5,47<=$D$5),1,0) | AY31: =IF(AND(48>=$B$5,48<=$D$5),1,0) | AZ31: =IF(AND(49>=$B$5,49<=$D$5),1,0) | BA31: =IF(AND(50>=$B$5,50<=$D$5),1,0) | BB31: =IF(AND(51>=$B$5,51<=$D$5),1,0) | BC31: =IF(AND(52>=$B$5,52<=$D$5),1,0) | BD31: =IF(AND(53>=$B$5,53<=$D$5),1,0) | BE31: =IF(AND(54>=$B$5,54<=$D$5),1,0) | BF31: =IF(AND(55>=$B$5,55<=$D$5),1,0) | BG31: =IF(AND(56>=$B$5,56<=$D$5),1,0) | BH31: =IF(AND(57>=$B$5,57<=$D$5),1,0) | BI31: =IF(AND(58>=$B$5,58<=$D$5),1,0) | BJ31: =IF(AND(59>=$B$5,59<=$D$5),1,0) | BK31: =IF(AND(60>=$B$5,60<=$D$5),1,0) | BL31: =IF(AND(61>=$B$5,61<=$D$5),1,0) | BM31: =IF(AND(62>=$B$5,62<=$D$5),1,0) | BN31: =IF(AND(63>=$B$5,63<=$D$5),1,0) | BO31: =IF(AND(64>=$B$5,64<=$D$5),1,0) | BP31: =IF(AND(65>=$B$5,65<=$D$5),1,0) | BQ31: =IF(AND(66>=$B$5,66<=$D$5),1,0) | BR31: =IF(AND(67>=$B$5,67<=$D$5),1,0) | BS31: =IF(AND(68>=$B$5,68<=$D$5),1,0) | BT31: =IF(AND(69>=$B$5,69<=$D$5),1,0) | BU31: =IF(AND(70>=$B$5,70<=$D$5),1,0) | BV31: =IF(AND(71>=$B$5,71<=$D$5),1,0) | BW31: =IF(AND(72>=$B$5,72<=$D$5),1,0) | BX31: =IF(AND(73>=$B$5,73<=$D$5),1,0) | BY31: =IF(AND(74>=$B$5,74<=$D$5),1,0) | BZ31: =IF(AND(75>=$B$5,75<=$D$5),1,0) | CA31: =IF(AND(76>=$B$5,76<=$D$5),1,0) | CB31: =IF(AND(77>=$B$5,77<=$D$5),1,0) | CC31: =IF(AND(78>=$B$5,78<=$D$5),1,0) | CD31: =IF(AND(79>=$B$5,79<=$D$5),1,0) | CE31: =IF(AND(80>=$B$5,80<=$D$5),1,0) | CF31: =IF(AND(81>=$B$5,81<=$D$5),1,0) | CG31: =IF(AND(82>=$B$5,82<=$D$5),1,0) | CH31: =IF(AND(83>=$B$5,83<=$D$5),1,0) | CI31: =IF(AND(84>=$B$5,84<=$D$5),1,0) | CJ31: =IF(AND(85>=$B$5,85<=$D$5),1,0) | CK31: =IF(AND(86>=$B$5,86<=$D$5),1,0) | CL31: =IF(AND(87>=$B$5,87<=$D$5),1,0) | CM31: =IF(AND(88>=$B$5,88<=$D$5),1,0) | CN31: =IF(AND(89>=$B$5,89<=$D$5),1,0) | CO31: =IF(AND(90>=$B$5,90<=$D$5),1,0) | CP31: =IF(AND(91>=$B$5,91<=$D$5),1,0) | CQ31: =IF(AND(92>=$B$5,92<=$D$5),1,0) | CR31: =IF(AND(93>=$B$5,93<=$D$5),1,0) | CS31: =IF(AND(94>=$B$5,94<=$D$5),1,0) | CT31: =IF(AND(95>=$B$5,95<=$D$5),1,0) | CU31: =IF(AND(96>=$B$5,96<=$D$5),1,0) | CV31: =IF(AND(97>=$B$5,97<=$D$5),1,0) | CW31: =IF(AND(98>=$B$5,98<=$D$5),1,0) | CX31: =IF(AND(99>=$B$5,99<=$D$5),1,0) | CY31: =IF(AND(100>=$B$5,100<=$D$5),1,0) | CZ31: =IF(AND(101>=$B$5,101<=$D$5),1,0) | DA31: =IF(AND(102>=$B$5,102<=$D$5),1,0) | DB31: =IF(AND(103>=$B$5,103<=$D$5),1,0) | DC31: =IF(AND(104>=$B$5,104<=$D$5),1,0) | DD31: =IF(AND(105>=$B$5,105<=$D$5),1,0) | DE31: =IF(AND(106>=$B$5,106<=$D$5),1,0) | DF31: =IF(AND(107>=$B$5,107<=$D$5),1,0) | DG31: =IF(AND(108>=$B$5,108<=$D$5),1,0) | DH31: =IF(AND(109>=$B$5,109<=$D$5),1,0) | DI31: =IF(AND(110>=$B$5,110<=$D$5),1,0) | DJ31: =IF(AND(111>=$B$5,111<=$D$5),1,0) | DK31: =IF(AND(112>=$B$5,112<=$D$5),1,0) | DL31: =IF(AND(113>=$B$5,113<=$D$5),1,0) | DM31: =IF(AND(114>=$B$5,114<=$D$5),1,0) | DN31: =IF(AND(115>=$B$5,115<=$D$5),1,0) | DO31: =IF(AND(116>=$B$5,116<=$D$5),1,0) | DP31: =IF(AND(117>=$B$5,117<=$D$5),1,0) | DQ31: =IF(AND(118>=$B$5,118<=$D$5),1,0) | DR31: =IF(AND(119>=$B$5,119<=$D$5),1,0) | DS31: =IF(AND(120>=$B$5,120<=$D$5),1,0) | DT31: =IF(AND(121>=$B$5,121<=$D$5),1,0) | DU31: =IF(AND(122>=$B$5,122<=$D$5),1,0) | DV31: =IF(AND(123>=$B$5,123<=$D$5),1,0) | DW31: =IF(AND(124>=$B$5,124<=$D$5),1,0) | DX31: =IF(AND(125>=$B$5,125<=$D$5),1,0) | DY31: =IF(AND(126>=$B$5,126<=$D$5),1,0) | DZ31: =IF(AND(127>=$B$5,127<=$D$5),1,0) | EA31: =IF(AND(128>=$B$5,128<=$D$5),1,0) | EB31: =IF(AND(129>=$B$5,129<=$D$5),1,0) | EC31: =IF(AND(130>=$B$5,130<=$D$5),1,0) | ED31: =IF(AND(131>=$B$5,131<=$D$5),1,0) | EE31: =IF(AND(132>=$B$5,132<=$D$5),1,0) | EF31: =IF(AND(133>=$B$5,133<=$D$5),1,0) | EG31: =IF(AND(134>=$B$5,134<=$D$5),1,0) | EH31: =IF(AND(135>=$B$5,135<=$D$5),1,0) | EI31: =IF(AND(136>=$B$5,136<=$D$5),1,0) | EJ31: =IF(AND(137>=$B$5,137<=$D$5),1,0) | EK31: =IF(AND(138>=$B$5,138<=$D$5),1,0) | EL31: =IF(AND(139>=$B$5,139<=$D$5),1,0) | EM31: =IF(AND(140>=$B$5,140<=$D$5),1,0) | EN31: =IF(AND(141>=$B$5,141<=$D$5),1,0) | EO31: =IF(AND(142>=$B$5,142<=$D$5),1,0) | EP31: =IF(AND(143>=$B$5,143<=$D$5),1,0) | EQ31: =IF(AND(144>=$B$5,144<=$D$5),1,0) | ER31: =IF(AND(145>=$B$5,145<=$D$5),1,0) | ES31: =IF(AND(146>=$B$5,146<=$D$5),1,0) | ET31: =IF(AND(147>=$B$5,147<=$D$5),1,0) | EU31: =IF(AND(148>=$B$5,148<=$D$5),1,0) | EV31: =IF(AND(149>=$B$5,149<=$D$5),1,0) | EW31: =IF(AND(150>=$B$5,150<=$D$5),1,0) | EX31: =IF(AND(151>=$B$5,151<=$D$5),1,0) | EY31: =IF(AND(152>=$B$5,152<=$D$5),1,0) | EZ31: =IF(AND(153>=$B$5,153<=$D$5),1,0) | FA31: =IF(AND(154>=$B$5,154<=$D$5),1,0) | FB31: =IF(AND(155>=$B$5,155<=$D$5),1,0) | FC31: =IF(AND(156>=$B$5,156<=$D$5),1,0) | FD31: =IF(AND(157>=$B$5,157<=$D$5),1,0) | FE31: =IF(AND(158>=$B$5,158<=$D$5),1,0) | FF31: =IF(AND(159>=$B$5,159<=$D$5),1,0) | FG31: =IF(AND(160>=$B$5,160<=$D$5),1,0) | FH31: =IF(AND(161>=$B$5,161<=$D$5),1,0) | FI31: =IF(AND(162>=$B$5,162<=$D$5),1,0) | FJ31: =IF(AND(163>=$B$5,163<=$D$5),1,0) | FK31: =IF(AND(164>=$B$5,164<=$D$5),1,0) | FL31: =IF(AND(165>=$B$5,165<=$D$5),1,0) | FM31: =IF(AND(166>=$B$5,166<=$D$5),1,0) | FN31: =IF(AND(167>=$B$5,167<=$D$5),1,0) | FO31: =IF(AND(168>=$B$5,168<=$D$5),1,0) | FP31: =IF(AND(169>=$B$5,169<=$D$5),1,0) | FQ31: =IF(AND(170>=$B$5,170<=$D$5),1,0) | FR31: =IF(AND(171>=$B$5,171<=$D$5),1,0) | FS31: =IF(AND(172>=$B$5,172<=$D$5),1,0) | FT31: =IF(AND(173>=$B$5,173<=$D$5),1,0) | FU31: =IF(AND(174>=$B$5,174<=$D$5),1,0) | FV31: =IF(AND(175>=$B$5,175<=$D$5),1,0) | FW31: =IF(AND(176>=$B$5,176<=$D$5),1,0) | FX31: =IF(AND(177>=$B$5,177<=$D$5),1,0) | FY31: =IF(AND(178>=$B$5,178<=$D$5),1,0) | FZ31: =IF(AND(179>=$B$5,179<=$D$5),1,0) | GA31: =IF(AND(180>=$B$5,180<=$D$5),1,0) | GB31: =IF(AND(181>=$B$5,181<=$D$5),1,0) | GC31: =IF(AND(182>=$B$5,182<=$D$5),1,0) | GD31: =IF(AND(183>=$B$5,183<=$D$5),1,0) | GE31: =IF(AND(184>=$B$5,184<=$D$5),1,0) | GF31: =IF(AND(185>=$B$5,185<=$D$5),1,0) | GG31: =IF(AND(186>=$B$5,186<=$D$5),1,0) | GH31: =IF(AND(187>=$B$5,187<=$D$5),1,0) | GI31: =IF(AND(188>=$B$5,188<=$D$5),1,0) | GJ31: =IF(AND(189>=$B$5,189<=$D$5),1,0) | GK31: =IF(AND(190>=$B$5,190<=$D$5),1,0) | GL31: =IF(AND(191>=$B$5,191<=$D$5),1,0) | GM31: =IF(AND(192>=$B$5,192<=$D$5),1,0) | GN31: =IF(AND(193>=$B$5,193<=$D$5),1,0) | GO31: =IF(AND(194>=$B$5,194<=$D$5),1,0) | GP31: =IF(AND(195>=$B$5,195<=$D$5),1,0) | GQ31: =IF(AND(196>=$B$5,196<=$D$5),1,0) | GR31: =IF(AND(197>=$B$5,197<=$D$5),1,0) | GS31: =IF(AND(198>=$B$5,198<=$D$5),1,0) | GT31: =IF(AND(199>=$B$5,199<=$D$5),1,0) | GU31: =IF(AND(200>=$B$5,200<=$D$5),1,0) | GV31: =IF(AND(201>=$B$5,201<=$D$5),1,0) | GW31: =IF(AND(202>=$B$5,202<=$D$5),1,0) | GX31: =IF(AND(203>=$B$5,203<=$D$5),1,0) | GY31: =IF(AND(204>=$B$5,204<=$D$5),1,0) | GZ31: =IF(AND(205>=$B$5,205<=$D$5),1,0) | HA31: =IF(AND(206>=$B$5,206<=$D$5),1,0) | HB31: =IF(AND(207>=$B$5,207<=$D$5),1,0) | HC31: =IF(AND(208>=$B$5,208<=$D$5),1,0) | HD31: =IF(AND(209>=$B$5,209<=$D$5),1,0) | HE31: =IF(AND(210>=$B$5,210<=$D$5),1,0) | HF31: =IF(AND(211>=$B$5,211<=$D$5),1,0) | HG31: =IF(AND(212>=$B$5,212<=$D$5),1,0) | HH31: =IF(AND(213>=$B$5,213<=$D$5),1,0) | HI31: =IF(AND(214>=$B$5,214<=$D$5),1,0) | HJ31: =IF(AND(215>=$B$5,215<=$D$5),1,0) | HK31: =IF(AND(216>=$B$5,216<=$D$5),1,0) | HL31: =IF(AND(217>=$B$5,217<=$D$5),1,0) | HM31: =IF(AND(218>=$B$5,218<=$D$5),1,0) | HN31: =IF(AND(219>=$B$5,219<=$D$5),1,0) | HO31: =IF(AND(220>=$B$5,220<=$D$5),1,0) | HP31: =IF(AND(221>=$B$5,221<=$D$5),1,0) | HQ31: =IF(AND(222>=$B$5,222<=$D$5),1,0) | HR31: =IF(AND(223>=$B$5,223<=$D$5),1,0) | HS31: =IF(AND(224>=$B$5,224<=$D$5),1,0) | HT31: =IF(AND(225>=$B$5,225<=$D$5),1,0) | HU31: =IF(AND(226>=$B$5,226<=$D$5),1,0) | HV31: =IF(AND(227>=$B$5,227<=$D$5),1,0) | HW31: =IF(AND(228>=$B$5,228<=$D$5),1,0) | HX31: =IF(AND(229>=$B$5,229<=$D$5),1,0) | HY31: =IF(AND(230>=$B$5,230<=$D$5),1,0) | HZ31: =IF(AND(231>=$B$5,231<=$D$5),1,0) | IA31: =IF(AND(232>=$B$5,232<=$D$5),1,0) | IB31: =IF(AND(233>=$B$5,233<=$D$5),1,0) | IC31: =IF(AND(234>=$B$5,234<=$D$5),1,0) | ID31: =IF(AND(235>=$B$5,235<=$D$5),1,0) | IE31: =IF(AND(236>=$B$5,236<=$D$5),1,0) | IF31: =IF(AND(237>=$B$5,237<=$D$5),1,0) | IG31: =IF(AND(238>=$B$5,238<=$D$5),1,0) | IH31: =IF(AND(239>=$B$5,239<=$D$5),1,0) | II31: =IF(AND(240>=$B$5,240<=$D$5),1,0) | IJ31: =IF(AND(241>=$B$5,241<=$D$5),1,0) | IK31: =IF(AND(242>=$B$5,242<=$D$5),1,0) | IL31: =IF(AND(243>=$B$5,243<=$D$5),1,0) | IM31: =IF(AND(244>=$B$5,244<=$D$5),1,0) | IN31: =IF(AND(245>=$B$5,245<=$D$5),1,0) | IO31: =IF(AND(246>=$B$5,246<=$D$5),1,0) | IP31: =IF(AND(247>=$B$5,247<=$D$5),1,0) | IQ31: =IF(AND(248>=$B$5,248<=$D$5),1,0) | IR31: =IF(AND(249>=$B$5,249<=$D$5),1,0) | IS31: =IF(AND(250>=$B$5,250<=$D$5),1,0) | IT31: =IF(AND(251>=$B$5,251<=$D$5),1,0) | IU31: =IF(AND(252>=$B$5,252<=$D$5),1,0) | IV31: =IF(AND(253>=$B$5,253<=$D$5),1,0) | IW31: =IF(AND(254>=$B$5,254<=$D$5),1,0) | IX31: =IF(AND(255>=$B$5,255<=$D$5),1,0) | IY31: =IF(AND(256>=$B$5,256<=$D$5),1,0) | IZ31: =IF(AND(257>=$B$5,257<=$D$5),1,0) | JA31: =IF(AND(258>=$B$5,258<=$D$5),1,0) | JB31: =IF(AND(259>=$B$5,259<=$D$5),1,0) | JC31: =IF(AND(260>=$B$5,260<=$D$5),1,0) | JD31: =IF(AND(261>=$B$5,261<=$D$5),1,0) | JE31: =IF(AND(262>=$B$5,262<=$D$5),1,0) | JF31: =IF(AND(263>=$B$5,263<=$D$5),1,0) | JG31: =IF(AND(264>=$B$5,264<=$D$5),1,0) | JH31: =IF(AND(265>=$B$5,265<=$D$5),1,0) | JI31: =IF(AND(266>=$B$5,266<=$D$5),1,0) | JJ31: =IF(AND(267>=$B$5,267<=$D$5),1,0) | JK31: =IF(AND(268>=$B$5,268<=$D$5),1,0) | JL31: =IF(AND(269>=$B$5,269<=$D$5),1,0) | JM31: =IF(AND(270>=$B$5,270<=$D$5),1,0) | JN31: =IF(AND(271>=$B$5,271<=$D$5),1,0) | JO31: =IF(AND(272>=$B$5,272<=$D$5),1,0) | JP31: =IF(AND(273>=$B$5,273<=$D$5),1,0) | JQ31: =IF(AND(274>=$B$5,274<=$D$5),1,0) | JR31: =IF(AND(275>=$B$5,275<=$D$5),1,0) | JS31: =IF(AND(276>=$B$5,276<=$D$5),1,0) | JT31: =IF(AND(277>=$B$5,277<=$D$5),1,0) | JU31: =IF(AND(278>=$B$5,278<=$D$5),1,0) | JV31: =IF(AND(279>=$B$5,279<=$D$5),1,0) | JW31: =IF(AND(280>=$B$5,280<=$D$5),1,0) | JX31: =IF(AND(281>=$B$5,281<=$D$5),1,0) | JY31: =IF(AND(282>=$B$5,282<=$D$5),1,0) | JZ31: =IF(AND(283>=$B$5,283<=$D$5),1,0) | KA31: =IF(AND(284>=$B$5,284<=$D$5),1,0) | KB31: =IF(AND(285>=$B$5,285<=$D$5),1,0) | KC31: =IF(AND(286>=$B$5,286<=$D$5),1,0) | KD31: =IF(AND(287>=$B$5,287<=$D$5),1,0) | KE31: =IF(AND(288>=$B$5,288<=$D$5),1,0) | KF31: =IF(AND(289>=$B$5,289<=$D$5),1,0) | KG31: =IF(AND(290>=$B$5,290<=$D$5),1,0) | KH31: =IF(AND(291>=$B$5,291<=$D$5),1,0) | KI31: =IF(AND(292>=$B$5,292<=$D$5),1,0) | KJ31: =IF(AND(293>=$B$5,293<=$D$5),1,0) | KK31: =IF(AND(294>=$B$5,294<=$D$5),1,0) | KL31: =IF(AND(295>=$B$5,295<=$D$5),1,0) | KM31: =IF(AND(296>=$B$5,296<=$D$5),1,0) | KN31: =IF(AND(297>=$B$5,297<=$D$5),1,0) | KO31: =IF(AND(298>=$B$5,298<=$D$5),1,0) | KP31: =IF(AND(299>=$B$5,299<=$D$5),1,0) | KQ31: =IF(AND(300>=$B$5,300<=$D$5),1,0) | KR31: =IF(AND(301>=$B$5,301<=$D$5),1,0) | KS31: =IF(AND(302>=$B$5,302<=$D$5),1,0) | KT31: =IF(AND(303>=$B$5,303<=$D$5),1,0) | KU31: =IF(AND(304>=$B$5,304<=$D$5),1,0) | KV31: =IF(AND(305>=$B$5,305<=$D$5),1,0) | KW31: =IF(AND(306>=$B$5,306<=$D$5),1,0) | KX31: =IF(AND(307>=$B$5,307<=$D$5),1,0) | KY31: =IF(AND(308>=$B$5,308<=$D$5),1,0) | KZ31: =IF(AND(309>=$B$5,309<=$D$5),1,0) | LA31: =IF(AND(310>=$B$5,310<=$D$5),1,0) | LB31: =IF(AND(311>=$B$5,311<=$D$5),1,0) | LC31: =IF(AND(312>=$B$5,312<=$D$5),1,0) | LD31: =IF(AND(313>=$B$5,313<=$D$5),1,0) | LE31: =IF(AND(314>=$B$5,314<=$D$5),1,0) | LF31: =IF(AND(315>=$B$5,315<=$D$5),1,0) | LG31: =IF(AND(316>=$B$5,316<=$D$5),1,0) | LH31: =IF(AND(317>=$B$5,317<=$D$5),1,0) | LI31: =IF(AND(318>=$B$5,318<=$D$5),1,0) | LJ31: =IF(AND(319>=$B$5,319<=$D$5),1,0) | LK31: =IF(AND(320>=$B$5,320<=$D$5),1,0) | LL31: =IF(AND(321>=$B$5,321<=$D$5),1,0) | LM31: =IF(AND(322>=$B$5,322<=$D$5),1,0) | LN31: =IF(AND(323>=$B$5,323<=$D$5),1,0) | LO31: =IF(AND(324>=$B$5,324<=$D$5),1,0) | LP31: =IF(AND(325>=$B$5,325<=$D$5),1,0) | LQ31: =IF(AND(326>=$B$5,326<=$D$5),1,0) | LR31: =IF(AND(327>=$B$5,327<=$D$5),1,0) | LS31: =IF(AND(328>=$B$5,328<=$D$5),1,0) | LT31: =IF(AND(329>=$B$5,329<=$D$5),1,0) | LU31: =IF(AND(330>=$B$5,330<=$D$5),1,0) | LV31: =IF(AND(331>=$B$5,331<=$D$5),1,0) | LW31: =IF(AND(332>=$B$5,332<=$D$5),1,0) | LX31: =IF(AND(333>=$B$5,333<=$D$5),1,0) | LY31: =IF(AND(334>=$B$5,334<=$D$5),1,0) | LZ31: =IF(AND(335>=$B$5,335<=$D$5),1,0) | MA31: =IF(AND(336>=$B$5,336<=$D$5),1,0) | MB31: =IF(AND(337>=$B$5,337<=$D$5),1,0) | MC31: =IF(AND(338>=$B$5,338<=$D$5),1,0) | MD31: =IF(AND(339>=$B$5,339<=$D$5),1,0) | ME31: =IF(AND(340>=$B$5,340<=$D$5),1,0) | MF31: =IF(AND(341>=$B$5,341<=$D$5),1,0) | MG31: =IF(AND(342>=$B$5,342<=$D$5),1,0) | MH31: =IF(AND(343>=$B$5,343<=$D$5),1,0) | MI31: =IF(AND(344>=$B$5,344<=$D$5),1,0) | MJ31: =IF(AND(345>=$B$5,345<=$D$5),1,0) | MK31: =IF(AND(346>=$B$5,346<=$D$5),1,0) | ML31: =IF(AND(347>=$B$5,347<=$D$5),1,0) | MM31: =IF(AND(348>=$B$5,348<=$D$5),1,0) | MN31: =IF(AND(349>=$B$5,349<=$D$5),1,0) | MO31: =IF(AND(350>=$B$5,350<=$D$5),1,0) | MP31: =IF(AND(351>=$B$5,351<=$D$5),1,0) | MQ31: =IF(AND(352>=$B$5,352<=$D$5),1,0) | MR31: =IF(AND(353>=$B$5,353<=$D$5),1,0) | MS31: =IF(AND(354>=$B$5,354<=$D$5),1,0) | MT31: =IF(AND(355>=$B$5,355<=$D$5),1,0) | MU31: =IF(AND(356>=$B$5,356<=$D$5),1,0) | MV31: =IF(AND(357>=$B$5,357<=$D$5),1,0) | MW31: =IF(AND(358>=$B$5,358<=$D$5),1,0) | MX31: =IF(AND(359>=$B$5,359<=$D$5),1,0) | MY31: =IF(AND(360>=$B$5,360<=$D$5),1,0) | MZ31: =IF(AND(361>=$B$5,361<=$D$5),1,0) | NA31: =IF(AND(362>=$B$5,362<=$D$5),1,0) | NB31: =IF(AND(363>=$B$5,363<=$D$5),1,0) | NC31: =IF(AND(364>=$B$5,364<=$D$5),1,0) | ND31: =IF(AND(365>=$B$5,365<=$D$5),1,0) | NE31: =IF(AND(366>=$B$5,366<=$D$5),1,0) | NF31: =IF(AND(367>=$B$5,367<=$D$5),1,0) | NG31: =IF(AND(368>=$B$5,368<=$D$5),1,0) | NH31: =IF(AND(369>=$B$5,369<=$D$5),1,0) | NI31: =IF(AND(370>=$B$5,370<=$D$5),1,0) | NJ31: =IF(AND(371>=$B$5,371<=$D$5),1,0) | NK31: =IF(AND(372>=$B$5,372<=$D$5),1,0)
A32: Flag: Entitlement | D32: =IF(AND(1>=$B$6,1<=$D$6),1,0) | E32: =IF(AND(2>=$B$6,2<=$D$6),1,0) | F32: =IF(AND(3>=$B$6,3<=$D$6),1,0) | G32: =IF(AND(4>=$B$6,4<=$D$6),1,0) | H32: =IF(AND(5>=$B$6,5<=$D$6),1,0) | I32: =IF(AND(6>=$B$6,6<=$D$6),1,0) | J32: =IF(AND(7>=$B$6,7<=$D$6),1,0) | K32: =IF(AND(8>=$B$6,8<=$D$6),1,0) | L32: =IF(AND(9>=$B$6,9<=$D$6),1,0) | M32: =IF(AND(10>=$B$6,10<=$D$6),1,0) | N32: =IF(AND(11>=$B$6,11<=$D$6),1,0) | O32: =IF(AND(12>=$B$6,12<=$D$6),1,0) | P32: =IF(AND(13>=$B$6,13<=$D$6),1,0) | Q32: =IF(AND(14>=$B$6,14<=$D$6),1,0) | R32: =IF(AND(15>=$B$6,15<=$D$6),1,0) | S32: =IF(AND(16>=$B$6,16<=$D$6),1,0) | T32: =IF(AND(17>=$B$6,17<=$D$6),1,0) | U32: =IF(AND(18>=$B$6,18<=$D$6),1,0) | V32: =IF(AND(19>=$B$6,19<=$D$6),1,0) | W32: =IF(AND(20>=$B$6,20<=$D$6),1,0) | X32: =IF(AND(21>=$B$6,21<=$D$6),1,0) | Y32: =IF(AND(22>=$B$6,22<=$D$6),1,0) | Z32: =IF(AND(23>=$B$6,23<=$D$6),1,0) | AA32: =IF(AND(24>=$B$6,24<=$D$6),1,0) | AB32: =IF(AND(25>=$B$6,25<=$D$6),1,0) | AC32: =IF(AND(26>=$B$6,26<=$D$6),1,0) | AD32: =IF(AND(27>=$B$6,27<=$D$6),1,0) | AE32: =IF(AND(28>=$B$6,28<=$D$6),1,0) | AF32: =IF(AND(29>=$B$6,29<=$D$6),1,0) | AG32: =IF(AND(30>=$B$6,30<=$D$6),1,0) | AH32: =IF(AND(31>=$B$6,31<=$D$6),1,0) | AI32: =IF(AND(32>=$B$6,32<=$D$6),1,0) | AJ32: =IF(AND(33>=$B$6,33<=$D$6),1,0) | AK32: =IF(AND(34>=$B$6,34<=$D$6),1,0) | AL32: =IF(AND(35>=$B$6,35<=$D$6),1,0) | AM32: =IF(AND(36>=$B$6,36<=$D$6),1,0) | AN32: =IF(AND(37>=$B$6,37<=$D$6),1,0) | AO32: =IF(AND(38>=$B$6,38<=$D$6),1,0) | AP32: =IF(AND(39>=$B$6,39<=$D$6),1,0) | AQ32: =IF(AND(40>=$B$6,40<=$D$6),1,0) | AR32: =IF(AND(41>=$B$6,41<=$D$6),1,0) | AS32: =IF(AND(42>=$B$6,42<=$D$6),1,0) | AT32: =IF(AND(43>=$B$6,43<=$D$6),1,0) | AU32: =IF(AND(44>=$B$6,44<=$D$6),1,0) | AV32: =IF(AND(45>=$B$6,45<=$D$6),1,0) | AW32: =IF(AND(46>=$B$6,46<=$D$6),1,0) | AX32: =IF(AND(47>=$B$6,47<=$D$6),1,0) | AY32: =IF(AND(48>=$B$6,48<=$D$6),1,0) | AZ32: =IF(AND(49>=$B$6,49<=$D$6),1,0) | BA32: =IF(AND(50>=$B$6,50<=$D$6),1,0) | BB32: =IF(AND(51>=$B$6,51<=$D$6),1,0) | BC32: =IF(AND(52>=$B$6,52<=$D$6),1,0) | BD32: =IF(AND(53>=$B$6,53<=$D$6),1,0) | BE32: =IF(AND(54>=$B$6,54<=$D$6),1,0) | BF32: =IF(AND(55>=$B$6,55<=$D$6),1,0) | BG32: =IF(AND(56>=$B$6,56<=$D$6),1,0) | BH32: =IF(AND(57>=$B$6,57<=$D$6),1,0) | BI32: =IF(AND(58>=$B$6,58<=$D$6),1,0) | BJ32: =IF(AND(59>=$B$6,59<=$D$6),1,0) | BK32: =IF(AND(60>=$B$6,60<=$D$6),1,0) | BL32: =IF(AND(61>=$B$6,61<=$D$6),1,0) | BM32: =IF(AND(62>=$B$6,62<=$D$6),1,0) | BN32: =IF(AND(63>=$B$6,63<=$D$6),1,0) | BO32: =IF(AND(64>=$B$6,64<=$D$6),1,0) | BP32: =IF(AND(65>=$B$6,65<=$D$6),1,0) | BQ32: =IF(AND(66>=$B$6,66<=$D$6),1,0) | BR32: =IF(AND(67>=$B$6,67<=$D$6),1,0) | BS32: =IF(AND(68>=$B$6,68<=$D$6),1,0) | BT32: =IF(AND(69>=$B$6,69<=$D$6),1,0) | BU32: =IF(AND(70>=$B$6,70<=$D$6),1,0) | BV32: =IF(AND(71>=$B$6,71<=$D$6),1,0) | BW32: =IF(AND(72>=$B$6,72<=$D$6),1,0) | BX32: =IF(AND(73>=$B$6,73<=$D$6),1,0) | BY32: =IF(AND(74>=$B$6,74<=$D$6),1,0) | BZ32: =IF(AND(75>=$B$6,75<=$D$6),1,0) | CA32: =IF(AND(76>=$B$6,76<=$D$6),1,0) | CB32: =IF(AND(77>=$B$6,77<=$D$6),1,0) | CC32: =IF(AND(78>=$B$6,78<=$D$6),1,0) | CD32: =IF(AND(79>=$B$6,79<=$D$6),1,0) | CE32: =IF(AND(80>=$B$6,80<=$D$6),1,0) | CF32: =IF(AND(81>=$B$6,81<=$D$6),1,0) | CG32: =IF(AND(82>=$B$6,82<=$D$6),1,0) | CH32: =IF(AND(83>=$B$6,83<=$D$6),1,0) | CI32: =IF(AND(84>=$B$6,84<=$D$6),1,0) | CJ32: =IF(AND(85>=$B$6,85<=$D$6),1,0) | CK32: =IF(AND(86>=$B$6,86<=$D$6),1,0) | CL32: =IF(AND(87>=$B$6,87<=$D$6),1,0) | CM32: =IF(AND(88>=$B$6,88<=$D$6),1,0) | CN32: =IF(AND(89>=$B$6,89<=$D$6),1,0) | CO32: =IF(AND(90>=$B$6,90<=$D$6),1,0) | CP32: =IF(AND(91>=$B$6,91<=$D$6),1,0) | CQ32: =IF(AND(92>=$B$6,92<=$D$6),1,0) | CR32: =IF(AND(93>=$B$6,93<=$D$6),1,0) | CS32: =IF(AND(94>=$B$6,94<=$D$6),1,0) | CT32: =IF(AND(95>=$B$6,95<=$D$6),1,0) | CU32: =IF(AND(96>=$B$6,96<=$D$6),1,0) | CV32: =IF(AND(97>=$B$6,97<=$D$6),1,0) | CW32: =IF(AND(98>=$B$6,98<=$D$6),1,0) | CX32: =IF(AND(99>=$B$6,99<=$D$6),1,0) | CY32: =IF(AND(100>=$B$6,100<=$D$6),1,0) | CZ32: =IF(AND(101>=$B$6,101<=$D$6),1,0) | DA32: =IF(AND(102>=$B$6,102<=$D$6),1,0) | DB32: =IF(AND(103>=$B$6,103<=$D$6),1,0) | DC32: =IF(AND(104>=$B$6,104<=$D$6),1,0) | DD32: =IF(AND(105>=$B$6,105<=$D$6),1,0) | DE32: =IF(AND(106>=$B$6,106<=$D$6),1,0) | DF32: =IF(AND(107>=$B$6,107<=$D$6),1,0) | DG32: =IF(AND(108>=$B$6,108<=$D$6),1,0) | DH32: =IF(AND(109>=$B$6,109<=$D$6),1,0) | DI32: =IF(AND(110>=$B$6,110<=$D$6),1,0) | DJ32: =IF(AND(111>=$B$6,111<=$D$6),1,0) | DK32: =IF(AND(112>=$B$6,112<=$D$6),1,0) | DL32: =IF(AND(113>=$B$6,113<=$D$6),1,0) | DM32: =IF(AND(114>=$B$6,114<=$D$6),1,0) | DN32: =IF(AND(115>=$B$6,115<=$D$6),1,0) | DO32: =IF(AND(116>=$B$6,116<=$D$6),1,0) | DP32: =IF(AND(117>=$B$6,117<=$D$6),1,0) | DQ32: =IF(AND(118>=$B$6,118<=$D$6),1,0) | DR32: =IF(AND(119>=$B$6,119<=$D$6),1,0) | DS32: =IF(AND(120>=$B$6,120<=$D$6),1,0) | DT32: =IF(AND(121>=$B$6,121<=$D$6),1,0) | DU32: =IF(AND(122>=$B$6,122<=$D$6),1,0) | DV32: =IF(AND(123>=$B$6,123<=$D$6),1,0) | DW32: =IF(AND(124>=$B$6,124<=$D$6),1,0) | DX32: =IF(AND(125>=$B$6,125<=$D$6),1,0) | DY32: =IF(AND(126>=$B$6,126<=$D$6),1,0) | DZ32: =IF(AND(127>=$B$6,127<=$D$6),1,0) | EA32: =IF(AND(128>=$B$6,128<=$D$6),1,0) | EB32: =IF(AND(129>=$B$6,129<=$D$6),1,0) | EC32: =IF(AND(130>=$B$6,130<=$D$6),1,0) | ED32: =IF(AND(131>=$B$6,131<=$D$6),1,0) | EE32: =IF(AND(132>=$B$6,132<=$D$6),1,0) | EF32: =IF(AND(133>=$B$6,133<=$D$6),1,0) | EG32: =IF(AND(134>=$B$6,134<=$D$6),1,0) | EH32: =IF(AND(135>=$B$6,135<=$D$6),1,0) | EI32: =IF(AND(136>=$B$6,136<=$D$6),1,0) | EJ32: =IF(AND(137>=$B$6,137<=$D$6),1,0) | EK32: =IF(AND(138>=$B$6,138<=$D$6),1,0) | EL32: =IF(AND(139>=$B$6,139<=$D$6),1,0) | EM32: =IF(AND(140>=$B$6,140<=$D$6),1,0) | EN32: =IF(AND(141>=$B$6,141<=$D$6),1,0) | EO32: =IF(AND(142>=$B$6,142<=$D$6),1,0) | EP32: =IF(AND(143>=$B$6,143<=$D$6),1,0) | EQ32: =IF(AND(144>=$B$6,144<=$D$6),1,0) | ER32: =IF(AND(145>=$B$6,145<=$D$6),1,0) | ES32: =IF(AND(146>=$B$6,146<=$D$6),1,0) | ET32: =IF(AND(147>=$B$6,147<=$D$6),1,0) | EU32: =IF(AND(148>=$B$6,148<=$D$6),1,0) | EV32: =IF(AND(149>=$B$6,149<=$D$6),1,0) | EW32: =IF(AND(150>=$B$6,150<=$D$6),1,0) | EX32: =IF(AND(151>=$B$6,151<=$D$6),1,0) | EY32: =IF(AND(152>=$B$6,152<=$D$6),1,0) | EZ32: =IF(AND(153>=$B$6,153<=$D$6),1,0) | FA32: =IF(AND(154>=$B$6,154<=$D$6),1,0) | FB32: =IF(AND(155>=$B$6,155<=$D$6),1,0) | FC32: =IF(AND(156>=$B$6,156<=$D$6),1,0) | FD32: =IF(AND(157>=$B$6,157<=$D$6),1,0) | FE32: =IF(AND(158>=$B$6,158<=$D$6),1,0) | FF32: =IF(AND(159>=$B$6,159<=$D$6),1,0) | FG32: =IF(AND(160>=$B$6,160<=$D$6),1,0) | FH32: =IF(AND(161>=$B$6,161<=$D$6),1,0) | FI32: =IF(AND(162>=$B$6,162<=$D$6),1,0) | FJ32: =IF(AND(163>=$B$6,163<=$D$6),1,0) | FK32: =IF(AND(164>=$B$6,164<=$D$6),1,0) | FL32: =IF(AND(165>=$B$6,165<=$D$6),1,0) | FM32: =IF(AND(166>=$B$6,166<=$D$6),1,0) | FN32: =IF(AND(167>=$B$6,167<=$D$6),1,0) | FO32: =IF(AND(168>=$B$6,168<=$D$6),1,0) | FP32: =IF(AND(169>=$B$6,169<=$D$6),1,0) | FQ32: =IF(AND(170>=$B$6,170<=$D$6),1,0) | FR32: =IF(AND(171>=$B$6,171<=$D$6),1,0) | FS32: =IF(AND(172>=$B$6,172<=$D$6),1,0) | FT32: =IF(AND(173>=$B$6,173<=$D$6),1,0) | FU32: =IF(AND(174>=$B$6,174<=$D$6),1,0) | FV32: =IF(AND(175>=$B$6,175<=$D$6),1,0) | FW32: =IF(AND(176>=$B$6,176<=$D$6),1,0) | FX32: =IF(AND(177>=$B$6,177<=$D$6),1,0) | FY32: =IF(AND(178>=$B$6,178<=$D$6),1,0) | FZ32: =IF(AND(179>=$B$6,179<=$D$6),1,0) | GA32: =IF(AND(180>=$B$6,180<=$D$6),1,0) | GB32: =IF(AND(181>=$B$6,181<=$D$6),1,0) | GC32: =IF(AND(182>=$B$6,182<=$D$6),1,0) | GD32: =IF(AND(183>=$B$6,183<=$D$6),1,0) | GE32: =IF(AND(184>=$B$6,184<=$D$6),1,0) | GF32: =IF(AND(185>=$B$6,185<=$D$6),1,0) | GG32: =IF(AND(186>=$B$6,186<=$D$6),1,0) | GH32: =IF(AND(187>=$B$6,187<=$D$6),1,0) | GI32: =IF(AND(188>=$B$6,188<=$D$6),1,0) | GJ32: =IF(AND(189>=$B$6,189<=$D$6),1,0) | GK32: =IF(AND(190>=$B$6,190<=$D$6),1,0) | GL32: =IF(AND(191>=$B$6,191<=$D$6),1,0) | GM32: =IF(AND(192>=$B$6,192<=$D$6),1,0) | GN32: =IF(AND(193>=$B$6,193<=$D$6),1,0) | GO32: =IF(AND(194>=$B$6,194<=$D$6),1,0) | GP32: =IF(AND(195>=$B$6,195<=$D$6),1,0) | GQ32: =IF(AND(196>=$B$6,196<=$D$6),1,0) | GR32: =IF(AND(197>=$B$6,197<=$D$6),1,0) | GS32: =IF(AND(198>=$B$6,198<=$D$6),1,0) | GT32: =IF(AND(199>=$B$6,199<=$D$6),1,0) | GU32: =IF(AND(200>=$B$6,200<=$D$6),1,0) | GV32: =IF(AND(201>=$B$6,201<=$D$6),1,0) | GW32: =IF(AND(202>=$B$6,202<=$D$6),1,0) | GX32: =IF(AND(203>=$B$6,203<=$D$6),1,0) | GY32: =IF(AND(204>=$B$6,204<=$D$6),1,0) | GZ32: =IF(AND(205>=$B$6,205<=$D$6),1,0) | HA32: =IF(AND(206>=$B$6,206<=$D$6),1,0) | HB32: =IF(AND(207>=$B$6,207<=$D$6),1,0) | HC32: =IF(AND(208>=$B$6,208<=$D$6),1,0) | HD32: =IF(AND(209>=$B$6,209<=$D$6),1,0) | HE32: =IF(AND(210>=$B$6,210<=$D$6),1,0) | HF32: =IF(AND(211>=$B$6,211<=$D$6),1,0) | HG32: =IF(AND(212>=$B$6,212<=$D$6),1,0) | HH32: =IF(AND(213>=$B$6,213<=$D$6),1,0) | HI32: =IF(AND(214>=$B$6,214<=$D$6),1,0) | HJ32: =IF(AND(215>=$B$6,215<=$D$6),1,0) | HK32: =IF(AND(216>=$B$6,216<=$D$6),1,0) | HL32: =IF(AND(217>=$B$6,217<=$D$6),1,0) | HM32: =IF(AND(218>=$B$6,218<=$D$6),1,0) | HN32: =IF(AND(219>=$B$6,219<=$D$6),1,0) | HO32: =IF(AND(220>=$B$6,220<=$D$6),1,0) | HP32: =IF(AND(221>=$B$6,221<=$D$6),1,0) | HQ32: =IF(AND(222>=$B$6,222<=$D$6),1,0) | HR32: =IF(AND(223>=$B$6,223<=$D$6),1,0) | HS32: =IF(AND(224>=$B$6,224<=$D$6),1,0) | HT32: =IF(AND(225>=$B$6,225<=$D$6),1,0) | HU32: =IF(AND(226>=$B$6,226<=$D$6),1,0) | HV32: =IF(AND(227>=$B$6,227<=$D$6),1,0) | HW32: =IF(AND(228>=$B$6,228<=$D$6),1,0) | HX32: =IF(AND(229>=$B$6,229<=$D$6),1,0) | HY32: =IF(AND(230>=$B$6,230<=$D$6),1,0) | HZ32: =IF(AND(231>=$B$6,231<=$D$6),1,0) | IA32: =IF(AND(232>=$B$6,232<=$D$6),1,0) | IB32: =IF(AND(233>=$B$6,233<=$D$6),1,0) | IC32: =IF(AND(234>=$B$6,234<=$D$6),1,0) | ID32: =IF(AND(235>=$B$6,235<=$D$6),1,0) | IE32: =IF(AND(236>=$B$6,236<=$D$6),1,0) | IF32: =IF(AND(237>=$B$6,237<=$D$6),1,0) | IG32: =IF(AND(238>=$B$6,238<=$D$6),1,0) | IH32: =IF(AND(239>=$B$6,239<=$D$6),1,0) | II32: =IF(AND(240>=$B$6,240<=$D$6),1,0) | IJ32: =IF(AND(241>=$B$6,241<=$D$6),1,0) | IK32: =IF(AND(242>=$B$6,242<=$D$6),1,0) | IL32: =IF(AND(243>=$B$6,243<=$D$6),1,0) | IM32: =IF(AND(244>=$B$6,244<=$D$6),1,0) | IN32: =IF(AND(245>=$B$6,245<=$D$6),1,0) | IO32: =IF(AND(246>=$B$6,246<=$D$6),1,0) | IP32: =IF(AND(247>=$B$6,247<=$D$6),1,0) | IQ32: =IF(AND(248>=$B$6,248<=$D$6),1,0) | IR32: =IF(AND(249>=$B$6,249<=$D$6),1,0) | IS32: =IF(AND(250>=$B$6,250<=$D$6),1,0) | IT32: =IF(AND(251>=$B$6,251<=$D$6),1,0) | IU32: =IF(AND(252>=$B$6,252<=$D$6),1,0) | IV32: =IF(AND(253>=$B$6,253<=$D$6),1,0) | IW32: =IF(AND(254>=$B$6,254<=$D$6),1,0) | IX32: =IF(AND(255>=$B$6,255<=$D$6),1,0) | IY32: =IF(AND(256>=$B$6,256<=$D$6),1,0) | IZ32: =IF(AND(257>=$B$6,257<=$D$6),1,0) | JA32: =IF(AND(258>=$B$6,258<=$D$6),1,0) | JB32: =IF(AND(259>=$B$6,259<=$D$6),1,0) | JC32: =IF(AND(260>=$B$6,260<=$D$6),1,0) | JD32: =IF(AND(261>=$B$6,261<=$D$6),1,0) | JE32: =IF(AND(262>=$B$6,262<=$D$6),1,0) | JF32: =IF(AND(263>=$B$6,263<=$D$6),1,0) | JG32: =IF(AND(264>=$B$6,264<=$D$6),1,0) | JH32: =IF(AND(265>=$B$6,265<=$D$6),1,0) | JI32: =IF(AND(266>=$B$6,266<=$D$6),1,0) | JJ32: =IF(AND(267>=$B$6,267<=$D$6),1,0) | JK32: =IF(AND(268>=$B$6,268<=$D$6),1,0) | JL32: =IF(AND(269>=$B$6,269<=$D$6),1,0) | JM32: =IF(AND(270>=$B$6,270<=$D$6),1,0) | JN32: =IF(AND(271>=$B$6,271<=$D$6),1,0) | JO32: =IF(AND(272>=$B$6,272<=$D$6),1,0) | JP32: =IF(AND(273>=$B$6,273<=$D$6),1,0) | JQ32: =IF(AND(274>=$B$6,274<=$D$6),1,0) | JR32: =IF(AND(275>=$B$6,275<=$D$6),1,0) | JS32: =IF(AND(276>=$B$6,276<=$D$6),1,0) | JT32: =IF(AND(277>=$B$6,277<=$D$6),1,0) | JU32: =IF(AND(278>=$B$6,278<=$D$6),1,0) | JV32: =IF(AND(279>=$B$6,279<=$D$6),1,0) | JW32: =IF(AND(280>=$B$6,280<=$D$6),1,0) | JX32: =IF(AND(281>=$B$6,281<=$D$6),1,0) | JY32: =IF(AND(282>=$B$6,282<=$D$6),1,0) | JZ32: =IF(AND(283>=$B$6,283<=$D$6),1,0) | KA32: =IF(AND(284>=$B$6,284<=$D$6),1,0) | KB32: =IF(AND(285>=$B$6,285<=$D$6),1,0) | KC32: =IF(AND(286>=$B$6,286<=$D$6),1,0) | KD32: =IF(AND(287>=$B$6,287<=$D$6),1,0) | KE32: =IF(AND(288>=$B$6,288<=$D$6),1,0) | KF32: =IF(AND(289>=$B$6,289<=$D$6),1,0) | KG32: =IF(AND(290>=$B$6,290<=$D$6),1,0) | KH32: =IF(AND(291>=$B$6,291<=$D$6),1,0) | KI32: =IF(AND(292>=$B$6,292<=$D$6),1,0) | KJ32: =IF(AND(293>=$B$6,293<=$D$6),1,0) | KK32: =IF(AND(294>=$B$6,294<=$D$6),1,0) | KL32: =IF(AND(295>=$B$6,295<=$D$6),1,0) | KM32: =IF(AND(296>=$B$6,296<=$D$6),1,0) | KN32: =IF(AND(297>=$B$6,297<=$D$6),1,0) | KO32: =IF(AND(298>=$B$6,298<=$D$6),1,0) | KP32: =IF(AND(299>=$B$6,299<=$D$6),1,0) | KQ32: =IF(AND(300>=$B$6,300<=$D$6),1,0) | KR32: =IF(AND(301>=$B$6,301<=$D$6),1,0) | KS32: =IF(AND(302>=$B$6,302<=$D$6),1,0) | KT32: =IF(AND(303>=$B$6,303<=$D$6),1,0) | KU32: =IF(AND(304>=$B$6,304<=$D$6),1,0) | KV32: =IF(AND(305>=$B$6,305<=$D$6),1,0) | KW32: =IF(AND(306>=$B$6,306<=$D$6),1,0) | KX32: =IF(AND(307>=$B$6,307<=$D$6),1,0) | KY32: =IF(AND(308>=$B$6,308<=$D$6),1,0) | KZ32: =IF(AND(309>=$B$6,309<=$D$6),1,0) | LA32: =IF(AND(310>=$B$6,310<=$D$6),1,0) | LB32: =IF(AND(311>=$B$6,311<=$D$6),1,0) | LC32: =IF(AND(312>=$B$6,312<=$D$6),1,0) | LD32: =IF(AND(313>=$B$6,313<=$D$6),1,0) | LE32: =IF(AND(314>=$B$6,314<=$D$6),1,0) | LF32: =IF(AND(315>=$B$6,315<=$D$6),1,0) | LG32: =IF(AND(316>=$B$6,316<=$D$6),1,0) | LH32: =IF(AND(317>=$B$6,317<=$D$6),1,0) | LI32: =IF(AND(318>=$B$6,318<=$D$6),1,0) | LJ32: =IF(AND(319>=$B$6,319<=$D$6),1,0) | LK32: =IF(AND(320>=$B$6,320<=$D$6),1,0) | LL32: =IF(AND(321>=$B$6,321<=$D$6),1,0) | LM32: =IF(AND(322>=$B$6,322<=$D$6),1,0) | LN32: =IF(AND(323>=$B$6,323<=$D$6),1,0) | LO32: =IF(AND(324>=$B$6,324<=$D$6),1,0) | LP32: =IF(AND(325>=$B$6,325<=$D$6),1,0) | LQ32: =IF(AND(326>=$B$6,326<=$D$6),1,0) | LR32: =IF(AND(327>=$B$6,327<=$D$6),1,0) | LS32: =IF(AND(328>=$B$6,328<=$D$6),1,0) | LT32: =IF(AND(329>=$B$6,329<=$D$6),1,0) | LU32: =IF(AND(330>=$B$6,330<=$D$6),1,0) | LV32: =IF(AND(331>=$B$6,331<=$D$6),1,0) | LW32: =IF(AND(332>=$B$6,332<=$D$6),1,0) | LX32: =IF(AND(333>=$B$6,333<=$D$6),1,0) | LY32: =IF(AND(334>=$B$6,334<=$D$6),1,0) | LZ32: =IF(AND(335>=$B$6,335<=$D$6),1,0) | MA32: =IF(AND(336>=$B$6,336<=$D$6),1,0) | MB32: =IF(AND(337>=$B$6,337<=$D$6),1,0) | MC32: =IF(AND(338>=$B$6,338<=$D$6),1,0) | MD32: =IF(AND(339>=$B$6,339<=$D$6),1,0) | ME32: =IF(AND(340>=$B$6,340<=$D$6),1,0) | MF32: =IF(AND(341>=$B$6,341<=$D$6),1,0) | MG32: =IF(AND(342>=$B$6,342<=$D$6),1,0) | MH32: =IF(AND(343>=$B$6,343<=$D$6),1,0) | MI32: =IF(AND(344>=$B$6,344<=$D$6),1,0) | MJ32: =IF(AND(345>=$B$6,345<=$D$6),1,0) | MK32: =IF(AND(346>=$B$6,346<=$D$6),1,0) | ML32: =IF(AND(347>=$B$6,347<=$D$6),1,0) | MM32: =IF(AND(348>=$B$6,348<=$D$6),1,0) | MN32: =IF(AND(349>=$B$6,349<=$D$6),1,0) | MO32: =IF(AND(350>=$B$6,350<=$D$6),1,0) | MP32: =IF(AND(351>=$B$6,351<=$D$6),1,0) | MQ32: =IF(AND(352>=$B$6,352<=$D$6),1,0) | MR32: =IF(AND(353>=$B$6,353<=$D$6),1,0) | MS32: =IF(AND(354>=$B$6,354<=$D$6),1,0) | MT32: =IF(AND(355>=$B$6,355<=$D$6),1,0) | MU32: =IF(AND(356>=$B$6,356<=$D$6),1,0) | MV32: =IF(AND(357>=$B$6,357<=$D$6),1,0) | MW32: =IF(AND(358>=$B$6,358<=$D$6),1,0) | MX32: =IF(AND(359>=$B$6,359<=$D$6),1,0) | MY32: =IF(AND(360>=$B$6,360<=$D$6),1,0) | MZ32: =IF(AND(361>=$B$6,361<=$D$6),1,0) | NA32: =IF(AND(362>=$B$6,362<=$D$6),1,0) | NB32: =IF(AND(363>=$B$6,363<=$D$6),1,0) | NC32: =IF(AND(364>=$B$6,364<=$D$6),1,0) | ND32: =IF(AND(365>=$B$6,365<=$D$6),1,0) | NE32: =IF(AND(366>=$B$6,366<=$D$6),1,0) | NF32: =IF(AND(367>=$B$6,367<=$D$6),1,0) | NG32: =IF(AND(368>=$B$6,368<=$D$6),1,0) | NH32: =IF(AND(369>=$B$6,369<=$D$6),1,0) | NI32: =IF(AND(370>=$B$6,370<=$D$6),1,0) | NJ32: =IF(AND(371>=$B$6,371<=$D$6),1,0) | NK32: =IF(AND(372>=$B$6,372<=$D$6),1,0)
A33: Flag: Pre-Construction | D33: =IF(AND(1>=$B$7,1<=$D$7),1,0) | E33: =IF(AND(2>=$B$7,2<=$D$7),1,0) | F33: =IF(AND(3>=$B$7,3<=$D$7),1,0) | G33: =IF(AND(4>=$B$7,4<=$D$7),1,0) | H33: =IF(AND(5>=$B$7,5<=$D$7),1,0) | I33: =IF(AND(6>=$B$7,6<=$D$7),1,0) | J33: =IF(AND(7>=$B$7,7<=$D$7),1,0) | K33: =IF(AND(8>=$B$7,8<=$D$7),1,0) | L33: =IF(AND(9>=$B$7,9<=$D$7),1,0) | M33: =IF(AND(10>=$B$7,10<=$D$7),1,0) | N33: =IF(AND(11>=$B$7,11<=$D$7),1,0) | O33: =IF(AND(12>=$B$7,12<=$D$7),1,0) | P33: =IF(AND(13>=$B$7,13<=$D$7),1,0) | Q33: =IF(AND(14>=$B$7,14<=$D$7),1,0) | R33: =IF(AND(15>=$B$7,15<=$D$7),1,0) | S33: =IF(AND(16>=$B$7,16<=$D$7),1,0) | T33: =IF(AND(17>=$B$7,17<=$D$7),1,0) | U33: =IF(AND(18>=$B$7,18<=$D$7),1,0) | V33: =IF(AND(19>=$B$7,19<=$D$7),1,0) | W33: =IF(AND(20>=$B$7,20<=$D$7),1,0) | X33: =IF(AND(21>=$B$7,21<=$D$7),1,0) | Y33: =IF(AND(22>=$B$7,22<=$D$7),1,0) | Z33: =IF(AND(23>=$B$7,23<=$D$7),1,0) | AA33: =IF(AND(24>=$B$7,24<=$D$7),1,0) | AB33: =IF(AND(25>=$B$7,25<=$D$7),1,0) | AC33: =IF(AND(26>=$B$7,26<=$D$7),1,0) | AD33: =IF(AND(27>=$B$7,27<=$D$7),1,0) | AE33: =IF(AND(28>=$B$7,28<=$D$7),1,0) | AF33: =IF(AND(29>=$B$7,29<=$D$7),1,0) | AG33: =IF(AND(30>=$B$7,30<=$D$7),1,0) | AH33: =IF(AND(31>=$B$7,31<=$D$7),1,0) | AI33: =IF(AND(32>=$B$7,32<=$D$7),1,0) | AJ33: =IF(AND(33>=$B$7,33<=$D$7),1,0) | AK33: =IF(AND(34>=$B$7,34<=$D$7),1,0) | AL33: =IF(AND(35>=$B$7,35<=$D$7),1,0) | AM33: =IF(AND(36>=$B$7,36<=$D$7),1,0) | AN33: =IF(AND(37>=$B$7,37<=$D$7),1,0) | AO33: =IF(AND(38>=$B$7,38<=$D$7),1,0) | AP33: =IF(AND(39>=$B$7,39<=$D$7),1,0) | AQ33: =IF(AND(40>=$B$7,40<=$D$7),1,0) | AR33: =IF(AND(41>=$B$7,41<=$D$7),1,0) | AS33: =IF(AND(42>=$B$7,42<=$D$7),1,0) | AT33: =IF(AND(43>=$B$7,43<=$D$7),1,0) | AU33: =IF(AND(44>=$B$7,44<=$D$7),1,0) | AV33: =IF(AND(45>=$B$7,45<=$D$7),1,0) | AW33: =IF(AND(46>=$B$7,46<=$D$7),1,0) | AX33: =IF(AND(47>=$B$7,47<=$D$7),1,0) | AY33: =IF(AND(48>=$B$7,48<=$D$7),1,0) | AZ33: =IF(AND(49>=$B$7,49<=$D$7),1,0) | BA33: =IF(AND(50>=$B$7,50<=$D$7),1,0) | BB33: =IF(AND(51>=$B$7,51<=$D$7),1,0) | BC33: =IF(AND(52>=$B$7,52<=$D$7),1,0) | BD33: =IF(AND(53>=$B$7,53<=$D$7),1,0) | BE33: =IF(AND(54>=$B$7,54<=$D$7),1,0) | BF33: =IF(AND(55>=$B$7,55<=$D$7),1,0) | BG33: =IF(AND(56>=$B$7,56<=$D$7),1,0) | BH33: =IF(AND(57>=$B$7,57<=$D$7),1,0) | BI33: =IF(AND(58>=$B$7,58<=$D$7),1,0) | BJ33: =IF(AND(59>=$B$7,59<=$D$7),1,0) | BK33: =IF(AND(60>=$B$7,60<=$D$7),1,0) | BL33: =IF(AND(61>=$B$7,61<=$D$7),1,0) | BM33: =IF(AND(62>=$B$7,62<=$D$7),1,0) | BN33: =IF(AND(63>=$B$7,63<=$D$7),1,0) | BO33: =IF(AND(64>=$B$7,64<=$D$7),1,0) | BP33: =IF(AND(65>=$B$7,65<=$D$7),1,0) | BQ33: =IF(AND(66>=$B$7,66<=$D$7),1,0) | BR33: =IF(AND(67>=$B$7,67<=$D$7),1,0) | BS33: =IF(AND(68>=$B$7,68<=$D$7),1,0) | BT33: =IF(AND(69>=$B$7,69<=$D$7),1,0) | BU33: =IF(AND(70>=$B$7,70<=$D$7),1,0) | BV33: =IF(AND(71>=$B$7,71<=$D$7),1,0) | BW33: =IF(AND(72>=$B$7,72<=$D$7),1,0) | BX33: =IF(AND(73>=$B$7,73<=$D$7),1,0) | BY33: =IF(AND(74>=$B$7,74<=$D$7),1,0) | BZ33: =IF(AND(75>=$B$7,75<=$D$7),1,0) | CA33: =IF(AND(76>=$B$7,76<=$D$7),1,0) | CB33: =IF(AND(77>=$B$7,77<=$D$7),1,0) | CC33: =IF(AND(78>=$B$7,78<=$D$7),1,0) | CD33: =IF(AND(79>=$B$7,79<=$D$7),1,0) | CE33: =IF(AND(80>=$B$7,80<=$D$7),1,0) | CF33: =IF(AND(81>=$B$7,81<=$D$7),1,0) | CG33: =IF(AND(82>=$B$7,82<=$D$7),1,0) | CH33: =IF(AND(83>=$B$7,83<=$D$7),1,0) | CI33: =IF(AND(84>=$B$7,84<=$D$7),1,0) | CJ33: =IF(AND(85>=$B$7,85<=$D$7),1,0) | CK33: =IF(AND(86>=$B$7,86<=$D$7),1,0) | CL33: =IF(AND(87>=$B$7,87<=$D$7),1,0) | CM33: =IF(AND(88>=$B$7,88<=$D$7),1,0) | CN33: =IF(AND(89>=$B$7,89<=$D$7),1,0) | CO33: =IF(AND(90>=$B$7,90<=$D$7),1,0) | CP33: =IF(AND(91>=$B$7,91<=$D$7),1,0) | CQ33: =IF(AND(92>=$B$7,92<=$D$7),1,0) | CR33: =IF(AND(93>=$B$7,93<=$D$7),1,0) | CS33: =IF(AND(94>=$B$7,94<=$D$7),1,0) | CT33: =IF(AND(95>=$B$7,95<=$D$7),1,0) | CU33: =IF(AND(96>=$B$7,96<=$D$7),1,0) | CV33: =IF(AND(97>=$B$7,97<=$D$7),1,0) | CW33: =IF(AND(98>=$B$7,98<=$D$7),1,0) | CX33: =IF(AND(99>=$B$7,99<=$D$7),1,0) | CY33: =IF(AND(100>=$B$7,100<=$D$7),1,0) | CZ33: =IF(AND(101>=$B$7,101<=$D$7),1,0) | DA33: =IF(AND(102>=$B$7,102<=$D$7),1,0) | DB33: =IF(AND(103>=$B$7,103<=$D$7),1,0) | DC33: =IF(AND(104>=$B$7,104<=$D$7),1,0) | DD33: =IF(AND(105>=$B$7,105<=$D$7),1,0) | DE33: =IF(AND(106>=$B$7,106<=$D$7),1,0) | DF33: =IF(AND(107>=$B$7,107<=$D$7),1,0) | DG33: =IF(AND(108>=$B$7,108<=$D$7),1,0) | DH33: =IF(AND(109>=$B$7,109<=$D$7),1,0) | DI33: =IF(AND(110>=$B$7,110<=$D$7),1,0) | DJ33: =IF(AND(111>=$B$7,111<=$D$7),1,0) | DK33: =IF(AND(112>=$B$7,112<=$D$7),1,0) | DL33: =IF(AND(113>=$B$7,113<=$D$7),1,0) | DM33: =IF(AND(114>=$B$7,114<=$D$7),1,0) | DN33: =IF(AND(115>=$B$7,115<=$D$7),1,0) | DO33: =IF(AND(116>=$B$7,116<=$D$7),1,0) | DP33: =IF(AND(117>=$B$7,117<=$D$7),1,0) | DQ33: =IF(AND(118>=$B$7,118<=$D$7),1,0) | DR33: =IF(AND(119>=$B$7,119<=$D$7),1,0) | DS33: =IF(AND(120>=$B$7,120<=$D$7),1,0) | DT33: =IF(AND(121>=$B$7,121<=$D$7),1,0) | DU33: =IF(AND(122>=$B$7,122<=$D$7),1,0) | DV33: =IF(AND(123>=$B$7,123<=$D$7),1,0) | DW33: =IF(AND(124>=$B$7,124<=$D$7),1,0) | DX33: =IF(AND(125>=$B$7,125<=$D$7),1,0) | DY33: =IF(AND(126>=$B$7,126<=$D$7),1,0) | DZ33: =IF(AND(127>=$B$7,127<=$D$7),1,0) | EA33: =IF(AND(128>=$B$7,128<=$D$7),1,0) | EB33: =IF(AND(129>=$B$7,129<=$D$7),1,0) | EC33: =IF(AND(130>=$B$7,130<=$D$7),1,0) | ED33: =IF(AND(131>=$B$7,131<=$D$7),1,0) | EE33: =IF(AND(132>=$B$7,132<=$D$7),1,0) | EF33: =IF(AND(133>=$B$7,133<=$D$7),1,0) | EG33: =IF(AND(134>=$B$7,134<=$D$7),1,0) | EH33: =IF(AND(135>=$B$7,135<=$D$7),1,0) | EI33: =IF(AND(136>=$B$7,136<=$D$7),1,0) | EJ33: =IF(AND(137>=$B$7,137<=$D$7),1,0) | EK33: =IF(AND(138>=$B$7,138<=$D$7),1,0) | EL33: =IF(AND(139>=$B$7,139<=$D$7),1,0) | EM33: =IF(AND(140>=$B$7,140<=$D$7),1,0) | EN33: =IF(AND(141>=$B$7,141<=$D$7),1,0) | EO33: =IF(AND(142>=$B$7,142<=$D$7),1,0) | EP33: =IF(AND(143>=$B$7,143<=$D$7),1,0) | EQ33: =IF(AND(144>=$B$7,144<=$D$7),1,0) | ER33: =IF(AND(145>=$B$7,145<=$D$7),1,0) | ES33: =IF(AND(146>=$B$7,146<=$D$7),1,0) | ET33: =IF(AND(147>=$B$7,147<=$D$7),1,0) | EU33: =IF(AND(148>=$B$7,148<=$D$7),1,0) | EV33: =IF(AND(149>=$B$7,149<=$D$7),1,0) | EW33: =IF(AND(150>=$B$7,150<=$D$7),1,0) | EX33: =IF(AND(151>=$B$7,151<=$D$7),1,0) | EY33: =IF(AND(152>=$B$7,152<=$D$7),1,0) | EZ33: =IF(AND(153>=$B$7,153<=$D$7),1,0) | FA33: =IF(AND(154>=$B$7,154<=$D$7),1,0) | FB33: =IF(AND(155>=$B$7,155<=$D$7),1,0) | FC33: =IF(AND(156>=$B$7,156<=$D$7),1,0) | FD33: =IF(AND(157>=$B$7,157<=$D$7),1,0) | FE33: =IF(AND(158>=$B$7,158<=$D$7),1,0) | FF33: =IF(AND(159>=$B$7,159<=$D$7),1,0) | FG33: =IF(AND(160>=$B$7,160<=$D$7),1,0) | FH33: =IF(AND(161>=$B$7,161<=$D$7),1,0) | FI33: =IF(AND(162>=$B$7,162<=$D$7),1,0) | FJ33: =IF(AND(163>=$B$7,163<=$D$7),1,0) | FK33: =IF(AND(164>=$B$7,164<=$D$7),1,0) | FL33: =IF(AND(165>=$B$7,165<=$D$7),1,0) | FM33: =IF(AND(166>=$B$7,166<=$D$7),1,0) | FN33: =IF(AND(167>=$B$7,167<=$D$7),1,0) | FO33: =IF(AND(168>=$B$7,168<=$D$7),1,0) | FP33: =IF(AND(169>=$B$7,169<=$D$7),1,0) | FQ33: =IF(AND(170>=$B$7,170<=$D$7),1,0) | FR33: =IF(AND(171>=$B$7,171<=$D$7),1,0) | FS33: =IF(AND(172>=$B$7,172<=$D$7),1,0) | FT33: =IF(AND(173>=$B$7,173<=$D$7),1,0) | FU33: =IF(AND(174>=$B$7,174<=$D$7),1,0) | FV33: =IF(AND(175>=$B$7,175<=$D$7),1,0) | FW33: =IF(AND(176>=$B$7,176<=$D$7),1,0) | FX33: =IF(AND(177>=$B$7,177<=$D$7),1,0) | FY33: =IF(AND(178>=$B$7,178<=$D$7),1,0) | FZ33: =IF(AND(179>=$B$7,179<=$D$7),1,0) | GA33: =IF(AND(180>=$B$7,180<=$D$7),1,0) | GB33: =IF(AND(181>=$B$7,181<=$D$7),1,0) | GC33: =IF(AND(182>=$B$7,182<=$D$7),1,0) | GD33: =IF(AND(183>=$B$7,183<=$D$7),1,0) | GE33: =IF(AND(184>=$B$7,184<=$D$7),1,0) | GF33: =IF(AND(185>=$B$7,185<=$D$7),1,0) | GG33: =IF(AND(186>=$B$7,186<=$D$7),1,0) | GH33: =IF(AND(187>=$B$7,187<=$D$7),1,0) | GI33: =IF(AND(188>=$B$7,188<=$D$7),1,0) | GJ33: =IF(AND(189>=$B$7,189<=$D$7),1,0) | GK33: =IF(AND(190>=$B$7,190<=$D$7),1,0) | GL33: =IF(AND(191>=$B$7,191<=$D$7),1,0) | GM33: =IF(AND(192>=$B$7,192<=$D$7),1,0) | GN33: =IF(AND(193>=$B$7,193<=$D$7),1,0) | GO33: =IF(AND(194>=$B$7,194<=$D$7),1,0) | GP33: =IF(AND(195>=$B$7,195<=$D$7),1,0) | GQ33: =IF(AND(196>=$B$7,196<=$D$7),1,0) | GR33: =IF(AND(197>=$B$7,197<=$D$7),1,0) | GS33: =IF(AND(198>=$B$7,198<=$D$7),1,0) | GT33: =IF(AND(199>=$B$7,199<=$D$7),1,0) | GU33: =IF(AND(200>=$B$7,200<=$D$7),1,0) | GV33: =IF(AND(201>=$B$7,201<=$D$7),1,0) | GW33: =IF(AND(202>=$B$7,202<=$D$7),1,0) | GX33: =IF(AND(203>=$B$7,203<=$D$7),1,0) | GY33: =IF(AND(204>=$B$7,204<=$D$7),1,0) | GZ33: =IF(AND(205>=$B$7,205<=$D$7),1,0) | HA33: =IF(AND(206>=$B$7,206<=$D$7),1,0) | HB33: =IF(AND(207>=$B$7,207<=$D$7),1,0) | HC33: =IF(AND(208>=$B$7,208<=$D$7),1,0) | HD33: =IF(AND(209>=$B$7,209<=$D$7),1,0) | HE33: =IF(AND(210>=$B$7,210<=$D$7),1,0) | HF33: =IF(AND(211>=$B$7,211<=$D$7),1,0) | HG33: =IF(AND(212>=$B$7,212<=$D$7),1,0) | HH33: =IF(AND(213>=$B$7,213<=$D$7),1,0) | HI33: =IF(AND(214>=$B$7,214<=$D$7),1,0) | HJ33: =IF(AND(215>=$B$7,215<=$D$7),1,0) | HK33: =IF(AND(216>=$B$7,216<=$D$7),1,0) | HL33: =IF(AND(217>=$B$7,217<=$D$7),1,0) | HM33: =IF(AND(218>=$B$7,218<=$D$7),1,0) | HN33: =IF(AND(219>=$B$7,219<=$D$7),1,0) | HO33: =IF(AND(220>=$B$7,220<=$D$7),1,0) | HP33: =IF(AND(221>=$B$7,221<=$D$7),1,0) | HQ33: =IF(AND(222>=$B$7,222<=$D$7),1,0) | HR33: =IF(AND(223>=$B$7,223<=$D$7),1,0) | HS33: =IF(AND(224>=$B$7,224<=$D$7),1,0) | HT33: =IF(AND(225>=$B$7,225<=$D$7),1,0) | HU33: =IF(AND(226>=$B$7,226<=$D$7),1,0) | HV33: =IF(AND(227>=$B$7,227<=$D$7),1,0) | HW33: =IF(AND(228>=$B$7,228<=$D$7),1,0) | HX33: =IF(AND(229>=$B$7,229<=$D$7),1,0) | HY33: =IF(AND(230>=$B$7,230<=$D$7),1,0) | HZ33: =IF(AND(231>=$B$7,231<=$D$7),1,0) | IA33: =IF(AND(232>=$B$7,232<=$D$7),1,0) | IB33: =IF(AND(233>=$B$7,233<=$D$7),1,0) | IC33: =IF(AND(234>=$B$7,234<=$D$7),1,0) | ID33: =IF(AND(235>=$B$7,235<=$D$7),1,0) | IE33: =IF(AND(236>=$B$7,236<=$D$7),1,0) | IF33: =IF(AND(237>=$B$7,237<=$D$7),1,0) | IG33: =IF(AND(238>=$B$7,238<=$D$7),1,0) | IH33: =IF(AND(239>=$B$7,239<=$D$7),1,0) | II33: =IF(AND(240>=$B$7,240<=$D$7),1,0) | IJ33: =IF(AND(241>=$B$7,241<=$D$7),1,0) | IK33: =IF(AND(242>=$B$7,242<=$D$7),1,0) | IL33: =IF(AND(243>=$B$7,243<=$D$7),1,0) | IM33: =IF(AND(244>=$B$7,244<=$D$7),1,0) | IN33: =IF(AND(245>=$B$7,245<=$D$7),1,0) | IO33: =IF(AND(246>=$B$7,246<=$D$7),1,0) | IP33: =IF(AND(247>=$B$7,247<=$D$7),1,0) | IQ33: =IF(AND(248>=$B$7,248<=$D$7),1,0) | IR33: =IF(AND(249>=$B$7,249<=$D$7),1,0) | IS33: =IF(AND(250>=$B$7,250<=$D$7),1,0) | IT33: =IF(AND(251>=$B$7,251<=$D$7),1,0) | IU33: =IF(AND(252>=$B$7,252<=$D$7),1,0) | IV33: =IF(AND(253>=$B$7,253<=$D$7),1,0) | IW33: =IF(AND(254>=$B$7,254<=$D$7),1,0) | IX33: =IF(AND(255>=$B$7,255<=$D$7),1,0) | IY33: =IF(AND(256>=$B$7,256<=$D$7),1,0) | IZ33: =IF(AND(257>=$B$7,257<=$D$7),1,0) | JA33: =IF(AND(258>=$B$7,258<=$D$7),1,0) | JB33: =IF(AND(259>=$B$7,259<=$D$7),1,0) | JC33: =IF(AND(260>=$B$7,260<=$D$7),1,0) | JD33: =IF(AND(261>=$B$7,261<=$D$7),1,0) | JE33: =IF(AND(262>=$B$7,262<=$D$7),1,0) | JF33: =IF(AND(263>=$B$7,263<=$D$7),1,0) | JG33: =IF(AND(264>=$B$7,264<=$D$7),1,0) | JH33: =IF(AND(265>=$B$7,265<=$D$7),1,0) | JI33: =IF(AND(266>=$B$7,266<=$D$7),1,0) | JJ33: =IF(AND(267>=$B$7,267<=$D$7),1,0) | JK33: =IF(AND(268>=$B$7,268<=$D$7),1,0) | JL33: =IF(AND(269>=$B$7,269<=$D$7),1,0) | JM33: =IF(AND(270>=$B$7,270<=$D$7),1,0) | JN33: =IF(AND(271>=$B$7,271<=$D$7),1,0) | JO33: =IF(AND(272>=$B$7,272<=$D$7),1,0) | JP33: =IF(AND(273>=$B$7,273<=$D$7),1,0) | JQ33: =IF(AND(274>=$B$7,274<=$D$7),1,0) | JR33: =IF(AND(275>=$B$7,275<=$D$7),1,0) | JS33: =IF(AND(276>=$B$7,276<=$D$7),1,0) | JT33: =IF(AND(277>=$B$7,277<=$D$7),1,0) | JU33: =IF(AND(278>=$B$7,278<=$D$7),1,0) | JV33: =IF(AND(279>=$B$7,279<=$D$7),1,0) | JW33: =IF(AND(280>=$B$7,280<=$D$7),1,0) | JX33: =IF(AND(281>=$B$7,281<=$D$7),1,0) | JY33: =IF(AND(282>=$B$7,282<=$D$7),1,0) | JZ33: =IF(AND(283>=$B$7,283<=$D$7),1,0) | KA33: =IF(AND(284>=$B$7,284<=$D$7),1,0) | KB33: =IF(AND(285>=$B$7,285<=$D$7),1,0) | KC33: =IF(AND(286>=$B$7,286<=$D$7),1,0) | KD33: =IF(AND(287>=$B$7,287<=$D$7),1,0) | KE33: =IF(AND(288>=$B$7,288<=$D$7),1,0) | KF33: =IF(AND(289>=$B$7,289<=$D$7),1,0) | KG33: =IF(AND(290>=$B$7,290<=$D$7),1,0) | KH33: =IF(AND(291>=$B$7,291<=$D$7),1,0) | KI33: =IF(AND(292>=$B$7,292<=$D$7),1,0) | KJ33: =IF(AND(293>=$B$7,293<=$D$7),1,0) | KK33: =IF(AND(294>=$B$7,294<=$D$7),1,0) | KL33: =IF(AND(295>=$B$7,295<=$D$7),1,0) | KM33: =IF(AND(296>=$B$7,296<=$D$7),1,0) | KN33: =IF(AND(297>=$B$7,297<=$D$7),1,0) | KO33: =IF(AND(298>=$B$7,298<=$D$7),1,0) | KP33: =IF(AND(299>=$B$7,299<=$D$7),1,0) | KQ33: =IF(AND(300>=$B$7,300<=$D$7),1,0) | KR33: =IF(AND(301>=$B$7,301<=$D$7),1,0) | KS33: =IF(AND(302>=$B$7,302<=$D$7),1,0) | KT33: =IF(AND(303>=$B$7,303<=$D$7),1,0) | KU33: =IF(AND(304>=$B$7,304<=$D$7),1,0) | KV33: =IF(AND(305>=$B$7,305<=$D$7),1,0) | KW33: =IF(AND(306>=$B$7,306<=$D$7),1,0) | KX33: =IF(AND(307>=$B$7,307<=$D$7),1,0) | KY33: =IF(AND(308>=$B$7,308<=$D$7),1,0) | KZ33: =IF(AND(309>=$B$7,309<=$D$7),1,0) | LA33: =IF(AND(310>=$B$7,310<=$D$7),1,0) | LB33: =IF(AND(311>=$B$7,311<=$D$7),1,0) | LC33: =IF(AND(312>=$B$7,312<=$D$7),1,0) | LD33: =IF(AND(313>=$B$7,313<=$D$7),1,0) | LE33: =IF(AND(314>=$B$7,314<=$D$7),1,0) | LF33: =IF(AND(315>=$B$7,315<=$D$7),1,0) | LG33: =IF(AND(316>=$B$7,316<=$D$7),1,0) | LH33: =IF(AND(317>=$B$7,317<=$D$7),1,0) | LI33: =IF(AND(318>=$B$7,318<=$D$7),1,0) | LJ33: =IF(AND(319>=$B$7,319<=$D$7),1,0) | LK33: =IF(AND(320>=$B$7,320<=$D$7),1,0) | LL33: =IF(AND(321>=$B$7,321<=$D$7),1,0) | LM33: =IF(AND(322>=$B$7,322<=$D$7),1,0) | LN33: =IF(AND(323>=$B$7,323<=$D$7),1,0) | LO33: =IF(AND(324>=$B$7,324<=$D$7),1,0) | LP33: =IF(AND(325>=$B$7,325<=$D$7),1,0) | LQ33: =IF(AND(326>=$B$7,326<=$D$7),1,0) | LR33: =IF(AND(327>=$B$7,327<=$D$7),1,0) | LS33: =IF(AND(328>=$B$7,328<=$D$7),1,0) | LT33: =IF(AND(329>=$B$7,329<=$D$7),1,0) | LU33: =IF(AND(330>=$B$7,330<=$D$7),1,0) | LV33: =IF(AND(331>=$B$7,331<=$D$7),1,0) | LW33: =IF(AND(332>=$B$7,332<=$D$7),1,0) | LX33: =IF(AND(333>=$B$7,333<=$D$7),1,0) | LY33: =IF(AND(334>=$B$7,334<=$D$7),1,0) | LZ33: =IF(AND(335>=$B$7,335<=$D$7),1,0) | MA33: =IF(AND(336>=$B$7,336<=$D$7),1,0) | MB33: =IF(AND(337>=$B$7,337<=$D$7),1,0) | MC33: =IF(AND(338>=$B$7,338<=$D$7),1,0) | MD33: =IF(AND(339>=$B$7,339<=$D$7),1,0) | ME33: =IF(AND(340>=$B$7,340<=$D$7),1,0) | MF33: =IF(AND(341>=$B$7,341<=$D$7),1,0) | MG33: =IF(AND(342>=$B$7,342<=$D$7),1,0) | MH33: =IF(AND(343>=$B$7,343<=$D$7),1,0) | MI33: =IF(AND(344>=$B$7,344<=$D$7),1,0) | MJ33: =IF(AND(345>=$B$7,345<=$D$7),1,0) | MK33: =IF(AND(346>=$B$7,346<=$D$7),1,0) | ML33: =IF(AND(347>=$B$7,347<=$D$7),1,0) | MM33: =IF(AND(348>=$B$7,348<=$D$7),1,0) | MN33: =IF(AND(349>=$B$7,349<=$D$7),1,0) | MO33: =IF(AND(350>=$B$7,350<=$D$7),1,0) | MP33: =IF(AND(351>=$B$7,351<=$D$7),1,0) | MQ33: =IF(AND(352>=$B$7,352<=$D$7),1,0) | MR33: =IF(AND(353>=$B$7,353<=$D$7),1,0) | MS33: =IF(AND(354>=$B$7,354<=$D$7),1,0) | MT33: =IF(AND(355>=$B$7,355<=$D$7),1,0) | MU33: =IF(AND(356>=$B$7,356<=$D$7),1,0) | MV33: =IF(AND(357>=$B$7,357<=$D$7),1,0) | MW33: =IF(AND(358>=$B$7,358<=$D$7),1,0) | MX33: =IF(AND(359>=$B$7,359<=$D$7),1,0) | MY33: =IF(AND(360>=$B$7,360<=$D$7),1,0) | MZ33: =IF(AND(361>=$B$7,361<=$D$7),1,0) | NA33: =IF(AND(362>=$B$7,362<=$D$7),1,0) | NB33: =IF(AND(363>=$B$7,363<=$D$7),1,0) | NC33: =IF(AND(364>=$B$7,364<=$D$7),1,0) | ND33: =IF(AND(365>=$B$7,365<=$D$7),1,0) | NE33: =IF(AND(366>=$B$7,366<=$D$7),1,0) | NF33: =IF(AND(367>=$B$7,367<=$D$7),1,0) | NG33: =IF(AND(368>=$B$7,368<=$D$7),1,0) | NH33: =IF(AND(369>=$B$7,369<=$D$7),1,0) | NI33: =IF(AND(370>=$B$7,370<=$D$7),1,0) | NJ33: =IF(AND(371>=$B$7,371<=$D$7),1,0) | NK33: =IF(AND(372>=$B$7,372<=$D$7),1,0)
A34: Flag: Initial Closing | D34: =IF(AND(1>=$B$8,1<=$D$8),1,0) | E34: =IF(AND(2>=$B$8,2<=$D$8),1,0) | F34: =IF(AND(3>=$B$8,3<=$D$8),1,0) | G34: =IF(AND(4>=$B$8,4<=$D$8),1,0) | H34: =IF(AND(5>=$B$8,5<=$D$8),1,0) | I34: =IF(AND(6>=$B$8,6<=$D$8),1,0) | J34: =IF(AND(7>=$B$8,7<=$D$8),1,0) | K34: =IF(AND(8>=$B$8,8<=$D$8),1,0) | L34: =IF(AND(9>=$B$8,9<=$D$8),1,0) | M34: =IF(AND(10>=$B$8,10<=$D$8),1,0) | N34: =IF(AND(11>=$B$8,11<=$D$8),1,0) | O34: =IF(AND(12>=$B$8,12<=$D$8),1,0) | P34: =IF(AND(13>=$B$8,13<=$D$8),1,0) | Q34: =IF(AND(14>=$B$8,14<=$D$8),1,0) | R34: =IF(AND(15>=$B$8,15<=$D$8),1,0) | S34: =IF(AND(16>=$B$8,16<=$D$8),1,0) | T34: =IF(AND(17>=$B$8,17<=$D$8),1,0) | U34: =IF(AND(18>=$B$8,18<=$D$8),1,0) | V34: =IF(AND(19>=$B$8,19<=$D$8),1,0) | W34: =IF(AND(20>=$B$8,20<=$D$8),1,0) | X34: =IF(AND(21>=$B$8,21<=$D$8),1,0) | Y34: =IF(AND(22>=$B$8,22<=$D$8),1,0) | Z34: =IF(AND(23>=$B$8,23<=$D$8),1,0) | AA34: =IF(AND(24>=$B$8,24<=$D$8),1,0) | AB34: =IF(AND(25>=$B$8,25<=$D$8),1,0) | AC34: =IF(AND(26>=$B$8,26<=$D$8),1,0) | AD34: =IF(AND(27>=$B$8,27<=$D$8),1,0) | AE34: =IF(AND(28>=$B$8,28<=$D$8),1,0) | AF34: =IF(AND(29>=$B$8,29<=$D$8),1,0) | AG34: =IF(AND(30>=$B$8,30<=$D$8),1,0) | AH34: =IF(AND(31>=$B$8,31<=$D$8),1,0) | AI34: =IF(AND(32>=$B$8,32<=$D$8),1,0) | AJ34: =IF(AND(33>=$B$8,33<=$D$8),1,0) | AK34: =IF(AND(34>=$B$8,34<=$D$8),1,0) | AL34: =IF(AND(35>=$B$8,35<=$D$8),1,0) | AM34: =IF(AND(36>=$B$8,36<=$D$8),1,0) | AN34: =IF(AND(37>=$B$8,37<=$D$8),1,0) | AO34: =IF(AND(38>=$B$8,38<=$D$8),1,0) | AP34: =IF(AND(39>=$B$8,39<=$D$8),1,0) | AQ34: =IF(AND(40>=$B$8,40<=$D$8),1,0) | AR34: =IF(AND(41>=$B$8,41<=$D$8),1,0) | AS34: =IF(AND(42>=$B$8,42<=$D$8),1,0) | AT34: =IF(AND(43>=$B$8,43<=$D$8),1,0) | AU34: =IF(AND(44>=$B$8,44<=$D$8),1,0) | AV34: =IF(AND(45>=$B$8,45<=$D$8),1,0) | AW34: =IF(AND(46>=$B$8,46<=$D$8),1,0) | AX34: =IF(AND(47>=$B$8,47<=$D$8),1,0) | AY34: =IF(AND(48>=$B$8,48<=$D$8),1,0) | AZ34: =IF(AND(49>=$B$8,49<=$D$8),1,0) | BA34: =IF(AND(50>=$B$8,50<=$D$8),1,0) | BB34: =IF(AND(51>=$B$8,51<=$D$8),1,0) | BC34: =IF(AND(52>=$B$8,52<=$D$8),1,0) | BD34: =IF(AND(53>=$B$8,53<=$D$8),1,0) | BE34: =IF(AND(54>=$B$8,54<=$D$8),1,0) | BF34: =IF(AND(55>=$B$8,55<=$D$8),1,0) | BG34: =IF(AND(56>=$B$8,56<=$D$8),1,0) | BH34: =IF(AND(57>=$B$8,57<=$D$8),1,0) | BI34: =IF(AND(58>=$B$8,58<=$D$8),1,0) | BJ34: =IF(AND(59>=$B$8,59<=$D$8),1,0) | BK34: =IF(AND(60>=$B$8,60<=$D$8),1,0) | BL34: =IF(AND(61>=$B$8,61<=$D$8),1,0) | BM34: =IF(AND(62>=$B$8,62<=$D$8),1,0) | BN34: =IF(AND(63>=$B$8,63<=$D$8),1,0) | BO34: =IF(AND(64>=$B$8,64<=$D$8),1,0) | BP34: =IF(AND(65>=$B$8,65<=$D$8),1,0) | BQ34: =IF(AND(66>=$B$8,66<=$D$8),1,0) | BR34: =IF(AND(67>=$B$8,67<=$D$8),1,0) | BS34: =IF(AND(68>=$B$8,68<=$D$8),1,0) | BT34: =IF(AND(69>=$B$8,69<=$D$8),1,0) | BU34: =IF(AND(70>=$B$8,70<=$D$8),1,0) | BV34: =IF(AND(71>=$B$8,71<=$D$8),1,0) | BW34: =IF(AND(72>=$B$8,72<=$D$8),1,0) | BX34: =IF(AND(73>=$B$8,73<=$D$8),1,0) | BY34: =IF(AND(74>=$B$8,74<=$D$8),1,0) | BZ34: =IF(AND(75>=$B$8,75<=$D$8),1,0) | CA34: =IF(AND(76>=$B$8,76<=$D$8),1,0) | CB34: =IF(AND(77>=$B$8,77<=$D$8),1,0) | CC34: =IF(AND(78>=$B$8,78<=$D$8),1,0) | CD34: =IF(AND(79>=$B$8,79<=$D$8),1,0) | CE34: =IF(AND(80>=$B$8,80<=$D$8),1,0) | CF34: =IF(AND(81>=$B$8,81<=$D$8),1,0) | CG34: =IF(AND(82>=$B$8,82<=$D$8),1,0) | CH34: =IF(AND(83>=$B$8,83<=$D$8),1,0) | CI34: =IF(AND(84>=$B$8,84<=$D$8),1,0) | CJ34: =IF(AND(85>=$B$8,85<=$D$8),1,0) | CK34: =IF(AND(86>=$B$8,86<=$D$8),1,0) | CL34: =IF(AND(87>=$B$8,87<=$D$8),1,0) | CM34: =IF(AND(88>=$B$8,88<=$D$8),1,0) | CN34: =IF(AND(89>=$B$8,89<=$D$8),1,0) | CO34: =IF(AND(90>=$B$8,90<=$D$8),1,0) | CP34: =IF(AND(91>=$B$8,91<=$D$8),1,0) | CQ34: =IF(AND(92>=$B$8,92<=$D$8),1,0) | CR34: =IF(AND(93>=$B$8,93<=$D$8),1,0) | CS34: =IF(AND(94>=$B$8,94<=$D$8),1,0) | CT34: =IF(AND(95>=$B$8,95<=$D$8),1,0) | CU34: =IF(AND(96>=$B$8,96<=$D$8),1,0) | CV34: =IF(AND(97>=$B$8,97<=$D$8),1,0) | CW34: =IF(AND(98>=$B$8,98<=$D$8),1,0) | CX34: =IF(AND(99>=$B$8,99<=$D$8),1,0) | CY34: =IF(AND(100>=$B$8,100<=$D$8),1,0) | CZ34: =IF(AND(101>=$B$8,101<=$D$8),1,0) | DA34: =IF(AND(102>=$B$8,102<=$D$8),1,0) | DB34: =IF(AND(103>=$B$8,103<=$D$8),1,0) | DC34: =IF(AND(104>=$B$8,104<=$D$8),1,0) | DD34: =IF(AND(105>=$B$8,105<=$D$8),1,0) | DE34: =IF(AND(106>=$B$8,106<=$D$8),1,0) | DF34: =IF(AND(107>=$B$8,107<=$D$8),1,0) | DG34: =IF(AND(108>=$B$8,108<=$D$8),1,0) | DH34: =IF(AND(109>=$B$8,109<=$D$8),1,0) | DI34: =IF(AND(110>=$B$8,110<=$D$8),1,0) | DJ34: =IF(AND(111>=$B$8,111<=$D$8),1,0) | DK34: =IF(AND(112>=$B$8,112<=$D$8),1,0) | DL34: =IF(AND(113>=$B$8,113<=$D$8),1,0) | DM34: =IF(AND(114>=$B$8,114<=$D$8),1,0) | DN34: =IF(AND(115>=$B$8,115<=$D$8),1,0) | DO34: =IF(AND(116>=$B$8,116<=$D$8),1,0) | DP34: =IF(AND(117>=$B$8,117<=$D$8),1,0) | DQ34: =IF(AND(118>=$B$8,118<=$D$8),1,0) | DR34: =IF(AND(119>=$B$8,119<=$D$8),1,0) | DS34: =IF(AND(120>=$B$8,120<=$D$8),1,0) | DT34: =IF(AND(121>=$B$8,121<=$D$8),1,0) | DU34: =IF(AND(122>=$B$8,122<=$D$8),1,0) | DV34: =IF(AND(123>=$B$8,123<=$D$8),1,0) | DW34: =IF(AND(124>=$B$8,124<=$D$8),1,0) | DX34: =IF(AND(125>=$B$8,125<=$D$8),1,0) | DY34: =IF(AND(126>=$B$8,126<=$D$8),1,0) | DZ34: =IF(AND(127>=$B$8,127<=$D$8),1,0) | EA34: =IF(AND(128>=$B$8,128<=$D$8),1,0) | EB34: =IF(AND(129>=$B$8,129<=$D$8),1,0) | EC34: =IF(AND(130>=$B$8,130<=$D$8),1,0) | ED34: =IF(AND(131>=$B$8,131<=$D$8),1,0) | EE34: =IF(AND(132>=$B$8,132<=$D$8),1,0) | EF34: =IF(AND(133>=$B$8,133<=$D$8),1,0) | EG34: =IF(AND(134>=$B$8,134<=$D$8),1,0) | EH34: =IF(AND(135>=$B$8,135<=$D$8),1,0) | EI34: =IF(AND(136>=$B$8,136<=$D$8),1,0) | EJ34: =IF(AND(137>=$B$8,137<=$D$8),1,0) | EK34: =IF(AND(138>=$B$8,138<=$D$8),1,0) | EL34: =IF(AND(139>=$B$8,139<=$D$8),1,0) | EM34: =IF(AND(140>=$B$8,140<=$D$8),1,0) | EN34: =IF(AND(141>=$B$8,141<=$D$8),1,0) | EO34: =IF(AND(142>=$B$8,142<=$D$8),1,0) | EP34: =IF(AND(143>=$B$8,143<=$D$8),1,0) | EQ34: =IF(AND(144>=$B$8,144<=$D$8),1,0) | ER34: =IF(AND(145>=$B$8,145<=$D$8),1,0) | ES34: =IF(AND(146>=$B$8,146<=$D$8),1,0) | ET34: =IF(AND(147>=$B$8,147<=$D$8),1,0) | EU34: =IF(AND(148>=$B$8,148<=$D$8),1,0) | EV34: =IF(AND(149>=$B$8,149<=$D$8),1,0) | EW34: =IF(AND(150>=$B$8,150<=$D$8),1,0) | EX34: =IF(AND(151>=$B$8,151<=$D$8),1,0) | EY34: =IF(AND(152>=$B$8,152<=$D$8),1,0) | EZ34: =IF(AND(153>=$B$8,153<=$D$8),1,0) | FA34: =IF(AND(154>=$B$8,154<=$D$8),1,0) | FB34: =IF(AND(155>=$B$8,155<=$D$8),1,0) | FC34: =IF(AND(156>=$B$8,156<=$D$8),1,0) | FD34: =IF(AND(157>=$B$8,157<=$D$8),1,0) | FE34: =IF(AND(158>=$B$8,158<=$D$8),1,0) | FF34: =IF(AND(159>=$B$8,159<=$D$8),1,0) | FG34: =IF(AND(160>=$B$8,160<=$D$8),1,0) | FH34: =IF(AND(161>=$B$8,161<=$D$8),1,0) | FI34: =IF(AND(162>=$B$8,162<=$D$8),1,0) | FJ34: =IF(AND(163>=$B$8,163<=$D$8),1,0) | FK34: =IF(AND(164>=$B$8,164<=$D$8),1,0) | FL34: =IF(AND(165>=$B$8,165<=$D$8),1,0) | FM34: =IF(AND(166>=$B$8,166<=$D$8),1,0) | FN34: =IF(AND(167>=$B$8,167<=$D$8),1,0) | FO34: =IF(AND(168>=$B$8,168<=$D$8),1,0) | FP34: =IF(AND(169>=$B$8,169<=$D$8),1,0) | FQ34: =IF(AND(170>=$B$8,170<=$D$8),1,0) | FR34: =IF(AND(171>=$B$8,171<=$D$8),1,0) | FS34: =IF(AND(172>=$B$8,172<=$D$8),1,0) | FT34: =IF(AND(173>=$B$8,173<=$D$8),1,0) | FU34: =IF(AND(174>=$B$8,174<=$D$8),1,0) | FV34: =IF(AND(175>=$B$8,175<=$D$8),1,0) | FW34: =IF(AND(176>=$B$8,176<=$D$8),1,0) | FX34: =IF(AND(177>=$B$8,177<=$D$8),1,0) | FY34: =IF(AND(178>=$B$8,178<=$D$8),1,0) | FZ34: =IF(AND(179>=$B$8,179<=$D$8),1,0) | GA34: =IF(AND(180>=$B$8,180<=$D$8),1,0) | GB34: =IF(AND(181>=$B$8,181<=$D$8),1,0) | GC34: =IF(AND(182>=$B$8,182<=$D$8),1,0) | GD34: =IF(AND(183>=$B$8,183<=$D$8),1,0) | GE34: =IF(AND(184>=$B$8,184<=$D$8),1,0) | GF34: =IF(AND(185>=$B$8,185<=$D$8),1,0) | GG34: =IF(AND(186>=$B$8,186<=$D$8),1,0) | GH34: =IF(AND(187>=$B$8,187<=$D$8),1,0) | GI34: =IF(AND(188>=$B$8,188<=$D$8),1,0) | GJ34: =IF(AND(189>=$B$8,189<=$D$8),1,0) | GK34: =IF(AND(190>=$B$8,190<=$D$8),1,0) | GL34: =IF(AND(191>=$B$8,191<=$D$8),1,0) | GM34: =IF(AND(192>=$B$8,192<=$D$8),1,0) | GN34: =IF(AND(193>=$B$8,193<=$D$8),1,0) | GO34: =IF(AND(194>=$B$8,194<=$D$8),1,0) | GP34: =IF(AND(195>=$B$8,195<=$D$8),1,0) | GQ34: =IF(AND(196>=$B$8,196<=$D$8),1,0) | GR34: =IF(AND(197>=$B$8,197<=$D$8),1,0) | GS34: =IF(AND(198>=$B$8,198<=$D$8),1,0) | GT34: =IF(AND(199>=$B$8,199<=$D$8),1,0) | GU34: =IF(AND(200>=$B$8,200<=$D$8),1,0) | GV34: =IF(AND(201>=$B$8,201<=$D$8),1,0) | GW34: =IF(AND(202>=$B$8,202<=$D$8),1,0) | GX34: =IF(AND(203>=$B$8,203<=$D$8),1,0) | GY34: =IF(AND(204>=$B$8,204<=$D$8),1,0) | GZ34: =IF(AND(205>=$B$8,205<=$D$8),1,0) | HA34: =IF(AND(206>=$B$8,206<=$D$8),1,0) | HB34: =IF(AND(207>=$B$8,207<=$D$8),1,0) | HC34: =IF(AND(208>=$B$8,208<=$D$8),1,0) | HD34: =IF(AND(209>=$B$8,209<=$D$8),1,0) | HE34: =IF(AND(210>=$B$8,210<=$D$8),1,0) | HF34: =IF(AND(211>=$B$8,211<=$D$8),1,0) | HG34: =IF(AND(212>=$B$8,212<=$D$8),1,0) | HH34: =IF(AND(213>=$B$8,213<=$D$8),1,0) | HI34: =IF(AND(214>=$B$8,214<=$D$8),1,0) | HJ34: =IF(AND(215>=$B$8,215<=$D$8),1,0) | HK34: =IF(AND(216>=$B$8,216<=$D$8),1,0) | HL34: =IF(AND(217>=$B$8,217<=$D$8),1,0) | HM34: =IF(AND(218>=$B$8,218<=$D$8),1,0) | HN34: =IF(AND(219>=$B$8,219<=$D$8),1,0) | HO34: =IF(AND(220>=$B$8,220<=$D$8),1,0) | HP34: =IF(AND(221>=$B$8,221<=$D$8),1,0) | HQ34: =IF(AND(222>=$B$8,222<=$D$8),1,0) | HR34: =IF(AND(223>=$B$8,223<=$D$8),1,0) | HS34: =IF(AND(224>=$B$8,224<=$D$8),1,0) | HT34: =IF(AND(225>=$B$8,225<=$D$8),1,0) | HU34: =IF(AND(226>=$B$8,226<=$D$8),1,0) | HV34: =IF(AND(227>=$B$8,227<=$D$8),1,0) | HW34: =IF(AND(228>=$B$8,228<=$D$8),1,0) | HX34: =IF(AND(229>=$B$8,229<=$D$8),1,0) | HY34: =IF(AND(230>=$B$8,230<=$D$8),1,0) | HZ34: =IF(AND(231>=$B$8,231<=$D$8),1,0) | IA34: =IF(AND(232>=$B$8,232<=$D$8),1,0) | IB34: =IF(AND(233>=$B$8,233<=$D$8),1,0) | IC34: =IF(AND(234>=$B$8,234<=$D$8),1,0) | ID34: =IF(AND(235>=$B$8,235<=$D$8),1,0) | IE34: =IF(AND(236>=$B$8,236<=$D$8),1,0) | IF34: =IF(AND(237>=$B$8,237<=$D$8),1,0) | IG34: =IF(AND(238>=$B$8,238<=$D$8),1,0) | IH34: =IF(AND(239>=$B$8,239<=$D$8),1,0) | II34: =IF(AND(240>=$B$8,240<=$D$8),1,0) | IJ34: =IF(AND(241>=$B$8,241<=$D$8),1,0) | IK34: =IF(AND(242>=$B$8,242<=$D$8),1,0) | IL34: =IF(AND(243>=$B$8,243<=$D$8),1,0) | IM34: =IF(AND(244>=$B$8,244<=$D$8),1,0) | IN34: =IF(AND(245>=$B$8,245<=$D$8),1,0) | IO34: =IF(AND(246>=$B$8,246<=$D$8),1,0) | IP34: =IF(AND(247>=$B$8,247<=$D$8),1,0) | IQ34: =IF(AND(248>=$B$8,248<=$D$8),1,0) | IR34: =IF(AND(249>=$B$8,249<=$D$8),1,0) | IS34: =IF(AND(250>=$B$8,250<=$D$8),1,0) | IT34: =IF(AND(251>=$B$8,251<=$D$8),1,0) | IU34: =IF(AND(252>=$B$8,252<=$D$8),1,0) | IV34: =IF(AND(253>=$B$8,253<=$D$8),1,0) | IW34: =IF(AND(254>=$B$8,254<=$D$8),1,0) | IX34: =IF(AND(255>=$B$8,255<=$D$8),1,0) | IY34: =IF(AND(256>=$B$8,256<=$D$8),1,0) | IZ34: =IF(AND(257>=$B$8,257<=$D$8),1,0) | JA34: =IF(AND(258>=$B$8,258<=$D$8),1,0) | JB34: =IF(AND(259>=$B$8,259<=$D$8),1,0) | JC34: =IF(AND(260>=$B$8,260<=$D$8),1,0) | JD34: =IF(AND(261>=$B$8,261<=$D$8),1,0) | JE34: =IF(AND(262>=$B$8,262<=$D$8),1,0) | JF34: =IF(AND(263>=$B$8,263<=$D$8),1,0) | JG34: =IF(AND(264>=$B$8,264<=$D$8),1,0) | JH34: =IF(AND(265>=$B$8,265<=$D$8),1,0) | JI34: =IF(AND(266>=$B$8,266<=$D$8),1,0) | JJ34: =IF(AND(267>=$B$8,267<=$D$8),1,0) | JK34: =IF(AND(268>=$B$8,268<=$D$8),1,0) | JL34: =IF(AND(269>=$B$8,269<=$D$8),1,0) | JM34: =IF(AND(270>=$B$8,270<=$D$8),1,0) | JN34: =IF(AND(271>=$B$8,271<=$D$8),1,0) | JO34: =IF(AND(272>=$B$8,272<=$D$8),1,0) | JP34: =IF(AND(273>=$B$8,273<=$D$8),1,0) | JQ34: =IF(AND(274>=$B$8,274<=$D$8),1,0) | JR34: =IF(AND(275>=$B$8,275<=$D$8),1,0) | JS34: =IF(AND(276>=$B$8,276<=$D$8),1,0) | JT34: =IF(AND(277>=$B$8,277<=$D$8),1,0) | JU34: =IF(AND(278>=$B$8,278<=$D$8),1,0) | JV34: =IF(AND(279>=$B$8,279<=$D$8),1,0) | JW34: =IF(AND(280>=$B$8,280<=$D$8),1,0) | JX34: =IF(AND(281>=$B$8,281<=$D$8),1,0) | JY34: =IF(AND(282>=$B$8,282<=$D$8),1,0) | JZ34: =IF(AND(283>=$B$8,283<=$D$8),1,0) | KA34: =IF(AND(284>=$B$8,284<=$D$8),1,0) | KB34: =IF(AND(285>=$B$8,285<=$D$8),1,0) | KC34: =IF(AND(286>=$B$8,286<=$D$8),1,0) | KD34: =IF(AND(287>=$B$8,287<=$D$8),1,0) | KE34: =IF(AND(288>=$B$8,288<=$D$8),1,0) | KF34: =IF(AND(289>=$B$8,289<=$D$8),1,0) | KG34: =IF(AND(290>=$B$8,290<=$D$8),1,0) | KH34: =IF(AND(291>=$B$8,291<=$D$8),1,0) | KI34: =IF(AND(292>=$B$8,292<=$D$8),1,0) | KJ34: =IF(AND(293>=$B$8,293<=$D$8),1,0) | KK34: =IF(AND(294>=$B$8,294<=$D$8),1,0) | KL34: =IF(AND(295>=$B$8,295<=$D$8),1,0) | KM34: =IF(AND(296>=$B$8,296<=$D$8),1,0) | KN34: =IF(AND(297>=$B$8,297<=$D$8),1,0) | KO34: =IF(AND(298>=$B$8,298<=$D$8),1,0) | KP34: =IF(AND(299>=$B$8,299<=$D$8),1,0) | KQ34: =IF(AND(300>=$B$8,300<=$D$8),1,0) | KR34: =IF(AND(301>=$B$8,301<=$D$8),1,0) | KS34: =IF(AND(302>=$B$8,302<=$D$8),1,0) | KT34: =IF(AND(303>=$B$8,303<=$D$8),1,0) | KU34: =IF(AND(304>=$B$8,304<=$D$8),1,0) | KV34: =IF(AND(305>=$B$8,305<=$D$8),1,0) | KW34: =IF(AND(306>=$B$8,306<=$D$8),1,0) | KX34: =IF(AND(307>=$B$8,307<=$D$8),1,0) | KY34: =IF(AND(308>=$B$8,308<=$D$8),1,0) | KZ34: =IF(AND(309>=$B$8,309<=$D$8),1,0) | LA34: =IF(AND(310>=$B$8,310<=$D$8),1,0) | LB34: =IF(AND(311>=$B$8,311<=$D$8),1,0) | LC34: =IF(AND(312>=$B$8,312<=$D$8),1,0) | LD34: =IF(AND(313>=$B$8,313<=$D$8),1,0) | LE34: =IF(AND(314>=$B$8,314<=$D$8),1,0) | LF34: =IF(AND(315>=$B$8,315<=$D$8),1,0) | LG34: =IF(AND(316>=$B$8,316<=$D$8),1,0) | LH34: =IF(AND(317>=$B$8,317<=$D$8),1,0) | LI34: =IF(AND(318>=$B$8,318<=$D$8),1,0) | LJ34: =IF(AND(319>=$B$8,319<=$D$8),1,0) | LK34: =IF(AND(320>=$B$8,320<=$D$8),1,0) | LL34: =IF(AND(321>=$B$8,321<=$D$8),1,0) | LM34: =IF(AND(322>=$B$8,322<=$D$8),1,0) | LN34: =IF(AND(323>=$B$8,323<=$D$8),1,0) | LO34: =IF(AND(324>=$B$8,324<=$D$8),1,0) | LP34: =IF(AND(325>=$B$8,325<=$D$8),1,0) | LQ34: =IF(AND(326>=$B$8,326<=$D$8),1,0) | LR34: =IF(AND(327>=$B$8,327<=$D$8),1,0) | LS34: =IF(AND(328>=$B$8,328<=$D$8),1,0) | LT34: =IF(AND(329>=$B$8,329<=$D$8),1,0) | LU34: =IF(AND(330>=$B$8,330<=$D$8),1,0) | LV34: =IF(AND(331>=$B$8,331<=$D$8),1,0) | LW34: =IF(AND(332>=$B$8,332<=$D$8),1,0) | LX34: =IF(AND(333>=$B$8,333<=$D$8),1,0) | LY34: =IF(AND(334>=$B$8,334<=$D$8),1,0) | LZ34: =IF(AND(335>=$B$8,335<=$D$8),1,0) | MA34: =IF(AND(336>=$B$8,336<=$D$8),1,0) | MB34: =IF(AND(337>=$B$8,337<=$D$8),1,0) | MC34: =IF(AND(338>=$B$8,338<=$D$8),1,0) | MD34: =IF(AND(339>=$B$8,339<=$D$8),1,0) | ME34: =IF(AND(340>=$B$8,340<=$D$8),1,0) | MF34: =IF(AND(341>=$B$8,341<=$D$8),1,0) | MG34: =IF(AND(342>=$B$8,342<=$D$8),1,0) | MH34: =IF(AND(343>=$B$8,343<=$D$8),1,0) | MI34: =IF(AND(344>=$B$8,344<=$D$8),1,0) | MJ34: =IF(AND(345>=$B$8,345<=$D$8),1,0) | MK34: =IF(AND(346>=$B$8,346<=$D$8),1,0) | ML34: =IF(AND(347>=$B$8,347<=$D$8),1,0) | MM34: =IF(AND(348>=$B$8,348<=$D$8),1,0) | MN34: =IF(AND(349>=$B$8,349<=$D$8),1,0) | MO34: =IF(AND(350>=$B$8,350<=$D$8),1,0) | MP34: =IF(AND(351>=$B$8,351<=$D$8),1,0) | MQ34: =IF(AND(352>=$B$8,352<=$D$8),1,0) | MR34: =IF(AND(353>=$B$8,353<=$D$8),1,0) | MS34: =IF(AND(354>=$B$8,354<=$D$8),1,0) | MT34: =IF(AND(355>=$B$8,355<=$D$8),1,0) | MU34: =IF(AND(356>=$B$8,356<=$D$8),1,0) | MV34: =IF(AND(357>=$B$8,357<=$D$8),1,0) | MW34: =IF(AND(358>=$B$8,358<=$D$8),1,0) | MX34: =IF(AND(359>=$B$8,359<=$D$8),1,0) | MY34: =IF(AND(360>=$B$8,360<=$D$8),1,0) | MZ34: =IF(AND(361>=$B$8,361<=$D$8),1,0) | NA34: =IF(AND(362>=$B$8,362<=$D$8),1,0) | NB34: =IF(AND(363>=$B$8,363<=$D$8),1,0) | NC34: =IF(AND(364>=$B$8,364<=$D$8),1,0) | ND34: =IF(AND(365>=$B$8,365<=$D$8),1,0) | NE34: =IF(AND(366>=$B$8,366<=$D$8),1,0) | NF34: =IF(AND(367>=$B$8,367<=$D$8),1,0) | NG34: =IF(AND(368>=$B$8,368<=$D$8),1,0) | NH34: =IF(AND(369>=$B$8,369<=$D$8),1,0) | NI34: =IF(AND(370>=$B$8,370<=$D$8),1,0) | NJ34: =IF(AND(371>=$B$8,371<=$D$8),1,0) | NK34: =IF(AND(372>=$B$8,372<=$D$8),1,0)
A35: Flag: Construction | D35: =IF(AND(1>=$B$9,1<=$D$9),1,0) | E35: =IF(AND(2>=$B$9,2<=$D$9),1,0) | F35: =IF(AND(3>=$B$9,3<=$D$9),1,0) | G35: =IF(AND(4>=$B$9,4<=$D$9),1,0) | H35: =IF(AND(5>=$B$9,5<=$D$9),1,0) | I35: =IF(AND(6>=$B$9,6<=$D$9),1,0) | J35: =IF(AND(7>=$B$9,7<=$D$9),1,0) | K35: =IF(AND(8>=$B$9,8<=$D$9),1,0) | L35: =IF(AND(9>=$B$9,9<=$D$9),1,0) | M35: =IF(AND(10>=$B$9,10<=$D$9),1,0) | N35: =IF(AND(11>=$B$9,11<=$D$9),1,0) | O35: =IF(AND(12>=$B$9,12<=$D$9),1,0) | P35: =IF(AND(13>=$B$9,13<=$D$9),1,0) | Q35: =IF(AND(14>=$B$9,14<=$D$9),1,0) | R35: =IF(AND(15>=$B$9,15<=$D$9),1,0) | S35: =IF(AND(16>=$B$9,16<=$D$9),1,0) | T35: =IF(AND(17>=$B$9,17<=$D$9),1,0) | U35: =IF(AND(18>=$B$9,18<=$D$9),1,0) | V35: =IF(AND(19>=$B$9,19<=$D$9),1,0) | W35: =IF(AND(20>=$B$9,20<=$D$9),1,0) | X35: =IF(AND(21>=$B$9,21<=$D$9),1,0) | Y35: =IF(AND(22>=$B$9,22<=$D$9),1,0) | Z35: =IF(AND(23>=$B$9,23<=$D$9),1,0) | AA35: =IF(AND(24>=$B$9,24<=$D$9),1,0) | AB35: =IF(AND(25>=$B$9,25<=$D$9),1,0) | AC35: =IF(AND(26>=$B$9,26<=$D$9),1,0) | AD35: =IF(AND(27>=$B$9,27<=$D$9),1,0) | AE35: =IF(AND(28>=$B$9,28<=$D$9),1,0) | AF35: =IF(AND(29>=$B$9,29<=$D$9),1,0) | AG35: =IF(AND(30>=$B$9,30<=$D$9),1,0) | AH35: =IF(AND(31>=$B$9,31<=$D$9),1,0) | AI35: =IF(AND(32>=$B$9,32<=$D$9),1,0) | AJ35: =IF(AND(33>=$B$9,33<=$D$9),1,0) | AK35: =IF(AND(34>=$B$9,34<=$D$9),1,0) | AL35: =IF(AND(35>=$B$9,35<=$D$9),1,0) | AM35: =IF(AND(36>=$B$9,36<=$D$9),1,0) | AN35: =IF(AND(37>=$B$9,37<=$D$9),1,0) | AO35: =IF(AND(38>=$B$9,38<=$D$9),1,0) | AP35: =IF(AND(39>=$B$9,39<=$D$9),1,0) | AQ35: =IF(AND(40>=$B$9,40<=$D$9),1,0) | AR35: =IF(AND(41>=$B$9,41<=$D$9),1,0) | AS35: =IF(AND(42>=$B$9,42<=$D$9),1,0) | AT35: =IF(AND(43>=$B$9,43<=$D$9),1,0) | AU35: =IF(AND(44>=$B$9,44<=$D$9),1,0) | AV35: =IF(AND(45>=$B$9,45<=$D$9),1,0) | AW35: =IF(AND(46>=$B$9,46<=$D$9),1,0) | AX35: =IF(AND(47>=$B$9,47<=$D$9),1,0) | AY35: =IF(AND(48>=$B$9,48<=$D$9),1,0) | AZ35: =IF(AND(49>=$B$9,49<=$D$9),1,0) | BA35: =IF(AND(50>=$B$9,50<=$D$9),1,0) | BB35: =IF(AND(51>=$B$9,51<=$D$9),1,0) | BC35: =IF(AND(52>=$B$9,52<=$D$9),1,0) | BD35: =IF(AND(53>=$B$9,53<=$D$9),1,0) | BE35: =IF(AND(54>=$B$9,54<=$D$9),1,0) | BF35: =IF(AND(55>=$B$9,55<=$D$9),1,0) | BG35: =IF(AND(56>=$B$9,56<=$D$9),1,0) | BH35: =IF(AND(57>=$B$9,57<=$D$9),1,0) | BI35: =IF(AND(58>=$B$9,58<=$D$9),1,0) | BJ35: =IF(AND(59>=$B$9,59<=$D$9),1,0) | BK35: =IF(AND(60>=$B$9,60<=$D$9),1,0) | BL35: =IF(AND(61>=$B$9,61<=$D$9),1,0) | BM35: =IF(AND(62>=$B$9,62<=$D$9),1,0) | BN35: =IF(AND(63>=$B$9,63<=$D$9),1,0) | BO35: =IF(AND(64>=$B$9,64<=$D$9),1,0) | BP35: =IF(AND(65>=$B$9,65<=$D$9),1,0) | BQ35: =IF(AND(66>=$B$9,66<=$D$9),1,0) | BR35: =IF(AND(67>=$B$9,67<=$D$9),1,0) | BS35: =IF(AND(68>=$B$9,68<=$D$9),1,0) | BT35: =IF(AND(69>=$B$9,69<=$D$9),1,0) | BU35: =IF(AND(70>=$B$9,70<=$D$9),1,0) | BV35: =IF(AND(71>=$B$9,71<=$D$9),1,0) | BW35: =IF(AND(72>=$B$9,72<=$D$9),1,0) | BX35: =IF(AND(73>=$B$9,73<=$D$9),1,0) | BY35: =IF(AND(74>=$B$9,74<=$D$9),1,0) | BZ35: =IF(AND(75>=$B$9,75<=$D$9),1,0) | CA35: =IF(AND(76>=$B$9,76<=$D$9),1,0) | CB35: =IF(AND(77>=$B$9,77<=$D$9),1,0) | CC35: =IF(AND(78>=$B$9,78<=$D$9),1,0) | CD35: =IF(AND(79>=$B$9,79<=$D$9),1,0) | CE35: =IF(AND(80>=$B$9,80<=$D$9),1,0) | CF35: =IF(AND(81>=$B$9,81<=$D$9),1,0) | CG35: =IF(AND(82>=$B$9,82<=$D$9),1,0) | CH35: =IF(AND(83>=$B$9,83<=$D$9),1,0) | CI35: =IF(AND(84>=$B$9,84<=$D$9),1,0) | CJ35: =IF(AND(85>=$B$9,85<=$D$9),1,0) | CK35: =IF(AND(86>=$B$9,86<=$D$9),1,0) | CL35: =IF(AND(87>=$B$9,87<=$D$9),1,0) | CM35: =IF(AND(88>=$B$9,88<=$D$9),1,0) | CN35: =IF(AND(89>=$B$9,89<=$D$9),1,0) | CO35: =IF(AND(90>=$B$9,90<=$D$9),1,0) | CP35: =IF(AND(91>=$B$9,91<=$D$9),1,0) | CQ35: =IF(AND(92>=$B$9,92<=$D$9),1,0) | CR35: =IF(AND(93>=$B$9,93<=$D$9),1,0) | CS35: =IF(AND(94>=$B$9,94<=$D$9),1,0) | CT35: =IF(AND(95>=$B$9,95<=$D$9),1,0) | CU35: =IF(AND(96>=$B$9,96<=$D$9),1,0) | CV35: =IF(AND(97>=$B$9,97<=$D$9),1,0) | CW35: =IF(AND(98>=$B$9,98<=$D$9),1,0) | CX35: =IF(AND(99>=$B$9,99<=$D$9),1,0) | CY35: =IF(AND(100>=$B$9,100<=$D$9),1,0) | CZ35: =IF(AND(101>=$B$9,101<=$D$9),1,0) | DA35: =IF(AND(102>=$B$9,102<=$D$9),1,0) | DB35: =IF(AND(103>=$B$9,103<=$D$9),1,0) | DC35: =IF(AND(104>=$B$9,104<=$D$9),1,0) | DD35: =IF(AND(105>=$B$9,105<=$D$9),1,0) | DE35: =IF(AND(106>=$B$9,106<=$D$9),1,0) | DF35: =IF(AND(107>=$B$9,107<=$D$9),1,0) | DG35: =IF(AND(108>=$B$9,108<=$D$9),1,0) | DH35: =IF(AND(109>=$B$9,109<=$D$9),1,0) | DI35: =IF(AND(110>=$B$9,110<=$D$9),1,0) | DJ35: =IF(AND(111>=$B$9,111<=$D$9),1,0) | DK35: =IF(AND(112>=$B$9,112<=$D$9),1,0) | DL35: =IF(AND(113>=$B$9,113<=$D$9),1,0) | DM35: =IF(AND(114>=$B$9,114<=$D$9),1,0) | DN35: =IF(AND(115>=$B$9,115<=$D$9),1,0) | DO35: =IF(AND(116>=$B$9,116<=$D$9),1,0) | DP35: =IF(AND(117>=$B$9,117<=$D$9),1,0) | DQ35: =IF(AND(118>=$B$9,118<=$D$9),1,0) | DR35: =IF(AND(119>=$B$9,119<=$D$9),1,0) | DS35: =IF(AND(120>=$B$9,120<=$D$9),1,0) | DT35: =IF(AND(121>=$B$9,121<=$D$9),1,0) | DU35: =IF(AND(122>=$B$9,122<=$D$9),1,0) | DV35: =IF(AND(123>=$B$9,123<=$D$9),1,0) | DW35: =IF(AND(124>=$B$9,124<=$D$9),1,0) | DX35: =IF(AND(125>=$B$9,125<=$D$9),1,0) | DY35: =IF(AND(126>=$B$9,126<=$D$9),1,0) | DZ35: =IF(AND(127>=$B$9,127<=$D$9),1,0) | EA35: =IF(AND(128>=$B$9,128<=$D$9),1,0) | EB35: =IF(AND(129>=$B$9,129<=$D$9),1,0) | EC35: =IF(AND(130>=$B$9,130<=$D$9),1,0) | ED35: =IF(AND(131>=$B$9,131<=$D$9),1,0) | EE35: =IF(AND(132>=$B$9,132<=$D$9),1,0) | EF35: =IF(AND(133>=$B$9,133<=$D$9),1,0) | EG35: =IF(AND(134>=$B$9,134<=$D$9),1,0) | EH35: =IF(AND(135>=$B$9,135<=$D$9),1,0) | EI35: =IF(AND(136>=$B$9,136<=$D$9),1,0) | EJ35: =IF(AND(137>=$B$9,137<=$D$9),1,0) | EK35: =IF(AND(138>=$B$9,138<=$D$9),1,0) | EL35: =IF(AND(139>=$B$9,139<=$D$9),1,0) | EM35: =IF(AND(140>=$B$9,140<=$D$9),1,0) | EN35: =IF(AND(141>=$B$9,141<=$D$9),1,0) | EO35: =IF(AND(142>=$B$9,142<=$D$9),1,0) | EP35: =IF(AND(143>=$B$9,143<=$D$9),1,0) | EQ35: =IF(AND(144>=$B$9,144<=$D$9),1,0) | ER35: =IF(AND(145>=$B$9,145<=$D$9),1,0) | ES35: =IF(AND(146>=$B$9,146<=$D$9),1,0) | ET35: =IF(AND(147>=$B$9,147<=$D$9),1,0) | EU35: =IF(AND(148>=$B$9,148<=$D$9),1,0) | EV35: =IF(AND(149>=$B$9,149<=$D$9),1,0) | EW35: =IF(AND(150>=$B$9,150<=$D$9),1,0) | EX35: =IF(AND(151>=$B$9,151<=$D$9),1,0) | EY35: =IF(AND(152>=$B$9,152<=$D$9),1,0) | EZ35: =IF(AND(153>=$B$9,153<=$D$9),1,0) | FA35: =IF(AND(154>=$B$9,154<=$D$9),1,0) | FB35: =IF(AND(155>=$B$9,155<=$D$9),1,0) | FC35: =IF(AND(156>=$B$9,156<=$D$9),1,0) | FD35: =IF(AND(157>=$B$9,157<=$D$9),1,0) | FE35: =IF(AND(158>=$B$9,158<=$D$9),1,0) | FF35: =IF(AND(159>=$B$9,159<=$D$9),1,0) | FG35: =IF(AND(160>=$B$9,160<=$D$9),1,0) | FH35: =IF(AND(161>=$B$9,161<=$D$9),1,0) | FI35: =IF(AND(162>=$B$9,162<=$D$9),1,0) | FJ35: =IF(AND(163>=$B$9,163<=$D$9),1,0) | FK35: =IF(AND(164>=$B$9,164<=$D$9),1,0) | FL35: =IF(AND(165>=$B$9,165<=$D$9),1,0) | FM35: =IF(AND(166>=$B$9,166<=$D$9),1,0) | FN35: =IF(AND(167>=$B$9,167<=$D$9),1,0) | FO35: =IF(AND(168>=$B$9,168<=$D$9),1,0) | FP35: =IF(AND(169>=$B$9,169<=$D$9),1,0) | FQ35: =IF(AND(170>=$B$9,170<=$D$9),1,0) | FR35: =IF(AND(171>=$B$9,171<=$D$9),1,0) | FS35: =IF(AND(172>=$B$9,172<=$D$9),1,0) | FT35: =IF(AND(173>=$B$9,173<=$D$9),1,0) | FU35: =IF(AND(174>=$B$9,174<=$D$9),1,0) | FV35: =IF(AND(175>=$B$9,175<=$D$9),1,0) | FW35: =IF(AND(176>=$B$9,176<=$D$9),1,0) | FX35: =IF(AND(177>=$B$9,177<=$D$9),1,0) | FY35: =IF(AND(178>=$B$9,178<=$D$9),1,0) | FZ35: =IF(AND(179>=$B$9,179<=$D$9),1,0) | GA35: =IF(AND(180>=$B$9,180<=$D$9),1,0) | GB35: =IF(AND(181>=$B$9,181<=$D$9),1,0) | GC35: =IF(AND(182>=$B$9,182<=$D$9),1,0) | GD35: =IF(AND(183>=$B$9,183<=$D$9),1,0) | GE35: =IF(AND(184>=$B$9,184<=$D$9),1,0) | GF35: =IF(AND(185>=$B$9,185<=$D$9),1,0) | GG35: =IF(AND(186>=$B$9,186<=$D$9),1,0) | GH35: =IF(AND(187>=$B$9,187<=$D$9),1,0) | GI35: =IF(AND(188>=$B$9,188<=$D$9),1,0) | GJ35: =IF(AND(189>=$B$9,189<=$D$9),1,0) | GK35: =IF(AND(190>=$B$9,190<=$D$9),1,0) | GL35: =IF(AND(191>=$B$9,191<=$D$9),1,0) | GM35: =IF(AND(192>=$B$9,192<=$D$9),1,0) | GN35: =IF(AND(193>=$B$9,193<=$D$9),1,0) | GO35: =IF(AND(194>=$B$9,194<=$D$9),1,0) | GP35: =IF(AND(195>=$B$9,195<=$D$9),1,0) | GQ35: =IF(AND(196>=$B$9,196<=$D$9),1,0) | GR35: =IF(AND(197>=$B$9,197<=$D$9),1,0) | GS35: =IF(AND(198>=$B$9,198<=$D$9),1,0) | GT35: =IF(AND(199>=$B$9,199<=$D$9),1,0) | GU35: =IF(AND(200>=$B$9,200<=$D$9),1,0) | GV35: =IF(AND(201>=$B$9,201<=$D$9),1,0) | GW35: =IF(AND(202>=$B$9,202<=$D$9),1,0) | GX35: =IF(AND(203>=$B$9,203<=$D$9),1,0) | GY35: =IF(AND(204>=$B$9,204<=$D$9),1,0) | GZ35: =IF(AND(205>=$B$9,205<=$D$9),1,0) | HA35: =IF(AND(206>=$B$9,206<=$D$9),1,0) | HB35: =IF(AND(207>=$B$9,207<=$D$9),1,0) | HC35: =IF(AND(208>=$B$9,208<=$D$9),1,0) | HD35: =IF(AND(209>=$B$9,209<=$D$9),1,0) | HE35: =IF(AND(210>=$B$9,210<=$D$9),1,0) | HF35: =IF(AND(211>=$B$9,211<=$D$9),1,0) | HG35: =IF(AND(212>=$B$9,212<=$D$9),1,0) | HH35: =IF(AND(213>=$B$9,213<=$D$9),1,0) | HI35: =IF(AND(214>=$B$9,214<=$D$9),1,0) | HJ35: =IF(AND(215>=$B$9,215<=$D$9),1,0) | HK35: =IF(AND(216>=$B$9,216<=$D$9),1,0) | HL35: =IF(AND(217>=$B$9,217<=$D$9),1,0) | HM35: =IF(AND(218>=$B$9,218<=$D$9),1,0) | HN35: =IF(AND(219>=$B$9,219<=$D$9),1,0) | HO35: =IF(AND(220>=$B$9,220<=$D$9),1,0) | HP35: =IF(AND(221>=$B$9,221<=$D$9),1,0) | HQ35: =IF(AND(222>=$B$9,222<=$D$9),1,0) | HR35: =IF(AND(223>=$B$9,223<=$D$9),1,0) | HS35: =IF(AND(224>=$B$9,224<=$D$9),1,0) | HT35: =IF(AND(225>=$B$9,225<=$D$9),1,0) | HU35: =IF(AND(226>=$B$9,226<=$D$9),1,0) | HV35: =IF(AND(227>=$B$9,227<=$D$9),1,0) | HW35: =IF(AND(228>=$B$9,228<=$D$9),1,0) | HX35: =IF(AND(229>=$B$9,229<=$D$9),1,0) | HY35: =IF(AND(230>=$B$9,230<=$D$9),1,0) | HZ35: =IF(AND(231>=$B$9,231<=$D$9),1,0) | IA35: =IF(AND(232>=$B$9,232<=$D$9),1,0) | IB35: =IF(AND(233>=$B$9,233<=$D$9),1,0) | IC35: =IF(AND(234>=$B$9,234<=$D$9),1,0) | ID35: =IF(AND(235>=$B$9,235<=$D$9),1,0) | IE35: =IF(AND(236>=$B$9,236<=$D$9),1,0) | IF35: =IF(AND(237>=$B$9,237<=$D$9),1,0) | IG35: =IF(AND(238>=$B$9,238<=$D$9),1,0) | IH35: =IF(AND(239>=$B$9,239<=$D$9),1,0) | II35: =IF(AND(240>=$B$9,240<=$D$9),1,0) | IJ35: =IF(AND(241>=$B$9,241<=$D$9),1,0) | IK35: =IF(AND(242>=$B$9,242<=$D$9),1,0) | IL35: =IF(AND(243>=$B$9,243<=$D$9),1,0) | IM35: =IF(AND(244>=$B$9,244<=$D$9),1,0) | IN35: =IF(AND(245>=$B$9,245<=$D$9),1,0) | IO35: =IF(AND(246>=$B$9,246<=$D$9),1,0) | IP35: =IF(AND(247>=$B$9,247<=$D$9),1,0) | IQ35: =IF(AND(248>=$B$9,248<=$D$9),1,0) | IR35: =IF(AND(249>=$B$9,249<=$D$9),1,0) | IS35: =IF(AND(250>=$B$9,250<=$D$9),1,0) | IT35: =IF(AND(251>=$B$9,251<=$D$9),1,0) | IU35: =IF(AND(252>=$B$9,252<=$D$9),1,0) | IV35: =IF(AND(253>=$B$9,253<=$D$9),1,0) | IW35: =IF(AND(254>=$B$9,254<=$D$9),1,0) | IX35: =IF(AND(255>=$B$9,255<=$D$9),1,0) | IY35: =IF(AND(256>=$B$9,256<=$D$9),1,0) | IZ35: =IF(AND(257>=$B$9,257<=$D$9),1,0) | JA35: =IF(AND(258>=$B$9,258<=$D$9),1,0) | JB35: =IF(AND(259>=$B$9,259<=$D$9),1,0) | JC35: =IF(AND(260>=$B$9,260<=$D$9),1,0) | JD35: =IF(AND(261>=$B$9,261<=$D$9),1,0) | JE35: =IF(AND(262>=$B$9,262<=$D$9),1,0) | JF35: =IF(AND(263>=$B$9,263<=$D$9),1,0) | JG35: =IF(AND(264>=$B$9,264<=$D$9),1,0) | JH35: =IF(AND(265>=$B$9,265<=$D$9),1,0) | JI35: =IF(AND(266>=$B$9,266<=$D$9),1,0) | JJ35: =IF(AND(267>=$B$9,267<=$D$9),1,0) | JK35: =IF(AND(268>=$B$9,268<=$D$9),1,0) | JL35: =IF(AND(269>=$B$9,269<=$D$9),1,0) | JM35: =IF(AND(270>=$B$9,270<=$D$9),1,0) | JN35: =IF(AND(271>=$B$9,271<=$D$9),1,0) | JO35: =IF(AND(272>=$B$9,272<=$D$9),1,0) | JP35: =IF(AND(273>=$B$9,273<=$D$9),1,0) | JQ35: =IF(AND(274>=$B$9,274<=$D$9),1,0) | JR35: =IF(AND(275>=$B$9,275<=$D$9),1,0) | JS35: =IF(AND(276>=$B$9,276<=$D$9),1,0) | JT35: =IF(AND(277>=$B$9,277<=$D$9),1,0) | JU35: =IF(AND(278>=$B$9,278<=$D$9),1,0) | JV35: =IF(AND(279>=$B$9,279<=$D$9),1,0) | JW35: =IF(AND(280>=$B$9,280<=$D$9),1,0) | JX35: =IF(AND(281>=$B$9,281<=$D$9),1,0) | JY35: =IF(AND(282>=$B$9,282<=$D$9),1,0) | JZ35: =IF(AND(283>=$B$9,283<=$D$9),1,0) | KA35: =IF(AND(284>=$B$9,284<=$D$9),1,0) | KB35: =IF(AND(285>=$B$9,285<=$D$9),1,0) | KC35: =IF(AND(286>=$B$9,286<=$D$9),1,0) | KD35: =IF(AND(287>=$B$9,287<=$D$9),1,0) | KE35: =IF(AND(288>=$B$9,288<=$D$9),1,0) | KF35: =IF(AND(289>=$B$9,289<=$D$9),1,0) | KG35: =IF(AND(290>=$B$9,290<=$D$9),1,0) | KH35: =IF(AND(291>=$B$9,291<=$D$9),1,0) | KI35: =IF(AND(292>=$B$9,292<=$D$9),1,0) | KJ35: =IF(AND(293>=$B$9,293<=$D$9),1,0) | KK35: =IF(AND(294>=$B$9,294<=$D$9),1,0) | KL35: =IF(AND(295>=$B$9,295<=$D$9),1,0) | KM35: =IF(AND(296>=$B$9,296<=$D$9),1,0) | KN35: =IF(AND(297>=$B$9,297<=$D$9),1,0) | KO35: =IF(AND(298>=$B$9,298<=$D$9),1,0) | KP35: =IF(AND(299>=$B$9,299<=$D$9),1,0) | KQ35: =IF(AND(300>=$B$9,300<=$D$9),1,0) | KR35: =IF(AND(301>=$B$9,301<=$D$9),1,0) | KS35: =IF(AND(302>=$B$9,302<=$D$9),1,0) | KT35: =IF(AND(303>=$B$9,303<=$D$9),1,0) | KU35: =IF(AND(304>=$B$9,304<=$D$9),1,0) | KV35: =IF(AND(305>=$B$9,305<=$D$9),1,0) | KW35: =IF(AND(306>=$B$9,306<=$D$9),1,0) | KX35: =IF(AND(307>=$B$9,307<=$D$9),1,0) | KY35: =IF(AND(308>=$B$9,308<=$D$9),1,0) | KZ35: =IF(AND(309>=$B$9,309<=$D$9),1,0) | LA35: =IF(AND(310>=$B$9,310<=$D$9),1,0) | LB35: =IF(AND(311>=$B$9,311<=$D$9),1,0) | LC35: =IF(AND(312>=$B$9,312<=$D$9),1,0) | LD35: =IF(AND(313>=$B$9,313<=$D$9),1,0) | LE35: =IF(AND(314>=$B$9,314<=$D$9),1,0) | LF35: =IF(AND(315>=$B$9,315<=$D$9),1,0) | LG35: =IF(AND(316>=$B$9,316<=$D$9),1,0) | LH35: =IF(AND(317>=$B$9,317<=$D$9),1,0) | LI35: =IF(AND(318>=$B$9,318<=$D$9),1,0) | LJ35: =IF(AND(319>=$B$9,319<=$D$9),1,0) | LK35: =IF(AND(320>=$B$9,320<=$D$9),1,0) | LL35: =IF(AND(321>=$B$9,321<=$D$9),1,0) | LM35: =IF(AND(322>=$B$9,322<=$D$9),1,0) | LN35: =IF(AND(323>=$B$9,323<=$D$9),1,0) | LO35: =IF(AND(324>=$B$9,324<=$D$9),1,0) | LP35: =IF(AND(325>=$B$9,325<=$D$9),1,0) | LQ35: =IF(AND(326>=$B$9,326<=$D$9),1,0) | LR35: =IF(AND(327>=$B$9,327<=$D$9),1,0) | LS35: =IF(AND(328>=$B$9,328<=$D$9),1,0) | LT35: =IF(AND(329>=$B$9,329<=$D$9),1,0) | LU35: =IF(AND(330>=$B$9,330<=$D$9),1,0) | LV35: =IF(AND(331>=$B$9,331<=$D$9),1,0) | LW35: =IF(AND(332>=$B$9,332<=$D$9),1,0) | LX35: =IF(AND(333>=$B$9,333<=$D$9),1,0) | LY35: =IF(AND(334>=$B$9,334<=$D$9),1,0) | LZ35: =IF(AND(335>=$B$9,335<=$D$9),1,0) | MA35: =IF(AND(336>=$B$9,336<=$D$9),1,0) | MB35: =IF(AND(337>=$B$9,337<=$D$9),1,0) | MC35: =IF(AND(338>=$B$9,338<=$D$9),1,0) | MD35: =IF(AND(339>=$B$9,339<=$D$9),1,0) | ME35: =IF(AND(340>=$B$9,340<=$D$9),1,0) | MF35: =IF(AND(341>=$B$9,341<=$D$9),1,0) | MG35: =IF(AND(342>=$B$9,342<=$D$9),1,0) | MH35: =IF(AND(343>=$B$9,343<=$D$9),1,0) | MI35: =IF(AND(344>=$B$9,344<=$D$9),1,0) | MJ35: =IF(AND(345>=$B$9,345<=$D$9),1,0) | MK35: =IF(AND(346>=$B$9,346<=$D$9),1,0) | ML35: =IF(AND(347>=$B$9,347<=$D$9),1,0) | MM35: =IF(AND(348>=$B$9,348<=$D$9),1,0) | MN35: =IF(AND(349>=$B$9,349<=$D$9),1,0) | MO35: =IF(AND(350>=$B$9,350<=$D$9),1,0) | MP35: =IF(AND(351>=$B$9,351<=$D$9),1,0) | MQ35: =IF(AND(352>=$B$9,352<=$D$9),1,0) | MR35: =IF(AND(353>=$B$9,353<=$D$9),1,0) | MS35: =IF(AND(354>=$B$9,354<=$D$9),1,0) | MT35: =IF(AND(355>=$B$9,355<=$D$9),1,0) | MU35: =IF(AND(356>=$B$9,356<=$D$9),1,0) | MV35: =IF(AND(357>=$B$9,357<=$D$9),1,0) | MW35: =IF(AND(358>=$B$9,358<=$D$9),1,0) | MX35: =IF(AND(359>=$B$9,359<=$D$9),1,0) | MY35: =IF(AND(360>=$B$9,360<=$D$9),1,0) | MZ35: =IF(AND(361>=$B$9,361<=$D$9),1,0) | NA35: =IF(AND(362>=$B$9,362<=$D$9),1,0) | NB35: =IF(AND(363>=$B$9,363<=$D$9),1,0) | NC35: =IF(AND(364>=$B$9,364<=$D$9),1,0) | ND35: =IF(AND(365>=$B$9,365<=$D$9),1,0) | NE35: =IF(AND(366>=$B$9,366<=$D$9),1,0) | NF35: =IF(AND(367>=$B$9,367<=$D$9),1,0) | NG35: =IF(AND(368>=$B$9,368<=$D$9),1,0) | NH35: =IF(AND(369>=$B$9,369<=$D$9),1,0) | NI35: =IF(AND(370>=$B$9,370<=$D$9),1,0) | NJ35: =IF(AND(371>=$B$9,371<=$D$9),1,0) | NK35: =IF(AND(372>=$B$9,372<=$D$9),1,0)
A36: Flag: 1st Unit Delivery | D36: =IF(AND(1>=$B$10,1<=$D$10),1,0) | E36: =IF(AND(2>=$B$10,2<=$D$10),1,0) | F36: =IF(AND(3>=$B$10,3<=$D$10),1,0) | G36: =IF(AND(4>=$B$10,4<=$D$10),1,0) | H36: =IF(AND(5>=$B$10,5<=$D$10),1,0) | I36: =IF(AND(6>=$B$10,6<=$D$10),1,0) | J36: =IF(AND(7>=$B$10,7<=$D$10),1,0) | K36: =IF(AND(8>=$B$10,8<=$D$10),1,0) | L36: =IF(AND(9>=$B$10,9<=$D$10),1,0) | M36: =IF(AND(10>=$B$10,10<=$D$10),1,0) | N36: =IF(AND(11>=$B$10,11<=$D$10),1,0) | O36: =IF(AND(12>=$B$10,12<=$D$10),1,0) | P36: =IF(AND(13>=$B$10,13<=$D$10),1,0) | Q36: =IF(AND(14>=$B$10,14<=$D$10),1,0) | R36: =IF(AND(15>=$B$10,15<=$D$10),1,0) | S36: =IF(AND(16>=$B$10,16<=$D$10),1,0) | T36: =IF(AND(17>=$B$10,17<=$D$10),1,0) | U36: =IF(AND(18>=$B$10,18<=$D$10),1,0) | V36: =IF(AND(19>=$B$10,19<=$D$10),1,0) | W36: =IF(AND(20>=$B$10,20<=$D$10),1,0) | X36: =IF(AND(21>=$B$10,21<=$D$10),1,0) | Y36: =IF(AND(22>=$B$10,22<=$D$10),1,0) | Z36: =IF(AND(23>=$B$10,23<=$D$10),1,0) | AA36: =IF(AND(24>=$B$10,24<=$D$10),1,0) | AB36: =IF(AND(25>=$B$10,25<=$D$10),1,0) | AC36: =IF(AND(26>=$B$10,26<=$D$10),1,0) | AD36: =IF(AND(27>=$B$10,27<=$D$10),1,0) | AE36: =IF(AND(28>=$B$10,28<=$D$10),1,0) | AF36: =IF(AND(29>=$B$10,29<=$D$10),1,0) | AG36: =IF(AND(30>=$B$10,30<=$D$10),1,0) | AH36: =IF(AND(31>=$B$10,31<=$D$10),1,0) | AI36: =IF(AND(32>=$B$10,32<=$D$10),1,0) | AJ36: =IF(AND(33>=$B$10,33<=$D$10),1,0) | AK36: =IF(AND(34>=$B$10,34<=$D$10),1,0) | AL36: =IF(AND(35>=$B$10,35<=$D$10),1,0) | AM36: =IF(AND(36>=$B$10,36<=$D$10),1,0) | AN36: =IF(AND(37>=$B$10,37<=$D$10),1,0) | AO36: =IF(AND(38>=$B$10,38<=$D$10),1,0) | AP36: =IF(AND(39>=$B$10,39<=$D$10),1,0) | AQ36: =IF(AND(40>=$B$10,40<=$D$10),1,0) | AR36: =IF(AND(41>=$B$10,41<=$D$10),1,0) | AS36: =IF(AND(42>=$B$10,42<=$D$10),1,0) | AT36: =IF(AND(43>=$B$10,43<=$D$10),1,0) | AU36: =IF(AND(44>=$B$10,44<=$D$10),1,0) | AV36: =IF(AND(45>=$B$10,45<=$D$10),1,0) | AW36: =IF(AND(46>=$B$10,46<=$D$10),1,0) | AX36: =IF(AND(47>=$B$10,47<=$D$10),1,0) | AY36: =IF(AND(48>=$B$10,48<=$D$10),1,0) | AZ36: =IF(AND(49>=$B$10,49<=$D$10),1,0) | BA36: =IF(AND(50>=$B$10,50<=$D$10),1,0) | BB36: =IF(AND(51>=$B$10,51<=$D$10),1,0) | BC36: =IF(AND(52>=$B$10,52<=$D$10),1,0) | BD36: =IF(AND(53>=$B$10,53<=$D$10),1,0) | BE36: =IF(AND(54>=$B$10,54<=$D$10),1,0) | BF36: =IF(AND(55>=$B$10,55<=$D$10),1,0) | BG36: =IF(AND(56>=$B$10,56<=$D$10),1,0) | BH36: =IF(AND(57>=$B$10,57<=$D$10),1,0) | BI36: =IF(AND(58>=$B$10,58<=$D$10),1,0) | BJ36: =IF(AND(59>=$B$10,59<=$D$10),1,0) | BK36: =IF(AND(60>=$B$10,60<=$D$10),1,0) | BL36: =IF(AND(61>=$B$10,61<=$D$10),1,0) | BM36: =IF(AND(62>=$B$10,62<=$D$10),1,0) | BN36: =IF(AND(63>=$B$10,63<=$D$10),1,0) | BO36: =IF(AND(64>=$B$10,64<=$D$10),1,0) | BP36: =IF(AND(65>=$B$10,65<=$D$10),1,0) | BQ36: =IF(AND(66>=$B$10,66<=$D$10),1,0) | BR36: =IF(AND(67>=$B$10,67<=$D$10),1,0) | BS36: =IF(AND(68>=$B$10,68<=$D$10),1,0) | BT36: =IF(AND(69>=$B$10,69<=$D$10),1,0) | BU36: =IF(AND(70>=$B$10,70<=$D$10),1,0) | BV36: =IF(AND(71>=$B$10,71<=$D$10),1,0) | BW36: =IF(AND(72>=$B$10,72<=$D$10),1,0) | BX36: =IF(AND(73>=$B$10,73<=$D$10),1,0) | BY36: =IF(AND(74>=$B$10,74<=$D$10),1,0) | BZ36: =IF(AND(75>=$B$10,75<=$D$10),1,0) | CA36: =IF(AND(76>=$B$10,76<=$D$10),1,0) | CB36: =IF(AND(77>=$B$10,77<=$D$10),1,0) | CC36: =IF(AND(78>=$B$10,78<=$D$10),1,0) | CD36: =IF(AND(79>=$B$10,79<=$D$10),1,0) | CE36: =IF(AND(80>=$B$10,80<=$D$10),1,0) | CF36: =IF(AND(81>=$B$10,81<=$D$10),1,0) | CG36: =IF(AND(82>=$B$10,82<=$D$10),1,0) | CH36: =IF(AND(83>=$B$10,83<=$D$10),1,0) | CI36: =IF(AND(84>=$B$10,84<=$D$10),1,0) | CJ36: =IF(AND(85>=$B$10,85<=$D$10),1,0) | CK36: =IF(AND(86>=$B$10,86<=$D$10),1,0) | CL36: =IF(AND(87>=$B$10,87<=$D$10),1,0) | CM36: =IF(AND(88>=$B$10,88<=$D$10),1,0) | CN36: =IF(AND(89>=$B$10,89<=$D$10),1,0) | CO36: =IF(AND(90>=$B$10,90<=$D$10),1,0) | CP36: =IF(AND(91>=$B$10,91<=$D$10),1,0) | CQ36: =IF(AND(92>=$B$10,92<=$D$10),1,0) | CR36: =IF(AND(93>=$B$10,93<=$D$10),1,0) | CS36: =IF(AND(94>=$B$10,94<=$D$10),1,0) | CT36: =IF(AND(95>=$B$10,95<=$D$10),1,0) | CU36: =IF(AND(96>=$B$10,96<=$D$10),1,0) | CV36: =IF(AND(97>=$B$10,97<=$D$10),1,0) | CW36: =IF(AND(98>=$B$10,98<=$D$10),1,0) | CX36: =IF(AND(99>=$B$10,99<=$D$10),1,0) | CY36: =IF(AND(100>=$B$10,100<=$D$10),1,0) | CZ36: =IF(AND(101>=$B$10,101<=$D$10),1,0) | DA36: =IF(AND(102>=$B$10,102<=$D$10),1,0) | DB36: =IF(AND(103>=$B$10,103<=$D$10),1,0) | DC36: =IF(AND(104>=$B$10,104<=$D$10),1,0) | DD36: =IF(AND(105>=$B$10,105<=$D$10),1,0) | DE36: =IF(AND(106>=$B$10,106<=$D$10),1,0) | DF36: =IF(AND(107>=$B$10,107<=$D$10),1,0) | DG36: =IF(AND(108>=$B$10,108<=$D$10),1,0) | DH36: =IF(AND(109>=$B$10,109<=$D$10),1,0) | DI36: =IF(AND(110>=$B$10,110<=$D$10),1,0) | DJ36: =IF(AND(111>=$B$10,111<=$D$10),1,0) | DK36: =IF(AND(112>=$B$10,112<=$D$10),1,0) | DL36: =IF(AND(113>=$B$10,113<=$D$10),1,0) | DM36: =IF(AND(114>=$B$10,114<=$D$10),1,0) | DN36: =IF(AND(115>=$B$10,115<=$D$10),1,0) | DO36: =IF(AND(116>=$B$10,116<=$D$10),1,0) | DP36: =IF(AND(117>=$B$10,117<=$D$10),1,0) | DQ36: =IF(AND(118>=$B$10,118<=$D$10),1,0) | DR36: =IF(AND(119>=$B$10,119<=$D$10),1,0) | DS36: =IF(AND(120>=$B$10,120<=$D$10),1,0) | DT36: =IF(AND(121>=$B$10,121<=$D$10),1,0) | DU36: =IF(AND(122>=$B$10,122<=$D$10),1,0) | DV36: =IF(AND(123>=$B$10,123<=$D$10),1,0) | DW36: =IF(AND(124>=$B$10,124<=$D$10),1,0) | DX36: =IF(AND(125>=$B$10,125<=$D$10),1,0) | DY36: =IF(AND(126>=$B$10,126<=$D$10),1,0) | DZ36: =IF(AND(127>=$B$10,127<=$D$10),1,0) | EA36: =IF(AND(128>=$B$10,128<=$D$10),1,0) | EB36: =IF(AND(129>=$B$10,129<=$D$10),1,0) | EC36: =IF(AND(130>=$B$10,130<=$D$10),1,0) | ED36: =IF(AND(131>=$B$10,131<=$D$10),1,0) | EE36: =IF(AND(132>=$B$10,132<=$D$10),1,0) | EF36: =IF(AND(133>=$B$10,133<=$D$10),1,0) | EG36: =IF(AND(134>=$B$10,134<=$D$10),1,0) | EH36: =IF(AND(135>=$B$10,135<=$D$10),1,0) | EI36: =IF(AND(136>=$B$10,136<=$D$10),1,0) | EJ36: =IF(AND(137>=$B$10,137<=$D$10),1,0) | EK36: =IF(AND(138>=$B$10,138<=$D$10),1,0) | EL36: =IF(AND(139>=$B$10,139<=$D$10),1,0) | EM36: =IF(AND(140>=$B$10,140<=$D$10),1,0) | EN36: =IF(AND(141>=$B$10,141<=$D$10),1,0) | EO36: =IF(AND(142>=$B$10,142<=$D$10),1,0) | EP36: =IF(AND(143>=$B$10,143<=$D$10),1,0) | EQ36: =IF(AND(144>=$B$10,144<=$D$10),1,0) | ER36: =IF(AND(145>=$B$10,145<=$D$10),1,0) | ES36: =IF(AND(146>=$B$10,146<=$D$10),1,0) | ET36: =IF(AND(147>=$B$10,147<=$D$10),1,0) | EU36: =IF(AND(148>=$B$10,148<=$D$10),1,0) | EV36: =IF(AND(149>=$B$10,149<=$D$10),1,0) | EW36: =IF(AND(150>=$B$10,150<=$D$10),1,0) | EX36: =IF(AND(151>=$B$10,151<=$D$10),1,0) | EY36: =IF(AND(152>=$B$10,152<=$D$10),1,0) | EZ36: =IF(AND(153>=$B$10,153<=$D$10),1,0) | FA36: =IF(AND(154>=$B$10,154<=$D$10),1,0) | FB36: =IF(AND(155>=$B$10,155<=$D$10),1,0) | FC36: =IF(AND(156>=$B$10,156<=$D$10),1,0) | FD36: =IF(AND(157>=$B$10,157<=$D$10),1,0) | FE36: =IF(AND(158>=$B$10,158<=$D$10),1,0) | FF36: =IF(AND(159>=$B$10,159<=$D$10),1,0) | FG36: =IF(AND(160>=$B$10,160<=$D$10),1,0) | FH36: =IF(AND(161>=$B$10,161<=$D$10),1,0) | FI36: =IF(AND(162>=$B$10,162<=$D$10),1,0) | FJ36: =IF(AND(163>=$B$10,163<=$D$10),1,0) | FK36: =IF(AND(164>=$B$10,164<=$D$10),1,0) | FL36: =IF(AND(165>=$B$10,165<=$D$10),1,0) | FM36: =IF(AND(166>=$B$10,166<=$D$10),1,0) | FN36: =IF(AND(167>=$B$10,167<=$D$10),1,0) | FO36: =IF(AND(168>=$B$10,168<=$D$10),1,0) | FP36: =IF(AND(169>=$B$10,169<=$D$10),1,0) | FQ36: =IF(AND(170>=$B$10,170<=$D$10),1,0) | FR36: =IF(AND(171>=$B$10,171<=$D$10),1,0) | FS36: =IF(AND(172>=$B$10,172<=$D$10),1,0) | FT36: =IF(AND(173>=$B$10,173<=$D$10),1,0) | FU36: =IF(AND(174>=$B$10,174<=$D$10),1,0) | FV36: =IF(AND(175>=$B$10,175<=$D$10),1,0) | FW36: =IF(AND(176>=$B$10,176<=$D$10),1,0) | FX36: =IF(AND(177>=$B$10,177<=$D$10),1,0) | FY36: =IF(AND(178>=$B$10,178<=$D$10),1,0) | FZ36: =IF(AND(179>=$B$10,179<=$D$10),1,0) | GA36: =IF(AND(180>=$B$10,180<=$D$10),1,0) | GB36: =IF(AND(181>=$B$10,181<=$D$10),1,0) | GC36: =IF(AND(182>=$B$10,182<=$D$10),1,0) | GD36: =IF(AND(183>=$B$10,183<=$D$10),1,0) | GE36: =IF(AND(184>=$B$10,184<=$D$10),1,0) | GF36: =IF(AND(185>=$B$10,185<=$D$10),1,0) | GG36: =IF(AND(186>=$B$10,186<=$D$10),1,0) | GH36: =IF(AND(187>=$B$10,187<=$D$10),1,0) | GI36: =IF(AND(188>=$B$10,188<=$D$10),1,0) | GJ36: =IF(AND(189>=$B$10,189<=$D$10),1,0) | GK36: =IF(AND(190>=$B$10,190<=$D$10),1,0) | GL36: =IF(AND(191>=$B$10,191<=$D$10),1,0) | GM36: =IF(AND(192>=$B$10,192<=$D$10),1,0) | GN36: =IF(AND(193>=$B$10,193<=$D$10),1,0) | GO36: =IF(AND(194>=$B$10,194<=$D$10),1,0) | GP36: =IF(AND(195>=$B$10,195<=$D$10),1,0) | GQ36: =IF(AND(196>=$B$10,196<=$D$10),1,0) | GR36: =IF(AND(197>=$B$10,197<=$D$10),1,0) | GS36: =IF(AND(198>=$B$10,198<=$D$10),1,0) | GT36: =IF(AND(199>=$B$10,199<=$D$10),1,0) | GU36: =IF(AND(200>=$B$10,200<=$D$10),1,0) | GV36: =IF(AND(201>=$B$10,201<=$D$10),1,0) | GW36: =IF(AND(202>=$B$10,202<=$D$10),1,0) | GX36: =IF(AND(203>=$B$10,203<=$D$10),1,0) | GY36: =IF(AND(204>=$B$10,204<=$D$10),1,0) | GZ36: =IF(AND(205>=$B$10,205<=$D$10),1,0) | HA36: =IF(AND(206>=$B$10,206<=$D$10),1,0) | HB36: =IF(AND(207>=$B$10,207<=$D$10),1,0) | HC36: =IF(AND(208>=$B$10,208<=$D$10),1,0) | HD36: =IF(AND(209>=$B$10,209<=$D$10),1,0) | HE36: =IF(AND(210>=$B$10,210<=$D$10),1,0) | HF36: =IF(AND(211>=$B$10,211<=$D$10),1,0) | HG36: =IF(AND(212>=$B$10,212<=$D$10),1,0) | HH36: =IF(AND(213>=$B$10,213<=$D$10),1,0) | HI36: =IF(AND(214>=$B$10,214<=$D$10),1,0) | HJ36: =IF(AND(215>=$B$10,215<=$D$10),1,0) | HK36: =IF(AND(216>=$B$10,216<=$D$10),1,0) | HL36: =IF(AND(217>=$B$10,217<=$D$10),1,0) | HM36: =IF(AND(218>=$B$10,218<=$D$10),1,0) | HN36: =IF(AND(219>=$B$10,219<=$D$10),1,0) | HO36: =IF(AND(220>=$B$10,220<=$D$10),1,0) | HP36: =IF(AND(221>=$B$10,221<=$D$10),1,0) | HQ36: =IF(AND(222>=$B$10,222<=$D$10),1,0) | HR36: =IF(AND(223>=$B$10,223<=$D$10),1,0) | HS36: =IF(AND(224>=$B$10,224<=$D$10),1,0) | HT36: =IF(AND(225>=$B$10,225<=$D$10),1,0) | HU36: =IF(AND(226>=$B$10,226<=$D$10),1,0) | HV36: =IF(AND(227>=$B$10,227<=$D$10),1,0) | HW36: =IF(AND(228>=$B$10,228<=$D$10),1,0) | HX36: =IF(AND(229>=$B$10,229<=$D$10),1,0) | HY36: =IF(AND(230>=$B$10,230<=$D$10),1,0) | HZ36: =IF(AND(231>=$B$10,231<=$D$10),1,0) | IA36: =IF(AND(232>=$B$10,232<=$D$10),1,0) | IB36: =IF(AND(233>=$B$10,233<=$D$10),1,0) | IC36: =IF(AND(234>=$B$10,234<=$D$10),1,0) | ID36: =IF(AND(235>=$B$10,235<=$D$10),1,0) | IE36: =IF(AND(236>=$B$10,236<=$D$10),1,0) | IF36: =IF(AND(237>=$B$10,237<=$D$10),1,0) | IG36: =IF(AND(238>=$B$10,238<=$D$10),1,0) | IH36: =IF(AND(239>=$B$10,239<=$D$10),1,0) | II36: =IF(AND(240>=$B$10,240<=$D$10),1,0) | IJ36: =IF(AND(241>=$B$10,241<=$D$10),1,0) | IK36: =IF(AND(242>=$B$10,242<=$D$10),1,0) | IL36: =IF(AND(243>=$B$10,243<=$D$10),1,0) | IM36: =IF(AND(244>=$B$10,244<=$D$10),1,0) | IN36: =IF(AND(245>=$B$10,245<=$D$10),1,0) | IO36: =IF(AND(246>=$B$10,246<=$D$10),1,0) | IP36: =IF(AND(247>=$B$10,247<=$D$10),1,0) | IQ36: =IF(AND(248>=$B$10,248<=$D$10),1,0) | IR36: =IF(AND(249>=$B$10,249<=$D$10),1,0) | IS36: =IF(AND(250>=$B$10,250<=$D$10),1,0) | IT36: =IF(AND(251>=$B$10,251<=$D$10),1,0) | IU36: =IF(AND(252>=$B$10,252<=$D$10),1,0) | IV36: =IF(AND(253>=$B$10,253<=$D$10),1,0) | IW36: =IF(AND(254>=$B$10,254<=$D$10),1,0) | IX36: =IF(AND(255>=$B$10,255<=$D$10),1,0) | IY36: =IF(AND(256>=$B$10,256<=$D$10),1,0) | IZ36: =IF(AND(257>=$B$10,257<=$D$10),1,0) | JA36: =IF(AND(258>=$B$10,258<=$D$10),1,0) | JB36: =IF(AND(259>=$B$10,259<=$D$10),1,0) | JC36: =IF(AND(260>=$B$10,260<=$D$10),1,0) | JD36: =IF(AND(261>=$B$10,261<=$D$10),1,0) | JE36: =IF(AND(262>=$B$10,262<=$D$10),1,0) | JF36: =IF(AND(263>=$B$10,263<=$D$10),1,0) | JG36: =IF(AND(264>=$B$10,264<=$D$10),1,0) | JH36: =IF(AND(265>=$B$10,265<=$D$10),1,0) | JI36: =IF(AND(266>=$B$10,266<=$D$10),1,0) | JJ36: =IF(AND(267>=$B$10,267<=$D$10),1,0) | JK36: =IF(AND(268>=$B$10,268<=$D$10),1,0) | JL36: =IF(AND(269>=$B$10,269<=$D$10),1,0) | JM36: =IF(AND(270>=$B$10,270<=$D$10),1,0) | JN36: =IF(AND(271>=$B$10,271<=$D$10),1,0) | JO36: =IF(AND(272>=$B$10,272<=$D$10),1,0) | JP36: =IF(AND(273>=$B$10,273<=$D$10),1,0) | JQ36: =IF(AND(274>=$B$10,274<=$D$10),1,0) | JR36: =IF(AND(275>=$B$10,275<=$D$10),1,0) | JS36: =IF(AND(276>=$B$10,276<=$D$10),1,0) | JT36: =IF(AND(277>=$B$10,277<=$D$10),1,0) | JU36: =IF(AND(278>=$B$10,278<=$D$10),1,0) | JV36: =IF(AND(279>=$B$10,279<=$D$10),1,0) | JW36: =IF(AND(280>=$B$10,280<=$D$10),1,0) | JX36: =IF(AND(281>=$B$10,281<=$D$10),1,0) | JY36: =IF(AND(282>=$B$10,282<=$D$10),1,0) | JZ36: =IF(AND(283>=$B$10,283<=$D$10),1,0) | KA36: =IF(AND(284>=$B$10,284<=$D$10),1,0) | KB36: =IF(AND(285>=$B$10,285<=$D$10),1,0) | KC36: =IF(AND(286>=$B$10,286<=$D$10),1,0) | KD36: =IF(AND(287>=$B$10,287<=$D$10),1,0) | KE36: =IF(AND(288>=$B$10,288<=$D$10),1,0) | KF36: =IF(AND(289>=$B$10,289<=$D$10),1,0) | KG36: =IF(AND(290>=$B$10,290<=$D$10),1,0) | KH36: =IF(AND(291>=$B$10,291<=$D$10),1,0) | KI36: =IF(AND(292>=$B$10,292<=$D$10),1,0) | KJ36: =IF(AND(293>=$B$10,293<=$D$10),1,0) | KK36: =IF(AND(294>=$B$10,294<=$D$10),1,0) | KL36: =IF(AND(295>=$B$10,295<=$D$10),1,0) | KM36: =IF(AND(296>=$B$10,296<=$D$10),1,0) | KN36: =IF(AND(297>=$B$10,297<=$D$10),1,0) | KO36: =IF(AND(298>=$B$10,298<=$D$10),1,0) | KP36: =IF(AND(299>=$B$10,299<=$D$10),1,0) | KQ36: =IF(AND(300>=$B$10,300<=$D$10),1,0) | KR36: =IF(AND(301>=$B$10,301<=$D$10),1,0) | KS36: =IF(AND(302>=$B$10,302<=$D$10),1,0) | KT36: =IF(AND(303>=$B$10,303<=$D$10),1,0) | KU36: =IF(AND(304>=$B$10,304<=$D$10),1,0) | KV36: =IF(AND(305>=$B$10,305<=$D$10),1,0) | KW36: =IF(AND(306>=$B$10,306<=$D$10),1,0) | KX36: =IF(AND(307>=$B$10,307<=$D$10),1,0) | KY36: =IF(AND(308>=$B$10,308<=$D$10),1,0) | KZ36: =IF(AND(309>=$B$10,309<=$D$10),1,0) | LA36: =IF(AND(310>=$B$10,310<=$D$10),1,0) | LB36: =IF(AND(311>=$B$10,311<=$D$10),1,0) | LC36: =IF(AND(312>=$B$10,312<=$D$10),1,0) | LD36: =IF(AND(313>=$B$10,313<=$D$10),1,0) | LE36: =IF(AND(314>=$B$10,314<=$D$10),1,0) | LF36: =IF(AND(315>=$B$10,315<=$D$10),1,0) | LG36: =IF(AND(316>=$B$10,316<=$D$10),1,0) | LH36: =IF(AND(317>=$B$10,317<=$D$10),1,0) | LI36: =IF(AND(318>=$B$10,318<=$D$10),1,0) | LJ36: =IF(AND(319>=$B$10,319<=$D$10),1,0) | LK36: =IF(AND(320>=$B$10,320<=$D$10),1,0) | LL36: =IF(AND(321>=$B$10,321<=$D$10),1,0) | LM36: =IF(AND(322>=$B$10,322<=$D$10),1,0) | LN36: =IF(AND(323>=$B$10,323<=$D$10),1,0) | LO36: =IF(AND(324>=$B$10,324<=$D$10),1,0) | LP36: =IF(AND(325>=$B$10,325<=$D$10),1,0) | LQ36: =IF(AND(326>=$B$10,326<=$D$10),1,0) | LR36: =IF(AND(327>=$B$10,327<=$D$10),1,0) | LS36: =IF(AND(328>=$B$10,328<=$D$10),1,0) | LT36: =IF(AND(329>=$B$10,329<=$D$10),1,0) | LU36: =IF(AND(330>=$B$10,330<=$D$10),1,0) | LV36: =IF(AND(331>=$B$10,331<=$D$10),1,0) | LW36: =IF(AND(332>=$B$10,332<=$D$10),1,0) | LX36: =IF(AND(333>=$B$10,333<=$D$10),1,0) | LY36: =IF(AND(334>=$B$10,334<=$D$10),1,0) | LZ36: =IF(AND(335>=$B$10,335<=$D$10),1,0) | MA36: =IF(AND(336>=$B$10,336<=$D$10),1,0) | MB36: =IF(AND(337>=$B$10,337<=$D$10),1,0) | MC36: =IF(AND(338>=$B$10,338<=$D$10),1,0) | MD36: =IF(AND(339>=$B$10,339<=$D$10),1,0) | ME36: =IF(AND(340>=$B$10,340<=$D$10),1,0) | MF36: =IF(AND(341>=$B$10,341<=$D$10),1,0) | MG36: =IF(AND(342>=$B$10,342<=$D$10),1,0) | MH36: =IF(AND(343>=$B$10,343<=$D$10),1,0) | MI36: =IF(AND(344>=$B$10,344<=$D$10),1,0) | MJ36: =IF(AND(345>=$B$10,345<=$D$10),1,0) | MK36: =IF(AND(346>=$B$10,346<=$D$10),1,0) | ML36: =IF(AND(347>=$B$10,347<=$D$10),1,0) | MM36: =IF(AND(348>=$B$10,348<=$D$10),1,0) | MN36: =IF(AND(349>=$B$10,349<=$D$10),1,0) | MO36: =IF(AND(350>=$B$10,350<=$D$10),1,0) | MP36: =IF(AND(351>=$B$10,351<=$D$10),1,0) | MQ36: =IF(AND(352>=$B$10,352<=$D$10),1,0) | MR36: =IF(AND(353>=$B$10,353<=$D$10),1,0) | MS36: =IF(AND(354>=$B$10,354<=$D$10),1,0) | MT36: =IF(AND(355>=$B$10,355<=$D$10),1,0) | MU36: =IF(AND(356>=$B$10,356<=$D$10),1,0) | MV36: =IF(AND(357>=$B$10,357<=$D$10),1,0) | MW36: =IF(AND(358>=$B$10,358<=$D$10),1,0) | MX36: =IF(AND(359>=$B$10,359<=$D$10),1,0) | MY36: =IF(AND(360>=$B$10,360<=$D$10),1,0) | MZ36: =IF(AND(361>=$B$10,361<=$D$10),1,0) | NA36: =IF(AND(362>=$B$10,362<=$D$10),1,0) | NB36: =IF(AND(363>=$B$10,363<=$D$10),1,0) | NC36: =IF(AND(364>=$B$10,364<=$D$10),1,0) | ND36: =IF(AND(365>=$B$10,365<=$D$10),1,0) | NE36: =IF(AND(366>=$B$10,366<=$D$10),1,0) | NF36: =IF(AND(367>=$B$10,367<=$D$10),1,0) | NG36: =IF(AND(368>=$B$10,368<=$D$10),1,0) | NH36: =IF(AND(369>=$B$10,369<=$D$10),1,0) | NI36: =IF(AND(370>=$B$10,370<=$D$10),1,0) | NJ36: =IF(AND(371>=$B$10,371<=$D$10),1,0) | NK36: =IF(AND(372>=$B$10,372<=$D$10),1,0)
A37: Flag: Lease-Up | D37: =IF(AND(1>=$B$11,1<=$D$11),1,0) | E37: =IF(AND(2>=$B$11,2<=$D$11),1,0) | F37: =IF(AND(3>=$B$11,3<=$D$11),1,0) | G37: =IF(AND(4>=$B$11,4<=$D$11),1,0) | H37: =IF(AND(5>=$B$11,5<=$D$11),1,0) | I37: =IF(AND(6>=$B$11,6<=$D$11),1,0) | J37: =IF(AND(7>=$B$11,7<=$D$11),1,0) | K37: =IF(AND(8>=$B$11,8<=$D$11),1,0) | L37: =IF(AND(9>=$B$11,9<=$D$11),1,0) | M37: =IF(AND(10>=$B$11,10<=$D$11),1,0) | N37: =IF(AND(11>=$B$11,11<=$D$11),1,0) | O37: =IF(AND(12>=$B$11,12<=$D$11),1,0) | P37: =IF(AND(13>=$B$11,13<=$D$11),1,0) | Q37: =IF(AND(14>=$B$11,14<=$D$11),1,0) | R37: =IF(AND(15>=$B$11,15<=$D$11),1,0) | S37: =IF(AND(16>=$B$11,16<=$D$11),1,0) | T37: =IF(AND(17>=$B$11,17<=$D$11),1,0) | U37: =IF(AND(18>=$B$11,18<=$D$11),1,0) | V37: =IF(AND(19>=$B$11,19<=$D$11),1,0) | W37: =IF(AND(20>=$B$11,20<=$D$11),1,0) | X37: =IF(AND(21>=$B$11,21<=$D$11),1,0) | Y37: =IF(AND(22>=$B$11,22<=$D$11),1,0) | Z37: =IF(AND(23>=$B$11,23<=$D$11),1,0) | AA37: =IF(AND(24>=$B$11,24<=$D$11),1,0) | AB37: =IF(AND(25>=$B$11,25<=$D$11),1,0) | AC37: =IF(AND(26>=$B$11,26<=$D$11),1,0) | AD37: =IF(AND(27>=$B$11,27<=$D$11),1,0) | AE37: =IF(AND(28>=$B$11,28<=$D$11),1,0) | AF37: =IF(AND(29>=$B$11,29<=$D$11),1,0) | AG37: =IF(AND(30>=$B$11,30<=$D$11),1,0) | AH37: =IF(AND(31>=$B$11,31<=$D$11),1,0) | AI37: =IF(AND(32>=$B$11,32<=$D$11),1,0) | AJ37: =IF(AND(33>=$B$11,33<=$D$11),1,0) | AK37: =IF(AND(34>=$B$11,34<=$D$11),1,0) | AL37: =IF(AND(35>=$B$11,35<=$D$11),1,0) | AM37: =IF(AND(36>=$B$11,36<=$D$11),1,0) | AN37: =IF(AND(37>=$B$11,37<=$D$11),1,0) | AO37: =IF(AND(38>=$B$11,38<=$D$11),1,0) | AP37: =IF(AND(39>=$B$11,39<=$D$11),1,0) | AQ37: =IF(AND(40>=$B$11,40<=$D$11),1,0) | AR37: =IF(AND(41>=$B$11,41<=$D$11),1,0) | AS37: =IF(AND(42>=$B$11,42<=$D$11),1,0) | AT37: =IF(AND(43>=$B$11,43<=$D$11),1,0) | AU37: =IF(AND(44>=$B$11,44<=$D$11),1,0) | AV37: =IF(AND(45>=$B$11,45<=$D$11),1,0) | AW37: =IF(AND(46>=$B$11,46<=$D$11),1,0) | AX37: =IF(AND(47>=$B$11,47<=$D$11),1,0) | AY37: =IF(AND(48>=$B$11,48<=$D$11),1,0) | AZ37: =IF(AND(49>=$B$11,49<=$D$11),1,0) | BA37: =IF(AND(50>=$B$11,50<=$D$11),1,0) | BB37: =IF(AND(51>=$B$11,51<=$D$11),1,0) | BC37: =IF(AND(52>=$B$11,52<=$D$11),1,0) | BD37: =IF(AND(53>=$B$11,53<=$D$11),1,0) | BE37: =IF(AND(54>=$B$11,54<=$D$11),1,0) | BF37: =IF(AND(55>=$B$11,55<=$D$11),1,0) | BG37: =IF(AND(56>=$B$11,56<=$D$11),1,0) | BH37: =IF(AND(57>=$B$11,57<=$D$11),1,0) | BI37: =IF(AND(58>=$B$11,58<=$D$11),1,0) | BJ37: =IF(AND(59>=$B$11,59<=$D$11),1,0) | BK37: =IF(AND(60>=$B$11,60<=$D$11),1,0) | BL37: =IF(AND(61>=$B$11,61<=$D$11),1,0) | BM37: =IF(AND(62>=$B$11,62<=$D$11),1,0) | BN37: =IF(AND(63>=$B$11,63<=$D$11),1,0) | BO37: =IF(AND(64>=$B$11,64<=$D$11),1,0) | BP37: =IF(AND(65>=$B$11,65<=$D$11),1,0) | BQ37: =IF(AND(66>=$B$11,66<=$D$11),1,0) | BR37: =IF(AND(67>=$B$11,67<=$D$11),1,0) | BS37: =IF(AND(68>=$B$11,68<=$D$11),1,0) | BT37: =IF(AND(69>=$B$11,69<=$D$11),1,0) | BU37: =IF(AND(70>=$B$11,70<=$D$11),1,0) | BV37: =IF(AND(71>=$B$11,71<=$D$11),1,0) | BW37: =IF(AND(72>=$B$11,72<=$D$11),1,0) | BX37: =IF(AND(73>=$B$11,73<=$D$11),1,0) | BY37: =IF(AND(74>=$B$11,74<=$D$11),1,0) | BZ37: =IF(AND(75>=$B$11,75<=$D$11),1,0) | CA37: =IF(AND(76>=$B$11,76<=$D$11),1,0) | CB37: =IF(AND(77>=$B$11,77<=$D$11),1,0) | CC37: =IF(AND(78>=$B$11,78<=$D$11),1,0) | CD37: =IF(AND(79>=$B$11,79<=$D$11),1,0) | CE37: =IF(AND(80>=$B$11,80<=$D$11),1,0) | CF37: =IF(AND(81>=$B$11,81<=$D$11),1,0) | CG37: =IF(AND(82>=$B$11,82<=$D$11),1,0) | CH37: =IF(AND(83>=$B$11,83<=$D$11),1,0) | CI37: =IF(AND(84>=$B$11,84<=$D$11),1,0) | CJ37: =IF(AND(85>=$B$11,85<=$D$11),1,0) | CK37: =IF(AND(86>=$B$11,86<=$D$11),1,0) | CL37: =IF(AND(87>=$B$11,87<=$D$11),1,0) | CM37: =IF(AND(88>=$B$11,88<=$D$11),1,0) | CN37: =IF(AND(89>=$B$11,89<=$D$11),1,0) | CO37: =IF(AND(90>=$B$11,90<=$D$11),1,0) | CP37: =IF(AND(91>=$B$11,91<=$D$11),1,0) | CQ37: =IF(AND(92>=$B$11,92<=$D$11),1,0) | CR37: =IF(AND(93>=$B$11,93<=$D$11),1,0) | CS37: =IF(AND(94>=$B$11,94<=$D$11),1,0) | CT37: =IF(AND(95>=$B$11,95<=$D$11),1,0) | CU37: =IF(AND(96>=$B$11,96<=$D$11),1,0) | CV37: =IF(AND(97>=$B$11,97<=$D$11),1,0) | CW37: =IF(AND(98>=$B$11,98<=$D$11),1,0) | CX37: =IF(AND(99>=$B$11,99<=$D$11),1,0) | CY37: =IF(AND(100>=$B$11,100<=$D$11),1,0) | CZ37: =IF(AND(101>=$B$11,101<=$D$11),1,0) | DA37: =IF(AND(102>=$B$11,102<=$D$11),1,0) | DB37: =IF(AND(103>=$B$11,103<=$D$11),1,0) | DC37: =IF(AND(104>=$B$11,104<=$D$11),1,0) | DD37: =IF(AND(105>=$B$11,105<=$D$11),1,0) | DE37: =IF(AND(106>=$B$11,106<=$D$11),1,0) | DF37: =IF(AND(107>=$B$11,107<=$D$11),1,0) | DG37: =IF(AND(108>=$B$11,108<=$D$11),1,0) | DH37: =IF(AND(109>=$B$11,109<=$D$11),1,0) | DI37: =IF(AND(110>=$B$11,110<=$D$11),1,0) | DJ37: =IF(AND(111>=$B$11,111<=$D$11),1,0) | DK37: =IF(AND(112>=$B$11,112<=$D$11),1,0) | DL37: =IF(AND(113>=$B$11,113<=$D$11),1,0) | DM37: =IF(AND(114>=$B$11,114<=$D$11),1,0) | DN37: =IF(AND(115>=$B$11,115<=$D$11),1,0) | DO37: =IF(AND(116>=$B$11,116<=$D$11),1,0) | DP37: =IF(AND(117>=$B$11,117<=$D$11),1,0) | DQ37: =IF(AND(118>=$B$11,118<=$D$11),1,0) | DR37: =IF(AND(119>=$B$11,119<=$D$11),1,0) | DS37: =IF(AND(120>=$B$11,120<=$D$11),1,0) | DT37: =IF(AND(121>=$B$11,121<=$D$11),1,0) | DU37: =IF(AND(122>=$B$11,122<=$D$11),1,0) | DV37: =IF(AND(123>=$B$11,123<=$D$11),1,0) | DW37: =IF(AND(124>=$B$11,124<=$D$11),1,0) | DX37: =IF(AND(125>=$B$11,125<=$D$11),1,0) | DY37: =IF(AND(126>=$B$11,126<=$D$11),1,0) | DZ37: =IF(AND(127>=$B$11,127<=$D$11),1,0) | EA37: =IF(AND(128>=$B$11,128<=$D$11),1,0) | EB37: =IF(AND(129>=$B$11,129<=$D$11),1,0) | EC37: =IF(AND(130>=$B$11,130<=$D$11),1,0) | ED37: =IF(AND(131>=$B$11,131<=$D$11),1,0) | EE37: =IF(AND(132>=$B$11,132<=$D$11),1,0) | EF37: =IF(AND(133>=$B$11,133<=$D$11),1,0) | EG37: =IF(AND(134>=$B$11,134<=$D$11),1,0) | EH37: =IF(AND(135>=$B$11,135<=$D$11),1,0) | EI37: =IF(AND(136>=$B$11,136<=$D$11),1,0) | EJ37: =IF(AND(137>=$B$11,137<=$D$11),1,0) | EK37: =IF(AND(138>=$B$11,138<=$D$11),1,0) | EL37: =IF(AND(139>=$B$11,139<=$D$11),1,0) | EM37: =IF(AND(140>=$B$11,140<=$D$11),1,0) | EN37: =IF(AND(141>=$B$11,141<=$D$11),1,0) | EO37: =IF(AND(142>=$B$11,142<=$D$11),1,0) | EP37: =IF(AND(143>=$B$11,143<=$D$11),1,0) | EQ37: =IF(AND(144>=$B$11,144<=$D$11),1,0) | ER37: =IF(AND(145>=$B$11,145<=$D$11),1,0) | ES37: =IF(AND(146>=$B$11,146<=$D$11),1,0) | ET37: =IF(AND(147>=$B$11,147<=$D$11),1,0) | EU37: =IF(AND(148>=$B$11,148<=$D$11),1,0) | EV37: =IF(AND(149>=$B$11,149<=$D$11),1,0) | EW37: =IF(AND(150>=$B$11,150<=$D$11),1,0) | EX37: =IF(AND(151>=$B$11,151<=$D$11),1,0) | EY37: =IF(AND(152>=$B$11,152<=$D$11),1,0) | EZ37: =IF(AND(153>=$B$11,153<=$D$11),1,0) | FA37: =IF(AND(154>=$B$11,154<=$D$11),1,0) | FB37: =IF(AND(155>=$B$11,155<=$D$11),1,0) | FC37: =IF(AND(156>=$B$11,156<=$D$11),1,0) | FD37: =IF(AND(157>=$B$11,157<=$D$11),1,0) | FE37: =IF(AND(158>=$B$11,158<=$D$11),1,0) | FF37: =IF(AND(159>=$B$11,159<=$D$11),1,0) | FG37: =IF(AND(160>=$B$11,160<=$D$11),1,0) | FH37: =IF(AND(161>=$B$11,161<=$D$11),1,0) | FI37: =IF(AND(162>=$B$11,162<=$D$11),1,0) | FJ37: =IF(AND(163>=$B$11,163<=$D$11),1,0) | FK37: =IF(AND(164>=$B$11,164<=$D$11),1,0) | FL37: =IF(AND(165>=$B$11,165<=$D$11),1,0) | FM37: =IF(AND(166>=$B$11,166<=$D$11),1,0) | FN37: =IF(AND(167>=$B$11,167<=$D$11),1,0) | FO37: =IF(AND(168>=$B$11,168<=$D$11),1,0) | FP37: =IF(AND(169>=$B$11,169<=$D$11),1,0) | FQ37: =IF(AND(170>=$B$11,170<=$D$11),1,0) | FR37: =IF(AND(171>=$B$11,171<=$D$11),1,0) | FS37: =IF(AND(172>=$B$11,172<=$D$11),1,0) | FT37: =IF(AND(173>=$B$11,173<=$D$11),1,0) | FU37: =IF(AND(174>=$B$11,174<=$D$11),1,0) | FV37: =IF(AND(175>=$B$11,175<=$D$11),1,0) | FW37: =IF(AND(176>=$B$11,176<=$D$11),1,0) | FX37: =IF(AND(177>=$B$11,177<=$D$11),1,0) | FY37: =IF(AND(178>=$B$11,178<=$D$11),1,0) | FZ37: =IF(AND(179>=$B$11,179<=$D$11),1,0) | GA37: =IF(AND(180>=$B$11,180<=$D$11),1,0) | GB37: =IF(AND(181>=$B$11,181<=$D$11),1,0) | GC37: =IF(AND(182>=$B$11,182<=$D$11),1,0) | GD37: =IF(AND(183>=$B$11,183<=$D$11),1,0) | GE37: =IF(AND(184>=$B$11,184<=$D$11),1,0) | GF37: =IF(AND(185>=$B$11,185<=$D$11),1,0) | GG37: =IF(AND(186>=$B$11,186<=$D$11),1,0) | GH37: =IF(AND(187>=$B$11,187<=$D$11),1,0) | GI37: =IF(AND(188>=$B$11,188<=$D$11),1,0) | GJ37: =IF(AND(189>=$B$11,189<=$D$11),1,0) | GK37: =IF(AND(190>=$B$11,190<=$D$11),1,0) | GL37: =IF(AND(191>=$B$11,191<=$D$11),1,0) | GM37: =IF(AND(192>=$B$11,192<=$D$11),1,0) | GN37: =IF(AND(193>=$B$11,193<=$D$11),1,0) | GO37: =IF(AND(194>=$B$11,194<=$D$11),1,0) | GP37: =IF(AND(195>=$B$11,195<=$D$11),1,0) | GQ37: =IF(AND(196>=$B$11,196<=$D$11),1,0) | GR37: =IF(AND(197>=$B$11,197<=$D$11),1,0) | GS37: =IF(AND(198>=$B$11,198<=$D$11),1,0) | GT37: =IF(AND(199>=$B$11,199<=$D$11),1,0) | GU37: =IF(AND(200>=$B$11,200<=$D$11),1,0) | GV37: =IF(AND(201>=$B$11,201<=$D$11),1,0) | GW37: =IF(AND(202>=$B$11,202<=$D$11),1,0) | GX37: =IF(AND(203>=$B$11,203<=$D$11),1,0) | GY37: =IF(AND(204>=$B$11,204<=$D$11),1,0) | GZ37: =IF(AND(205>=$B$11,205<=$D$11),1,0) | HA37: =IF(AND(206>=$B$11,206<=$D$11),1,0) | HB37: =IF(AND(207>=$B$11,207<=$D$11),1,0) | HC37: =IF(AND(208>=$B$11,208<=$D$11),1,0) | HD37: =IF(AND(209>=$B$11,209<=$D$11),1,0) | HE37: =IF(AND(210>=$B$11,210<=$D$11),1,0) | HF37: =IF(AND(211>=$B$11,211<=$D$11),1,0) | HG37: =IF(AND(212>=$B$11,212<=$D$11),1,0) | HH37: =IF(AND(213>=$B$11,213<=$D$11),1,0) | HI37: =IF(AND(214>=$B$11,214<=$D$11),1,0) | HJ37: =IF(AND(215>=$B$11,215<=$D$11),1,0) | HK37: =IF(AND(216>=$B$11,216<=$D$11),1,0) | HL37: =IF(AND(217>=$B$11,217<=$D$11),1,0) | HM37: =IF(AND(218>=$B$11,218<=$D$11),1,0) | HN37: =IF(AND(219>=$B$11,219<=$D$11),1,0) | HO37: =IF(AND(220>=$B$11,220<=$D$11),1,0) | HP37: =IF(AND(221>=$B$11,221<=$D$11),1,0) | HQ37: =IF(AND(222>=$B$11,222<=$D$11),1,0) | HR37: =IF(AND(223>=$B$11,223<=$D$11),1,0) | HS37: =IF(AND(224>=$B$11,224<=$D$11),1,0) | HT37: =IF(AND(225>=$B$11,225<=$D$11),1,0) | HU37: =IF(AND(226>=$B$11,226<=$D$11),1,0) | HV37: =IF(AND(227>=$B$11,227<=$D$11),1,0) | HW37: =IF(AND(228>=$B$11,228<=$D$11),1,0) | HX37: =IF(AND(229>=$B$11,229<=$D$11),1,0) | HY37: =IF(AND(230>=$B$11,230<=$D$11),1,0) | HZ37: =IF(AND(231>=$B$11,231<=$D$11),1,0) | IA37: =IF(AND(232>=$B$11,232<=$D$11),1,0) | IB37: =IF(AND(233>=$B$11,233<=$D$11),1,0) | IC37: =IF(AND(234>=$B$11,234<=$D$11),1,0) | ID37: =IF(AND(235>=$B$11,235<=$D$11),1,0) | IE37: =IF(AND(236>=$B$11,236<=$D$11),1,0) | IF37: =IF(AND(237>=$B$11,237<=$D$11),1,0) | IG37: =IF(AND(238>=$B$11,238<=$D$11),1,0) | IH37: =IF(AND(239>=$B$11,239<=$D$11),1,0) | II37: =IF(AND(240>=$B$11,240<=$D$11),1,0) | IJ37: =IF(AND(241>=$B$11,241<=$D$11),1,0) | IK37: =IF(AND(242>=$B$11,242<=$D$11),1,0) | IL37: =IF(AND(243>=$B$11,243<=$D$11),1,0) | IM37: =IF(AND(244>=$B$11,244<=$D$11),1,0) | IN37: =IF(AND(245>=$B$11,245<=$D$11),1,0) | IO37: =IF(AND(246>=$B$11,246<=$D$11),1,0) | IP37: =IF(AND(247>=$B$11,247<=$D$11),1,0) | IQ37: =IF(AND(248>=$B$11,248<=$D$11),1,0) | IR37: =IF(AND(249>=$B$11,249<=$D$11),1,0) | IS37: =IF(AND(250>=$B$11,250<=$D$11),1,0) | IT37: =IF(AND(251>=$B$11,251<=$D$11),1,0) | IU37: =IF(AND(252>=$B$11,252<=$D$11),1,0) | IV37: =IF(AND(253>=$B$11,253<=$D$11),1,0) | IW37: =IF(AND(254>=$B$11,254<=$D$11),1,0) | IX37: =IF(AND(255>=$B$11,255<=$D$11),1,0) | IY37: =IF(AND(256>=$B$11,256<=$D$11),1,0) | IZ37: =IF(AND(257>=$B$11,257<=$D$11),1,0) | JA37: =IF(AND(258>=$B$11,258<=$D$11),1,0) | JB37: =IF(AND(259>=$B$11,259<=$D$11),1,0) | JC37: =IF(AND(260>=$B$11,260<=$D$11),1,0) | JD37: =IF(AND(261>=$B$11,261<=$D$11),1,0) | JE37: =IF(AND(262>=$B$11,262<=$D$11),1,0) | JF37: =IF(AND(263>=$B$11,263<=$D$11),1,0) | JG37: =IF(AND(264>=$B$11,264<=$D$11),1,0) | JH37: =IF(AND(265>=$B$11,265<=$D$11),1,0) | JI37: =IF(AND(266>=$B$11,266<=$D$11),1,0) | JJ37: =IF(AND(267>=$B$11,267<=$D$11),1,0) | JK37: =IF(AND(268>=$B$11,268<=$D$11),1,0) | JL37: =IF(AND(269>=$B$11,269<=$D$11),1,0) | JM37: =IF(AND(270>=$B$11,270<=$D$11),1,0) | JN37: =IF(AND(271>=$B$11,271<=$D$11),1,0) | JO37: =IF(AND(272>=$B$11,272<=$D$11),1,0) | JP37: =IF(AND(273>=$B$11,273<=$D$11),1,0) | JQ37: =IF(AND(274>=$B$11,274<=$D$11),1,0) | JR37: =IF(AND(275>=$B$11,275<=$D$11),1,0) | JS37: =IF(AND(276>=$B$11,276<=$D$11),1,0) | JT37: =IF(AND(277>=$B$11,277<=$D$11),1,0) | JU37: =IF(AND(278>=$B$11,278<=$D$11),1,0) | JV37: =IF(AND(279>=$B$11,279<=$D$11),1,0) | JW37: =IF(AND(280>=$B$11,280<=$D$11),1,0) | JX37: =IF(AND(281>=$B$11,281<=$D$11),1,0) | JY37: =IF(AND(282>=$B$11,282<=$D$11),1,0) | JZ37: =IF(AND(283>=$B$11,283<=$D$11),1,0) | KA37: =IF(AND(284>=$B$11,284<=$D$11),1,0) | KB37: =IF(AND(285>=$B$11,285<=$D$11),1,0) | KC37: =IF(AND(286>=$B$11,286<=$D$11),1,0) | KD37: =IF(AND(287>=$B$11,287<=$D$11),1,0) | KE37: =IF(AND(288>=$B$11,288<=$D$11),1,0) | KF37: =IF(AND(289>=$B$11,289<=$D$11),1,0) | KG37: =IF(AND(290>=$B$11,290<=$D$11),1,0) | KH37: =IF(AND(291>=$B$11,291<=$D$11),1,0) | KI37: =IF(AND(292>=$B$11,292<=$D$11),1,0) | KJ37: =IF(AND(293>=$B$11,293<=$D$11),1,0) | KK37: =IF(AND(294>=$B$11,294<=$D$11),1,0) | KL37: =IF(AND(295>=$B$11,295<=$D$11),1,0) | KM37: =IF(AND(296>=$B$11,296<=$D$11),1,0) | KN37: =IF(AND(297>=$B$11,297<=$D$11),1,0) | KO37: =IF(AND(298>=$B$11,298<=$D$11),1,0) | KP37: =IF(AND(299>=$B$11,299<=$D$11),1,0) | KQ37: =IF(AND(300>=$B$11,300<=$D$11),1,0) | KR37: =IF(AND(301>=$B$11,301<=$D$11),1,0) | KS37: =IF(AND(302>=$B$11,302<=$D$11),1,0) | KT37: =IF(AND(303>=$B$11,303<=$D$11),1,0) | KU37: =IF(AND(304>=$B$11,304<=$D$11),1,0) | KV37: =IF(AND(305>=$B$11,305<=$D$11),1,0) | KW37: =IF(AND(306>=$B$11,306<=$D$11),1,0) | KX37: =IF(AND(307>=$B$11,307<=$D$11),1,0) | KY37: =IF(AND(308>=$B$11,308<=$D$11),1,0) | KZ37: =IF(AND(309>=$B$11,309<=$D$11),1,0) | LA37: =IF(AND(310>=$B$11,310<=$D$11),1,0) | LB37: =IF(AND(311>=$B$11,311<=$D$11),1,0) | LC37: =IF(AND(312>=$B$11,312<=$D$11),1,0) | LD37: =IF(AND(313>=$B$11,313<=$D$11),1,0) | LE37: =IF(AND(314>=$B$11,314<=$D$11),1,0) | LF37: =IF(AND(315>=$B$11,315<=$D$11),1,0) | LG37: =IF(AND(316>=$B$11,316<=$D$11),1,0) | LH37: =IF(AND(317>=$B$11,317<=$D$11),1,0) | LI37: =IF(AND(318>=$B$11,318<=$D$11),1,0) | LJ37: =IF(AND(319>=$B$11,319<=$D$11),1,0) | LK37: =IF(AND(320>=$B$11,320<=$D$11),1,0) | LL37: =IF(AND(321>=$B$11,321<=$D$11),1,0) | LM37: =IF(AND(322>=$B$11,322<=$D$11),1,0) | LN37: =IF(AND(323>=$B$11,323<=$D$11),1,0) | LO37: =IF(AND(324>=$B$11,324<=$D$11),1,0) | LP37: =IF(AND(325>=$B$11,325<=$D$11),1,0) | LQ37: =IF(AND(326>=$B$11,326<=$D$11),1,0) | LR37: =IF(AND(327>=$B$11,327<=$D$11),1,0) | LS37: =IF(AND(328>=$B$11,328<=$D$11),1,0) | LT37: =IF(AND(329>=$B$11,329<=$D$11),1,0) | LU37: =IF(AND(330>=$B$11,330<=$D$11),1,0) | LV37: =IF(AND(331>=$B$11,331<=$D$11),1,0) | LW37: =IF(AND(332>=$B$11,332<=$D$11),1,0) | LX37: =IF(AND(333>=$B$11,333<=$D$11),1,0) | LY37: =IF(AND(334>=$B$11,334<=$D$11),1,0) | LZ37: =IF(AND(335>=$B$11,335<=$D$11),1,0) | MA37: =IF(AND(336>=$B$11,336<=$D$11),1,0) | MB37: =IF(AND(337>=$B$11,337<=$D$11),1,0) | MC37: =IF(AND(338>=$B$11,338<=$D$11),1,0) | MD37: =IF(AND(339>=$B$11,339<=$D$11),1,0) | ME37: =IF(AND(340>=$B$11,340<=$D$11),1,0) | MF37: =IF(AND(341>=$B$11,341<=$D$11),1,0) | MG37: =IF(AND(342>=$B$11,342<=$D$11),1,0) | MH37: =IF(AND(343>=$B$11,343<=$D$11),1,0) | MI37: =IF(AND(344>=$B$11,344<=$D$11),1,0) | MJ37: =IF(AND(345>=$B$11,345<=$D$11),1,0) | MK37: =IF(AND(346>=$B$11,346<=$D$11),1,0) | ML37: =IF(AND(347>=$B$11,347<=$D$11),1,0) | MM37: =IF(AND(348>=$B$11,348<=$D$11),1,0) | MN37: =IF(AND(349>=$B$11,349<=$D$11),1,0) | MO37: =IF(AND(350>=$B$11,350<=$D$11),1,0) | MP37: =IF(AND(351>=$B$11,351<=$D$11),1,0) | MQ37: =IF(AND(352>=$B$11,352<=$D$11),1,0) | MR37: =IF(AND(353>=$B$11,353<=$D$11),1,0) | MS37: =IF(AND(354>=$B$11,354<=$D$11),1,0) | MT37: =IF(AND(355>=$B$11,355<=$D$11),1,0) | MU37: =IF(AND(356>=$B$11,356<=$D$11),1,0) | MV37: =IF(AND(357>=$B$11,357<=$D$11),1,0) | MW37: =IF(AND(358>=$B$11,358<=$D$11),1,0) | MX37: =IF(AND(359>=$B$11,359<=$D$11),1,0) | MY37: =IF(AND(360>=$B$11,360<=$D$11),1,0) | MZ37: =IF(AND(361>=$B$11,361<=$D$11),1,0) | NA37: =IF(AND(362>=$B$11,362<=$D$11),1,0) | NB37: =IF(AND(363>=$B$11,363<=$D$11),1,0) | NC37: =IF(AND(364>=$B$11,364<=$D$11),1,0) | ND37: =IF(AND(365>=$B$11,365<=$D$11),1,0) | NE37: =IF(AND(366>=$B$11,366<=$D$11),1,0) | NF37: =IF(AND(367>=$B$11,367<=$D$11),1,0) | NG37: =IF(AND(368>=$B$11,368<=$D$11),1,0) | NH37: =IF(AND(369>=$B$11,369<=$D$11),1,0) | NI37: =IF(AND(370>=$B$11,370<=$D$11),1,0) | NJ37: =IF(AND(371>=$B$11,371<=$D$11),1,0) | NK37: =IF(AND(372>=$B$11,372<=$D$11),1,0)
A38: Flag: Stabilization | D38: =IF(AND(1>=$B$12,1<=$D$12),1,0) | E38: =IF(AND(2>=$B$12,2<=$D$12),1,0) | F38: =IF(AND(3>=$B$12,3<=$D$12),1,0) | G38: =IF(AND(4>=$B$12,4<=$D$12),1,0) | H38: =IF(AND(5>=$B$12,5<=$D$12),1,0) | I38: =IF(AND(6>=$B$12,6<=$D$12),1,0) | J38: =IF(AND(7>=$B$12,7<=$D$12),1,0) | K38: =IF(AND(8>=$B$12,8<=$D$12),1,0) | L38: =IF(AND(9>=$B$12,9<=$D$12),1,0) | M38: =IF(AND(10>=$B$12,10<=$D$12),1,0) | N38: =IF(AND(11>=$B$12,11<=$D$12),1,0) | O38: =IF(AND(12>=$B$12,12<=$D$12),1,0) | P38: =IF(AND(13>=$B$12,13<=$D$12),1,0) | Q38: =IF(AND(14>=$B$12,14<=$D$12),1,0) | R38: =IF(AND(15>=$B$12,15<=$D$12),1,0) | S38: =IF(AND(16>=$B$12,16<=$D$12),1,0) | T38: =IF(AND(17>=$B$12,17<=$D$12),1,0) | U38: =IF(AND(18>=$B$12,18<=$D$12),1,0) | V38: =IF(AND(19>=$B$12,19<=$D$12),1,0) | W38: =IF(AND(20>=$B$12,20<=$D$12),1,0) | X38: =IF(AND(21>=$B$12,21<=$D$12),1,0) | Y38: =IF(AND(22>=$B$12,22<=$D$12),1,0) | Z38: =IF(AND(23>=$B$12,23<=$D$12),1,0) | AA38: =IF(AND(24>=$B$12,24<=$D$12),1,0) | AB38: =IF(AND(25>=$B$12,25<=$D$12),1,0) | AC38: =IF(AND(26>=$B$12,26<=$D$12),1,0) | AD38: =IF(AND(27>=$B$12,27<=$D$12),1,0) | AE38: =IF(AND(28>=$B$12,28<=$D$12),1,0) | AF38: =IF(AND(29>=$B$12,29<=$D$12),1,0) | AG38: =IF(AND(30>=$B$12,30<=$D$12),1,0) | AH38: =IF(AND(31>=$B$12,31<=$D$12),1,0) | AI38: =IF(AND(32>=$B$12,32<=$D$12),1,0) | AJ38: =IF(AND(33>=$B$12,33<=$D$12),1,0) | AK38: =IF(AND(34>=$B$12,34<=$D$12),1,0) | AL38: =IF(AND(35>=$B$12,35<=$D$12),1,0) | AM38: =IF(AND(36>=$B$12,36<=$D$12),1,0) | AN38: =IF(AND(37>=$B$12,37<=$D$12),1,0) | AO38: =IF(AND(38>=$B$12,38<=$D$12),1,0) | AP38: =IF(AND(39>=$B$12,39<=$D$12),1,0) | AQ38: =IF(AND(40>=$B$12,40<=$D$12),1,0) | AR38: =IF(AND(41>=$B$12,41<=$D$12),1,0) | AS38: =IF(AND(42>=$B$12,42<=$D$12),1,0) | AT38: =IF(AND(43>=$B$12,43<=$D$12),1,0) | AU38: =IF(AND(44>=$B$12,44<=$D$12),1,0) | AV38: =IF(AND(45>=$B$12,45<=$D$12),1,0) | AW38: =IF(AND(46>=$B$12,46<=$D$12),1,0) | AX38: =IF(AND(47>=$B$12,47<=$D$12),1,0) | AY38: =IF(AND(48>=$B$12,48<=$D$12),1,0) | AZ38: =IF(AND(49>=$B$12,49<=$D$12),1,0) | BA38: =IF(AND(50>=$B$12,50<=$D$12),1,0) | BB38: =IF(AND(51>=$B$12,51<=$D$12),1,0) | BC38: =IF(AND(52>=$B$12,52<=$D$12),1,0) | BD38: =IF(AND(53>=$B$12,53<=$D$12),1,0) | BE38: =IF(AND(54>=$B$12,54<=$D$12),1,0) | BF38: =IF(AND(55>=$B$12,55<=$D$12),1,0) | BG38: =IF(AND(56>=$B$12,56<=$D$12),1,0) | BH38: =IF(AND(57>=$B$12,57<=$D$12),1,0) | BI38: =IF(AND(58>=$B$12,58<=$D$12),1,0) | BJ38: =IF(AND(59>=$B$12,59<=$D$12),1,0) | BK38: =IF(AND(60>=$B$12,60<=$D$12),1,0) | BL38: =IF(AND(61>=$B$12,61<=$D$12),1,0) | BM38: =IF(AND(62>=$B$12,62<=$D$12),1,0) | BN38: =IF(AND(63>=$B$12,63<=$D$12),1,0) | BO38: =IF(AND(64>=$B$12,64<=$D$12),1,0) | BP38: =IF(AND(65>=$B$12,65<=$D$12),1,0) | BQ38: =IF(AND(66>=$B$12,66<=$D$12),1,0) | BR38: =IF(AND(67>=$B$12,67<=$D$12),1,0) | BS38: =IF(AND(68>=$B$12,68<=$D$12),1,0) | BT38: =IF(AND(69>=$B$12,69<=$D$12),1,0) | BU38: =IF(AND(70>=$B$12,70<=$D$12),1,0) | BV38: =IF(AND(71>=$B$12,71<=$D$12),1,0) | BW38: =IF(AND(72>=$B$12,72<=$D$12),1,0) | BX38: =IF(AND(73>=$B$12,73<=$D$12),1,0) | BY38: =IF(AND(74>=$B$12,74<=$D$12),1,0) | BZ38: =IF(AND(75>=$B$12,75<=$D$12),1,0) | CA38: =IF(AND(76>=$B$12,76<=$D$12),1,0) | CB38: =IF(AND(77>=$B$12,77<=$D$12),1,0) | CC38: =IF(AND(78>=$B$12,78<=$D$12),1,0) | CD38: =IF(AND(79>=$B$12,79<=$D$12),1,0) | CE38: =IF(AND(80>=$B$12,80<=$D$12),1,0) | CF38: =IF(AND(81>=$B$12,81<=$D$12),1,0) | CG38: =IF(AND(82>=$B$12,82<=$D$12),1,0) | CH38: =IF(AND(83>=$B$12,83<=$D$12),1,0) | CI38: =IF(AND(84>=$B$12,84<=$D$12),1,0) | CJ38: =IF(AND(85>=$B$12,85<=$D$12),1,0) | CK38: =IF(AND(86>=$B$12,86<=$D$12),1,0) | CL38: =IF(AND(87>=$B$12,87<=$D$12),1,0) | CM38: =IF(AND(88>=$B$12,88<=$D$12),1,0) | CN38: =IF(AND(89>=$B$12,89<=$D$12),1,0) | CO38: =IF(AND(90>=$B$12,90<=$D$12),1,0) | CP38: =IF(AND(91>=$B$12,91<=$D$12),1,0) | CQ38: =IF(AND(92>=$B$12,92<=$D$12),1,0) | CR38: =IF(AND(93>=$B$12,93<=$D$12),1,0) | CS38: =IF(AND(94>=$B$12,94<=$D$12),1,0) | CT38: =IF(AND(95>=$B$12,95<=$D$12),1,0) | CU38: =IF(AND(96>=$B$12,96<=$D$12),1,0) | CV38: =IF(AND(97>=$B$12,97<=$D$12),1,0) | CW38: =IF(AND(98>=$B$12,98<=$D$12),1,0) | CX38: =IF(AND(99>=$B$12,99<=$D$12),1,0) | CY38: =IF(AND(100>=$B$12,100<=$D$12),1,0) | CZ38: =IF(AND(101>=$B$12,101<=$D$12),1,0) | DA38: =IF(AND(102>=$B$12,102<=$D$12),1,0) | DB38: =IF(AND(103>=$B$12,103<=$D$12),1,0) | DC38: =IF(AND(104>=$B$12,104<=$D$12),1,0) | DD38: =IF(AND(105>=$B$12,105<=$D$12),1,0) | DE38: =IF(AND(106>=$B$12,106<=$D$12),1,0) | DF38: =IF(AND(107>=$B$12,107<=$D$12),1,0) | DG38: =IF(AND(108>=$B$12,108<=$D$12),1,0) | DH38: =IF(AND(109>=$B$12,109<=$D$12),1,0) | DI38: =IF(AND(110>=$B$12,110<=$D$12),1,0) | DJ38: =IF(AND(111>=$B$12,111<=$D$12),1,0) | DK38: =IF(AND(112>=$B$12,112<=$D$12),1,0) | DL38: =IF(AND(113>=$B$12,113<=$D$12),1,0) | DM38: =IF(AND(114>=$B$12,114<=$D$12),1,0) | DN38: =IF(AND(115>=$B$12,115<=$D$12),1,0) | DO38: =IF(AND(116>=$B$12,116<=$D$12),1,0) | DP38: =IF(AND(117>=$B$12,117<=$D$12),1,0) | DQ38: =IF(AND(118>=$B$12,118<=$D$12),1,0) | DR38: =IF(AND(119>=$B$12,119<=$D$12),1,0) | DS38: =IF(AND(120>=$B$12,120<=$D$12),1,0) | DT38: =IF(AND(121>=$B$12,121<=$D$12),1,0) | DU38: =IF(AND(122>=$B$12,122<=$D$12),1,0) | DV38: =IF(AND(123>=$B$12,123<=$D$12),1,0) | DW38: =IF(AND(124>=$B$12,124<=$D$12),1,0) | DX38: =IF(AND(125>=$B$12,125<=$D$12),1,0) | DY38: =IF(AND(126>=$B$12,126<=$D$12),1,0) | DZ38: =IF(AND(127>=$B$12,127<=$D$12),1,0) | EA38: =IF(AND(128>=$B$12,128<=$D$12),1,0) | EB38: =IF(AND(129>=$B$12,129<=$D$12),1,0) | EC38: =IF(AND(130>=$B$12,130<=$D$12),1,0) | ED38: =IF(AND(131>=$B$12,131<=$D$12),1,0) | EE38: =IF(AND(132>=$B$12,132<=$D$12),1,0) | EF38: =IF(AND(133>=$B$12,133<=$D$12),1,0) | EG38: =IF(AND(134>=$B$12,134<=$D$12),1,0) | EH38: =IF(AND(135>=$B$12,135<=$D$12),1,0) | EI38: =IF(AND(136>=$B$12,136<=$D$12),1,0) | EJ38: =IF(AND(137>=$B$12,137<=$D$12),1,0) | EK38: =IF(AND(138>=$B$12,138<=$D$12),1,0) | EL38: =IF(AND(139>=$B$12,139<=$D$12),1,0) | EM38: =IF(AND(140>=$B$12,140<=$D$12),1,0) | EN38: =IF(AND(141>=$B$12,141<=$D$12),1,0) | EO38: =IF(AND(142>=$B$12,142<=$D$12),1,0) | EP38: =IF(AND(143>=$B$12,143<=$D$12),1,0) | EQ38: =IF(AND(144>=$B$12,144<=$D$12),1,0) | ER38: =IF(AND(145>=$B$12,145<=$D$12),1,0) | ES38: =IF(AND(146>=$B$12,146<=$D$12),1,0) | ET38: =IF(AND(147>=$B$12,147<=$D$12),1,0) | EU38: =IF(AND(148>=$B$12,148<=$D$12),1,0) | EV38: =IF(AND(149>=$B$12,149<=$D$12),1,0) | EW38: =IF(AND(150>=$B$12,150<=$D$12),1,0) | EX38: =IF(AND(151>=$B$12,151<=$D$12),1,0) | EY38: =IF(AND(152>=$B$12,152<=$D$12),1,0) | EZ38: =IF(AND(153>=$B$12,153<=$D$12),1,0) | FA38: =IF(AND(154>=$B$12,154<=$D$12),1,0) | FB38: =IF(AND(155>=$B$12,155<=$D$12),1,0) | FC38: =IF(AND(156>=$B$12,156<=$D$12),1,0) | FD38: =IF(AND(157>=$B$12,157<=$D$12),1,0) | FE38: =IF(AND(158>=$B$12,158<=$D$12),1,0) | FF38: =IF(AND(159>=$B$12,159<=$D$12),1,0) | FG38: =IF(AND(160>=$B$12,160<=$D$12),1,0) | FH38: =IF(AND(161>=$B$12,161<=$D$12),1,0) | FI38: =IF(AND(162>=$B$12,162<=$D$12),1,0) | FJ38: =IF(AND(163>=$B$12,163<=$D$12),1,0) | FK38: =IF(AND(164>=$B$12,164<=$D$12),1,0) | FL38: =IF(AND(165>=$B$12,165<=$D$12),1,0) | FM38: =IF(AND(166>=$B$12,166<=$D$12),1,0) | FN38: =IF(AND(167>=$B$12,167<=$D$12),1,0) | FO38: =IF(AND(168>=$B$12,168<=$D$12),1,0) | FP38: =IF(AND(169>=$B$12,169<=$D$12),1,0) | FQ38: =IF(AND(170>=$B$12,170<=$D$12),1,0) | FR38: =IF(AND(171>=$B$12,171<=$D$12),1,0) | FS38: =IF(AND(172>=$B$12,172<=$D$12),1,0) | FT38: =IF(AND(173>=$B$12,173<=$D$12),1,0) | FU38: =IF(AND(174>=$B$12,174<=$D$12),1,0) | FV38: =IF(AND(175>=$B$12,175<=$D$12),1,0) | FW38: =IF(AND(176>=$B$12,176<=$D$12),1,0) | FX38: =IF(AND(177>=$B$12,177<=$D$12),1,0) | FY38: =IF(AND(178>=$B$12,178<=$D$12),1,0) | FZ38: =IF(AND(179>=$B$12,179<=$D$12),1,0) | GA38: =IF(AND(180>=$B$12,180<=$D$12),1,0) | GB38: =IF(AND(181>=$B$12,181<=$D$12),1,0) | GC38: =IF(AND(182>=$B$12,182<=$D$12),1,0) | GD38: =IF(AND(183>=$B$12,183<=$D$12),1,0) | GE38: =IF(AND(184>=$B$12,184<=$D$12),1,0) | GF38: =IF(AND(185>=$B$12,185<=$D$12),1,0) | GG38: =IF(AND(186>=$B$12,186<=$D$12),1,0) | GH38: =IF(AND(187>=$B$12,187<=$D$12),1,0) | GI38: =IF(AND(188>=$B$12,188<=$D$12),1,0) | GJ38: =IF(AND(189>=$B$12,189<=$D$12),1,0) | GK38: =IF(AND(190>=$B$12,190<=$D$12),1,0) | GL38: =IF(AND(191>=$B$12,191<=$D$12),1,0) | GM38: =IF(AND(192>=$B$12,192<=$D$12),1,0) | GN38: =IF(AND(193>=$B$12,193<=$D$12),1,0) | GO38: =IF(AND(194>=$B$12,194<=$D$12),1,0) | GP38: =IF(AND(195>=$B$12,195<=$D$12),1,0) | GQ38: =IF(AND(196>=$B$12,196<=$D$12),1,0) | GR38: =IF(AND(197>=$B$12,197<=$D$12),1,0) | GS38: =IF(AND(198>=$B$12,198<=$D$12),1,0) | GT38: =IF(AND(199>=$B$12,199<=$D$12),1,0) | GU38: =IF(AND(200>=$B$12,200<=$D$12),1,0) | GV38: =IF(AND(201>=$B$12,201<=$D$12),1,0) | GW38: =IF(AND(202>=$B$12,202<=$D$12),1,0) | GX38: =IF(AND(203>=$B$12,203<=$D$12),1,0) | GY38: =IF(AND(204>=$B$12,204<=$D$12),1,0) | GZ38: =IF(AND(205>=$B$12,205<=$D$12),1,0) | HA38: =IF(AND(206>=$B$12,206<=$D$12),1,0) | HB38: =IF(AND(207>=$B$12,207<=$D$12),1,0) | HC38: =IF(AND(208>=$B$12,208<=$D$12),1,0) | HD38: =IF(AND(209>=$B$12,209<=$D$12),1,0) | HE38: =IF(AND(210>=$B$12,210<=$D$12),1,0) | HF38: =IF(AND(211>=$B$12,211<=$D$12),1,0) | HG38: =IF(AND(212>=$B$12,212<=$D$12),1,0) | HH38: =IF(AND(213>=$B$12,213<=$D$12),1,0) | HI38: =IF(AND(214>=$B$12,214<=$D$12),1,0) | HJ38: =IF(AND(215>=$B$12,215<=$D$12),1,0) | HK38: =IF(AND(216>=$B$12,216<=$D$12),1,0) | HL38: =IF(AND(217>=$B$12,217<=$D$12),1,0) | HM38: =IF(AND(218>=$B$12,218<=$D$12),1,0) | HN38: =IF(AND(219>=$B$12,219<=$D$12),1,0) | HO38: =IF(AND(220>=$B$12,220<=$D$12),1,0) | HP38: =IF(AND(221>=$B$12,221<=$D$12),1,0) | HQ38: =IF(AND(222>=$B$12,222<=$D$12),1,0) | HR38: =IF(AND(223>=$B$12,223<=$D$12),1,0) | HS38: =IF(AND(224>=$B$12,224<=$D$12),1,0) | HT38: =IF(AND(225>=$B$12,225<=$D$12),1,0) | HU38: =IF(AND(226>=$B$12,226<=$D$12),1,0) | HV38: =IF(AND(227>=$B$12,227<=$D$12),1,0) | HW38: =IF(AND(228>=$B$12,228<=$D$12),1,0) | HX38: =IF(AND(229>=$B$12,229<=$D$12),1,0) | HY38: =IF(AND(230>=$B$12,230<=$D$12),1,0) | HZ38: =IF(AND(231>=$B$12,231<=$D$12),1,0) | IA38: =IF(AND(232>=$B$12,232<=$D$12),1,0) | IB38: =IF(AND(233>=$B$12,233<=$D$12),1,0) | IC38: =IF(AND(234>=$B$12,234<=$D$12),1,0) | ID38: =IF(AND(235>=$B$12,235<=$D$12),1,0) | IE38: =IF(AND(236>=$B$12,236<=$D$12),1,0) | IF38: =IF(AND(237>=$B$12,237<=$D$12),1,0) | IG38: =IF(AND(238>=$B$12,238<=$D$12),1,0) | IH38: =IF(AND(239>=$B$12,239<=$D$12),1,0) | II38: =IF(AND(240>=$B$12,240<=$D$12),1,0) | IJ38: =IF(AND(241>=$B$12,241<=$D$12),1,0) | IK38: =IF(AND(242>=$B$12,242<=$D$12),1,0) | IL38: =IF(AND(243>=$B$12,243<=$D$12),1,0) | IM38: =IF(AND(244>=$B$12,244<=$D$12),1,0) | IN38: =IF(AND(245>=$B$12,245<=$D$12),1,0) | IO38: =IF(AND(246>=$B$12,246<=$D$12),1,0) | IP38: =IF(AND(247>=$B$12,247<=$D$12),1,0) | IQ38: =IF(AND(248>=$B$12,248<=$D$12),1,0) | IR38: =IF(AND(249>=$B$12,249<=$D$12),1,0) | IS38: =IF(AND(250>=$B$12,250<=$D$12),1,0) | IT38: =IF(AND(251>=$B$12,251<=$D$12),1,0) | IU38: =IF(AND(252>=$B$12,252<=$D$12),1,0) | IV38: =IF(AND(253>=$B$12,253<=$D$12),1,0) | IW38: =IF(AND(254>=$B$12,254<=$D$12),1,0) | IX38: =IF(AND(255>=$B$12,255<=$D$12),1,0) | IY38: =IF(AND(256>=$B$12,256<=$D$12),1,0) | IZ38: =IF(AND(257>=$B$12,257<=$D$12),1,0) | JA38: =IF(AND(258>=$B$12,258<=$D$12),1,0) | JB38: =IF(AND(259>=$B$12,259<=$D$12),1,0) | JC38: =IF(AND(260>=$B$12,260<=$D$12),1,0) | JD38: =IF(AND(261>=$B$12,261<=$D$12),1,0) | JE38: =IF(AND(262>=$B$12,262<=$D$12),1,0) | JF38: =IF(AND(263>=$B$12,263<=$D$12),1,0) | JG38: =IF(AND(264>=$B$12,264<=$D$12),1,0) | JH38: =IF(AND(265>=$B$12,265<=$D$12),1,0) | JI38: =IF(AND(266>=$B$12,266<=$D$12),1,0) | JJ38: =IF(AND(267>=$B$12,267<=$D$12),1,0) | JK38: =IF(AND(268>=$B$12,268<=$D$12),1,0) | JL38: =IF(AND(269>=$B$12,269<=$D$12),1,0) | JM38: =IF(AND(270>=$B$12,270<=$D$12),1,0) | JN38: =IF(AND(271>=$B$12,271<=$D$12),1,0) | JO38: =IF(AND(272>=$B$12,272<=$D$12),1,0) | JP38: =IF(AND(273>=$B$12,273<=$D$12),1,0) | JQ38: =IF(AND(274>=$B$12,274<=$D$12),1,0) | JR38: =IF(AND(275>=$B$12,275<=$D$12),1,0) | JS38: =IF(AND(276>=$B$12,276<=$D$12),1,0) | JT38: =IF(AND(277>=$B$12,277<=$D$12),1,0) | JU38: =IF(AND(278>=$B$12,278<=$D$12),1,0) | JV38: =IF(AND(279>=$B$12,279<=$D$12),1,0) | JW38: =IF(AND(280>=$B$12,280<=$D$12),1,0) | JX38: =IF(AND(281>=$B$12,281<=$D$12),1,0) | JY38: =IF(AND(282>=$B$12,282<=$D$12),1,0) | JZ38: =IF(AND(283>=$B$12,283<=$D$12),1,0) | KA38: =IF(AND(284>=$B$12,284<=$D$12),1,0) | KB38: =IF(AND(285>=$B$12,285<=$D$12),1,0) | KC38: =IF(AND(286>=$B$12,286<=$D$12),1,0) | KD38: =IF(AND(287>=$B$12,287<=$D$12),1,0) | KE38: =IF(AND(288>=$B$12,288<=$D$12),1,0) | KF38: =IF(AND(289>=$B$12,289<=$D$12),1,0) | KG38: =IF(AND(290>=$B$12,290<=$D$12),1,0) | KH38: =IF(AND(291>=$B$12,291<=$D$12),1,0) | KI38: =IF(AND(292>=$B$12,292<=$D$12),1,0) | KJ38: =IF(AND(293>=$B$12,293<=$D$12),1,0) | KK38: =IF(AND(294>=$B$12,294<=$D$12),1,0) | KL38: =IF(AND(295>=$B$12,295<=$D$12),1,0) | KM38: =IF(AND(296>=$B$12,296<=$D$12),1,0) | KN38: =IF(AND(297>=$B$12,297<=$D$12),1,0) | KO38: =IF(AND(298>=$B$12,298<=$D$12),1,0) | KP38: =IF(AND(299>=$B$12,299<=$D$12),1,0) | KQ38: =IF(AND(300>=$B$12,300<=$D$12),1,0) | KR38: =IF(AND(301>=$B$12,301<=$D$12),1,0) | KS38: =IF(AND(302>=$B$12,302<=$D$12),1,0) | KT38: =IF(AND(303>=$B$12,303<=$D$12),1,0) | KU38: =IF(AND(304>=$B$12,304<=$D$12),1,0) | KV38: =IF(AND(305>=$B$12,305<=$D$12),1,0) | KW38: =IF(AND(306>=$B$12,306<=$D$12),1,0) | KX38: =IF(AND(307>=$B$12,307<=$D$12),1,0) | KY38: =IF(AND(308>=$B$12,308<=$D$12),1,0) | KZ38: =IF(AND(309>=$B$12,309<=$D$12),1,0) | LA38: =IF(AND(310>=$B$12,310<=$D$12),1,0) | LB38: =IF(AND(311>=$B$12,311<=$D$12),1,0) | LC38: =IF(AND(312>=$B$12,312<=$D$12),1,0) | LD38: =IF(AND(313>=$B$12,313<=$D$12),1,0) | LE38: =IF(AND(314>=$B$12,314<=$D$12),1,0) | LF38: =IF(AND(315>=$B$12,315<=$D$12),1,0) | LG38: =IF(AND(316>=$B$12,316<=$D$12),1,0) | LH38: =IF(AND(317>=$B$12,317<=$D$12),1,0) | LI38: =IF(AND(318>=$B$12,318<=$D$12),1,0) | LJ38: =IF(AND(319>=$B$12,319<=$D$12),1,0) | LK38: =IF(AND(320>=$B$12,320<=$D$12),1,0) | LL38: =IF(AND(321>=$B$12,321<=$D$12),1,0) | LM38: =IF(AND(322>=$B$12,322<=$D$12),1,0) | LN38: =IF(AND(323>=$B$12,323<=$D$12),1,0) | LO38: =IF(AND(324>=$B$12,324<=$D$12),1,0) | LP38: =IF(AND(325>=$B$12,325<=$D$12),1,0) | LQ38: =IF(AND(326>=$B$12,326<=$D$12),1,0) | LR38: =IF(AND(327>=$B$12,327<=$D$12),1,0) | LS38: =IF(AND(328>=$B$12,328<=$D$12),1,0) | LT38: =IF(AND(329>=$B$12,329<=$D$12),1,0) | LU38: =IF(AND(330>=$B$12,330<=$D$12),1,0) | LV38: =IF(AND(331>=$B$12,331<=$D$12),1,0) | LW38: =IF(AND(332>=$B$12,332<=$D$12),1,0) | LX38: =IF(AND(333>=$B$12,333<=$D$12),1,0) | LY38: =IF(AND(334>=$B$12,334<=$D$12),1,0) | LZ38: =IF(AND(335>=$B$12,335<=$D$12),1,0) | MA38: =IF(AND(336>=$B$12,336<=$D$12),1,0) | MB38: =IF(AND(337>=$B$12,337<=$D$12),1,0) | MC38: =IF(AND(338>=$B$12,338<=$D$12),1,0) | MD38: =IF(AND(339>=$B$12,339<=$D$12),1,0) | ME38: =IF(AND(340>=$B$12,340<=$D$12),1,0) | MF38: =IF(AND(341>=$B$12,341<=$D$12),1,0) | MG38: =IF(AND(342>=$B$12,342<=$D$12),1,0) | MH38: =IF(AND(343>=$B$12,343<=$D$12),1,0) | MI38: =IF(AND(344>=$B$12,344<=$D$12),1,0) | MJ38: =IF(AND(345>=$B$12,345<=$D$12),1,0) | MK38: =IF(AND(346>=$B$12,346<=$D$12),1,0) | ML38: =IF(AND(347>=$B$12,347<=$D$12),1,0) | MM38: =IF(AND(348>=$B$12,348<=$D$12),1,0) | MN38: =IF(AND(349>=$B$12,349<=$D$12),1,0) | MO38: =IF(AND(350>=$B$12,350<=$D$12),1,0) | MP38: =IF(AND(351>=$B$12,351<=$D$12),1,0) | MQ38: =IF(AND(352>=$B$12,352<=$D$12),1,0) | MR38: =IF(AND(353>=$B$12,353<=$D$12),1,0) | MS38: =IF(AND(354>=$B$12,354<=$D$12),1,0) | MT38: =IF(AND(355>=$B$12,355<=$D$12),1,0) | MU38: =IF(AND(356>=$B$12,356<=$D$12),1,0) | MV38: =IF(AND(357>=$B$12,357<=$D$12),1,0) | MW38: =IF(AND(358>=$B$12,358<=$D$12),1,0) | MX38: =IF(AND(359>=$B$12,359<=$D$12),1,0) | MY38: =IF(AND(360>=$B$12,360<=$D$12),1,0) | MZ38: =IF(AND(361>=$B$12,361<=$D$12),1,0) | NA38: =IF(AND(362>=$B$12,362<=$D$12),1,0) | NB38: =IF(AND(363>=$B$12,363<=$D$12),1,0) | NC38: =IF(AND(364>=$B$12,364<=$D$12),1,0) | ND38: =IF(AND(365>=$B$12,365<=$D$12),1,0) | NE38: =IF(AND(366>=$B$12,366<=$D$12),1,0) | NF38: =IF(AND(367>=$B$12,367<=$D$12),1,0) | NG38: =IF(AND(368>=$B$12,368<=$D$12),1,0) | NH38: =IF(AND(369>=$B$12,369<=$D$12),1,0) | NI38: =IF(AND(370>=$B$12,370<=$D$12),1,0) | NJ38: =IF(AND(371>=$B$12,371<=$D$12),1,0) | NK38: =IF(AND(372>=$B$12,372<=$D$12),1,0)
A39: Flag: Recapitalization/Refinance | D39: =IF(AND(1>=$B$13,1<=$D$13),1,0) | E39: =IF(AND(2>=$B$13,2<=$D$13),1,0) | F39: =IF(AND(3>=$B$13,3<=$D$13),1,0) | G39: =IF(AND(4>=$B$13,4<=$D$13),1,0) | H39: =IF(AND(5>=$B$13,5<=$D$13),1,0) | I39: =IF(AND(6>=$B$13,6<=$D$13),1,0) | J39: =IF(AND(7>=$B$13,7<=$D$13),1,0) | K39: =IF(AND(8>=$B$13,8<=$D$13),1,0) | L39: =IF(AND(9>=$B$13,9<=$D$13),1,0) | M39: =IF(AND(10>=$B$13,10<=$D$13),1,0) | N39: =IF(AND(11>=$B$13,11<=$D$13),1,0) | O39: =IF(AND(12>=$B$13,12<=$D$13),1,0) | P39: =IF(AND(13>=$B$13,13<=$D$13),1,0) | Q39: =IF(AND(14>=$B$13,14<=$D$13),1,0) | R39: =IF(AND(15>=$B$13,15<=$D$13),1,0) | S39: =IF(AND(16>=$B$13,16<=$D$13),1,0) | T39: =IF(AND(17>=$B$13,17<=$D$13),1,0) | U39: =IF(AND(18>=$B$13,18<=$D$13),1,0) | V39: =IF(AND(19>=$B$13,19<=$D$13),1,0) | W39: =IF(AND(20>=$B$13,20<=$D$13),1,0) | X39: =IF(AND(21>=$B$13,21<=$D$13),1,0) | Y39: =IF(AND(22>=$B$13,22<=$D$13),1,0) | Z39: =IF(AND(23>=$B$13,23<=$D$13),1,0) | AA39: =IF(AND(24>=$B$13,24<=$D$13),1,0) | AB39: =IF(AND(25>=$B$13,25<=$D$13),1,0) | AC39: =IF(AND(26>=$B$13,26<=$D$13),1,0) | AD39: =IF(AND(27>=$B$13,27<=$D$13),1,0) | AE39: =IF(AND(28>=$B$13,28<=$D$13),1,0) | AF39: =IF(AND(29>=$B$13,29<=$D$13),1,0) | AG39: =IF(AND(30>=$B$13,30<=$D$13),1,0) | AH39: =IF(AND(31>=$B$13,31<=$D$13),1,0) | AI39: =IF(AND(32>=$B$13,32<=$D$13),1,0) | AJ39: =IF(AND(33>=$B$13,33<=$D$13),1,0) | AK39: =IF(AND(34>=$B$13,34<=$D$13),1,0) | AL39: =IF(AND(35>=$B$13,35<=$D$13),1,0) | AM39: =IF(AND(36>=$B$13,36<=$D$13),1,0) | AN39: =IF(AND(37>=$B$13,37<=$D$13),1,0) | AO39: =IF(AND(38>=$B$13,38<=$D$13),1,0) | AP39: =IF(AND(39>=$B$13,39<=$D$13),1,0) | AQ39: =IF(AND(40>=$B$13,40<=$D$13),1,0) | AR39: =IF(AND(41>=$B$13,41<=$D$13),1,0) | AS39: =IF(AND(42>=$B$13,42<=$D$13),1,0) | AT39: =IF(AND(43>=$B$13,43<=$D$13),1,0) | AU39: =IF(AND(44>=$B$13,44<=$D$13),1,0) | AV39: =IF(AND(45>=$B$13,45<=$D$13),1,0) | AW39: =IF(AND(46>=$B$13,46<=$D$13),1,0) | AX39: =IF(AND(47>=$B$13,47<=$D$13),1,0) | AY39: =IF(AND(48>=$B$13,48<=$D$13),1,0) | AZ39: =IF(AND(49>=$B$13,49<=$D$13),1,0) | BA39: =IF(AND(50>=$B$13,50<=$D$13),1,0) | BB39: =IF(AND(51>=$B$13,51<=$D$13),1,0) | BC39: =IF(AND(52>=$B$13,52<=$D$13),1,0) | BD39: =IF(AND(53>=$B$13,53<=$D$13),1,0) | BE39: =IF(AND(54>=$B$13,54<=$D$13),1,0) | BF39: =IF(AND(55>=$B$13,55<=$D$13),1,0) | BG39: =IF(AND(56>=$B$13,56<=$D$13),1,0) | BH39: =IF(AND(57>=$B$13,57<=$D$13),1,0) | BI39: =IF(AND(58>=$B$13,58<=$D$13),1,0) | BJ39: =IF(AND(59>=$B$13,59<=$D$13),1,0) | BK39: =IF(AND(60>=$B$13,60<=$D$13),1,0) | BL39: =IF(AND(61>=$B$13,61<=$D$13),1,0) | BM39: =IF(AND(62>=$B$13,62<=$D$13),1,0) | BN39: =IF(AND(63>=$B$13,63<=$D$13),1,0) | BO39: =IF(AND(64>=$B$13,64<=$D$13),1,0) | BP39: =IF(AND(65>=$B$13,65<=$D$13),1,0) | BQ39: =IF(AND(66>=$B$13,66<=$D$13),1,0) | BR39: =IF(AND(67>=$B$13,67<=$D$13),1,0) | BS39: =IF(AND(68>=$B$13,68<=$D$13),1,0) | BT39: =IF(AND(69>=$B$13,69<=$D$13),1,0) | BU39: =IF(AND(70>=$B$13,70<=$D$13),1,0) | BV39: =IF(AND(71>=$B$13,71<=$D$13),1,0) | BW39: =IF(AND(72>=$B$13,72<=$D$13),1,0) | BX39: =IF(AND(73>=$B$13,73<=$D$13),1,0) | BY39: =IF(AND(74>=$B$13,74<=$D$13),1,0) | BZ39: =IF(AND(75>=$B$13,75<=$D$13),1,0) | CA39: =IF(AND(76>=$B$13,76<=$D$13),1,0) | CB39: =IF(AND(77>=$B$13,77<=$D$13),1,0) | CC39: =IF(AND(78>=$B$13,78<=$D$13),1,0) | CD39: =IF(AND(79>=$B$13,79<=$D$13),1,0) | CE39: =IF(AND(80>=$B$13,80<=$D$13),1,0) | CF39: =IF(AND(81>=$B$13,81<=$D$13),1,0) | CG39: =IF(AND(82>=$B$13,82<=$D$13),1,0) | CH39: =IF(AND(83>=$B$13,83<=$D$13),1,0) | CI39: =IF(AND(84>=$B$13,84<=$D$13),1,0) | CJ39: =IF(AND(85>=$B$13,85<=$D$13),1,0) | CK39: =IF(AND(86>=$B$13,86<=$D$13),1,0) | CL39: =IF(AND(87>=$B$13,87<=$D$13),1,0) | CM39: =IF(AND(88>=$B$13,88<=$D$13),1,0) | CN39: =IF(AND(89>=$B$13,89<=$D$13),1,0) | CO39: =IF(AND(90>=$B$13,90<=$D$13),1,0) | CP39: =IF(AND(91>=$B$13,91<=$D$13),1,0) | CQ39: =IF(AND(92>=$B$13,92<=$D$13),1,0) | CR39: =IF(AND(93>=$B$13,93<=$D$13),1,0) | CS39: =IF(AND(94>=$B$13,94<=$D$13),1,0) | CT39: =IF(AND(95>=$B$13,95<=$D$13),1,0) | CU39: =IF(AND(96>=$B$13,96<=$D$13),1,0) | CV39: =IF(AND(97>=$B$13,97<=$D$13),1,0) | CW39: =IF(AND(98>=$B$13,98<=$D$13),1,0) | CX39: =IF(AND(99>=$B$13,99<=$D$13),1,0) | CY39: =IF(AND(100>=$B$13,100<=$D$13),1,0) | CZ39: =IF(AND(101>=$B$13,101<=$D$13),1,0) | DA39: =IF(AND(102>=$B$13,102<=$D$13),1,0) | DB39: =IF(AND(103>=$B$13,103<=$D$13),1,0) | DC39: =IF(AND(104>=$B$13,104<=$D$13),1,0) | DD39: =IF(AND(105>=$B$13,105<=$D$13),1,0) | DE39: =IF(AND(106>=$B$13,106<=$D$13),1,0) | DF39: =IF(AND(107>=$B$13,107<=$D$13),1,0) | DG39: =IF(AND(108>=$B$13,108<=$D$13),1,0) | DH39: =IF(AND(109>=$B$13,109<=$D$13),1,0) | DI39: =IF(AND(110>=$B$13,110<=$D$13),1,0) | DJ39: =IF(AND(111>=$B$13,111<=$D$13),1,0) | DK39: =IF(AND(112>=$B$13,112<=$D$13),1,0) | DL39: =IF(AND(113>=$B$13,113<=$D$13),1,0) | DM39: =IF(AND(114>=$B$13,114<=$D$13),1,0) | DN39: =IF(AND(115>=$B$13,115<=$D$13),1,0) | DO39: =IF(AND(116>=$B$13,116<=$D$13),1,0) | DP39: =IF(AND(117>=$B$13,117<=$D$13),1,0) | DQ39: =IF(AND(118>=$B$13,118<=$D$13),1,0) | DR39: =IF(AND(119>=$B$13,119<=$D$13),1,0) | DS39: =IF(AND(120>=$B$13,120<=$D$13),1,0) | DT39: =IF(AND(121>=$B$13,121<=$D$13),1,0) | DU39: =IF(AND(122>=$B$13,122<=$D$13),1,0) | DV39: =IF(AND(123>=$B$13,123<=$D$13),1,0) | DW39: =IF(AND(124>=$B$13,124<=$D$13),1,0) | DX39: =IF(AND(125>=$B$13,125<=$D$13),1,0) | DY39: =IF(AND(126>=$B$13,126<=$D$13),1,0) | DZ39: =IF(AND(127>=$B$13,127<=$D$13),1,0) | EA39: =IF(AND(128>=$B$13,128<=$D$13),1,0) | EB39: =IF(AND(129>=$B$13,129<=$D$13),1,0) | EC39: =IF(AND(130>=$B$13,130<=$D$13),1,0) | ED39: =IF(AND(131>=$B$13,131<=$D$13),1,0) | EE39: =IF(AND(132>=$B$13,132<=$D$13),1,0) | EF39: =IF(AND(133>=$B$13,133<=$D$13),1,0) | EG39: =IF(AND(134>=$B$13,134<=$D$13),1,0) | EH39: =IF(AND(135>=$B$13,135<=$D$13),1,0) | EI39: =IF(AND(136>=$B$13,136<=$D$13),1,0) | EJ39: =IF(AND(137>=$B$13,137<=$D$13),1,0) | EK39: =IF(AND(138>=$B$13,138<=$D$13),1,0) | EL39: =IF(AND(139>=$B$13,139<=$D$13),1,0) | EM39: =IF(AND(140>=$B$13,140<=$D$13),1,0) | EN39: =IF(AND(141>=$B$13,141<=$D$13),1,0) | EO39: =IF(AND(142>=$B$13,142<=$D$13),1,0) | EP39: =IF(AND(143>=$B$13,143<=$D$13),1,0) | EQ39: =IF(AND(144>=$B$13,144<=$D$13),1,0) | ER39: =IF(AND(145>=$B$13,145<=$D$13),1,0) | ES39: =IF(AND(146>=$B$13,146<=$D$13),1,0) | ET39: =IF(AND(147>=$B$13,147<=$D$13),1,0) | EU39: =IF(AND(148>=$B$13,148<=$D$13),1,0) | EV39: =IF(AND(149>=$B$13,149<=$D$13),1,0) | EW39: =IF(AND(150>=$B$13,150<=$D$13),1,0) | EX39: =IF(AND(151>=$B$13,151<=$D$13),1,0) | EY39: =IF(AND(152>=$B$13,152<=$D$13),1,0) | EZ39: =IF(AND(153>=$B$13,153<=$D$13),1,0) | FA39: =IF(AND(154>=$B$13,154<=$D$13),1,0) | FB39: =IF(AND(155>=$B$13,155<=$D$13),1,0) | FC39: =IF(AND(156>=$B$13,156<=$D$13),1,0) | FD39: =IF(AND(157>=$B$13,157<=$D$13),1,0) | FE39: =IF(AND(158>=$B$13,158<=$D$13),1,0) | FF39: =IF(AND(159>=$B$13,159<=$D$13),1,0) | FG39: =IF(AND(160>=$B$13,160<=$D$13),1,0) | FH39: =IF(AND(161>=$B$13,161<=$D$13),1,0) | FI39: =IF(AND(162>=$B$13,162<=$D$13),1,0) | FJ39: =IF(AND(163>=$B$13,163<=$D$13),1,0) | FK39: =IF(AND(164>=$B$13,164<=$D$13),1,0) | FL39: =IF(AND(165>=$B$13,165<=$D$13),1,0) | FM39: =IF(AND(166>=$B$13,166<=$D$13),1,0) | FN39: =IF(AND(167>=$B$13,167<=$D$13),1,0) | FO39: =IF(AND(168>=$B$13,168<=$D$13),1,0) | FP39: =IF(AND(169>=$B$13,169<=$D$13),1,0) | FQ39: =IF(AND(170>=$B$13,170<=$D$13),1,0) | FR39: =IF(AND(171>=$B$13,171<=$D$13),1,0) | FS39: =IF(AND(172>=$B$13,172<=$D$13),1,0) | FT39: =IF(AND(173>=$B$13,173<=$D$13),1,0) | FU39: =IF(AND(174>=$B$13,174<=$D$13),1,0) | FV39: =IF(AND(175>=$B$13,175<=$D$13),1,0) | FW39: =IF(AND(176>=$B$13,176<=$D$13),1,0) | FX39: =IF(AND(177>=$B$13,177<=$D$13),1,0) | FY39: =IF(AND(178>=$B$13,178<=$D$13),1,0) | FZ39: =IF(AND(179>=$B$13,179<=$D$13),1,0) | GA39: =IF(AND(180>=$B$13,180<=$D$13),1,0) | GB39: =IF(AND(181>=$B$13,181<=$D$13),1,0) | GC39: =IF(AND(182>=$B$13,182<=$D$13),1,0) | GD39: =IF(AND(183>=$B$13,183<=$D$13),1,0) | GE39: =IF(AND(184>=$B$13,184<=$D$13),1,0) | GF39: =IF(AND(185>=$B$13,185<=$D$13),1,0) | GG39: =IF(AND(186>=$B$13,186<=$D$13),1,0) | GH39: =IF(AND(187>=$B$13,187<=$D$13),1,0) | GI39: =IF(AND(188>=$B$13,188<=$D$13),1,0) | GJ39: =IF(AND(189>=$B$13,189<=$D$13),1,0) | GK39: =IF(AND(190>=$B$13,190<=$D$13),1,0) | GL39: =IF(AND(191>=$B$13,191<=$D$13),1,0) | GM39: =IF(AND(192>=$B$13,192<=$D$13),1,0) | GN39: =IF(AND(193>=$B$13,193<=$D$13),1,0) | GO39: =IF(AND(194>=$B$13,194<=$D$13),1,0) | GP39: =IF(AND(195>=$B$13,195<=$D$13),1,0) | GQ39: =IF(AND(196>=$B$13,196<=$D$13),1,0) | GR39: =IF(AND(197>=$B$13,197<=$D$13),1,0) | GS39: =IF(AND(198>=$B$13,198<=$D$13),1,0) | GT39: =IF(AND(199>=$B$13,199<=$D$13),1,0) | GU39: =IF(AND(200>=$B$13,200<=$D$13),1,0) | GV39: =IF(AND(201>=$B$13,201<=$D$13),1,0) | GW39: =IF(AND(202>=$B$13,202<=$D$13),1,0) | GX39: =IF(AND(203>=$B$13,203<=$D$13),1,0) | GY39: =IF(AND(204>=$B$13,204<=$D$13),1,0) | GZ39: =IF(AND(205>=$B$13,205<=$D$13),1,0) | HA39: =IF(AND(206>=$B$13,206<=$D$13),1,0) | HB39: =IF(AND(207>=$B$13,207<=$D$13),1,0) | HC39: =IF(AND(208>=$B$13,208<=$D$13),1,0) | HD39: =IF(AND(209>=$B$13,209<=$D$13),1,0) | HE39: =IF(AND(210>=$B$13,210<=$D$13),1,0) | HF39: =IF(AND(211>=$B$13,211<=$D$13),1,0) | HG39: =IF(AND(212>=$B$13,212<=$D$13),1,0) | HH39: =IF(AND(213>=$B$13,213<=$D$13),1,0) | HI39: =IF(AND(214>=$B$13,214<=$D$13),1,0) | HJ39: =IF(AND(215>=$B$13,215<=$D$13),1,0) | HK39: =IF(AND(216>=$B$13,216<=$D$13),1,0) | HL39: =IF(AND(217>=$B$13,217<=$D$13),1,0) | HM39: =IF(AND(218>=$B$13,218<=$D$13),1,0) | HN39: =IF(AND(219>=$B$13,219<=$D$13),1,0) | HO39: =IF(AND(220>=$B$13,220<=$D$13),1,0) | HP39: =IF(AND(221>=$B$13,221<=$D$13),1,0) | HQ39: =IF(AND(222>=$B$13,222<=$D$13),1,0) | HR39: =IF(AND(223>=$B$13,223<=$D$13),1,0) | HS39: =IF(AND(224>=$B$13,224<=$D$13),1,0) | HT39: =IF(AND(225>=$B$13,225<=$D$13),1,0) | HU39: =IF(AND(226>=$B$13,226<=$D$13),1,0) | HV39: =IF(AND(227>=$B$13,227<=$D$13),1,0) | HW39: =IF(AND(228>=$B$13,228<=$D$13),1,0) | HX39: =IF(AND(229>=$B$13,229<=$D$13),1,0) | HY39: =IF(AND(230>=$B$13,230<=$D$13),1,0) | HZ39: =IF(AND(231>=$B$13,231<=$D$13),1,0) | IA39: =IF(AND(232>=$B$13,232<=$D$13),1,0) | IB39: =IF(AND(233>=$B$13,233<=$D$13),1,0) | IC39: =IF(AND(234>=$B$13,234<=$D$13),1,0) | ID39: =IF(AND(235>=$B$13,235<=$D$13),1,0) | IE39: =IF(AND(236>=$B$13,236<=$D$13),1,0) | IF39: =IF(AND(237>=$B$13,237<=$D$13),1,0) | IG39: =IF(AND(238>=$B$13,238<=$D$13),1,0) | IH39: =IF(AND(239>=$B$13,239<=$D$13),1,0) | II39: =IF(AND(240>=$B$13,240<=$D$13),1,0) | IJ39: =IF(AND(241>=$B$13,241<=$D$13),1,0) | IK39: =IF(AND(242>=$B$13,242<=$D$13),1,0) | IL39: =IF(AND(243>=$B$13,243<=$D$13),1,0) | IM39: =IF(AND(244>=$B$13,244<=$D$13),1,0) | IN39: =IF(AND(245>=$B$13,245<=$D$13),1,0) | IO39: =IF(AND(246>=$B$13,246<=$D$13),1,0) | IP39: =IF(AND(247>=$B$13,247<=$D$13),1,0) | IQ39: =IF(AND(248>=$B$13,248<=$D$13),1,0) | IR39: =IF(AND(249>=$B$13,249<=$D$13),1,0) | IS39: =IF(AND(250>=$B$13,250<=$D$13),1,0) | IT39: =IF(AND(251>=$B$13,251<=$D$13),1,0) | IU39: =IF(AND(252>=$B$13,252<=$D$13),1,0) | IV39: =IF(AND(253>=$B$13,253<=$D$13),1,0) | IW39: =IF(AND(254>=$B$13,254<=$D$13),1,0) | IX39: =IF(AND(255>=$B$13,255<=$D$13),1,0) | IY39: =IF(AND(256>=$B$13,256<=$D$13),1,0) | IZ39: =IF(AND(257>=$B$13,257<=$D$13),1,0) | JA39: =IF(AND(258>=$B$13,258<=$D$13),1,0) | JB39: =IF(AND(259>=$B$13,259<=$D$13),1,0) | JC39: =IF(AND(260>=$B$13,260<=$D$13),1,0) | JD39: =IF(AND(261>=$B$13,261<=$D$13),1,0) | JE39: =IF(AND(262>=$B$13,262<=$D$13),1,0) | JF39: =IF(AND(263>=$B$13,263<=$D$13),1,0) | JG39: =IF(AND(264>=$B$13,264<=$D$13),1,0) | JH39: =IF(AND(265>=$B$13,265<=$D$13),1,0) | JI39: =IF(AND(266>=$B$13,266<=$D$13),1,0) | JJ39: =IF(AND(267>=$B$13,267<=$D$13),1,0) | JK39: =IF(AND(268>=$B$13,268<=$D$13),1,0) | JL39: =IF(AND(269>=$B$13,269<=$D$13),1,0) | JM39: =IF(AND(270>=$B$13,270<=$D$13),1,0) | JN39: =IF(AND(271>=$B$13,271<=$D$13),1,0) | JO39: =IF(AND(272>=$B$13,272<=$D$13),1,0) | JP39: =IF(AND(273>=$B$13,273<=$D$13),1,0) | JQ39: =IF(AND(274>=$B$13,274<=$D$13),1,0) | JR39: =IF(AND(275>=$B$13,275<=$D$13),1,0) | JS39: =IF(AND(276>=$B$13,276<=$D$13),1,0) | JT39: =IF(AND(277>=$B$13,277<=$D$13),1,0) | JU39: =IF(AND(278>=$B$13,278<=$D$13),1,0) | JV39: =IF(AND(279>=$B$13,279<=$D$13),1,0) | JW39: =IF(AND(280>=$B$13,280<=$D$13),1,0) | JX39: =IF(AND(281>=$B$13,281<=$D$13),1,0) | JY39: =IF(AND(282>=$B$13,282<=$D$13),1,0) | JZ39: =IF(AND(283>=$B$13,283<=$D$13),1,0) | KA39: =IF(AND(284>=$B$13,284<=$D$13),1,0) | KB39: =IF(AND(285>=$B$13,285<=$D$13),1,0) | KC39: =IF(AND(286>=$B$13,286<=$D$13),1,0) | KD39: =IF(AND(287>=$B$13,287<=$D$13),1,0) | KE39: =IF(AND(288>=$B$13,288<=$D$13),1,0) | KF39: =IF(AND(289>=$B$13,289<=$D$13),1,0) | KG39: =IF(AND(290>=$B$13,290<=$D$13),1,0) | KH39: =IF(AND(291>=$B$13,291<=$D$13),1,0) | KI39: =IF(AND(292>=$B$13,292<=$D$13),1,0) | KJ39: =IF(AND(293>=$B$13,293<=$D$13),1,0) | KK39: =IF(AND(294>=$B$13,294<=$D$13),1,0) | KL39: =IF(AND(295>=$B$13,295<=$D$13),1,0) | KM39: =IF(AND(296>=$B$13,296<=$D$13),1,0) | KN39: =IF(AND(297>=$B$13,297<=$D$13),1,0) | KO39: =IF(AND(298>=$B$13,298<=$D$13),1,0) | KP39: =IF(AND(299>=$B$13,299<=$D$13),1,0) | KQ39: =IF(AND(300>=$B$13,300<=$D$13),1,0) | KR39: =IF(AND(301>=$B$13,301<=$D$13),1,0) | KS39: =IF(AND(302>=$B$13,302<=$D$13),1,0) | KT39: =IF(AND(303>=$B$13,303<=$D$13),1,0) | KU39: =IF(AND(304>=$B$13,304<=$D$13),1,0) | KV39: =IF(AND(305>=$B$13,305<=$D$13),1,0) | KW39: =IF(AND(306>=$B$13,306<=$D$13),1,0) | KX39: =IF(AND(307>=$B$13,307<=$D$13),1,0) | KY39: =IF(AND(308>=$B$13,308<=$D$13),1,0) | KZ39: =IF(AND(309>=$B$13,309<=$D$13),1,0) | LA39: =IF(AND(310>=$B$13,310<=$D$13),1,0) | LB39: =IF(AND(311>=$B$13,311<=$D$13),1,0) | LC39: =IF(AND(312>=$B$13,312<=$D$13),1,0) | LD39: =IF(AND(313>=$B$13,313<=$D$13),1,0) | LE39: =IF(AND(314>=$B$13,314<=$D$13),1,0) | LF39: =IF(AND(315>=$B$13,315<=$D$13),1,0) | LG39: =IF(AND(316>=$B$13,316<=$D$13),1,0) | LH39: =IF(AND(317>=$B$13,317<=$D$13),1,0) | LI39: =IF(AND(318>=$B$13,318<=$D$13),1,0) | LJ39: =IF(AND(319>=$B$13,319<=$D$13),1,0) | LK39: =IF(AND(320>=$B$13,320<=$D$13),1,0) | LL39: =IF(AND(321>=$B$13,321<=$D$13),1,0) | LM39: =IF(AND(322>=$B$13,322<=$D$13),1,0) | LN39: =IF(AND(323>=$B$13,323<=$D$13),1,0) | LO39: =IF(AND(324>=$B$13,324<=$D$13),1,0) | LP39: =IF(AND(325>=$B$13,325<=$D$13),1,0) | LQ39: =IF(AND(326>=$B$13,326<=$D$13),1,0) | LR39: =IF(AND(327>=$B$13,327<=$D$13),1,0) | LS39: =IF(AND(328>=$B$13,328<=$D$13),1,0) | LT39: =IF(AND(329>=$B$13,329<=$D$13),1,0) | LU39: =IF(AND(330>=$B$13,330<=$D$13),1,0) | LV39: =IF(AND(331>=$B$13,331<=$D$13),1,0) | LW39: =IF(AND(332>=$B$13,332<=$D$13),1,0) | LX39: =IF(AND(333>=$B$13,333<=$D$13),1,0) | LY39: =IF(AND(334>=$B$13,334<=$D$13),1,0) | LZ39: =IF(AND(335>=$B$13,335<=$D$13),1,0) | MA39: =IF(AND(336>=$B$13,336<=$D$13),1,0) | MB39: =IF(AND(337>=$B$13,337<=$D$13),1,0) | MC39: =IF(AND(338>=$B$13,338<=$D$13),1,0) | MD39: =IF(AND(339>=$B$13,339<=$D$13),1,0) | ME39: =IF(AND(340>=$B$13,340<=$D$13),1,0) | MF39: =IF(AND(341>=$B$13,341<=$D$13),1,0) | MG39: =IF(AND(342>=$B$13,342<=$D$13),1,0) | MH39: =IF(AND(343>=$B$13,343<=$D$13),1,0) | MI39: =IF(AND(344>=$B$13,344<=$D$13),1,0) | MJ39: =IF(AND(345>=$B$13,345<=$D$13),1,0) | MK39: =IF(AND(346>=$B$13,346<=$D$13),1,0) | ML39: =IF(AND(347>=$B$13,347<=$D$13),1,0) | MM39: =IF(AND(348>=$B$13,348<=$D$13),1,0) | MN39: =IF(AND(349>=$B$13,349<=$D$13),1,0) | MO39: =IF(AND(350>=$B$13,350<=$D$13),1,0) | MP39: =IF(AND(351>=$B$13,351<=$D$13),1,0) | MQ39: =IF(AND(352>=$B$13,352<=$D$13),1,0) | MR39: =IF(AND(353>=$B$13,353<=$D$13),1,0) | MS39: =IF(AND(354>=$B$13,354<=$D$13),1,0) | MT39: =IF(AND(355>=$B$13,355<=$D$13),1,0) | MU39: =IF(AND(356>=$B$13,356<=$D$13),1,0) | MV39: =IF(AND(357>=$B$13,357<=$D$13),1,0) | MW39: =IF(AND(358>=$B$13,358<=$D$13),1,0) | MX39: =IF(AND(359>=$B$13,359<=$D$13),1,0) | MY39: =IF(AND(360>=$B$13,360<=$D$13),1,0) | MZ39: =IF(AND(361>=$B$13,361<=$D$13),1,0) | NA39: =IF(AND(362>=$B$13,362<=$D$13),1,0) | NB39: =IF(AND(363>=$B$13,363<=$D$13),1,0) | NC39: =IF(AND(364>=$B$13,364<=$D$13),1,0) | ND39: =IF(AND(365>=$B$13,365<=$D$13),1,0) | NE39: =IF(AND(366>=$B$13,366<=$D$13),1,0) | NF39: =IF(AND(367>=$B$13,367<=$D$13),1,0) | NG39: =IF(AND(368>=$B$13,368<=$D$13),1,0) | NH39: =IF(AND(369>=$B$13,369<=$D$13),1,0) | NI39: =IF(AND(370>=$B$13,370<=$D$13),1,0) | NJ39: =IF(AND(371>=$B$13,371<=$D$13),1,0) | NK39: =IF(AND(372>=$B$13,372<=$D$13),1,0)
